Workbook

Sheet 00_Value_Drivers
A1: Under equal conditions: where does LaaS value come from?
A2: Decompose incremental value drivers and payback pressure.
A4: Snapshot
A6: Baseline electricity (Y1) | B6: ='Inputs_Data'!C6
A7: Owner annual budget | B7: ='Inputs_Data'!B6
A8: Initial CAPEX | B8: ='Inputs_Data'!H5

Sheet Inputs_Data
A1: Inputs (from /data)
A2: All values are RMB/year unless noted.
A4: Year | B4: Trust_fee | C4: Elec_OPEX | D4: Staff+Other_OPEX | E4: Cash_OPEX | F4: Depreciation | G4: Debt_service | H4: CAPEX_y0
A5: 0 | B5: 0 | C5: 0 | D5: 0 | E5: 0 | F5: 0 | G5: 0 | H5: 3539400
A6: 1 | B6: 2342300 | C6: 1028000 | D6: 610000 | E6: 1638000 | F6: 407780 | G6: 867700 | H6: 0
A7: 2 | B7: 2342300 | C7: 1028000 | D7: 610000 | E7: 1638000 | F7: 407780 | G7: 840400 | H7: 0
A8: 3 | B8: 2342300 | C8: 1028000 | D8: 610000 | E8: 1638000 | F8: 407780 | G8: 813100 | H8: 0
A9: 4 | B9: 2342300 | C9: 1028000 | D9: 610000 | E9: 1638000 | F9: 407780 | G9: 785800 | H9: 0
A10: 5 | B10: 2342300 | C10: 1028000 | D10: 610000 | E10: 1638000 | F10: 407780 | G10: 758500 | H10: 0
A11: 6 | B11: 2342300 | C11: 1028000 | D11: 610000 | E11: 1638000 | F11: 407780 | G11: 731200 | H11: 0
A12: 7 | B12: 2342300 | C12: 1028000 | D12: 610000 | E12: 1638000 | F12: 407780 | G12: 103900 | H12: 0
A13: 8 | B13: 2342300 | C13: 1028000 | D13: 610000 | E13: 1638000 | F13: 407780 | G13: 600600 | H13: 0
A14: 9 | B14: 2342300 | C14: 1028000 | D14: 610000 | E14: 1638000 | F14: 407780 | G14: 0 | H14: 0
A15: 10 | B15: 2342300 | C15: 1028000 | D15: 610000 | E15: 1638000 | F15: 407780 | G15: 0 | H15: 0

Sheet Assumptions
A1: Assumptions (editable)
A2: Highlighted cells drive all outputs via formulas.
A4: OPEX reduction factors (by line item)
A5: Item | B5: Value | C5: Notes | D5: Ref
A6: Electricity OPEX reduction % | B6: 0.4 | C6: Used in electricity_only_pct tier (conservative vs case studies). | D6: Story_and_Sources
A7: Staff OPEX reduction % | B7: 0.35 | C7: Remote monitoring + optimized dispatch; applied to non-electric OPEX. | D7: Story_and_Sources
A8: Vehicles OPEX reduction % | B8: 0.3 | C8: Truck-roll reduction; applied to non-electric OPEX. | D8: Story_and_Sources
A9: Materials OPEX reduction % | B9: 0.15 | C9: Predictive grouping reduces waste; applied to non-electric OPEX. | D9: Story_and_Sources
A10: Management OPEX reduction % | B10: 0.1 | C10: Automation reduces overhead; applied to non-electric OPEX. | D10: Story_and_Sources
A11: Max AI OPEX reduction cap % | B11: 0.85 | C11: Model guardrail: avoid unrealistic improvements; requires evidence for >85%. | D11: Story_and_Sources

Sheet Scenarios_10
A1: 10 win-win tiers
A2: Each tier uses a distinct mechanism; all outputs are formula-driven.
A4: Tier | B4: Term_y | C4: OPEX_mode | D4: Base_fee_RMB | E4: Upfront_RMB | F4: TailDisc_RMB | G4: AI_red_pct | H4: Story
A5: Tier1_UniformAI_20 | B5: 10 | C5: uniform_pct | D5: ='Inputs_Data'!B6*0.95 | E5: 0 | F5: 0 | G5: 0.2 | H5: AI dispatch + predictive maintenance reduces non-electric OPEX
A6: Tier2_UniformAI_35 | B6: 10 | C6: uniform_pct | D6: ='Inputs_Data'!B6*0.97 | E6: 0 | F6: 0 | G6: 0.35 | H6: Higher AI ops maturity; still within cited ranges
A7: Tier3_ElecOnly_40 | B7: 10 | C7: electricity_only_pct | D7: ='Inputs_Data'!B6*0.96 | E7: 0 | F7: 0 | G7: 0.4 | H7: Adaptive dimming/controls reduce electricity cost
A8: Tier4_ElecOnly_60 | B8: 10 | C8: electricity_only_pct | D8: ='Inputs_Data'!B6*0.98 | E8: 0 | F8: 0 | G8: 0.6 | H8: Aggressive controls (case-like), needs stronger acceptance
A9: Tier5_AISolar | B9: 10 | C9: ai_plus_solar | D9: ='Inputs_Data'!B6*1.05 | E9: 0 | F9: 0 | G9: 0 | H9: AI+Solar: electricity OPEX to 0 (engineering/contract assumption)
A10: Tier6_Upfront_Prepay | B10: 10 | C10: uniform_pct | D10: ='Inputs_Data'!B6*1.00 | E10: 1000000 | F10: 0 | G10: 0.25 | H10: Upfront as prepayment reduces annual fee; improves payback
A11: Tier7_TailDiscount | B11: 10 | C11: uniform_pct | D11: ='Inputs_Data'!B6*1.02 | E11: 0 | F11: 250000 | G11: 0.25 | H11: SLA-style tail discount in last 4 years
A12: Tier8_HigherFee_StrongerSLA | B12: 10 | C12: uniform_pct | D12: ='Inputs_Data'!B6*1.08 | E12: 0 | F12: 350000 | G12: 0.3 | H12: Higher fee but more SLA credit; keep client whole
A13: Tier9_MidTerm_8y | B13: 8 | C13: uniform_pct | D13: ='Inputs_Data'!B6*1.00 | E13: 500000 | F13: 0 | G13: 0.3 | H13: Shorter term with upfront to keep 36m payback
A14: Tier10_Conservative | B14: 10 | C14: uniform_pct | D14: ='Inputs_Data'!B6*0.92 | E14: 0 | F14: 0 | G14: 0.1 | H14: Low fee + modest AI improvements (very conservative)

Sheet Model_Calc
A1: Model (formula-driven)
A2: Each scenario computed via formulas from Inputs_Data + Assumptions.
A4: Scenario summary metrics (computed)
A5: Tier | B5: ClientPay_Y1 | C5: BaselinePay_Y1 | D5: ClientSavings_Y1 | E5: LaaS_CashOPEX_Y1 | F5: Baseline_CashOPEX_Y1 | G5: ProviderGP_Uplift_Y1 | H5: Payback_months(approx) | I5: WinWin?
A6: ='Scenarios_10'!A5 | B6: =MAX(0,'Scenarios_10'!D5-'Scenarios_10'!E5/'Scenarios_10'!B5) | C6: ='Inputs_Data'!B6 | D6: =('Inputs_Data'!B6-(MAX(0,'Scenarios_10'!D5-'Scenarios_10'!E5/'Scenarios_10'!B5))) | E6: =IF('Scenarios_10'!C5="uniform_pct",'Inputs_Data'!E6*(1-MIN('Scenarios_10'!G5,'Assumptions'!B10)),IF('Scenarios_10'!C5="electricity_only_pct",('Inputs_Data'!C6*(1-MIN('Scenarios_10'!G5,'Assumptions'!B10)))+'Inputs_Data'!D6,0+('Inputs_Data'!D6*(1-AVERAGE('Assumptions'!B6,'Assumptions'!B7,'Assumptions'!B8,'Assumptions'!B9))))) | F6: ='Inputs_Data'!E6 | G6: =((MAX(0,'Scenarios_10'!D5-'Scenarios_10'!E5/'Scenarios_10'!B5)-(IF('Scenarios_10'!C5="uniform_pct",'Inputs_Data'!E6*(1-MIN('Scenarios_10'!G5,'Assumptions'!B10)),IF('Scenarios_10'!C5="electricity_only_pct",('Inputs_Data'!C6*(1-MIN('Scenarios_10'!G5,'Assumptions'!B10)))+'Inputs_Data'!D6,0+('Inputs_Data'!D6*(1-AVERAGE('Assumptions'!B6,'Assumptions'!B7,'Assumptions'!B8,'Assumptions'!B9)))))+'Inputs_Data'!F6))-('Inputs_Data'!B6-('Inputs_Data'!E6+'Inputs_Data'!F6))) | H6: =IF((MAX(0,'Scenarios_10'!D5-'Scenarios_10'!E5/'Scenarios_10'!B5)-(IF('Scenarios_10'!C5="uniform_pct",'Inputs_Data'!E6*(1-MIN('Scenarios_10'!G5,'Assumptions'!B10)),IF('Scenarios_10'!C5="electricity_only_pct",('Inputs_Data'!C6*(1-MIN('Scenarios_10'!G5,'Assumptions'!B10)))+'Inputs_Data'!D6,0+('Inputs_Data'!D6*(1-AVERAGE('Assumptions'!B6,'Assumptions'!B7,'Assumptions'!B8,'Assumptions'!B9)))))))<=0,999,ROUNDUP('Inputs_Data'!H5/((MAX(0,'Scenarios_10'!D5-'Scenarios_10'!E5/'Scenarios_10'!B5)-(IF('Scenarios_10'!C5="uniform_pct",'Inputs_Data'!E6*(1-MIN('Scenarios_10'!G5,'Assumptions'!B10)),IF('Scenarios_10'!C5="electricity_only_pct",('Inputs_Data'!C6*(1-MIN('Scenarios_10'!G5,'Assumptions'!B10)))+'Inputs_Data'!D6,0+('Inputs_Data'!D6*(1-AVERAGE('Assumptions'!B6,'Assumptions'!B7,'Assumptions'!B8,'Assumptions'!B9)))))))/12),0)) | I6: =AND(MAX(0,'Scenarios_10'!D5-'Scenarios_10'!E5/'Scenarios_10'!B5)<='Inputs_Data'!B6,((MAX(0,'Scenarios_10'!D5-'Scenarios_10'!E5/'Scenarios_10'!B5)-(IF('Scenarios_10'!C5="uniform_pct",'Inputs_Data'!E6*(1-MIN('Scenarios_10'!G5,'Assumptions'!B10)),IF('Scenarios_10'!C5="electricity_only_pct",('Inputs_Data'!C6*(1-MIN('Scenarios_10'!G5,'Assumptions'!B10)))+'Inputs_Data'!D6,0+('Inputs_Data'!D6*(1-AVERAGE('Assumptions'!B6,'Assumptions'!B7,'Assumptions'!B8,'Assumptions'!B9)))))+'Inputs_Data'!F6))-('Inputs_Data'!B6-('Inputs_Data'!E6+'Inputs_Data'!F6)))>=0,IF((MAX(0,'Scenarios_10'!D5-'Scenarios_10'!E5/'Scenarios_10'!B5)-(IF('Scenarios_10'!C5="uniform_pct",'Inputs_Data'!E6*(1-MIN('Scenarios_10'!G5,'Assumptions'!B10)),IF('Scenarios_10'!C5="electricity_only_pct",('Inputs_Data'!C6*(1-MIN('Scenarios_10'!G5,'Assumptions'!B10)))+'Inputs_Data'!D6,0+('Inputs_Data'!D6*(1-AVERAGE('Assumptions'!B6,'Assumptions'!B7,'Assumptions'!B8,'Assumptions'!B9)))))))<=0,999,ROUNDUP('Inputs_Data'!H5/((MAX(0,'Scenarios_10'!D5-'Scenarios_10'!E5/'Scenarios_10'!B5)-(IF('Scenarios_10'!C5="uniform_pct",'Inputs_Data'!E6*(1-MIN('Scenarios_10'!G5,'Assumptions'!B10)),IF('Scenarios_10'!C5="electricity_only_pct",('Inputs_Data'!C6*(1-MIN('Scenarios_10'!G5,'Assumptions'!B10)))+'Inputs_Data'!D6,0+('Inputs_Data'!D6*(1-AVERAGE('Assumptions'!B6,'Assumptions'!B7,'Assumptions'!B8,'Assumptions'!B9)))))))/12),0))<=36)
A7: ='Scenarios_10'!A6 | B7: =MAX(0,'Scenarios_10'!D6-'Scenarios_10'!E6/'Scenarios_10'!B6) | C7: ='Inputs_Data'!B6 | D7: =('Inputs_Data'!B6-(MAX(0,'Scenarios_10'!D6-'Scenarios_10'!E6/'Scenarios_10'!B6))) | E7: =IF('Scenarios_10'!C6="uniform_pct",'Inputs_Data'!E6*(1-MIN('Scenarios_10'!G6,'Assumptions'!B10)),IF('Scenarios_10'!C6="electricity_only_pct",('Inputs_Data'!C6*(1-MIN('Scenarios_10'!G6,'Assumptions'!B10)))+'Inputs_Data'!D6,0+('Inputs_Data'!D6*(1-AVERAGE('Assumptions'!B6,'Assumptions'!B7,'Assumptions'!B8,'Assumptions'!B9))))) | F7: ='Inputs_Data'!E6 | G7: =((MAX(0,'Scenarios_10'!D6-'Scenarios_10'!E6/'Scenarios_10'!B6)-(IF('Scenarios_10'!C6="uniform_pct",'Inputs_Data'!E6*(1-MIN('Scenarios_10'!G6,'Assumptions'!B10)),IF('Scenarios_10'!C6="electricity_only_pct",('Inputs_Data'!C6*(1-MIN('Scenarios_10'!G6,'Assumptions'!B10)))+'Inputs_Data'!D6,0+('Inputs_Data'!D6*(1-AVERAGE('Assumptions'!B6,'Assumptions'!B7,'Assumptions'!B8,'Assumptions'!B9)))))+'Inputs_Data'!F6))-('Inputs_Data'!B6-('Inputs_Data'!E6+'Inputs_Data'!F6))) | H7: =IF((MAX(0,'Scenarios_10'!D6-'Scenarios_10'!E6/'Scenarios_10'!B6)-(IF('Scenarios_10'!C6="uniform_pct",'Inputs_Data'!E6*(1-MIN('Scenarios_10'!G6,'Assumptions'!B10)),IF('Scenarios_10'!C6="electricity_only_pct",('Inputs_Data'!C6*(1-MIN('Scenarios_10'!G6,'Assumptions'!B10)))+'Inputs_Data'!D6,0+('Inputs_Data'!D6*(1-AVERAGE('Assumptions'!B6,'Assumptions'!B7,'Assumptions'!B8,'Assumptions'!B9)))))))<=0,999,ROUNDUP('Inputs_Data'!H5/((MAX(0,'Scenarios_10'!D6-'Scenarios_10'!E6/'Scenarios_10'!B6)-(IF('Scenarios_10'!C6="uniform_pct",'Inputs_Data'!E6*(1-MIN('Scenarios_10'!G6,'Assumptions'!B10)),IF('Scenarios_10'!C6="electricity_only_pct",('Inputs_Data'!C6*(1-MIN('Scenarios_10'!G6,'Assumptions'!B10)))+'Inputs_Data'!D6,0+('Inputs_Data'!D6*(1-AVERAGE('Assumptions'!B6,'Assumptions'!B7,'Assumptions'!B8,'Assumptions'!B9)))))))/12),0)) | I7: =AND(MAX(0,'Scenarios_10'!D6-'Scenarios_10'!E6/'Scenarios_10'!B6)<='Inputs_Data'!B6,((MAX(0,'Scenarios_10'!D6-'Scenarios_10'!E6/'Scenarios_10'!B6)-(IF('Scenarios_10'!C6="uniform_pct",'Inputs_Data'!E6*(1-MIN('Scenarios_10'!G6,'Assumptions'!B10)),IF('Scenarios_10'!C6="electricity_only_pct",('Inputs_Data'!C6*(1-MIN('Scenarios_10'!G6,'Assumptions'!B10)))+'Inputs_Data'!D6,0+('Inputs_Data'!D6*(1-AVERAGE('Assumptions'!B6,'Assumptions'!B7,'Assumptions'!B8,'Assumptions'!B9)))))+'Inputs_Data'!F6))-('Inputs_Data'!B6-('Inputs_Data'!E6+'Inputs_Data'!F6)))>=0,IF((MAX(0,'Scenarios_10'!D6-'Scenarios_10'!E6/'Scenarios_10'!B6)-(IF('Scenarios_10'!C6="uniform_pct",'Inputs_Data'!E6*(1-MIN('Scenarios_10'!G6,'Assumptions'!B10)),IF('Scenarios_10'!C6="electricity_only_pct",('Inputs_Data'!C6*(1-MIN('Scenarios_10'!G6,'Assumptions'!B10)))+'Inputs_Data'!D6,0+('Inputs_Data'!D6*(1-AVERAGE('Assumptions'!B6,'Assumptions'!B7,'Assumptions'!B8,'Assumptions'!B9)))))))<=0,999,ROUNDUP('Inputs_Data'!H5/((MAX(0,'Scenarios_10'!D6-'Scenarios_10'!E6/'Scenarios_10'!B6)-(IF('Scenarios_10'!C6="uniform_pct",'Inputs_Data'!E6*(1-MIN('Scenarios_10'!G6,'Assumptions'!B10)),IF('Scenarios_10'!C6="electricity_only_pct",('Inputs_Data'!C6*(1-MIN('Scenarios_10'!G6,'Assumptions'!B10)))+'Inputs_Data'!D6,0+('Inputs_Data'!D6*(1-AVERAGE('Assumptions'!B6,'Assumptions'!B7,'Assumptions'!B8,'Assumptions'!B9)))))))/12),0))<=36)
A8: ='Scenarios_10'!A7 | B8: =MAX(0,'Scenarios_10'!D7-'Scenarios_10'!E7/'Scenarios_10'!B7) | C8: ='Inputs_Data'!B6 | D8: =('Inputs_Data'!B6-(MAX(0,'Scenarios_10'!D7-'Scenarios_10'!E7/'Scenarios_10'!B7))) | E8: =IF('Scenarios_10'!C7="uniform_pct",'Inputs_Data'!E6*(1-MIN('Scenarios_10'!G7,'Assumptions'!B10)),IF('Scenarios_10'!C7="electricity_only_pct",('Inputs_Data'!C6*(1-MIN('Scenarios_10'!G7,'Assumptions'!B10)))+'Inputs_Data'!D6,0+('Inputs_Data'!D6*(1-AVERAGE('Assumptions'!B6,'Assumptions'!B7,'Assumptions'!B8,'Assumptions'!B9))))) | F8: ='Inputs_Data'!E6 | G8: =((MAX(0,'Scenarios_10'!D7-'Scenarios_10'!E7/'Scenarios_10'!B7)-(IF('Scenarios_10'!C7="uniform_pct",'Inputs_Data'!E6*(1-MIN('Scenarios_10'!G7,'Assumptions'!B10)),IF('Scenarios_10'!C7="electricity_only_pct",('Inputs_Data'!C6*(1-MIN('Scenarios_10'!G7,'Assumptions'!B10)))+'Inputs_Data'!D6,0+('Inputs_Data'!D6*(1-AVERAGE('Assumptions'!B6,'Assumptions'!B7,'Assumptions'!B8,'Assumptions'!B9)))))+'Inputs_Data'!F6))-('Inputs_Data'!B6-('Inputs_Data'!E6+'Inputs_Data'!F6))) | H8: =IF((MAX(0,'Scenarios_10'!D7-'Scenarios_10'!E7/'Scenarios_10'!B7)-(IF('Scenarios_10'!C7="uniform_pct",'Inputs_Data'!E6*(1-MIN('Scenarios_10'!G7,'Assumptions'!B10)),IF('Scenarios_10'!C7="electricity_only_pct",('Inputs_Data'!C6*(1-MIN('Scenarios_10'!G7,'Assumptions'!B10)))+'Inputs_Data'!D6,0+('Inputs_Data'!D6*(1-AVERAGE('Assumptions'!B6,'Assumptions'!B7,'Assumptions'!B8,'Assumptions'!B9)))))))<=0,999,ROUNDUP('Inputs_Data'!H5/((MAX(0,'Scenarios_10'!D7-'Scenarios_10'!E7/'Scenarios_10'!B7)-(IF('Scenarios_10'!C7="uniform_pct",'Inputs_Data'!E6*(1-MIN('Scenarios_10'!G7,'Assumptions'!B10)),IF('Scenarios_10'!C7="electricity_only_pct",('Inputs_Data'!C6*(1-MIN('Scenarios_10'!G7,'Assumptions'!B10)))+'Inputs_Data'!D6,0+('Inputs_Data'!D6*(1-AVERAGE('Assumptions'!B6,'Assumptions'!B7,'Assumptions'!B8,'Assumptions'!B9)))))))/12),0)) | I8: =AND(MAX(0,'Scenarios_10'!D7-'Scenarios_10'!E7/'Scenarios_10'!B7)<='Inputs_Data'!B6,((MAX(0,'Scenarios_10'!D7-'Scenarios_10'!E7/'Scenarios_10'!B7)-(IF('Scenarios_10'!C7="uniform_pct",'Inputs_Data'!E6*(1-MIN('Scenarios_10'!G7,'Assumptions'!B10)),IF('Scenarios_10'!C7="electricity_only_pct",('Inputs_Data'!C6*(1-MIN('Scenarios_10'!G7,'Assumptions'!B10)))+'Inputs_Data'!D6,0+('Inputs_Data'!D6*(1-AVERAGE('Assumptions'!B6,'Assumptions'!B7,'Assumptions'!B8,'Assumptions'!B9)))))+'Inputs_Data'!F6))-('Inputs_Data'!B6-('Inputs_Data'!E6+'Inputs_Data'!F6)))>=0,IF((MAX(0,'Scenarios_10'!D7-'Scenarios_10'!E7/'Scenarios_10'!B7)-(IF('Scenarios_10'!C7="uniform_pct",'Inputs_Data'!E6*(1-MIN('Scenarios_10'!G7,'Assumptions'!B10)),IF('Scenarios_10'!C7="electricity_only_pct",('Inputs_Data'!C6*(1-MIN('Scenarios_10'!G7,'Assumptions'!B10)))+'Inputs_Data'!D6,0+('Inputs_Data'!D6*(1-AVERAGE('Assumptions'!B6,'Assumptions'!B7,'Assumptions'!B8,'Assumptions'!B9)))))))<=0,999,ROUNDUP('Inputs_Data'!H5/((MAX(0,'Scenarios_10'!D7-'Scenarios_10'!E7/'Scenarios_10'!B7)-(IF('Scenarios_10'!C7="uniform_pct",'Inputs_Data'!E6*(1-MIN('Scenarios_10'!G7,'Assumptions'!B10)),IF('Scenarios_10'!C7="electricity_only_pct",('Inputs_Data'!C6*(1-MIN('Scenarios_10'!G7,'Assumptions'!B10)))+'Inputs_Data'!D6,0+('Inputs_Data'!D6*(1-AVERAGE('Assumptions'!B6,'Assumptions'!B7,'Assumptions'!B8,'Assumptions'!B9)))))))/12),0))<=36)
A9: ='Scenarios_10'!A8 | B9: =MAX(0,'Scenarios_10'!D8-'Scenarios_10'!E8/'Scenarios_10'!B8) | C9: ='Inputs_Data'!B6 | D9: =('Inputs_Data'!B6-(MAX(0,'Scenarios_10'!D8-'Scenarios_10'!E8/'Scenarios_10'!B8))) | E9: =IF('Scenarios_10'!C8="uniform_pct",'Inputs_Data'!E6*(1-MIN('Scenarios_10'!G8,'Assumptions'!B10)),IF('Scenarios_10'!C8="electricity_only_pct",('Inputs_Data'!C6*(1-MIN('Scenarios_10'!G8,'Assumptions'!B10)))+'Inputs_Data'!D6,0+('Inputs_Data'!D6*(1-AVERAGE('Assumptions'!B6,'Assumptions'!B7,'Assumptions'!B8,'Assumptions'!B9))))) | F9: ='Inputs_Data'!E6 | G9: =((MAX(0,'Scenarios_10'!D8-'Scenarios_10'!E8/'Scenarios_10'!B8)-(IF('Scenarios_10'!C8="uniform_pct",'Inputs_Data'!E6*(1-MIN('Scenarios_10'!G8,'Assumptions'!B10)),IF('Scenarios_10'!C8="electricity_only_pct",('Inputs_Data'!C6*(1-MIN('Scenarios_10'!G8,'Assumptions'!B10)))+'Inputs_Data'!D6,0+('Inputs_Data'!D6*(1-AVERAGE('Assumptions'!B6,'Assumptions'!B7,'Assumptions'!B8,'Assumptions'!B9)))))+'Inputs_Data'!F6))-('Inputs_Data'!B6-('Inputs_Data'!E6+'Inputs_Data'!F6))) | H9: =IF((MAX(0,'Scenarios_10'!D8-'Scenarios_10'!E8/'Scenarios_10'!B8)-(IF('Scenarios_10'!C8="uniform_pct",'Inputs_Data'!E6*(1-MIN('Scenarios_10'!G8,'Assumptions'!B10)),IF('Scenarios_10'!C8="electricity_only_pct",('Inputs_Data'!C6*(1-MIN('Scenarios_10'!G8,'Assumptions'!B10)))+'Inputs_Data'!D6,0+('Inputs_Data'!D6*(1-AVERAGE('Assumptions'!B6,'Assumptions'!B7,'Assumptions'!B8,'Assumptions'!B9)))))))<=0,999,ROUNDUP('Inputs_Data'!H5/((MAX(0,'Scenarios_10'!D8-'Scenarios_10'!E8/'Scenarios_10'!B8)-(IF('Scenarios_10'!C8="uniform_pct",'Inputs_Data'!E6*(1-MIN('Scenarios_10'!G8,'Assumptions'!B10)),IF('Scenarios_10'!C8="electricity_only_pct",('Inputs_Data'!C6*(1-MIN('Scenarios_10'!G8,'Assumptions'!B10)))+'Inputs_Data'!D6,0+('Inputs_Data'!D6*(1-AVERAGE('Assumptions'!B6,'Assumptions'!B7,'Assumptions'!B8,'Assumptions'!B9)))))))/12),0)) | I9: =AND(MAX(0,'Scenarios_10'!D8-'Scenarios_10'!E8/'Scenarios_10'!B8)<='Inputs_Data'!B6,((MAX(0,'Scenarios_10'!D8-'Scenarios_10'!E8/'Scenarios_10'!B8)-(IF('Scenarios_10'!C8="uniform_pct",'Inputs_Data'!E6*(1-MIN('Scenarios_10'!G8,'Assumptions'!B10)),IF('Scenarios_10'!C8="electricity_only_pct",('Inputs_Data'!C6*(1-MIN('Scenarios_10'!G8,'Assumptions'!B10)))+'Inputs_Data'!D6,0+('Inputs_Data'!D6*(1-AVERAGE('Assumptions'!B6,'Assumptions'!B7,'Assumptions'!B8,'Assumptions'!B9)))))+'Inputs_Data'!F6))-('Inputs_Data'!B6-('Inputs_Data'!E6+'Inputs_Data'!F6)))>=0,IF((MAX(0,'Scenarios_10'!D8-'Scenarios_10'!E8/'Scenarios_10'!B8)-(IF('Scenarios_10'!C8="uniform_pct",'Inputs_Data'!E6*(1-MIN('Scenarios_10'!G8,'Assumptions'!B10)),IF('Scenarios_10'!C8="electricity_only_pct",('Inputs_Data'!C6*(1-MIN('Scenarios_10'!G8,'Assumptions'!B10)))+'Inputs_Data'!D6,0+('Inputs_Data'!D6*(1-AVERAGE('Assumptions'!B6,'Assumptions'!B7,'Assumptions'!B8,'Assumptions'!B9)))))))<=0,999,ROUNDUP('Inputs_Data'!H5/((MAX(0,'Scenarios_10'!D8-'Scenarios_10'!E8/'Scenarios_10'!B8)-(IF('Scenarios_10'!C8="uniform_pct",'Inputs_Data'!E6*(1-MIN('Scenarios_10'!G8,'Assumptions'!B10)),IF('Scenarios_10'!C8="electricity_only_pct",('Inputs_Data'!C6*(1-MIN('Scenarios_10'!G8,'Assumptions'!B10)))+'Inputs_Data'!D6,0+('Inputs_Data'!D6*(1-AVERAGE('Assumptions'!B6,'Assumptions'!B7,'Assumptions'!B8,'Assumptions'!B9)))))))/12),0))<=36)
A10: ='Scenarios_10'!A9 | B10: =MAX(0,'Scenarios_10'!D9-'Scenarios_10'!E9/'Scenarios_10'!B9) | C10: ='Inputs_Data'!B6 | D10: =('Inputs_Data'!B6-(MAX(0,'Scenarios_10'!D9-'Scenarios_10'!E9/'Scenarios_10'!B9))) | E10: =IF('Scenarios_10'!C9="uniform_pct",'Inputs_Data'!E6*(1-MIN('Scenarios_10'!G9,'Assumptions'!B10)),IF('Scenarios_10'!C9="electricity_only_pct",('Inputs_Data'!C6*(1-MIN('Scenarios_10'!G9,'Assumptions'!B10)))+'Inputs_Data'!D6,0+('Inputs_Data'!D6*(1-AVERAGE('Assumptions'!B6,'Assumptions'!B7,'Assumptions'!B8,'Assumptions'!B9))))) | F10: ='Inputs_Data'!E6 | G10: =((MAX(0,'Scenarios_10'!D9-'Scenarios_10'!E9/'Scenarios_10'!B9)-(IF('Scenarios_10'!C9="uniform_pct",'Inputs_Data'!E6*(1-MIN('Scenarios_10'!G9,'Assumptions'!B10)),IF('Scenarios_10'!C9="electricity_only_pct",('Inputs_Data'!C6*(1-MIN('Scenarios_10'!G9,'Assumptions'!B10)))+'Inputs_Data'!D6,0+('Inputs_Data'!D6*(1-AVERAGE('Assumptions'!B6,'Assumptions'!B7,'Assumptions'!B8,'Assumptions'!B9)))))+'Inputs_Data'!F6))-('Inputs_Data'!B6-('Inputs_Data'!E6+'Inputs_Data'!F6))) | H10: =IF((MAX(0,'Scenarios_10'!D9-'Scenarios_10'!E9/'Scenarios_10'!B9)-(IF('Scenarios_10'!C9="uniform_pct",'Inputs_Data'!E6*(1-MIN('Scenarios_10'!G9,'Assumptions'!B10)),IF('Scenarios_10'!C9="electricity_only_pct",('Inputs_Data'!C6*(1-MIN('Scenarios_10'!G9,'Assumptions'!B10)))+'Inputs_Data'!D6,0+('Inputs_Data'!D6*(1-AVERAGE('Assumptions'!B6,'Assumptions'!B7,'Assumptions'!B8,'Assumptions'!B9)))))))<=0,999,ROUNDUP('Inputs_Data'!H5/((MAX(0,'Scenarios_10'!D9-'Scenarios_10'!E9/'Scenarios_10'!B9)-(IF('Scenarios_10'!C9="uniform_pct",'Inputs_Data'!E6*(1-MIN('Scenarios_10'!G9,'Assumptions'!B10)),IF('Scenarios_10'!C9="electricity_only_pct",('Inputs_Data'!C6*(1-MIN('Scenarios_10'!G9,'Assumptions'!B10)))+'Inputs_Data'!D6,0+('Inputs_Data'!D6*(1-AVERAGE('Assumptions'!B6,'Assumptions'!B7,'Assumptions'!B8,'Assumptions'!B9)))))))/12),0)) | I10: =AND(MAX(0,'Scenarios_10'!D9-'Scenarios_10'!E9/'Scenarios_10'!B9)<='Inputs_Data'!B6,((MAX(0,'Scenarios_10'!D9-'Scenarios_10'!E9/'Scenarios_10'!B9)-(IF('Scenarios_10'!C9="uniform_pct",'Inputs_Data'!E6*(1-MIN('Scenarios_10'!G9,'Assumptions'!B10)),IF('Scenarios_10'!C9="electricity_only_pct",('Inputs_Data'!C6*(1-MIN('Scenarios_10'!G9,'Assumptions'!B10)))+'Inputs_Data'!D6,0+('Inputs_Data'!D6*(1-AVERAGE('Assumptions'!B6,'Assumptions'!B7,'Assumptions'!B8,'Assumptions'!B9)))))+'Inputs_Data'!F6))-('Inputs_Data'!B6-('Inputs_Data'!E6+'Inputs_Data'!F6)))>=0,IF((MAX(0,'Scenarios_10'!D9-'Scenarios_10'!E9/'Scenarios_10'!B9)-(IF('Scenarios_10'!C9="uniform_pct",'Inputs_Data'!E6*(1-MIN('Scenarios_10'!G9,'Assumptions'!B10)),IF('Scenarios_10'!C9="electricity_only_pct",('Inputs_Data'!C6*(1-MIN('Scenarios_10'!G9,'Assumptions'!B10)))+'Inputs_Data'!D6,0+('Inputs_Data'!D6*(1-AVERAGE('Assumptions'!B6,'Assumptions'!B7,'Assumptions'!B8,'Assumptions'!B9)))))))<=0,999,ROUNDUP('Inputs_Data'!H5/((MAX(0,'Scenarios_10'!D9-'Scenarios_10'!E9/'Scenarios_10'!B9)-(IF('Scenarios_10'!C9="uniform_pct",'Inputs_Data'!E6*(1-MIN('Scenarios_10'!G9,'Assumptions'!B10)),IF('Scenarios_10'!C9="electricity_only_pct",('Inputs_Data'!C6*(1-MIN('Scenarios_10'!G9,'Assumptions'!B10)))+'Inputs_Data'!D6,0+('Inputs_Data'!D6*(1-AVERAGE('Assumptions'!B6,'Assumptions'!B7,'Assumptions'!B8,'Assumptions'!B9)))))))/12),0))<=36)
A11: ='Scenarios_10'!A10 | B11: =MAX(0,'Scenarios_10'!D10-'Scenarios_10'!E10/'Scenarios_10'!B10) | C11: ='Inputs_Data'!B6 | D11: =('Inputs_Data'!B6-(MAX(0,'Scenarios_10'!D10-'Scenarios_10'!E10/'Scenarios_10'!B10))) | E11: =IF('Scenarios_10'!C10="uniform_pct",'Inputs_Data'!E6*(1-MIN('Scenarios_10'!G10,'Assumptions'!B10)),IF('Scenarios_10'!C10="electricity_only_pct",('Inputs_Data'!C6*(1-MIN('Scenarios_10'!G10,'Assumptions'!B10)))+'Inputs_Data'!D6,0+('Inputs_Data'!D6*(1-AVERAGE('Assumptions'!B6,'Assumptions'!B7,'Assumptions'!B8,'Assumptions'!B9))))) | F11: ='Inputs_Data'!E6 | G11: =((MAX(0,'Scenarios_10'!D10-'Scenarios_10'!E10/'Scenarios_10'!B10)-(IF('Scenarios_10'!C10="uniform_pct",'Inputs_Data'!E6*(1-MIN('Scenarios_10'!G10,'Assumptions'!B10)),IF('Scenarios_10'!C10="electricity_only_pct",('Inputs_Data'!C6*(1-MIN('Scenarios_10'!G10,'Assumptions'!B10)))+'Inputs_Data'!D6,0+('Inputs_Data'!D6*(1-AVERAGE('Assumptions'!B6,'Assumptions'!B7,'Assumptions'!B8,'Assumptions'!B9)))))+'Inputs_Data'!F6))-('Inputs_Data'!B6-('Inputs_Data'!E6+'Inputs_Data'!F6))) | H11: =IF((MAX(0,'Scenarios_10'!D10-'Scenarios_10'!E10/'Scenarios_10'!B10)-(IF('Scenarios_10'!C10="uniform_pct",'Inputs_Data'!E6*(1-MIN('Scenarios_10'!G10,'Assumptions'!B10)),IF('Scenarios_10'!C10="electricity_only_pct",('Inputs_Data'!C6*(1-MIN('Scenarios_10'!G10,'Assumptions'!B10)))+'Inputs_Data'!D6,0+('Inputs_Data'!D6*(1-AVERAGE('Assumptions'!B6,'Assumptions'!B7,'Assumptions'!B8,'Assumptions'!B9)))))))<=0,999,ROUNDUP('Inputs_Data'!H5/((MAX(0,'Scenarios_10'!D10-'Scenarios_10'!E10/'Scenarios_10'!B10)-(IF('Scenarios_10'!C10="uniform_pct",'Inputs_Data'!E6*(1-MIN('Scenarios_10'!G10,'Assumptions'!B10)),IF('Scenarios_10'!C10="electricity_only_pct",('Inputs_Data'!C6*(1-MIN('Scenarios_10'!G10,'Assumptions'!B10)))+'Inputs_Data'!D6,0+('Inputs_Data'!D6*(1-AVERAGE('Assumptions'!B6,'Assumptions'!B7,'Assumptions'!B8,'Assumptions'!B9)))))))/12),0)) | I11: =AND(MAX(0,'Scenarios_10'!D10-'Scenarios_10'!E10/'Scenarios_10'!B10)<='Inputs_Data'!B6,((MAX(0,'Scenarios_10'!D10-'Scenarios_10'!E10/'Scenarios_10'!B10)-(IF('Scenarios_10'!C10="uniform_pct",'Inputs_Data'!E6*(1-MIN('Scenarios_10'!G10,'Assumptions'!B10)),IF('Scenarios_10'!C10="electricity_only_pct",('Inputs_Data'!C6*(1-MIN('Scenarios_10'!G10,'Assumptions'!B10)))+'Inputs_Data'!D6,0+('Inputs_Data'!D6*(1-AVERAGE('Assumptions'!B6,'Assumptions'!B7,'Assumptions'!B8,'Assumptions'!B9)))))+'Inputs_Data'!F6))-('Inputs_Data'!B6-('Inputs_Data'!E6+'Inputs_Data'!F6)))>=0,IF((MAX(0,'Scenarios_10'!D10-'Scenarios_10'!E10/'Scenarios_10'!B10)-(IF('Scenarios_10'!C10="uniform_pct",'Inputs_Data'!E6*(1-MIN('Scenarios_10'!G10,'Assumptions'!B10)),IF('Scenarios_10'!C10="electricity_only_pct",('Inputs_Data'!C6*(1-MIN('Scenarios_10'!G10,'Assumptions'!B10)))+'Inputs_Data'!D6,0+('Inputs_Data'!D6*(1-AVERAGE('Assumptions'!B6,'Assumptions'!B7,'Assumptions'!B8,'Assumptions'!B9)))))))<=0,999,ROUNDUP('Inputs_Data'!H5/((MAX(0,'Scenarios_10'!D10-'Scenarios_10'!E10/'Scenarios_10'!B10)-(IF('Scenarios_10'!C10="uniform_pct",'Inputs_Data'!E6*(1-MIN('Scenarios_10'!G10,'Assumptions'!B10)),IF('Scenarios_10'!C10="electricity_only_pct",('Inputs_Data'!C6*(1-MIN('Scenarios_10'!G10,'Assumptions'!B10)))+'Inputs_Data'!D6,0+('Inputs_Data'!D6*(1-AVERAGE('Assumptions'!B6,'Assumptions'!B7,'Assumptions'!B8,'Assumptions'!B9)))))))/12),0))<=36)
A12: ='Scenarios_10'!A11 | B12: =MAX(0,'Scenarios_10'!D11-'Scenarios_10'!E11/'Scenarios_10'!B11) | C12: ='Inputs_Data'!B6 | D12: =('Inputs_Data'!B6-(MAX(0,'Scenarios_10'!D11-'Scenarios_10'!E11/'Scenarios_10'!B11))) | E12: =IF('Scenarios_10'!C11="uniform_pct",'Inputs_Data'!E6*(1-MIN('Scenarios_10'!G11,'Assumptions'!B10)),IF('Scenarios_10'!C11="electricity_only_pct",('Inputs_Data'!C6*(1-MIN('Scenarios_10'!G11,'Assumptions'!B10)))+'Inputs_Data'!D6,0+('Inputs_Data'!D6*(1-AVERAGE('Assumptions'!B6,'Assumptions'!B7,'Assumptions'!B8,'Assumptions'!B9))))) | F12: ='Inputs_Data'!E6 | G12: =((MAX(0,'Scenarios_10'!D11-'Scenarios_10'!E11/'Scenarios_10'!B11)-(IF('Scenarios_10'!C11="uniform_pct",'Inputs_Data'!E6*(1-MIN('Scenarios_10'!G11,'Assumptions'!B10)),IF('Scenarios_10'!C11="electricity_only_pct",('Inputs_Data'!C6*(1-MIN('Scenarios_10'!G11,'Assumptions'!B10)))+'Inputs_Data'!D6,0+('Inputs_Data'!D6*(1-AVERAGE('Assumptions'!B6,'Assumptions'!B7,'Assumptions'!B8,'Assumptions'!B9)))))+'Inputs_Data'!F6))-('Inputs_Data'!B6-('Inputs_Data'!E6+'Inputs_Data'!F6))) | H12: =IF((MAX(0,'Scenarios_10'!D11-'Scenarios_10'!E11/'Scenarios_10'!B11)-(IF('Scenarios_10'!C11="uniform_pct",'Inputs_Data'!E6*(1-MIN('Scenarios_10'!G11,'Assumptions'!B10)),IF('Scenarios_10'!C11="electricity_only_pct",('Inputs_Data'!C6*(1-MIN('Scenarios_10'!G11,'Assumptions'!B10)))+'Inputs_Data'!D6,0+('Inputs_Data'!D6*(1-AVERAGE('Assumptions'!B6,'Assumptions'!B7,'Assumptions'!B8,'Assumptions'!B9)))))))<=0,999,ROUNDUP('Inputs_Data'!H5/((MAX(0,'Scenarios_10'!D11-'Scenarios_10'!E11/'Scenarios_10'!B11)-(IF('Scenarios_10'!C11="uniform_pct",'Inputs_Data'!E6*(1-MIN('Scenarios_10'!G11,'Assumptions'!B10)),IF('Scenarios_10'!C11="electricity_only_pct",('Inputs_Data'!C6*(1-MIN('Scenarios_10'!G11,'Assumptions'!B10)))+'Inputs_Data'!D6,0+('Inputs_Data'!D6*(1-AVERAGE('Assumptions'!B6,'Assumptions'!B7,'Assumptions'!B8,'Assumptions'!B9)))))))/12),0)) | I12: =AND(MAX(0,'Scenarios_10'!D11-'Scenarios_10'!E11/'Scenarios_10'!B11)<='Inputs_Data'!B6,((MAX(0,'Scenarios_10'!D11-'Scenarios_10'!E11/'Scenarios_10'!B11)-(IF('Scenarios_10'!C11="uniform_pct",'Inputs_Data'!E6*(1-MIN('Scenarios_10'!G11,'Assumptions'!B10)),IF('Scenarios_10'!C11="electricity_only_pct",('Inputs_Data'!C6*(1-MIN('Scenarios_10'!G11,'Assumptions'!B10)))+'Inputs_Data'!D6,0+('Inputs_Data'!D6*(1-AVERAGE('Assumptions'!B6,'Assumptions'!B7,'Assumptions'!B8,'Assumptions'!B9)))))+'Inputs_Data'!F6))-('Inputs_Data'!B6-('Inputs_Data'!E6+'Inputs_Data'!F6)))>=0,IF((MAX(0,'Scenarios_10'!D11-'Scenarios_10'!E11/'Scenarios_10'!B11)-(IF('Scenarios_10'!C11="uniform_pct",'Inputs_Data'!E6*(1-MIN('Scenarios_10'!G11,'Assumptions'!B10)),IF('Scenarios_10'!C11="electricity_only_pct",('Inputs_Data'!C6*(1-MIN('Scenarios_10'!G11,'Assumptions'!B10)))+'Inputs_Data'!D6,0+('Inputs_Data'!D6*(1-AVERAGE('Assumptions'!B6,'Assumptions'!B7,'Assumptions'!B8,'Assumptions'!B9)))))))<=0,999,ROUNDUP('Inputs_Data'!H5/((MAX(0,'Scenarios_10'!D11-'Scenarios_10'!E11/'Scenarios_10'!B11)-(IF('Scenarios_10'!C11="uniform_pct",'Inputs_Data'!E6*(1-MIN('Scenarios_10'!G11,'Assumptions'!B10)),IF('Scenarios_10'!C11="electricity_only_pct",('Inputs_Data'!C6*(1-MIN('Scenarios_10'!G11,'Assumptions'!B10)))+'Inputs_Data'!D6,0+('Inputs_Data'!D6*(1-AVERAGE('Assumptions'!B6,'Assumptions'!B7,'Assumptions'!B8,'Assumptions'!B9)))))))/12),0))<=36)
A13: ='Scenarios_10'!A12 | B13: =MAX(0,'Scenarios_10'!D12-'Scenarios_10'!E12/'Scenarios_10'!B12) | C13: ='Inputs_Data'!B6 | D13: =('Inputs_Data'!B6-(MAX(0,'Scenarios_10'!D12-'Scenarios_10'!E12/'Scenarios_10'!B12))) | E13: =IF('Scenarios_10'!C12="uniform_pct",'Inputs_Data'!E6*(1-MIN('Scenarios_10'!G12,'Assumptions'!B10)),IF('Scenarios_10'!C12="electricity_only_pct",('Inputs_Data'!C6*(1-MIN('Scenarios_10'!G12,'Assumptions'!B10)))+'Inputs_Data'!D6,0+('Inputs_Data'!D6*(1-AVERAGE('Assumptions'!B6,'Assumptions'!B7,'Assumptions'!B8,'Assumptions'!B9))))) | F13: ='Inputs_Data'!E6 | G13: =((MAX(0,'Scenarios_10'!D12-'Scenarios_10'!E12/'Scenarios_10'!B12)-(IF('Scenarios_10'!C12="uniform_pct",'Inputs_Data'!E6*(1-MIN('Scenarios_10'!G12,'Assumptions'!B10)),IF('Scenarios_10'!C12="electricity_only_pct",('Inputs_Data'!C6*(1-MIN('Scenarios_10'!G12,'Assumptions'!B10)))+'Inputs_Data'!D6,0+('Inputs_Data'!D6*(1-AVERAGE('Assumptions'!B6,'Assumptions'!B7,'Assumptions'!B8,'Assumptions'!B9)))))+'Inputs_Data'!F6))-('Inputs_Data'!B6-('Inputs_Data'!E6+'Inputs_Data'!F6))) | H13: =IF((MAX(0,'Scenarios_10'!D12-'Scenarios_10'!E12/'Scenarios_10'!B12)-(IF('Scenarios_10'!C12="uniform_pct",'Inputs_Data'!E6*(1-MIN('Scenarios_10'!G12,'Assumptions'!B10)),IF('Scenarios_10'!C12="electricity_only_pct",('Inputs_Data'!C6*(1-MIN('Scenarios_10'!G12,'Assumptions'!B10)))+'Inputs_Data'!D6,0+('Inputs_Data'!D6*(1-AVERAGE('Assumptions'!B6,'Assumptions'!B7,'Assumptions'!B8,'Assumptions'!B9)))))))<=0,999,ROUNDUP('Inputs_Data'!H5/((MAX(0,'Scenarios_10'!D12-'Scenarios_10'!E12/'Scenarios_10'!B12)-(IF('Scenarios_10'!C12="uniform_pct",'Inputs_Data'!E6*(1-MIN('Scenarios_10'!G12,'Assumptions'!B10)),IF('Scenarios_10'!C12="electricity_only_pct",('Inputs_Data'!C6*(1-MIN('Scenarios_10'!G12,'Assumptions'!B10)))+'Inputs_Data'!D6,0+('Inputs_Data'!D6*(1-AVERAGE('Assumptions'!B6,'Assumptions'!B7,'Assumptions'!B8,'Assumptions'!B9)))))))/12),0)) | I13: =AND(MAX(0,'Scenarios_10'!D12-'Scenarios_10'!E12/'Scenarios_10'!B12)<='Inputs_Data'!B6,((MAX(0,'Scenarios_10'!D12-'Scenarios_10'!E12/'Scenarios_10'!B12)-(IF('Scenarios_10'!C12="uniform_pct",'Inputs_Data'!E6*(1-MIN('Scenarios_10'!G12,'Assumptions'!B10)),IF('Scenarios_10'!C12="electricity_only_pct",('Inputs_Data'!C6*(1-MIN('Scenarios_10'!G12,'Assumptions'!B10)))+'Inputs_Data'!D6,0+('Inputs_Data'!D6*(1-AVERAGE('Assumptions'!B6,'Assumptions'!B7,'Assumptions'!B8,'Assumptions'!B9)))))+'Inputs_Data'!F6))-('Inputs_Data'!B6-('Inputs_Data'!E6+'Inputs_Data'!F6)))>=0,IF((MAX(0,'Scenarios_10'!D12-'Scenarios_10'!E12/'Scenarios_10'!B12)-(IF('Scenarios_10'!C12="uniform_pct",'Inputs_Data'!E6*(1-MIN('Scenarios_10'!G12,'Assumptions'!B10)),IF('Scenarios_10'!C12="electricity_only_pct",('Inputs_Data'!C6*(1-MIN('Scenarios_10'!G12,'Assumptions'!B10)))+'Inputs_Data'!D6,0+('Inputs_Data'!D6*(1-AVERAGE('Assumptions'!B6,'Assumptions'!B7,'Assumptions'!B8,'Assumptions'!B9)))))))<=0,999,ROUNDUP('Inputs_Data'!H5/((MAX(0,'Scenarios_10'!D12-'Scenarios_10'!E12/'Scenarios_10'!B12)-(IF('Scenarios_10'!C12="uniform_pct",'Inputs_Data'!E6*(1-MIN('Scenarios_10'!G12,'Assumptions'!B10)),IF('Scenarios_10'!C12="electricity_only_pct",('Inputs_Data'!C6*(1-MIN('Scenarios_10'!G12,'Assumptions'!B10)))+'Inputs_Data'!D6,0+('Inputs_Data'!D6*(1-AVERAGE('Assumptions'!B6,'Assumptions'!B7,'Assumptions'!B8,'Assumptions'!B9)))))))/12),0))<=36)
A14: ='Scenarios_10'!A13 | B14: =MAX(0,'Scenarios_10'!D13-'Scenarios_10'!E13/'Scenarios_10'!B13) | C14: ='Inputs_Data'!B6 | D14: =('Inputs_Data'!B6-(MAX(0,'Scenarios_10'!D13-'Scenarios_10'!E13/'Scenarios_10'!B13))) | E14: =IF('Scenarios_10'!C13="uniform_pct",'Inputs_Data'!E6*(1-MIN('Scenarios_10'!G13,'Assumptions'!B10)),IF('Scenarios_10'!C13="electricity_only_pct",('Inputs_Data'!C6*(1-MIN('Scenarios_10'!G13,'Assumptions'!B10)))+'Inputs_Data'!D6,0+('Inputs_Data'!D6*(1-AVERAGE('Assumptions'!B6,'Assumptions'!B7,'Assumptions'!B8,'Assumptions'!B9))))) | F14: ='Inputs_Data'!E6 | G14: =((MAX(0,'Scenarios_10'!D13-'Scenarios_10'!E13/'Scenarios_10'!B13)-(IF('Scenarios_10'!C13="uniform_pct",'Inputs_Data'!E6*(1-MIN('Scenarios_10'!G13,'Assumptions'!B10)),IF('Scenarios_10'!C13="electricity_only_pct",('Inputs_Data'!C6*(1-MIN('Scenarios_10'!G13,'Assumptions'!B10)))+'Inputs_Data'!D6,0+('Inputs_Data'!D6*(1-AVERAGE('Assumptions'!B6,'Assumptions'!B7,'Assumptions'!B8,'Assumptions'!B9)))))+'Inputs_Data'!F6))-('Inputs_Data'!B6-('Inputs_Data'!E6+'Inputs_Data'!F6))) | H14: =IF((MAX(0,'Scenarios_10'!D13-'Scenarios_10'!E13/'Scenarios_10'!B13)-(IF('Scenarios_10'!C13="uniform_pct",'Inputs_Data'!E6*(1-MIN('Scenarios_10'!G13,'Assumptions'!B10)),IF('Scenarios_10'!C13="electricity_only_pct",('Inputs_Data'!C6*(1-MIN('Scenarios_10'!G13,'Assumptions'!B10)))+'Inputs_Data'!D6,0+('Inputs_Data'!D6*(1-AVERAGE('Assumptions'!B6,'Assumptions'!B7,'Assumptions'!B8,'Assumptions'!B9)))))))<=0,999,ROUNDUP('Inputs_Data'!H5/((MAX(0,'Scenarios_10'!D13-'Scenarios_10'!E13/'Scenarios_10'!B13)-(IF('Scenarios_10'!C13="uniform_pct",'Inputs_Data'!E6*(1-MIN('Scenarios_10'!G13,'Assumptions'!B10)),IF('Scenarios_10'!C13="electricity_only_pct",('Inputs_Data'!C6*(1-MIN('Scenarios_10'!G13,'Assumptions'!B10)))+'Inputs_Data'!D6,0+('Inputs_Data'!D6*(1-AVERAGE('Assumptions'!B6,'Assumptions'!B7,'Assumptions'!B8,'Assumptions'!B9)))))))/12),0)) | I14: =AND(MAX(0,'Scenarios_10'!D13-'Scenarios_10'!E13/'Scenarios_10'!B13)<='Inputs_Data'!B6,((MAX(0,'Scenarios_10'!D13-'Scenarios_10'!E13/'Scenarios_10'!B13)-(IF('Scenarios_10'!C13="uniform_pct",'Inputs_Data'!E6*(1-MIN('Scenarios_10'!G13,'Assumptions'!B10)),IF('Scenarios_10'!C13="electricity_only_pct",('Inputs_Data'!C6*(1-MIN('Scenarios_10'!G13,'Assumptions'!B10)))+'Inputs_Data'!D6,0+('Inputs_Data'!D6*(1-AVERAGE('Assumptions'!B6,'Assumptions'!B7,'Assumptions'!B8,'Assumptions'!B9)))))+'Inputs_Data'!F6))-('Inputs_Data'!B6-('Inputs_Data'!E6+'Inputs_Data'!F6)))>=0,IF((MAX(0,'Scenarios_10'!D13-'Scenarios_10'!E13/'Scenarios_10'!B13)-(IF('Scenarios_10'!C13="uniform_pct",'Inputs_Data'!E6*(1-MIN('Scenarios_10'!G13,'Assumptions'!B10)),IF('Scenarios_10'!C13="electricity_only_pct",('Inputs_Data'!C6*(1-MIN('Scenarios_10'!G13,'Assumptions'!B10)))+'Inputs_Data'!D6,0+('Inputs_Data'!D6*(1-AVERAGE('Assumptions'!B6,'Assumptions'!B7,'Assumptions'!B8,'Assumptions'!B9)))))))<=0,999,ROUNDUP('Inputs_Data'!H5/((MAX(0,'Scenarios_10'!D13-'Scenarios_10'!E13/'Scenarios_10'!B13)-(IF('Scenarios_10'!C13="uniform_pct",'Inputs_Data'!E6*(1-MIN('Scenarios_10'!G13,'Assumptions'!B10)),IF('Scenarios_10'!C13="electricity_only_pct",('Inputs_Data'!C6*(1-MIN('Scenarios_10'!G13,'Assumptions'!B10)))+'Inputs_Data'!D6,0+('Inputs_Data'!D6*(1-AVERAGE('Assumptions'!B6,'Assumptions'!B7,'Assumptions'!B8,'Assumptions'!B9)))))))/12),0))<=36)
A15: ='Scenarios_10'!A14 | B15: =MAX(0,'Scenarios_10'!D14-'Scenarios_10'!E14/'Scenarios_10'!B14) | C15: ='Inputs_Data'!B6 | D15: =('Inputs_Data'!B6-(MAX(0,'Scenarios_10'!D14-'Scenarios_10'!E14/'Scenarios_10'!B14))) | E15: =IF('Scenarios_10'!C14="uniform_pct",'Inputs_Data'!E6*(1-MIN('Scenarios_10'!G14,'Assumptions'!B10)),IF('Scenarios_10'!C14="electricity_only_pct",('Inputs_Data'!C6*(1-MIN('Scenarios_10'!G14,'Assumptions'!B10)))+'Inputs_Data'!D6,0+('Inputs_Data'!D6*(1-AVERAGE('Assumptions'!B6,'Assumptions'!B7,'Assumptions'!B8,'Assumptions'!B9))))) | F15: ='Inputs_Data'!E6 | G15: =((MAX(0,'Scenarios_10'!D14-'Scenarios_10'!E14/'Scenarios_10'!B14)-(IF('Scenarios_10'!C14="uniform_pct",'Inputs_Data'!E6*(1-MIN('Scenarios_10'!G14,'Assumptions'!B10)),IF('Scenarios_10'!C14="electricity_only_pct",('Inputs_Data'!C6*(1-MIN('Scenarios_10'!G14,'Assumptions'!B10)))+'Inputs_Data'!D6,0+('Inputs_Data'!D6*(1-AVERAGE('Assumptions'!B6,'Assumptions'!B7,'Assumptions'!B8,'Assumptions'!B9)))))+'Inputs_Data'!F6))-('Inputs_Data'!B6-('Inputs_Data'!E6+'Inputs_Data'!F6))) | H15: =IF((MAX(0,'Scenarios_10'!D14-'Scenarios_10'!E14/'Scenarios_10'!B14)-(IF('Scenarios_10'!C14="uniform_pct",'Inputs_Data'!E6*(1-MIN('Scenarios_10'!G14,'Assumptions'!B10)),IF('Scenarios_10'!C14="electricity_only_pct",('Inputs_Data'!C6*(1-MIN('Scenarios_10'!G14,'Assumptions'!B10)))+'Inputs_Data'!D6,0+('Inputs_Data'!D6*(1-AVERAGE('Assumptions'!B6,'Assumptions'!B7,'Assumptions'!B8,'Assumptions'!B9)))))))<=0,999,ROUNDUP('Inputs_Data'!H5/((MAX(0,'Scenarios_10'!D14-'Scenarios_10'!E14/'Scenarios_10'!B14)-(IF('Scenarios_10'!C14="uniform_pct",'Inputs_Data'!E6*(1-MIN('Scenarios_10'!G14,'Assumptions'!B10)),IF('Scenarios_10'!C14="electricity_only_pct",('Inputs_Data'!C6*(1-MIN('Scenarios_10'!G14,'Assumptions'!B10)))+'Inputs_Data'!D6,0+('Inputs_Data'!D6*(1-AVERAGE('Assumptions'!B6,'Assumptions'!B7,'Assumptions'!B8,'Assumptions'!B9)))))))/12),0)) | I15: =AND(MAX(0,'Scenarios_10'!D14-'Scenarios_10'!E14/'Scenarios_10'!B14)<='Inputs_Data'!B6,((MAX(0,'Scenarios_10'!D14-'Scenarios_10'!E14/'Scenarios_10'!B14)-(IF('Scenarios_10'!C14="uniform_pct",'Inputs_Data'!E6*(1-MIN('Scenarios_10'!G14,'Assumptions'!B10)),IF('Scenarios_10'!C14="electricity_only_pct",('Inputs_Data'!C6*(1-MIN('Scenarios_10'!G14,'Assumptions'!B10)))+'Inputs_Data'!D6,0+('Inputs_Data'!D6*(1-AVERAGE('Assumptions'!B6,'Assumptions'!B7,'Assumptions'!B8,'Assumptions'!B9)))))+'Inputs_Data'!F6))-('Inputs_Data'!B6-('Inputs_Data'!E6+'Inputs_Data'!F6)))>=0,IF((MAX(0,'Scenarios_10'!D14-'Scenarios_10'!E14/'Scenarios_10'!B14)-(IF('Scenarios_10'!C14="uniform_pct",'Inputs_Data'!E6*(1-MIN('Scenarios_10'!G14,'Assumptions'!B10)),IF('Scenarios_10'!C14="electricity_only_pct",('Inputs_Data'!C6*(1-MIN('Scenarios_10'!G14,'Assumptions'!B10)))+'Inputs_Data'!D6,0+('Inputs_Data'!D6*(1-AVERAGE('Assumptions'!B6,'Assumptions'!B7,'Assumptions'!B8,'Assumptions'!B9)))))))<=0,999,ROUNDUP('Inputs_Data'!H5/((MAX(0,'Scenarios_10'!D14-'Scenarios_10'!E14/'Scenarios_10'!B14)-(IF('Scenarios_10'!C14="uniform_pct",'Inputs_Data'!E6*(1-MIN('Scenarios_10'!G14,'Assumptions'!B10)),IF('Scenarios_10'!C14="electricity_only_pct",('Inputs_Data'!C6*(1-MIN('Scenarios_10'!G14,'Assumptions'!B10)))+'Inputs_Data'!D6,0+('Inputs_Data'!D6*(1-AVERAGE('Assumptions'!B6,'Assumptions'!B7,'Assumptions'!B8,'Assumptions'!B9)))))))/12),0))<=36)
A18: Chart: Client payment vs baseline (Year 1)
A19: Tier | B19: ClientPay_Y1 | C19: BaselinePay_Y1
A20: =Model_Calc!A5 | B20: =Model_Calc!B5 | C20: =Model_Calc!C5
A21: =Model_Calc!A6 | B21: =Model_Calc!B6 | C21: =Model_Calc!C6
A22: =Model_Calc!A7 | B22: =Model_Calc!B7 | C22: =Model_Calc!C7
A23: =Model_Calc!A8 | B23: =Model_Calc!B8 | C23: =Model_Calc!C8
A24: =Model_Calc!A9 | B24: =Model_Calc!B9 | C24: =Model_Calc!C9
A25: =Model_Calc!A10 | B25: =Model_Calc!B10 | C25: =Model_Calc!C10
A26: =Model_Calc!A11 | B26: =Model_Calc!B11 | C26: =Model_Calc!C11
A27: =Model_Calc!A12 | B27: =Model_Calc!B12 | C27: =Model_Calc!C12
A28: =Model_Calc!A13 | B28: =Model_Calc!B13 | C28: =Model_Calc!C13
A29: =Model_Calc!A14 | B29: =Model_Calc!B14 | C29: =Model_Calc!C14

Sheet Scenario_Tables
A1: Scenario cashflow tables (all formulas)
A2: Baseline vs LaaS year-by-year cashflow; same structure for all 10 tiers.
A5: Tier: ='Scenarios_10'!A5
A6: year | B6: trust_capex | C6: trust_fee | D6: trust_cash_opex | E6: trust_net_cf | F6: trust_cum_cf | G6: laas_capex | H6: laas_fee | I6: laas_upfront | J6: laas_cash_opex | K6: laas_net_cf | L6: laas_cum_cf
A7: 0 | B7: =IF(0=0,-'Inputs_Data'!H5,0) | C7: =IF(0=0,0,'Inputs_Data'!B5) | D7: =IF(0=0,0,'Inputs_Data'!E5) | E7: =(IF(0=0,-'Inputs_Data'!H5,0))+(IF(0=0,0,'Inputs_Data'!B5))-(IF(0=0,0,'Inputs_Data'!E5)) | F7: =(0)+(E7) | G7: =IF(0=0,-'Inputs_Data'!H5,0) | H7: =IF(AND(0>=1,0<='Scenarios_10'!B5),MAX(0,(MAX(0,'Scenarios_10'!D5-'Scenarios_10'!E5/'Scenarios_10'!B5))-IF(AND(0>('Scenarios_10'!B5-4),0<='Scenarios_10'!B5),'Scenarios_10'!F5,0)),0) | I7: =IF(0=0,'Scenarios_10'!E5,0) | J7: =IF(0=0,0,IF('Scenarios_10'!C5="uniform_pct",'Inputs_Data'!E5*(1-(MIN('Scenarios_10'!G5,'Assumptions'!B10))),IF('Scenarios_10'!C5="electricity_only_pct",('Inputs_Data'!C5*(1-(MIN('Scenarios_10'!G5,'Assumptions'!B10))))+'Inputs_Data'!D5,0+('Inputs_Data'!D5*(1-AVERAGE('Assumptions'!B6,'Assumptions'!B7,'Assumptions'!B8,'Assumptions'!B9)))))) | K7: =(IF(0=0,-'Inputs_Data'!H5,0))+(IF(AND(0>=1,0<='Scenarios_10'!B5),MAX(0,(MAX(0,'Scenarios_10'!D5-'Scenarios_10'!E5/'Scenarios_10'!B5))-IF(AND(0>('Scenarios_10'!B5-4),0<='Scenarios_10'!B5),'Scenarios_10'!F5,0)),0))+(IF(0=0,'Scenarios_10'!E5,0))-(IF(0=0,0,IF('Scenarios_10'!C5="uniform_pct",'Inputs_Data'!E5*(1-(MIN('Scenarios_10'!G5,'Assumptions'!B10))),IF('Scenarios_10'!C5="electricity_only_pct",('Inputs_Data'!C5*(1-(MIN('Scenarios_10'!G5,'Assumptions'!B10))))+'Inputs_Data'!D5,0+('Inputs_Data'!D5*(1-AVERAGE('Assumptions'!B6,'Assumptions'!B7,'Assumptions'!B8,'Assumptions'!B9))))))) | L7: =(0)+(K7)
A8: 1 | B8: =IF(1=0,-'Inputs_Data'!H5,0) | C8: =IF(1=0,0,'Inputs_Data'!B6) | D8: =IF(1=0,0,'Inputs_Data'!E6) | E8: =(IF(1=0,-'Inputs_Data'!H5,0))+(IF(1=0,0,'Inputs_Data'!B6))-(IF(1=0,0,'Inputs_Data'!E6)) | F8: =(F7)+(E8) | G8: =IF(1=0,-'Inputs_Data'!H5,0) | H8: =IF(AND(1>=1,1<='Scenarios_10'!B5),MAX(0,(MAX(0,'Scenarios_10'!D5-'Scenarios_10'!E5/'Scenarios_10'!B5))-IF(AND(1>('Scenarios_10'!B5-4),1<='Scenarios_10'!B5),'Scenarios_10'!F5,0)),0) | I8: =IF(1=0,'Scenarios_10'!E5,0) | J8: =IF(1=0,0,IF('Scenarios_10'!C5="uniform_pct",'Inputs_Data'!E6*(1-(MIN('Scenarios_10'!G5,'Assumptions'!B10))),IF('Scenarios_10'!C5="electricity_only_pct",('Inputs_Data'!C6*(1-(MIN('Scenarios_10'!G5,'Assumptions'!B10))))+'Inputs_Data'!D6,0+('Inputs_Data'!D6*(1-AVERAGE('Assumptions'!B6,'Assumptions'!B7,'Assumptions'!B8,'Assumptions'!B9)))))) | K8: =(IF(1=0,-'Inputs_Data'!H5,0))+(IF(AND(1>=1,1<='Scenarios_10'!B5),MAX(0,(MAX(0,'Scenarios_10'!D5-'Scenarios_10'!E5/'Scenarios_10'!B5))-IF(AND(1>('Scenarios_10'!B5-4),1<='Scenarios_10'!B5),'Scenarios_10'!F5,0)),0))+(IF(1=0,'Scenarios_10'!E5,0))-(IF(1=0,0,IF('Scenarios_10'!C5="uniform_pct",'Inputs_Data'!E6*(1-(MIN('Scenarios_10'!G5,'Assumptions'!B10))),IF('Scenarios_10'!C5="electricity_only_pct",('Inputs_Data'!C6*(1-(MIN('Scenarios_10'!G5,'Assumptions'!B10))))+'Inputs_Data'!D6,0+('Inputs_Data'!D6*(1-AVERAGE('Assumptions'!B6,'Assumptions'!B7,'Assumptions'!B8,'Assumptions'!B9))))))) | L8: =(L7)+(K8)
A9: 2 | B9: =IF(2=0,-'Inputs_Data'!H5,0) | C9: =IF(2=0,0,'Inputs_Data'!B7) | D9: =IF(2=0,0,'Inputs_Data'!E7) | E9: =(IF(2=0,-'Inputs_Data'!H5,0))+(IF(2=0,0,'Inputs_Data'!B7))-(IF(2=0,0,'Inputs_Data'!E7)) | F9: =(F8)+(E9) | G9: =IF(2=0,-'Inputs_Data'!H5,0) | H9: =IF(AND(2>=1,2<='Scenarios_10'!B5),MAX(0,(MAX(0,'Scenarios_10'!D5-'Scenarios_10'!E5/'Scenarios_10'!B5))-IF(AND(2>('Scenarios_10'!B5-4),2<='Scenarios_10'!B5),'Scenarios_10'!F5,0)),0) | I9: =IF(2=0,'Scenarios_10'!E5,0) | J9: =IF(2=0,0,IF('Scenarios_10'!C5="uniform_pct",'Inputs_Data'!E7*(1-(MIN('Scenarios_10'!G5,'Assumptions'!B10))),IF('Scenarios_10'!C5="electricity_only_pct",('Inputs_Data'!C7*(1-(MIN('Scenarios_10'!G5,'Assumptions'!B10))))+'Inputs_Data'!D7,0+('Inputs_Data'!D7*(1-AVERAGE('Assumptions'!B6,'Assumptions'!B7,'Assumptions'!B8,'Assumptions'!B9)))))) | K9: =(IF(2=0,-'Inputs_Data'!H5,0))+(IF(AND(2>=1,2<='Scenarios_10'!B5),MAX(0,(MAX(0,'Scenarios_10'!D5-'Scenarios_10'!E5/'Scenarios_10'!B5))-IF(AND(2>('Scenarios_10'!B5-4),2<='Scenarios_10'!B5),'Scenarios_10'!F5,0)),0))+(IF(2=0,'Scenarios_10'!E5,0))-(IF(2=0,0,IF('Scenarios_10'!C5="uniform_pct",'Inputs_Data'!E7*(1-(MIN('Scenarios_10'!G5,'Assumptions'!B10))),IF('Scenarios_10'!C5="electricity_only_pct",('Inputs_Data'!C7*(1-(MIN('Scenarios_10'!G5,'Assumptions'!B10))))+'Inputs_Data'!D7,0+('Inputs_Data'!D7*(1-AVERAGE('Assumptions'!B6,'Assumptions'!B7,'Assumptions'!B8,'Assumptions'!B9))))))) | L9: =(L8)+(K9)
A10: 3 | B10: =IF(3=0,-'Inputs_Data'!H5,0) | C10: =IF(3=0,0,'Inputs_Data'!B8) | D10: =IF(3=0,0,'Inputs_Data'!E8) | E10: =(IF(3=0,-'Inputs_Data'!H5,0))+(IF(3=0,0,'Inputs_Data'!B8))-(IF(3=0,0,'Inputs_Data'!E8)) | F10: =(F9)+(E10) | G10: =IF(3=0,-'Inputs_Data'!H5,0) | H10: =IF(AND(3>=1,3<='Scenarios_10'!B5),MAX(0,(MAX(0,'Scenarios_10'!D5-'Scenarios_10'!E5/'Scenarios_10'!B5))-IF(AND(3>('Scenarios_10'!B5-4),3<='Scenarios_10'!B5),'Scenarios_10'!F5,0)),0) | I10: =IF(3=0,'Scenarios_10'!E5,0) | J10: =IF(3=0,0,IF('Scenarios_10'!C5="uniform_pct",'Inputs_Data'!E8*(1-(MIN('Scenarios_10'!G5,'Assumptions'!B10))),IF('Scenarios_10'!C5="electricity_only_pct",('Inputs_Data'!C8*(1-(MIN('Scenarios_10'!G5,'Assumptions'!B10))))+'Inputs_Data'!D8,0+('Inputs_Data'!D8*(1-AVERAGE('Assumptions'!B6,'Assumptions'!B7,'Assumptions'!B8,'Assumptions'!B9)))))) | K10: =(IF(3=0,-'Inputs_Data'!H5,0))+(IF(AND(3>=1,3<='Scenarios_10'!B5),MAX(0,(MAX(0,'Scenarios_10'!D5-'Scenarios_10'!E5/'Scenarios_10'!B5))-IF(AND(3>('Scenarios_10'!B5-4),3<='Scenarios_10'!B5),'Scenarios_10'!F5,0)),0))+(IF(3=0,'Scenarios_10'!E5,0))-(IF(3=0,0,IF('Scenarios_10'!C5="uniform_pct",'Inputs_Data'!E8*(1-(MIN('Scenarios_10'!G5,'Assumptions'!B10))),IF('Scenarios_10'!C5="electricity_only_pct",('Inputs_Data'!C8*(1-(MIN('Scenarios_10'!G5,'Assumptions'!B10))))+'Inputs_Data'!D8,0+('Inputs_Data'!D8*(1-AVERAGE('Assumptions'!B6,'Assumptions'!B7,'Assumptions'!B8,'Assumptions'!B9))))))) | L10: =(L9)+(K10)
A11: 4 | B11: =IF(4=0,-'Inputs_Data'!H5,0) | C11: =IF(4=0,0,'Inputs_Data'!B9) | D11: =IF(4=0,0,'Inputs_Data'!E9) | E11: =(IF(4=0,-'Inputs_Data'!H5,0))+(IF(4=0,0,'Inputs_Data'!B9))-(IF(4=0,0,'Inputs_Data'!E9)) | F11: =(F10)+(E11) | G11: =IF(4=0,-'Inputs_Data'!H5,0) | H11: =IF(AND(4>=1,4<='Scenarios_10'!B5),MAX(0,(MAX(0,'Scenarios_10'!D5-'Scenarios_10'!E5/'Scenarios_10'!B5))-IF(AND(4>('Scenarios_10'!B5-4),4<='Scenarios_10'!B5),'Scenarios_10'!F5,0)),0) | I11: =IF(4=0,'Scenarios_10'!E5,0) | J11: =IF(4=0,0,IF('Scenarios_10'!C5="uniform_pct",'Inputs_Data'!E9*(1-(MIN('Scenarios_10'!G5,'Assumptions'!B10))),IF('Scenarios_10'!C5="electricity_only_pct",('Inputs_Data'!C9*(1-(MIN('Scenarios_10'!G5,'Assumptions'!B10))))+'Inputs_Data'!D9,0+('Inputs_Data'!D9*(1-AVERAGE('Assumptions'!B6,'Assumptions'!B7,'Assumptions'!B8,'Assumptions'!B9)))))) | K11: =(IF(4=0,-'Inputs_Data'!H5,0))+(IF(AND(4>=1,4<='Scenarios_10'!B5),MAX(0,(MAX(0,'Scenarios_10'!D5-'Scenarios_10'!E5/'Scenarios_10'!B5))-IF(AND(4>('Scenarios_10'!B5-4),4<='Scenarios_10'!B5),'Scenarios_10'!F5,0)),0))+(IF(4=0,'Scenarios_10'!E5,0))-(IF(4=0,0,IF('Scenarios_10'!C5="uniform_pct",'Inputs_Data'!E9*(1-(MIN('Scenarios_10'!G5,'Assumptions'!B10))),IF('Scenarios_10'!C5="electricity_only_pct",('Inputs_Data'!C9*(1-(MIN('Scenarios_10'!G5,'Assumptions'!B10))))+'Inputs_Data'!D9,0+('Inputs_Data'!D9*(1-AVERAGE('Assumptions'!B6,'Assumptions'!B7,'Assumptions'!B8,'Assumptions'!B9))))))) | L11: =(L10)+(K11)
A12: 5 | B12: =IF(5=0,-'Inputs_Data'!H5,0) | C12: =IF(5=0,0,'Inputs_Data'!B10) | D12: =IF(5=0,0,'Inputs_Data'!E10) | E12: =(IF(5=0,-'Inputs_Data'!H5,0))+(IF(5=0,0,'Inputs_Data'!B10))-(IF(5=0,0,'Inputs_Data'!E10)) | F12: =(F11)+(E12) | G12: =IF(5=0,-'Inputs_Data'!H5,0) | H12: =IF(AND(5>=1,5<='Scenarios_10'!B5),MAX(0,(MAX(0,'Scenarios_10'!D5-'Scenarios_10'!E5/'Scenarios_10'!B5))-IF(AND(5>('Scenarios_10'!B5-4),5<='Scenarios_10'!B5),'Scenarios_10'!F5,0)),0) | I12: =IF(5=0,'Scenarios_10'!E5,0) | J12: =IF(5=0,0,IF('Scenarios_10'!C5="uniform_pct",'Inputs_Data'!E10*(1-(MIN('Scenarios_10'!G5,'Assumptions'!B10))),IF('Scenarios_10'!C5="electricity_only_pct",('Inputs_Data'!C10*(1-(MIN('Scenarios_10'!G5,'Assumptions'!B10))))+'Inputs_Data'!D10,0+('Inputs_Data'!D10*(1-AVERAGE('Assumptions'!B6,'Assumptions'!B7,'Assumptions'!B8,'Assumptions'!B9)))))) | K12: =(IF(5=0,-'Inputs_Data'!H5,0))+(IF(AND(5>=1,5<='Scenarios_10'!B5),MAX(0,(MAX(0,'Scenarios_10'!D5-'Scenarios_10'!E5/'Scenarios_10'!B5))-IF(AND(5>('Scenarios_10'!B5-4),5<='Scenarios_10'!B5),'Scenarios_10'!F5,0)),0))+(IF(5=0,'Scenarios_10'!E5,0))-(IF(5=0,0,IF('Scenarios_10'!C5="uniform_pct",'Inputs_Data'!E10*(1-(MIN('Scenarios_10'!G5,'Assumptions'!B10))),IF('Scenarios_10'!C5="electricity_only_pct",('Inputs_Data'!C10*(1-(MIN('Scenarios_10'!G5,'Assumptions'!B10))))+'Inputs_Data'!D10,0+('Inputs_Data'!D10*(1-AVERAGE('Assumptions'!B6,'Assumptions'!B7,'Assumptions'!B8,'Assumptions'!B9))))))) | L12: =(L11)+(K12)
A13: 6 | B13: =IF(6=0,-'Inputs_Data'!H5,0) | C13: =IF(6=0,0,'Inputs_Data'!B11) | D13: =IF(6=0,0,'Inputs_Data'!E11) | E13: =(IF(6=0,-'Inputs_Data'!H5,0))+(IF(6=0,0,'Inputs_Data'!B11))-(IF(6=0,0,'Inputs_Data'!E11)) | F13: =(F12)+(E13) | G13: =IF(6=0,-'Inputs_Data'!H5,0) | H13: =IF(AND(6>=1,6<='Scenarios_10'!B5),MAX(0,(MAX(0,'Scenarios_10'!D5-'Scenarios_10'!E5/'Scenarios_10'!B5))-IF(AND(6>('Scenarios_10'!B5-4),6<='Scenarios_10'!B5),'Scenarios_10'!F5,0)),0) | I13: =IF(6=0,'Scenarios_10'!E5,0) | J13: =IF(6=0,0,IF('Scenarios_10'!C5="uniform_pct",'Inputs_Data'!E11*(1-(MIN('Scenarios_10'!G5,'Assumptions'!B10))),IF('Scenarios_10'!C5="electricity_only_pct",('Inputs_Data'!C11*(1-(MIN('Scenarios_10'!G5,'Assumptions'!B10))))+'Inputs_Data'!D11,0+('Inputs_Data'!D11*(1-AVERAGE('Assumptions'!B6,'Assumptions'!B7,'Assumptions'!B8,'Assumptions'!B9)))))) | K13: =(IF(6=0,-'Inputs_Data'!H5,0))+(IF(AND(6>=1,6<='Scenarios_10'!B5),MAX(0,(MAX(0,'Scenarios_10'!D5-'Scenarios_10'!E5/'Scenarios_10'!B5))-IF(AND(6>('Scenarios_10'!B5-4),6<='Scenarios_10'!B5),'Scenarios_10'!F5,0)),0))+(IF(6=0,'Scenarios_10'!E5,0))-(IF(6=0,0,IF('Scenarios_10'!C5="uniform_pct",'Inputs_Data'!E11*(1-(MIN('Scenarios_10'!G5,'Assumptions'!B10))),IF('Scenarios_10'!C5="electricity_only_pct",('Inputs_Data'!C11*(1-(MIN('Scenarios_10'!G5,'Assumptions'!B10))))+'Inputs_Data'!D11,0+('Inputs_Data'!D11*(1-AVERAGE('Assumptions'!B6,'Assumptions'!B7,'Assumptions'!B8,'Assumptions'!B9))))))) | L13: =(L12)+(K13)
A14: 7 | B14: =IF(7=0,-'Inputs_Data'!H5,0) | C14: =IF(7=0,0,'Inputs_Data'!B12) | D14: =IF(7=0,0,'Inputs_Data'!E12) | E14: =(IF(7=0,-'Inputs_Data'!H5,0))+(IF(7=0,0,'Inputs_Data'!B12))-(IF(7=0,0,'Inputs_Data'!E12)) | F14: =(F13)+(E14) | G14: =IF(7=0,-'Inputs_Data'!H5,0) | H14: =IF(AND(7>=1,7<='Scenarios_10'!B5),MAX(0,(MAX(0,'Scenarios_10'!D5-'Scenarios_10'!E5/'Scenarios_10'!B5))-IF(AND(7>('Scenarios_10'!B5-4),7<='Scenarios_10'!B5),'Scenarios_10'!F5,0)),0) | I14: =IF(7=0,'Scenarios_10'!E5,0) | J14: =IF(7=0,0,IF('Scenarios_10'!C5="uniform_pct",'Inputs_Data'!E12*(1-(MIN('Scenarios_10'!G5,'Assumptions'!B10))),IF('Scenarios_10'!C5="electricity_only_pct",('Inputs_Data'!C12*(1-(MIN('Scenarios_10'!G5,'Assumptions'!B10))))+'Inputs_Data'!D12,0+('Inputs_Data'!D12*(1-AVERAGE('Assumptions'!B6,'Assumptions'!B7,'Assumptions'!B8,'Assumptions'!B9)))))) | K14: =(IF(7=0,-'Inputs_Data'!H5,0))+(IF(AND(7>=1,7<='Scenarios_10'!B5),MAX(0,(MAX(0,'Scenarios_10'!D5-'Scenarios_10'!E5/'Scenarios_10'!B5))-IF(AND(7>('Scenarios_10'!B5-4),7<='Scenarios_10'!B5),'Scenarios_10'!F5,0)),0))+(IF(7=0,'Scenarios_10'!E5,0))-(IF(7=0,0,IF('Scenarios_10'!C5="uniform_pct",'Inputs_Data'!E12*(1-(MIN('Scenarios_10'!G5,'Assumptions'!B10))),IF('Scenarios_10'!C5="electricity_only_pct",('Inputs_Data'!C12*(1-(MIN('Scenarios_10'!G5,'Assumptions'!B10))))+'Inputs_Data'!D12,0+('Inputs_Data'!D12*(1-AVERAGE('Assumptions'!B6,'Assumptions'!B7,'Assumptions'!B8,'Assumptions'!B9))))))) | L14: =(L13)+(K14)
A15: 8 | B15: =IF(8=0,-'Inputs_Data'!H5,0) | C15: =IF(8=0,0,'Inputs_Data'!B13) | D15: =IF(8=0,0,'Inputs_Data'!E13) | E15: =(IF(8=0,-'Inputs_Data'!H5,0))+(IF(8=0,0,'Inputs_Data'!B13))-(IF(8=0,0,'Inputs_Data'!E13)) | F15: =(F14)+(E15) | G15: =IF(8=0,-'Inputs_Data'!H5,0) | H15: =IF(AND(8>=1,8<='Scenarios_10'!B5),MAX(0,(MAX(0,'Scenarios_10'!D5-'Scenarios_10'!E5/'Scenarios_10'!B5))-IF(AND(8>('Scenarios_10'!B5-4),8<='Scenarios_10'!B5),'Scenarios_10'!F5,0)),0) | I15: =IF(8=0,'Scenarios_10'!E5,0) | J15: =IF(8=0,0,IF('Scenarios_10'!C5="uniform_pct",'Inputs_Data'!E13*(1-(MIN('Scenarios_10'!G5,'Assumptions'!B10))),IF('Scenarios_10'!C5="electricity_only_pct",('Inputs_Data'!C13*(1-(MIN('Scenarios_10'!G5,'Assumptions'!B10))))+'Inputs_Data'!D13,0+('Inputs_Data'!D13*(1-AVERAGE('Assumptions'!B6,'Assumptions'!B7,'Assumptions'!B8,'Assumptions'!B9)))))) | K15: =(IF(8=0,-'Inputs_Data'!H5,0))+(IF(AND(8>=1,8<='Scenarios_10'!B5),MAX(0,(MAX(0,'Scenarios_10'!D5-'Scenarios_10'!E5/'Scenarios_10'!B5))-IF(AND(8>('Scenarios_10'!B5-4),8<='Scenarios_10'!B5),'Scenarios_10'!F5,0)),0))+(IF(8=0,'Scenarios_10'!E5,0))-(IF(8=0,0,IF('Scenarios_10'!C5="uniform_pct",'Inputs_Data'!E13*(1-(MIN('Scenarios_10'!G5,'Assumptions'!B10))),IF('Scenarios_10'!C5="electricity_only_pct",('Inputs_Data'!C13*(1-(MIN('Scenarios_10'!G5,'Assumptions'!B10))))+'Inputs_Data'!D13,0+('Inputs_Data'!D13*(1-AVERAGE('Assumptions'!B6,'Assumptions'!B7,'Assumptions'!B8,'Assumptions'!B9))))))) | L15: =(L14)+(K15)
A16: 9 | B16: =IF(9=0,-'Inputs_Data'!H5,0) | C16: =IF(9=0,0,'Inputs_Data'!B14) | D16: =IF(9=0,0,'Inputs_Data'!E14) | E16: =(IF(9=0,-'Inputs_Data'!H5,0))+(IF(9=0,0,'Inputs_Data'!B14))-(IF(9=0,0,'Inputs_Data'!E14)) | F16: =(F15)+(E16) | G16: =IF(9=0,-'Inputs_Data'!H5,0) | H16: =IF(AND(9>=1,9<='Scenarios_10'!B5),MAX(0,(MAX(0,'Scenarios_10'!D5-'Scenarios_10'!E5/'Scenarios_10'!B5))-IF(AND(9>('Scenarios_10'!B5-4),9<='Scenarios_10'!B5),'Scenarios_10'!F5,0)),0) | I16: =IF(9=0,'Scenarios_10'!E5,0) | J16: =IF(9=0,0,IF('Scenarios_10'!C5="uniform_pct",'Inputs_Data'!E14*(1-(MIN('Scenarios_10'!G5,'Assumptions'!B10))),IF('Scenarios_10'!C5="electricity_only_pct",('Inputs_Data'!C14*(1-(MIN('Scenarios_10'!G5,'Assumptions'!B10))))+'Inputs_Data'!D14,0+('Inputs_Data'!D14*(1-AVERAGE('Assumptions'!B6,'Assumptions'!B7,'Assumptions'!B8,'Assumptions'!B9)))))) | K16: =(IF(9=0,-'Inputs_Data'!H5,0))+(IF(AND(9>=1,9<='Scenarios_10'!B5),MAX(0,(MAX(0,'Scenarios_10'!D5-'Scenarios_10'!E5/'Scenarios_10'!B5))-IF(AND(9>('Scenarios_10'!B5-4),9<='Scenarios_10'!B5),'Scenarios_10'!F5,0)),0))+(IF(9=0,'Scenarios_10'!E5,0))-(IF(9=0,0,IF('Scenarios_10'!C5="uniform_pct",'Inputs_Data'!E14*(1-(MIN('Scenarios_10'!G5,'Assumptions'!B10))),IF('Scenarios_10'!C5="electricity_only_pct",('Inputs_Data'!C14*(1-(MIN('Scenarios_10'!G5,'Assumptions'!B10))))+'Inputs_Data'!D14,0+('Inputs_Data'!D14*(1-AVERAGE('Assumptions'!B6,'Assumptions'!B7,'Assumptions'!B8,'Assumptions'!B9))))))) | L16: =(L15)+(K16)
A17: 10 | B17: =IF(10=0,-'Inputs_Data'!H5,0) | C17: =IF(10=0,0,'Inputs_Data'!B15) | D17: =IF(10=0,0,'Inputs_Data'!E15) | E17: =(IF(10=0,-'Inputs_Data'!H5,0))+(IF(10=0,0,'Inputs_Data'!B15))-(IF(10=0,0,'Inputs_Data'!E15)) | F17: =(F16)+(E17) | G17: =IF(10=0,-'Inputs_Data'!H5,0) | H17: =IF(AND(10>=1,10<='Scenarios_10'!B5),MAX(0,(MAX(0,'Scenarios_10'!D5-'Scenarios_10'!E5/'Scenarios_10'!B5))-IF(AND(10>('Scenarios_10'!B5-4),10<='Scenarios_10'!B5),'Scenarios_10'!F5,0)),0) | I17: =IF(10=0,'Scenarios_10'!E5,0) | J17: =IF(10=0,0,IF('Scenarios_10'!C5="uniform_pct",'Inputs_Data'!E15*(1-(MIN('Scenarios_10'!G5,'Assumptions'!B10))),IF('Scenarios_10'!C5="electricity_only_pct",('Inputs_Data'!C15*(1-(MIN('Scenarios_10'!G5,'Assumptions'!B10))))+'Inputs_Data'!D15,0+('Inputs_Data'!D15*(1-AVERAGE('Assumptions'!B6,'Assumptions'!B7,'Assumptions'!B8,'Assumptions'!B9)))))) | K17: =(IF(10=0,-'Inputs_Data'!H5,0))+(IF(AND(10>=1,10<='Scenarios_10'!B5),MAX(0,(MAX(0,'Scenarios_10'!D5-'Scenarios_10'!E5/'Scenarios_10'!B5))-IF(AND(10>('Scenarios_10'!B5-4),10<='Scenarios_10'!B5),'Scenarios_10'!F5,0)),0))+(IF(10=0,'Scenarios_10'!E5,0))-(IF(10=0,0,IF('Scenarios_10'!C5="uniform_pct",'Inputs_Data'!E15*(1-(MIN('Scenarios_10'!G5,'Assumptions'!B10))),IF('Scenarios_10'!C5="electricity_only_pct",('Inputs_Data'!C15*(1-(MIN('Scenarios_10'!G5,'Assumptions'!B10))))+'Inputs_Data'!D15,0+('Inputs_Data'!D15*(1-AVERAGE('Assumptions'!B6,'Assumptions'!B7,'Assumptions'!B8,'Assumptions'!B9))))))) | L17: =(L16)+(K17)
A20: Tier: ='Scenarios_10'!A6
A21: year | B21: trust_capex | C21: trust_fee | D21: trust_cash_opex | E21: trust_net_cf | F21: trust_cum_cf | G21: laas_capex | H21: laas_fee | I21: laas_upfront | J21: laas_cash_opex | K21: laas_net_cf | L21: laas_cum_cf
A22: 0 | B22: =IF(0=0,-'Inputs_Data'!H5,0) | C22: =IF(0=0,0,'Inputs_Data'!B5) | D22: =IF(0=0,0,'Inputs_Data'!E5) | E22: =(IF(0=0,-'Inputs_Data'!H5,0))+(IF(0=0,0,'Inputs_Data'!B5))-(IF(0=0,0,'Inputs_Data'!E5)) | F22: =(0)+(E22) | G22: =IF(0=0,-'Inputs_Data'!H5,0) | H22: =IF(AND(0>=1,0<='Scenarios_10'!B6),MAX(0,(MAX(0,'Scenarios_10'!D6-'Scenarios_10'!E6/'Scenarios_10'!B6))-IF(AND(0>('Scenarios_10'!B6-4),0<='Scenarios_10'!B6),'Scenarios_10'!F6,0)),0) | I22: =IF(0=0,'Scenarios_10'!E6,0) | J22: =IF(0=0,0,IF('Scenarios_10'!C6="uniform_pct",'Inputs_Data'!E5*(1-(MIN('Scenarios_10'!G6,'Assumptions'!B10))),IF('Scenarios_10'!C6="electricity_only_pct",('Inputs_Data'!C5*(1-(MIN('Scenarios_10'!G6,'Assumptions'!B10))))+'Inputs_Data'!D5,0+('Inputs_Data'!D5*(1-AVERAGE('Assumptions'!B6,'Assumptions'!B7,'Assumptions'!B8,'Assumptions'!B9)))))) | K22: =(IF(0=0,-'Inputs_Data'!H5,0))+(IF(AND(0>=1,0<='Scenarios_10'!B6),MAX(0,(MAX(0,'Scenarios_10'!D6-'Scenarios_10'!E6/'Scenarios_10'!B6))-IF(AND(0>('Scenarios_10'!B6-4),0<='Scenarios_10'!B6),'Scenarios_10'!F6,0)),0))+(IF(0=0,'Scenarios_10'!E6,0))-(IF(0=0,0,IF('Scenarios_10'!C6="uniform_pct",'Inputs_Data'!E5*(1-(MIN('Scenarios_10'!G6,'Assumptions'!B10))),IF('Scenarios_10'!C6="electricity_only_pct",('Inputs_Data'!C5*(1-(MIN('Scenarios_10'!G6,'Assumptions'!B10))))+'Inputs_Data'!D5,0+('Inputs_Data'!D5*(1-AVERAGE('Assumptions'!B6,'Assumptions'!B7,'Assumptions'!B8,'Assumptions'!B9))))))) | L22: =(0)+(K22)
A23: 1 | B23: =IF(1=0,-'Inputs_Data'!H5,0) | C23: =IF(1=0,0,'Inputs_Data'!B6) | D23: =IF(1=0,0,'Inputs_Data'!E6) | E23: =(IF(1=0,-'Inputs_Data'!H5,0))+(IF(1=0,0,'Inputs_Data'!B6))-(IF(1=0,0,'Inputs_Data'!E6)) | F23: =(F22)+(E23) | G23: =IF(1=0,-'Inputs_Data'!H5,0) | H23: =IF(AND(1>=1,1<='Scenarios_10'!B6),MAX(0,(MAX(0,'Scenarios_10'!D6-'Scenarios_10'!E6/'Scenarios_10'!B6))-IF(AND(1>('Scenarios_10'!B6-4),1<='Scenarios_10'!B6),'Scenarios_10'!F6,0)),0) | I23: =IF(1=0,'Scenarios_10'!E6,0) | J23: =IF(1=0,0,IF('Scenarios_10'!C6="uniform_pct",'Inputs_Data'!E6*(1-(MIN('Scenarios_10'!G6,'Assumptions'!B10))),IF('Scenarios_10'!C6="electricity_only_pct",('Inputs_Data'!C6*(1-(MIN('Scenarios_10'!G6,'Assumptions'!B10))))+'Inputs_Data'!D6,0+('Inputs_Data'!D6*(1-AVERAGE('Assumptions'!B6,'Assumptions'!B7,'Assumptions'!B8,'Assumptions'!B9)))))) | K23: =(IF(1=0,-'Inputs_Data'!H5,0))+(IF(AND(1>=1,1<='Scenarios_10'!B6),MAX(0,(MAX(0,'Scenarios_10'!D6-'Scenarios_10'!E6/'Scenarios_10'!B6))-IF(AND(1>('Scenarios_10'!B6-4),1<='Scenarios_10'!B6),'Scenarios_10'!F6,0)),0))+(IF(1=0,'Scenarios_10'!E6,0))-(IF(1=0,0,IF('Scenarios_10'!C6="uniform_pct",'Inputs_Data'!E6*(1-(MIN('Scenarios_10'!G6,'Assumptions'!B10))),IF('Scenarios_10'!C6="electricity_only_pct",('Inputs_Data'!C6*(1-(MIN('Scenarios_10'!G6,'Assumptions'!B10))))+'Inputs_Data'!D6,0+('Inputs_Data'!D6*(1-AVERAGE('Assumptions'!B6,'Assumptions'!B7,'Assumptions'!B8,'Assumptions'!B9))))))) | L23: =(L22)+(K23)
A24: 2 | B24: =IF(2=0,-'Inputs_Data'!H5,0) | C24: =IF(2=0,0,'Inputs_Data'!B7) | D24: =IF(2=0,0,'Inputs_Data'!E7) | E24: =(IF(2=0,-'Inputs_Data'!H5,0))+(IF(2=0,0,'Inputs_Data'!B7))-(IF(2=0,0,'Inputs_Data'!E7)) | F24: =(F23)+(E24) | G24: =IF(2=0,-'Inputs_Data'!H5,0) | H24: =IF(AND(2>=1,2<='Scenarios_10'!B6),MAX(0,(MAX(0,'Scenarios_10'!D6-'Scenarios_10'!E6/'Scenarios_10'!B6))-IF(AND(2>('Scenarios_10'!B6-4),2<='Scenarios_10'!B6),'Scenarios_10'!F6,0)),0) | I24: =IF(2=0,'Scenarios_10'!E6,0) | J24: =IF(2=0,0,IF('Scenarios_10'!C6="uniform_pct",'Inputs_Data'!E7*(1-(MIN('Scenarios_10'!G6,'Assumptions'!B10))),IF('Scenarios_10'!C6="electricity_only_pct",('Inputs_Data'!C7*(1-(MIN('Scenarios_10'!G6,'Assumptions'!B10))))+'Inputs_Data'!D7,0+('Inputs_Data'!D7*(1-AVERAGE('Assumptions'!B6,'Assumptions'!B7,'Assumptions'!B8,'Assumptions'!B9)))))) | K24: =(IF(2=0,-'Inputs_Data'!H5,0))+(IF(AND(2>=1,2<='Scenarios_10'!B6),MAX(0,(MAX(0,'Scenarios_10'!D6-'Scenarios_10'!E6/'Scenarios_10'!B6))-IF(AND(2>('Scenarios_10'!B6-4),2<='Scenarios_10'!B6),'Scenarios_10'!F6,0)),0))+(IF(2=0,'Scenarios_10'!E6,0))-(IF(2=0,0,IF('Scenarios_10'!C6="uniform_pct",'Inputs_Data'!E7*(1-(MIN('Scenarios_10'!G6,'Assumptions'!B10))),IF('Scenarios_10'!C6="electricity_only_pct",('Inputs_Data'!C7*(1-(MIN('Scenarios_10'!G6,'Assumptions'!B10))))+'Inputs_Data'!D7,0+('Inputs_Data'!D7*(1-AVERAGE('Assumptions'!B6,'Assumptions'!B7,'Assumptions'!B8,'Assumptions'!B9))))))) | L24: =(L23)+(K24)
A25: 3 | B25: =IF(3=0,-'Inputs_Data'!H5,0) | C25: =IF(3=0,0,'Inputs_Data'!B8) | D25: =IF(3=0,0,'Inputs_Data'!E8) | E25: =(IF(3=0,-'Inputs_Data'!H5,0))+(IF(3=0,0,'Inputs_Data'!B8))-(IF(3=0,0,'Inputs_Data'!E8)) | F25: =(F24)+(E25) | G25: =IF(3=0,-'Inputs_Data'!H5,0) | H25: =IF(AND(3>=1,3<='Scenarios_10'!B6),MAX(0,(MAX(0,'Scenarios_10'!D6-'Scenarios_10'!E6/'Scenarios_10'!B6))-IF(AND(3>('Scenarios_10'!B6-4),3<='Scenarios_10'!B6),'Scenarios_10'!F6,0)),0) | I25: =IF(3=0,'Scenarios_10'!E6,0) | J25: =IF(3=0,0,IF('Scenarios_10'!C6="uniform_pct",'Inputs_Data'!E8*(1-(MIN('Scenarios_10'!G6,'Assumptions'!B10))),IF('Scenarios_10'!C6="electricity_only_pct",('Inputs_Data'!C8*(1-(MIN('Scenarios_10'!G6,'Assumptions'!B10))))+'Inputs_Data'!D8,0+('Inputs_Data'!D8*(1-AVERAGE('Assumptions'!B6,'Assumptions'!B7,'Assumptions'!B8,'Assumptions'!B9)))))) | K25: =(IF(3=0,-'Inputs_Data'!H5,0))+(IF(AND(3>=1,3<='Scenarios_10'!B6),MAX(0,(MAX(0,'Scenarios_10'!D6-'Scenarios_10'!E6/'Scenarios_10'!B6))-IF(AND(3>('Scenarios_10'!B6-4),3<='Scenarios_10'!B6),'Scenarios_10'!F6,0)),0))+(IF(3=0,'Scenarios_10'!E6,0))-(IF(3=0,0,IF('Scenarios_10'!C6="uniform_pct",'Inputs_Data'!E8*(1-(MIN('Scenarios_10'!G6,'Assumptions'!B10))),IF('Scenarios_10'!C6="electricity_only_pct",('Inputs_Data'!C8*(1-(MIN('Scenarios_10'!G6,'Assumptions'!B10))))+'Inputs_Data'!D8,0+('Inputs_Data'!D8*(1-AVERAGE('Assumptions'!B6,'Assumptions'!B7,'Assumptions'!B8,'Assumptions'!B9))))))) | L25: =(L24)+(K25)
A26: 4 | B26: =IF(4=0,-'Inputs_Data'!H5,0) | C26: =IF(4=0,0,'Inputs_Data'!B9) | D26: =IF(4=0,0,'Inputs_Data'!E9) | E26: =(IF(4=0,-'Inputs_Data'!H5,0))+(IF(4=0,0,'Inputs_Data'!B9))-(IF(4=0,0,'Inputs_Data'!E9)) | F26: =(F25)+(E26) | G26: =IF(4=0,-'Inputs_Data'!H5,0) | H26: =IF(AND(4>=1,4<='Scenarios_10'!B6),MAX(0,(MAX(0,'Scenarios_10'!D6-'Scenarios_10'!E6/'Scenarios_10'!B6))-IF(AND(4>('Scenarios_10'!B6-4),4<='Scenarios_10'!B6),'Scenarios_10'!F6,0)),0) | I26: =IF(4=0,'Scenarios_10'!E6,0) | J26: =IF(4=0,0,IF('Scenarios_10'!C6="uniform_pct",'Inputs_Data'!E9*(1-(MIN('Scenarios_10'!G6,'Assumptions'!B10))),IF('Scenarios_10'!C6="electricity_only_pct",('Inputs_Data'!C9*(1-(MIN('Scenarios_10'!G6,'Assumptions'!B10))))+'Inputs_Data'!D9,0+('Inputs_Data'!D9*(1-AVERAGE('Assumptions'!B6,'Assumptions'!B7,'Assumptions'!B8,'Assumptions'!B9)))))) | K26: =(IF(4=0,-'Inputs_Data'!H5,0))+(IF(AND(4>=1,4<='Scenarios_10'!B6),MAX(0,(MAX(0,'Scenarios_10'!D6-'Scenarios_10'!E6/'Scenarios_10'!B6))-IF(AND(4>('Scenarios_10'!B6-4),4<='Scenarios_10'!B6),'Scenarios_10'!F6,0)),0))+(IF(4=0,'Scenarios_10'!E6,0))-(IF(4=0,0,IF('Scenarios_10'!C6="uniform_pct",'Inputs_Data'!E9*(1-(MIN('Scenarios_10'!G6,'Assumptions'!B10))),IF('Scenarios_10'!C6="electricity_only_pct",('Inputs_Data'!C9*(1-(MIN('Scenarios_10'!G6,'Assumptions'!B10))))+'Inputs_Data'!D9,0+('Inputs_Data'!D9*(1-AVERAGE('Assumptions'!B6,'Assumptions'!B7,'Assumptions'!B8,'Assumptions'!B9))))))) | L26: =(L25)+(K26)
A27: 5 | B27: =IF(5=0,-'Inputs_Data'!H5,0) | C27: =IF(5=0,0,'Inputs_Data'!B10) | D27: =IF(5=0,0,'Inputs_Data'!E10) | E27: =(IF(5=0,-'Inputs_Data'!H5,0))+(IF(5=0,0,'Inputs_Data'!B10))-(IF(5=0,0,'Inputs_Data'!E10)) | F27: =(F26)+(E27) | G27: =IF(5=0,-'Inputs_Data'!H5,0) | H27: =IF(AND(5>=1,5<='Scenarios_10'!B6),MAX(0,(MAX(0,'Scenarios_10'!D6-'Scenarios_10'!E6/'Scenarios_10'!B6))-IF(AND(5>('Scenarios_10'!B6-4),5<='Scenarios_10'!B6),'Scenarios_10'!F6,0)),0) | I27: =IF(5=0,'Scenarios_10'!E6,0) | J27: =IF(5=0,0,IF('Scenarios_10'!C6="uniform_pct",'Inputs_Data'!E10*(1-(MIN('Scenarios_10'!G6,'Assumptions'!B10))),IF('Scenarios_10'!C6="electricity_only_pct",('Inputs_Data'!C10*(1-(MIN('Scenarios_10'!G6,'Assumptions'!B10))))+'Inputs_Data'!D10,0+('Inputs_Data'!D10*(1-AVERAGE('Assumptions'!B6,'Assumptions'!B7,'Assumptions'!B8,'Assumptions'!B9)))))) | K27: =(IF(5=0,-'Inputs_Data'!H5,0))+(IF(AND(5>=1,5<='Scenarios_10'!B6),MAX(0,(MAX(0,'Scenarios_10'!D6-'Scenarios_10'!E6/'Scenarios_10'!B6))-IF(AND(5>('Scenarios_10'!B6-4),5<='Scenarios_10'!B6),'Scenarios_10'!F6,0)),0))+(IF(5=0,'Scenarios_10'!E6,0))-(IF(5=0,0,IF('Scenarios_10'!C6="uniform_pct",'Inputs_Data'!E10*(1-(MIN('Scenarios_10'!G6,'Assumptions'!B10))),IF('Scenarios_10'!C6="electricity_only_pct",('Inputs_Data'!C10*(1-(MIN('Scenarios_10'!G6,'Assumptions'!B10))))+'Inputs_Data'!D10,0+('Inputs_Data'!D10*(1-AVERAGE('Assumptions'!B6,'Assumptions'!B7,'Assumptions'!B8,'Assumptions'!B9))))))) | L27: =(L26)+(K27)
A28: 6 | B28: =IF(6=0,-'Inputs_Data'!H5,0) | C28: =IF(6=0,0,'Inputs_Data'!B11) | D28: =IF(6=0,0,'Inputs_Data'!E11) | E28: =(IF(6=0,-'Inputs_Data'!H5,0))+(IF(6=0,0,'Inputs_Data'!B11))-(IF(6=0,0,'Inputs_Data'!E11)) | F28: =(F27)+(E28) | G28: =IF(6=0,-'Inputs_Data'!H5,0) | H28: =IF(AND(6>=1,6<='Scenarios_10'!B6),MAX(0,(MAX(0,'Scenarios_10'!D6-'Scenarios_10'!E6/'Scenarios_10'!B6))-IF(AND(6>('Scenarios_10'!B6-4),6<='Scenarios_10'!B6),'Scenarios_10'!F6,0)),0) | I28: =IF(6=0,'Scenarios_10'!E6,0) | J28: =IF(6=0,0,IF('Scenarios_10'!C6="uniform_pct",'Inputs_Data'!E11*(1-(MIN('Scenarios_10'!G6,'Assumptions'!B10))),IF('Scenarios_10'!C6="electricity_only_pct",('Inputs_Data'!C11*(1-(MIN('Scenarios_10'!G6,'Assumptions'!B10))))+'Inputs_Data'!D11,0+('Inputs_Data'!D11*(1-AVERAGE('Assumptions'!B6,'Assumptions'!B7,'Assumptions'!B8,'Assumptions'!B9)))))) | K28: =(IF(6=0,-'Inputs_Data'!H5,0))+(IF(AND(6>=1,6<='Scenarios_10'!B6),MAX(0,(MAX(0,'Scenarios_10'!D6-'Scenarios_10'!E6/'Scenarios_10'!B6))-IF(AND(6>('Scenarios_10'!B6-4),6<='Scenarios_10'!B6),'Scenarios_10'!F6,0)),0))+(IF(6=0,'Scenarios_10'!E6,0))-(IF(6=0,0,IF('Scenarios_10'!C6="uniform_pct",'Inputs_Data'!E11*(1-(MIN('Scenarios_10'!G6,'Assumptions'!B10))),IF('Scenarios_10'!C6="electricity_only_pct",('Inputs_Data'!C11*(1-(MIN('Scenarios_10'!G6,'Assumptions'!B10))))+'Inputs_Data'!D11,0+('Inputs_Data'!D11*(1-AVERAGE('Assumptions'!B6,'Assumptions'!B7,'Assumptions'!B8,'Assumptions'!B9))))))) | L28: =(L27)+(K28)
A29: 7 | B29: =IF(7=0,-'Inputs_Data'!H5,0) | C29: =IF(7=0,0,'Inputs_Data'!B12) | D29: =IF(7=0,0,'Inputs_Data'!E12) | E29: =(IF(7=0,-'Inputs_Data'!H5,0))+(IF(7=0,0,'Inputs_Data'!B12))-(IF(7=0,0,'Inputs_Data'!E12)) | F29: =(F28)+(E29) | G29: =IF(7=0,-'Inputs_Data'!H5,0) | H29: =IF(AND(7>=1,7<='Scenarios_10'!B6),MAX(0,(MAX(0,'Scenarios_10'!D6-'Scenarios_10'!E6/'Scenarios_10'!B6))-IF(AND(7>('Scenarios_10'!B6-4),7<='Scenarios_10'!B6),'Scenarios_10'!F6,0)),0) | I29: =IF(7=0,'Scenarios_10'!E6,0) | J29: =IF(7=0,0,IF('Scenarios_10'!C6="uniform_pct",'Inputs_Data'!E12*(1-(MIN('Scenarios_10'!G6,'Assumptions'!B10))),IF('Scenarios_10'!C6="electricity_only_pct",('Inputs_Data'!C12*(1-(MIN('Scenarios_10'!G6,'Assumptions'!B10))))+'Inputs_Data'!D12,0+('Inputs_Data'!D12*(1-AVERAGE('Assumptions'!B6,'Assumptions'!B7,'Assumptions'!B8,'Assumptions'!B9)))))) | K29: =(IF(7=0,-'Inputs_Data'!H5,0))+(IF(AND(7>=1,7<='Scenarios_10'!B6),MAX(0,(MAX(0,'Scenarios_10'!D6-'Scenarios_10'!E6/'Scenarios_10'!B6))-IF(AND(7>('Scenarios_10'!B6-4),7<='Scenarios_10'!B6),'Scenarios_10'!F6,0)),0))+(IF(7=0,'Scenarios_10'!E6,0))-(IF(7=0,0,IF('Scenarios_10'!C6="uniform_pct",'Inputs_Data'!E12*(1-(MIN('Scenarios_10'!G6,'Assumptions'!B10))),IF('Scenarios_10'!C6="electricity_only_pct",('Inputs_Data'!C12*(1-(MIN('Scenarios_10'!G6,'Assumptions'!B10))))+'Inputs_Data'!D12,0+('Inputs_Data'!D12*(1-AVERAGE('Assumptions'!B6,'Assumptions'!B7,'Assumptions'!B8,'Assumptions'!B9))))))) | L29: =(L28)+(K29)
A30: 8 | B30: =IF(8=0,-'Inputs_Data'!H5,0) | C30: =IF(8=0,0,'Inputs_Data'!B13) | D30: =IF(8=0,0,'Inputs_Data'!E13) | E30: =(IF(8=0,-'Inputs_Data'!H5,0))+(IF(8=0,0,'Inputs_Data'!B13))-(IF(8=0,0,'Inputs_Data'!E13)) | F30: =(F29)+(E30) | G30: =IF(8=0,-'Inputs_Data'!H5,0) | H30: =IF(AND(8>=1,8<='Scenarios_10'!B6),MAX(0,(MAX(0,'Scenarios_10'!D6-'Scenarios_10'!E6/'Scenarios_10'!B6))-IF(AND(8>('Scenarios_10'!B6-4),8<='Scenarios_10'!B6),'Scenarios_10'!F6,0)),0) | I30: =IF(8=0,'Scenarios_10'!E6,0) | J30: =IF(8=0,0,IF('Scenarios_10'!C6="uniform_pct",'Inputs_Data'!E13*(1-(MIN('Scenarios_10'!G6,'Assumptions'!B10))),IF('Scenarios_10'!C6="electricity_only_pct",('Inputs_Data'!C13*(1-(MIN('Scenarios_10'!G6,'Assumptions'!B10))))+'Inputs_Data'!D13,0+('Inputs_Data'!D13*(1-AVERAGE('Assumptions'!B6,'Assumptions'!B7,'Assumptions'!B8,'Assumptions'!B9)))))) | K30: =(IF(8=0,-'Inputs_Data'!H5,0))+(IF(AND(8>=1,8<='Scenarios_10'!B6),MAX(0,(MAX(0,'Scenarios_10'!D6-'Scenarios_10'!E6/'Scenarios_10'!B6))-IF(AND(8>('Scenarios_10'!B6-4),8<='Scenarios_10'!B6),'Scenarios_10'!F6,0)),0))+(IF(8=0,'Scenarios_10'!E6,0))-(IF(8=0,0,IF('Scenarios_10'!C6="uniform_pct",'Inputs_Data'!E13*(1-(MIN('Scenarios_10'!G6,'Assumptions'!B10))),IF('Scenarios_10'!C6="electricity_only_pct",('Inputs_Data'!C13*(1-(MIN('Scenarios_10'!G6,'Assumptions'!B10))))+'Inputs_Data'!D13,0+('Inputs_Data'!D13*(1-AVERAGE('Assumptions'!B6,'Assumptions'!B7,'Assumptions'!B8,'Assumptions'!B9))))))) | L30: =(L29)+(K30)
A31: 9 | B31: =IF(9=0,-'Inputs_Data'!H5,0) | C31: =IF(9=0,0,'Inputs_Data'!B14) | D31: =IF(9=0,0,'Inputs_Data'!E14) | E31: =(IF(9=0,-'Inputs_Data'!H5,0))+(IF(9=0,0,'Inputs_Data'!B14))-(IF(9=0,0,'Inputs_Data'!E14)) | F31: =(F30)+(E31) | G31: =IF(9=0,-'Inputs_Data'!H5,0) | H31: =IF(AND(9>=1,9<='Scenarios_10'!B6),MAX(0,(MAX(0,'Scenarios_10'!D6-'Scenarios_10'!E6/'Scenarios_10'!B6))-IF(AND(9>('Scenarios_10'!B6-4),9<='Scenarios_10'!B6),'Scenarios_10'!F6,0)),0) | I31: =IF(9=0,'Scenarios_10'!E6,0) | J31: =IF(9=0,0,IF('Scenarios_10'!C6="uniform_pct",'Inputs_Data'!E14*(1-(MIN('Scenarios_10'!G6,'Assumptions'!B10))),IF('Scenarios_10'!C6="electricity_only_pct",('Inputs_Data'!C14*(1-(MIN('Scenarios_10'!G6,'Assumptions'!B10))))+'Inputs_Data'!D14,0+('Inputs_Data'!D14*(1-AVERAGE('Assumptions'!B6,'Assumptions'!B7,'Assumptions'!B8,'Assumptions'!B9)))))) | K31: =(IF(9=0,-'Inputs_Data'!H5,0))+(IF(AND(9>=1,9<='Scenarios_10'!B6),MAX(0,(MAX(0,'Scenarios_10'!D6-'Scenarios_10'!E6/'Scenarios_10'!B6))-IF(AND(9>('Scenarios_10'!B6-4),9<='Scenarios_10'!B6),'Scenarios_10'!F6,0)),0))+(IF(9=0,'Scenarios_10'!E6,0))-(IF(9=0,0,IF('Scenarios_10'!C6="uniform_pct",'Inputs_Data'!E14*(1-(MIN('Scenarios_10'!G6,'Assumptions'!B10))),IF('Scenarios_10'!C6="electricity_only_pct",('Inputs_Data'!C14*(1-(MIN('Scenarios_10'!G6,'Assumptions'!B10))))+'Inputs_Data'!D14,0+('Inputs_Data'!D14*(1-AVERAGE('Assumptions'!B6,'Assumptions'!B7,'Assumptions'!B8,'Assumptions'!B9))))))) | L31: =(L30)+(K31)
A32: 10 | B32: =IF(10=0,-'Inputs_Data'!H5,0) | C32: =IF(10=0,0,'Inputs_Data'!B15) | D32: =IF(10=0,0,'Inputs_Data'!E15) | E32: =(IF(10=0,-'Inputs_Data'!H5,0))+(IF(10=0,0,'Inputs_Data'!B15))-(IF(10=0,0,'Inputs_Data'!E15)) | F32: =(F31)+(E32) | G32: =IF(10=0,-'Inputs_Data'!H5,0) | H32: =IF(AND(10>=1,10<='Scenarios_10'!B6),MAX(0,(MAX(0,'Scenarios_10'!D6-'Scenarios_10'!E6/'Scenarios_10'!B6))-IF(AND(10>('Scenarios_10'!B6-4),10<='Scenarios_10'!B6),'Scenarios_10'!F6,0)),0) | I32: =IF(10=0,'Scenarios_10'!E6,0) | J32: =IF(10=0,0,IF('Scenarios_10'!C6="uniform_pct",'Inputs_Data'!E15*(1-(MIN('Scenarios_10'!G6,'Assumptions'!B10))),IF('Scenarios_10'!C6="electricity_only_pct",('Inputs_Data'!C15*(1-(MIN('Scenarios_10'!G6,'Assumptions'!B10))))+'Inputs_Data'!D15,0+('Inputs_Data'!D15*(1-AVERAGE('Assumptions'!B6,'Assumptions'!B7,'Assumptions'!B8,'Assumptions'!B9)))))) | K32: =(IF(10=0,-'Inputs_Data'!H5,0))+(IF(AND(10>=1,10<='Scenarios_10'!B6),MAX(0,(MAX(0,'Scenarios_10'!D6-'Scenarios_10'!E6/'Scenarios_10'!B6))-IF(AND(10>('Scenarios_10'!B6-4),10<='Scenarios_10'!B6),'Scenarios_10'!F6,0)),0))+(IF(10=0,'Scenarios_10'!E6,0))-(IF(10=0,0,IF('Scenarios_10'!C6="uniform_pct",'Inputs_Data'!E15*(1-(MIN('Scenarios_10'!G6,'Assumptions'!B10))),IF('Scenarios_10'!C6="electricity_only_pct",('Inputs_Data'!C15*(1-(MIN('Scenarios_10'!G6,'Assumptions'!B10))))+'Inputs_Data'!D15,0+('Inputs_Data'!D15*(1-AVERAGE('Assumptions'!B6,'Assumptions'!B7,'Assumptions'!B8,'Assumptions'!B9))))))) | L32: =(L31)+(K32)
A35: Tier: ='Scenarios_10'!A7
A36: year | B36: trust_capex | C36: trust_fee | D36: trust_cash_opex | E36: trust_net_cf | F36: trust_cum_cf | G36: laas_capex | H36: laas_fee | I36: laas_upfront | J36: laas_cash_opex | K36: laas_net_cf | L36: laas_cum_cf
A37: 0 | B37: =IF(0=0,-'Inputs_Data'!H5,0) | C37: =IF(0=0,0,'Inputs_Data'!B5) | D37: =IF(0=0,0,'Inputs_Data'!E5) | E37: =(IF(0=0,-'Inputs_Data'!H5,0))+(IF(0=0,0,'Inputs_Data'!B5))-(IF(0=0,0,'Inputs_Data'!E5)) | F37: =(0)+(E37) | G37: =IF(0=0,-'Inputs_Data'!H5,0) | H37: =IF(AND(0>=1,0<='Scenarios_10'!B7),MAX(0,(MAX(0,'Scenarios_10'!D7-'Scenarios_10'!E7/'Scenarios_10'!B7))-IF(AND(0>('Scenarios_10'!B7-4),0<='Scenarios_10'!B7),'Scenarios_10'!F7,0)),0) | I37: =IF(0=0,'Scenarios_10'!E7,0) | J37: =IF(0=0,0,IF('Scenarios_10'!C7="uniform_pct",'Inputs_Data'!E5*(1-(MIN('Scenarios_10'!G7,'Assumptions'!B10))),IF('Scenarios_10'!C7="electricity_only_pct",('Inputs_Data'!C5*(1-(MIN('Scenarios_10'!G7,'Assumptions'!B10))))+'Inputs_Data'!D5,0+('Inputs_Data'!D5*(1-AVERAGE('Assumptions'!B6,'Assumptions'!B7,'Assumptions'!B8,'Assumptions'!B9)))))) | K37: =(IF(0=0,-'Inputs_Data'!H5,0))+(IF(AND(0>=1,0<='Scenarios_10'!B7),MAX(0,(MAX(0,'Scenarios_10'!D7-'Scenarios_10'!E7/'Scenarios_10'!B7))-IF(AND(0>('Scenarios_10'!B7-4),0<='Scenarios_10'!B7),'Scenarios_10'!F7,0)),0))+(IF(0=0,'Scenarios_10'!E7,0))-(IF(0=0,0,IF('Scenarios_10'!C7="uniform_pct",'Inputs_Data'!E5*(1-(MIN('Scenarios_10'!G7,'Assumptions'!B10))),IF('Scenarios_10'!C7="electricity_only_pct",('Inputs_Data'!C5*(1-(MIN('Scenarios_10'!G7,'Assumptions'!B10))))+'Inputs_Data'!D5,0+('Inputs_Data'!D5*(1-AVERAGE('Assumptions'!B6,'Assumptions'!B7,'Assumptions'!B8,'Assumptions'!B9))))))) | L37: =(0)+(K37)
A38: 1 | B38: =IF(1=0,-'Inputs_Data'!H5,0) | C38: =IF(1=0,0,'Inputs_Data'!B6) | D38: =IF(1=0,0,'Inputs_Data'!E6) | E38: =(IF(1=0,-'Inputs_Data'!H5,0))+(IF(1=0,0,'Inputs_Data'!B6))-(IF(1=0,0,'Inputs_Data'!E6)) | F38: =(F37)+(E38) | G38: =IF(1=0,-'Inputs_Data'!H5,0) | H38: =IF(AND(1>=1,1<='Scenarios_10'!B7),MAX(0,(MAX(0,'Scenarios_10'!D7-'Scenarios_10'!E7/'Scenarios_10'!B7))-IF(AND(1>('Scenarios_10'!B7-4),1<='Scenarios_10'!B7),'Scenarios_10'!F7,0)),0) | I38: =IF(1=0,'Scenarios_10'!E7,0) | J38: =IF(1=0,0,IF('Scenarios_10'!C7="uniform_pct",'Inputs_Data'!E6*(1-(MIN('Scenarios_10'!G7,'Assumptions'!B10))),IF('Scenarios_10'!C7="electricity_only_pct",('Inputs_Data'!C6*(1-(MIN('Scenarios_10'!G7,'Assumptions'!B10))))+'Inputs_Data'!D6,0+('Inputs_Data'!D6*(1-AVERAGE('Assumptions'!B6,'Assumptions'!B7,'Assumptions'!B8,'Assumptions'!B9)))))) | K38: =(IF(1=0,-'Inputs_Data'!H5,0))+(IF(AND(1>=1,1<='Scenarios_10'!B7),MAX(0,(MAX(0,'Scenarios_10'!D7-'Scenarios_10'!E7/'Scenarios_10'!B7))-IF(AND(1>('Scenarios_10'!B7-4),1<='Scenarios_10'!B7),'Scenarios_10'!F7,0)),0))+(IF(1=0,'Scenarios_10'!E7,0))-(IF(1=0,0,IF('Scenarios_10'!C7="uniform_pct",'Inputs_Data'!E6*(1-(MIN('Scenarios_10'!G7,'Assumptions'!B10))),IF('Scenarios_10'!C7="electricity_only_pct",('Inputs_Data'!C6*(1-(MIN('Scenarios_10'!G7,'Assumptions'!B10))))+'Inputs_Data'!D6,0+('Inputs_Data'!D6*(1-AVERAGE('Assumptions'!B6,'Assumptions'!B7,'Assumptions'!B8,'Assumptions'!B9))))))) | L38: =(L37)+(K38)
A39: 2 | B39: =IF(2=0,-'Inputs_Data'!H5,0) | C39: =IF(2=0,0,'Inputs_Data'!B7) | D39: =IF(2=0,0,'Inputs_Data'!E7) | E39: =(IF(2=0,-'Inputs_Data'!H5,0))+(IF(2=0,0,'Inputs_Data'!B7))-(IF(2=0,0,'Inputs_Data'!E7)) | F39: =(F38)+(E39) | G39: =IF(2=0,-'Inputs_Data'!H5,0) | H39: =IF(AND(2>=1,2<='Scenarios_10'!B7),MAX(0,(MAX(0,'Scenarios_10'!D7-'Scenarios_10'!E7/'Scenarios_10'!B7))-IF(AND(2>('Scenarios_10'!B7-4),2<='Scenarios_10'!B7),'Scenarios_10'!F7,0)),0) | I39: =IF(2=0,'Scenarios_10'!E7,0) | J39: =IF(2=0,0,IF('Scenarios_10'!C7="uniform_pct",'Inputs_Data'!E7*(1-(MIN('Scenarios_10'!G7,'Assumptions'!B10))),IF('Scenarios_10'!C7="electricity_only_pct",('Inputs_Data'!C7*(1-(MIN('Scenarios_10'!G7,'Assumptions'!B10))))+'Inputs_Data'!D7,0+('Inputs_Data'!D7*(1-AVERAGE('Assumptions'!B6,'Assumptions'!B7,'Assumptions'!B8,'Assumptions'!B9)))))) | K39: =(IF(2=0,-'Inputs_Data'!H5,0))+(IF(AND(2>=1,2<='Scenarios_10'!B7),MAX(0,(MAX(0,'Scenarios_10'!D7-'Scenarios_10'!E7/'Scenarios_10'!B7))-IF(AND(2>('Scenarios_10'!B7-4),2<='Scenarios_10'!B7),'Scenarios_10'!F7,0)),0))+(IF(2=0,'Scenarios_10'!E7,0))-(IF(2=0,0,IF('Scenarios_10'!C7="uniform_pct",'Inputs_Data'!E7*(1-(MIN('Scenarios_10'!G7,'Assumptions'!B10))),IF('Scenarios_10'!C7="electricity_only_pct",('Inputs_Data'!C7*(1-(MIN('Scenarios_10'!G7,'Assumptions'!B10))))+'Inputs_Data'!D7,0+('Inputs_Data'!D7*(1-AVERAGE('Assumptions'!B6,'Assumptions'!B7,'Assumptions'!B8,'Assumptions'!B9))))))) | L39: =(L38)+(K39)
A40: 3 | B40: =IF(3=0,-'Inputs_Data'!H5,0) | C40: =IF(3=0,0,'Inputs_Data'!B8) | D40: =IF(3=0,0,'Inputs_Data'!E8) | E40: =(IF(3=0,-'Inputs_Data'!H5,0))+(IF(3=0,0,'Inputs_Data'!B8))-(IF(3=0,0,'Inputs_Data'!E8)) | F40: =(F39)+(E40) | G40: =IF(3=0,-'Inputs_Data'!H5,0) | H40: =IF(AND(3>=1,3<='Scenarios_10'!B7),MAX(0,(MAX(0,'Scenarios_10'!D7-'Scenarios_10'!E7/'Scenarios_10'!B7))-IF(AND(3>('Scenarios_10'!B7-4),3<='Scenarios_10'!B7),'Scenarios_10'!F7,0)),0) | I40: =IF(3=0,'Scenarios_10'!E7,0) | J40: =IF(3=0,0,IF('Scenarios_10'!C7="uniform_pct",'Inputs_Data'!E8*(1-(MIN('Scenarios_10'!G7,'Assumptions'!B10))),IF('Scenarios_10'!C7="electricity_only_pct",('Inputs_Data'!C8*(1-(MIN('Scenarios_10'!G7,'Assumptions'!B10))))+'Inputs_Data'!D8,0+('Inputs_Data'!D8*(1-AVERAGE('Assumptions'!B6,'Assumptions'!B7,'Assumptions'!B8,'Assumptions'!B9)))))) | K40: =(IF(3=0,-'Inputs_Data'!H5,0))+(IF(AND(3>=1,3<='Scenarios_10'!B7),MAX(0,(MAX(0,'Scenarios_10'!D7-'Scenarios_10'!E7/'Scenarios_10'!B7))-IF(AND(3>('Scenarios_10'!B7-4),3<='Scenarios_10'!B7),'Scenarios_10'!F7,0)),0))+(IF(3=0,'Scenarios_10'!E7,0))-(IF(3=0,0,IF('Scenarios_10'!C7="uniform_pct",'Inputs_Data'!E8*(1-(MIN('Scenarios_10'!G7,'Assumptions'!B10))),IF('Scenarios_10'!C7="electricity_only_pct",('Inputs_Data'!C8*(1-(MIN('Scenarios_10'!G7,'Assumptions'!B10))))+'Inputs_Data'!D8,0+('Inputs_Data'!D8*(1-AVERAGE('Assumptions'!B6,'Assumptions'!B7,'Assumptions'!B8,'Assumptions'!B9))))))) | L40: =(L39)+(K40)
A41: 4 | B41: =IF(4=0,-'Inputs_Data'!H5,0) | C41: =IF(4=0,0,'Inputs_Data'!B9) | D41: =IF(4=0,0,'Inputs_Data'!E9) | E41: =(IF(4=0,-'Inputs_Data'!H5,0))+(IF(4=0,0,'Inputs_Data'!B9))-(IF(4=0,0,'Inputs_Data'!E9)) | F41: =(F40)+(E41) | G41: =IF(4=0,-'Inputs_Data'!H5,0) | H41: =IF(AND(4>=1,4<='Scenarios_10'!B7),MAX(0,(MAX(0,'Scenarios_10'!D7-'Scenarios_10'!E7/'Scenarios_10'!B7))-IF(AND(4>('Scenarios_10'!B7-4),4<='Scenarios_10'!B7),'Scenarios_10'!F7,0)),0) | I41: =IF(4=0,'Scenarios_10'!E7,0) | J41: =IF(4=0,0,IF('Scenarios_10'!C7="uniform_pct",'Inputs_Data'!E9*(1-(MIN('Scenarios_10'!G7,'Assumptions'!B10))),IF('Scenarios_10'!C7="electricity_only_pct",('Inputs_Data'!C9*(1-(MIN('Scenarios_10'!G7,'Assumptions'!B10))))+'Inputs_Data'!D9,0+('Inputs_Data'!D9*(1-AVERAGE('Assumptions'!B6,'Assumptions'!B7,'Assumptions'!B8,'Assumptions'!B9)))))) | K41: =(IF(4=0,-'Inputs_Data'!H5,0))+(IF(AND(4>=1,4<='Scenarios_10'!B7),MAX(0,(MAX(0,'Scenarios_10'!D7-'Scenarios_10'!E7/'Scenarios_10'!B7))-IF(AND(4>('Scenarios_10'!B7-4),4<='Scenarios_10'!B7),'Scenarios_10'!F7,0)),0))+(IF(4=0,'Scenarios_10'!E7,0))-(IF(4=0,0,IF('Scenarios_10'!C7="uniform_pct",'Inputs_Data'!E9*(1-(MIN('Scenarios_10'!G7,'Assumptions'!B10))),IF('Scenarios_10'!C7="electricity_only_pct",('Inputs_Data'!C9*(1-(MIN('Scenarios_10'!G7,'Assumptions'!B10))))+'Inputs_Data'!D9,0+('Inputs_Data'!D9*(1-AVERAGE('Assumptions'!B6,'Assumptions'!B7,'Assumptions'!B8,'Assumptions'!B9))))))) | L41: =(L40)+(K41)
A42: 5 | B42: =IF(5=0,-'Inputs_Data'!H5,0) | C42: =IF(5=0,0,'Inputs_Data'!B10) | D42: =IF(5=0,0,'Inputs_Data'!E10) | E42: =(IF(5=0,-'Inputs_Data'!H5,0))+(IF(5=0,0,'Inputs_Data'!B10))-(IF(5=0,0,'Inputs_Data'!E10)) | F42: =(F41)+(E42) | G42: =IF(5=0,-'Inputs_Data'!H5,0) | H42: =IF(AND(5>=1,5<='Scenarios_10'!B7),MAX(0,(MAX(0,'Scenarios_10'!D7-'Scenarios_10'!E7/'Scenarios_10'!B7))-IF(AND(5>('Scenarios_10'!B7-4),5<='Scenarios_10'!B7),'Scenarios_10'!F7,0)),0) | I42: =IF(5=0,'Scenarios_10'!E7,0) | J42: =IF(5=0,0,IF('Scenarios_10'!C7="uniform_pct",'Inputs_Data'!E10*(1-(MIN('Scenarios_10'!G7,'Assumptions'!B10))),IF('Scenarios_10'!C7="electricity_only_pct",('Inputs_Data'!C10*(1-(MIN('Scenarios_10'!G7,'Assumptions'!B10))))+'Inputs_Data'!D10,0+('Inputs_Data'!D10*(1-AVERAGE('Assumptions'!B6,'Assumptions'!B7,'Assumptions'!B8,'Assumptions'!B9)))))) | K42: =(IF(5=0,-'Inputs_Data'!H5,0))+(IF(AND(5>=1,5<='Scenarios_10'!B7),MAX(0,(MAX(0,'Scenarios_10'!D7-'Scenarios_10'!E7/'Scenarios_10'!B7))-IF(AND(5>('Scenarios_10'!B7-4),5<='Scenarios_10'!B7),'Scenarios_10'!F7,0)),0))+(IF(5=0,'Scenarios_10'!E7,0))-(IF(5=0,0,IF('Scenarios_10'!C7="uniform_pct",'Inputs_Data'!E10*(1-(MIN('Scenarios_10'!G7,'Assumptions'!B10))),IF('Scenarios_10'!C7="electricity_only_pct",('Inputs_Data'!C10*(1-(MIN('Scenarios_10'!G7,'Assumptions'!B10))))+'Inputs_Data'!D10,0+('Inputs_Data'!D10*(1-AVERAGE('Assumptions'!B6,'Assumptions'!B7,'Assumptions'!B8,'Assumptions'!B9))))))) | L42: =(L41)+(K42)
A43: 6 | B43: =IF(6=0,-'Inputs_Data'!H5,0) | C43: =IF(6=0,0,'Inputs_Data'!B11) | D43: =IF(6=0,0,'Inputs_Data'!E11) | E43: =(IF(6=0,-'Inputs_Data'!H5,0))+(IF(6=0,0,'Inputs_Data'!B11))-(IF(6=0,0,'Inputs_Data'!E11)) | F43: =(F42)+(E43) | G43: =IF(6=0,-'Inputs_Data'!H5,0) | H43: =IF(AND(6>=1,6<='Scenarios_10'!B7),MAX(0,(MAX(0,'Scenarios_10'!D7-'Scenarios_10'!E7/'Scenarios_10'!B7))-IF(AND(6>('Scenarios_10'!B7-4),6<='Scenarios_10'!B7),'Scenarios_10'!F7,0)),0) | I43: =IF(6=0,'Scenarios_10'!E7,0) | J43: =IF(6=0,0,IF('Scenarios_10'!C7="uniform_pct",'Inputs_Data'!E11*(1-(MIN('Scenarios_10'!G7,'Assumptions'!B10))),IF('Scenarios_10'!C7="electricity_only_pct",('Inputs_Data'!C11*(1-(MIN('Scenarios_10'!G7,'Assumptions'!B10))))+'Inputs_Data'!D11,0+('Inputs_Data'!D11*(1-AVERAGE('Assumptions'!B6,'Assumptions'!B7,'Assumptions'!B8,'Assumptions'!B9)))))) | K43: =(IF(6=0,-'Inputs_Data'!H5,0))+(IF(AND(6>=1,6<='Scenarios_10'!B7),MAX(0,(MAX(0,'Scenarios_10'!D7-'Scenarios_10'!E7/'Scenarios_10'!B7))-IF(AND(6>('Scenarios_10'!B7-4),6<='Scenarios_10'!B7),'Scenarios_10'!F7,0)),0))+(IF(6=0,'Scenarios_10'!E7,0))-(IF(6=0,0,IF('Scenarios_10'!C7="uniform_pct",'Inputs_Data'!E11*(1-(MIN('Scenarios_10'!G7,'Assumptions'!B10))),IF('Scenarios_10'!C7="electricity_only_pct",('Inputs_Data'!C11*(1-(MIN('Scenarios_10'!G7,'Assumptions'!B10))))+'Inputs_Data'!D11,0+('Inputs_Data'!D11*(1-AVERAGE('Assumptions'!B6,'Assumptions'!B7,'Assumptions'!B8,'Assumptions'!B9))))))) | L43: =(L42)+(K43)
A44: 7 | B44: =IF(7=0,-'Inputs_Data'!H5,0) | C44: =IF(7=0,0,'Inputs_Data'!B12) | D44: =IF(7=0,0,'Inputs_Data'!E12) | E44: =(IF(7=0,-'Inputs_Data'!H5,0))+(IF(7=0,0,'Inputs_Data'!B12))-(IF(7=0,0,'Inputs_Data'!E12)) | F44: =(F43)+(E44) | G44: =IF(7=0,-'Inputs_Data'!H5,0) | H44: =IF(AND(7>=1,7<='Scenarios_10'!B7),MAX(0,(MAX(0,'Scenarios_10'!D7-'Scenarios_10'!E7/'Scenarios_10'!B7))-IF(AND(7>('Scenarios_10'!B7-4),7<='Scenarios_10'!B7),'Scenarios_10'!F7,0)),0) | I44: =IF(7=0,'Scenarios_10'!E7,0) | J44: =IF(7=0,0,IF('Scenarios_10'!C7="uniform_pct",'Inputs_Data'!E12*(1-(MIN('Scenarios_10'!G7,'Assumptions'!B10))),IF('Scenarios_10'!C7="electricity_only_pct",('Inputs_Data'!C12*(1-(MIN('Scenarios_10'!G7,'Assumptions'!B10))))+'Inputs_Data'!D12,0+('Inputs_Data'!D12*(1-AVERAGE('Assumptions'!B6,'Assumptions'!B7,'Assumptions'!B8,'Assumptions'!B9)))))) | K44: =(IF(7=0,-'Inputs_Data'!H5,0))+(IF(AND(7>=1,7<='Scenarios_10'!B7),MAX(0,(MAX(0,'Scenarios_10'!D7-'Scenarios_10'!E7/'Scenarios_10'!B7))-IF(AND(7>('Scenarios_10'!B7-4),7<='Scenarios_10'!B7),'Scenarios_10'!F7,0)),0))+(IF(7=0,'Scenarios_10'!E7,0))-(IF(7=0,0,IF('Scenarios_10'!C7="uniform_pct",'Inputs_Data'!E12*(1-(MIN('Scenarios_10'!G7,'Assumptions'!B10))),IF('Scenarios_10'!C7="electricity_only_pct",('Inputs_Data'!C12*(1-(MIN('Scenarios_10'!G7,'Assumptions'!B10))))+'Inputs_Data'!D12,0+('Inputs_Data'!D12*(1-AVERAGE('Assumptions'!B6,'Assumptions'!B7,'Assumptions'!B8,'Assumptions'!B9))))))) | L44: =(L43)+(K44)
A45: 8 | B45: =IF(8=0,-'Inputs_Data'!H5,0) | C45: =IF(8=0,0,'Inputs_Data'!B13) | D45: =IF(8=0,0,'Inputs_Data'!E13) | E45: =(IF(8=0,-'Inputs_Data'!H5,0))+(IF(8=0,0,'Inputs_Data'!B13))-(IF(8=0,0,'Inputs_Data'!E13)) | F45: =(F44)+(E45) | G45: =IF(8=0,-'Inputs_Data'!H5,0) | H45: =IF(AND(8>=1,8<='Scenarios_10'!B7),MAX(0,(MAX(0,'Scenarios_10'!D7-'Scenarios_10'!E7/'Scenarios_10'!B7))-IF(AND(8>('Scenarios_10'!B7-4),8<='Scenarios_10'!B7),'Scenarios_10'!F7,0)),0) | I45: =IF(8=0,'Scenarios_10'!E7,0) | J45: =IF(8=0,0,IF('Scenarios_10'!C7="uniform_pct",'Inputs_Data'!E13*(1-(MIN('Scenarios_10'!G7,'Assumptions'!B10))),IF('Scenarios_10'!C7="electricity_only_pct",('Inputs_Data'!C13*(1-(MIN('Scenarios_10'!G7,'Assumptions'!B10))))+'Inputs_Data'!D13,0+('Inputs_Data'!D13*(1-AVERAGE('Assumptions'!B6,'Assumptions'!B7,'Assumptions'!B8,'Assumptions'!B9)))))) | K45: =(IF(8=0,-'Inputs_Data'!H5,0))+(IF(AND(8>=1,8<='Scenarios_10'!B7),MAX(0,(MAX(0,'Scenarios_10'!D7-'Scenarios_10'!E7/'Scenarios_10'!B7))-IF(AND(8>('Scenarios_10'!B7-4),8<='Scenarios_10'!B7),'Scenarios_10'!F7,0)),0))+(IF(8=0,'Scenarios_10'!E7,0))-(IF(8=0,0,IF('Scenarios_10'!C7="uniform_pct",'Inputs_Data'!E13*(1-(MIN('Scenarios_10'!G7,'Assumptions'!B10))),IF('Scenarios_10'!C7="electricity_only_pct",('Inputs_Data'!C13*(1-(MIN('Scenarios_10'!G7,'Assumptions'!B10))))+'Inputs_Data'!D13,0+('Inputs_Data'!D13*(1-AVERAGE('Assumptions'!B6,'Assumptions'!B7,'Assumptions'!B8,'Assumptions'!B9))))))) | L45: =(L44)+(K45)
A46: 9 | B46: =IF(9=0,-'Inputs_Data'!H5,0) | C46: =IF(9=0,0,'Inputs_Data'!B14) | D46: =IF(9=0,0,'Inputs_Data'!E14) | E46: =(IF(9=0,-'Inputs_Data'!H5,0))+(IF(9=0,0,'Inputs_Data'!B14))-(IF(9=0,0,'Inputs_Data'!E14)) | F46: =(F45)+(E46) | G46: =IF(9=0,-'Inputs_Data'!H5,0) | H46: =IF(AND(9>=1,9<='Scenarios_10'!B7),MAX(0,(MAX(0,'Scenarios_10'!D7-'Scenarios_10'!E7/'Scenarios_10'!B7))-IF(AND(9>('Scenarios_10'!B7-4),9<='Scenarios_10'!B7),'Scenarios_10'!F7,0)),0) | I46: =IF(9=0,'Scenarios_10'!E7,0) | J46: =IF(9=0,0,IF('Scenarios_10'!C7="uniform_pct",'Inputs_Data'!E14*(1-(MIN('Scenarios_10'!G7,'Assumptions'!B10))),IF('Scenarios_10'!C7="electricity_only_pct",('Inputs_Data'!C14*(1-(MIN('Scenarios_10'!G7,'Assumptions'!B10))))+'Inputs_Data'!D14,0+('Inputs_Data'!D14*(1-AVERAGE('Assumptions'!B6,'Assumptions'!B7,'Assumptions'!B8,'Assumptions'!B9)))))) | K46: =(IF(9=0,-'Inputs_Data'!H5,0))+(IF(AND(9>=1,9<='Scenarios_10'!B7),MAX(0,(MAX(0,'Scenarios_10'!D7-'Scenarios_10'!E7/'Scenarios_10'!B7))-IF(AND(9>('Scenarios_10'!B7-4),9<='Scenarios_10'!B7),'Scenarios_10'!F7,0)),0))+(IF(9=0,'Scenarios_10'!E7,0))-(IF(9=0,0,IF('Scenarios_10'!C7="uniform_pct",'Inputs_Data'!E14*(1-(MIN('Scenarios_10'!G7,'Assumptions'!B10))),IF('Scenarios_10'!C7="electricity_only_pct",('Inputs_Data'!C14*(1-(MIN('Scenarios_10'!G7,'Assumptions'!B10))))+'Inputs_Data'!D14,0+('Inputs_Data'!D14*(1-AVERAGE('Assumptions'!B6,'Assumptions'!B7,'Assumptions'!B8,'Assumptions'!B9))))))) | L46: =(L45)+(K46)
A47: 10 | B47: =IF(10=0,-'Inputs_Data'!H5,0) | C47: =IF(10=0,0,'Inputs_Data'!B15) | D47: =IF(10=0,0,'Inputs_Data'!E15) | E47: =(IF(10=0,-'Inputs_Data'!H5,0))+(IF(10=0,0,'Inputs_Data'!B15))-(IF(10=0,0,'Inputs_Data'!E15)) | F47: =(F46)+(E47) | G47: =IF(10=0,-'Inputs_Data'!H5,0) | H47: =IF(AND(10>=1,10<='Scenarios_10'!B7),MAX(0,(MAX(0,'Scenarios_10'!D7-'Scenarios_10'!E7/'Scenarios_10'!B7))-IF(AND(10>('Scenarios_10'!B7-4),10<='Scenarios_10'!B7),'Scenarios_10'!F7,0)),0) | I47: =IF(10=0,'Scenarios_10'!E7,0) | J47: =IF(10=0,0,IF('Scenarios_10'!C7="uniform_pct",'Inputs_Data'!E15*(1-(MIN('Scenarios_10'!G7,'Assumptions'!B10))),IF('Scenarios_10'!C7="electricity_only_pct",('Inputs_Data'!C15*(1-(MIN('Scenarios_10'!G7,'Assumptions'!B10))))+'Inputs_Data'!D15,0+('Inputs_Data'!D15*(1-AVERAGE('Assumptions'!B6,'Assumptions'!B7,'Assumptions'!B8,'Assumptions'!B9)))))) | K47: =(IF(10=0,-'Inputs_Data'!H5,0))+(IF(AND(10>=1,10<='Scenarios_10'!B7),MAX(0,(MAX(0,'Scenarios_10'!D7-'Scenarios_10'!E7/'Scenarios_10'!B7))-IF(AND(10>('Scenarios_10'!B7-4),10<='Scenarios_10'!B7),'Scenarios_10'!F7,0)),0))+(IF(10=0,'Scenarios_10'!E7,0))-(IF(10=0,0,IF('Scenarios_10'!C7="uniform_pct",'Inputs_Data'!E15*(1-(MIN('Scenarios_10'!G7,'Assumptions'!B10))),IF('Scenarios_10'!C7="electricity_only_pct",('Inputs_Data'!C15*(1-(MIN('Scenarios_10'!G7,'Assumptions'!B10))))+'Inputs_Data'!D15,0+('Inputs_Data'!D15*(1-AVERAGE('Assumptions'!B6,'Assumptions'!B7,'Assumptions'!B8,'Assumptions'!B9))))))) | L47: =(L46)+(K47)
A50: Tier: ='Scenarios_10'!A8
A51: year | B51: trust_capex | C51: trust_fee | D51: trust_cash_opex | E51: trust_net_cf | F51: trust_cum_cf | G51: laas_capex | H51: laas_fee | I51: laas_upfront | J51: laas_cash_opex | K51: laas_net_cf | L51: laas_cum_cf
A52: 0 | B52: =IF(0=0,-'Inputs_Data'!H5,0) | C52: =IF(0=0,0,'Inputs_Data'!B5) | D52: =IF(0=0,0,'Inputs_Data'!E5) | E52: =(IF(0=0,-'Inputs_Data'!H5,0))+(IF(0=0,0,'Inputs_Data'!B5))-(IF(0=0,0,'Inputs_Data'!E5)) | F52: =(0)+(E52) | G52: =IF(0=0,-'Inputs_Data'!H5,0) | H52: =IF(AND(0>=1,0<='Scenarios_10'!B8),MAX(0,(MAX(0,'Scenarios_10'!D8-'Scenarios_10'!E8/'Scenarios_10'!B8))-IF(AND(0>('Scenarios_10'!B8-4),0<='Scenarios_10'!B8),'Scenarios_10'!F8,0)),0) | I52: =IF(0=0,'Scenarios_10'!E8,0) | J52: =IF(0=0,0,IF('Scenarios_10'!C8="uniform_pct",'Inputs_Data'!E5*(1-(MIN('Scenarios_10'!G8,'Assumptions'!B10))),IF('Scenarios_10'!C8="electricity_only_pct",('Inputs_Data'!C5*(1-(MIN('Scenarios_10'!G8,'Assumptions'!B10))))+'Inputs_Data'!D5,0+('Inputs_Data'!D5*(1-AVERAGE('Assumptions'!B6,'Assumptions'!B7,'Assumptions'!B8,'Assumptions'!B9)))))) | K52: =(IF(0=0,-'Inputs_Data'!H5,0))+(IF(AND(0>=1,0<='Scenarios_10'!B8),MAX(0,(MAX(0,'Scenarios_10'!D8-'Scenarios_10'!E8/'Scenarios_10'!B8))-IF(AND(0>('Scenarios_10'!B8-4),0<='Scenarios_10'!B8),'Scenarios_10'!F8,0)),0))+(IF(0=0,'Scenarios_10'!E8,0))-(IF(0=0,0,IF('Scenarios_10'!C8="uniform_pct",'Inputs_Data'!E5*(1-(MIN('Scenarios_10'!G8,'Assumptions'!B10))),IF('Scenarios_10'!C8="electricity_only_pct",('Inputs_Data'!C5*(1-(MIN('Scenarios_10'!G8,'Assumptions'!B10))))+'Inputs_Data'!D5,0+('Inputs_Data'!D5*(1-AVERAGE('Assumptions'!B6,'Assumptions'!B7,'Assumptions'!B8,'Assumptions'!B9))))))) | L52: =(0)+(K52)
A53: 1 | B53: =IF(1=0,-'Inputs_Data'!H5,0) | C53: =IF(1=0,0,'Inputs_Data'!B6) | D53: =IF(1=0,0,'Inputs_Data'!E6) | E53: =(IF(1=0,-'Inputs_Data'!H5,0))+(IF(1=0,0,'Inputs_Data'!B6))-(IF(1=0,0,'Inputs_Data'!E6)) | F53: =(F52)+(E53) | G53: =IF(1=0,-'Inputs_Data'!H5,0) | H53: =IF(AND(1>=1,1<='Scenarios_10'!B8),MAX(0,(MAX(0,'Scenarios_10'!D8-'Scenarios_10'!E8/'Scenarios_10'!B8))-IF(AND(1>('Scenarios_10'!B8-4),1<='Scenarios_10'!B8),'Scenarios_10'!F8,0)),0) | I53: =IF(1=0,'Scenarios_10'!E8,0) | J53: =IF(1=0,0,IF('Scenarios_10'!C8="uniform_pct",'Inputs_Data'!E6*(1-(MIN('Scenarios_10'!G8,'Assumptions'!B10))),IF('Scenarios_10'!C8="electricity_only_pct",('Inputs_Data'!C6*(1-(MIN('Scenarios_10'!G8,'Assumptions'!B10))))+'Inputs_Data'!D6,0+('Inputs_Data'!D6*(1-AVERAGE('Assumptions'!B6,'Assumptions'!B7,'Assumptions'!B8,'Assumptions'!B9)))))) | K53: =(IF(1=0,-'Inputs_Data'!H5,0))+(IF(AND(1>=1,1<='Scenarios_10'!B8),MAX(0,(MAX(0,'Scenarios_10'!D8-'Scenarios_10'!E8/'Scenarios_10'!B8))-IF(AND(1>('Scenarios_10'!B8-4),1<='Scenarios_10'!B8),'Scenarios_10'!F8,0)),0))+(IF(1=0,'Scenarios_10'!E8,0))-(IF(1=0,0,IF('Scenarios_10'!C8="uniform_pct",'Inputs_Data'!E6*(1-(MIN('Scenarios_10'!G8,'Assumptions'!B10))),IF('Scenarios_10'!C8="electricity_only_pct",('Inputs_Data'!C6*(1-(MIN('Scenarios_10'!G8,'Assumptions'!B10))))+'Inputs_Data'!D6,0+('Inputs_Data'!D6*(1-AVERAGE('Assumptions'!B6,'Assumptions'!B7,'Assumptions'!B8,'Assumptions'!B9))))))) | L53: =(L52)+(K53)
A54: 2 | B54: =IF(2=0,-'Inputs_Data'!H5,0) | C54: =IF(2=0,0,'Inputs_Data'!B7) | D54: =IF(2=0,0,'Inputs_Data'!E7) | E54: =(IF(2=0,-'Inputs_Data'!H5,0))+(IF(2=0,0,'Inputs_Data'!B7))-(IF(2=0,0,'Inputs_Data'!E7)) | F54: =(F53)+(E54) | G54: =IF(2=0,-'Inputs_Data'!H5,0) | H54: =IF(AND(2>=1,2<='Scenarios_10'!B8),MAX(0,(MAX(0,'Scenarios_10'!D8-'Scenarios_10'!E8/'Scenarios_10'!B8))-IF(AND(2>('Scenarios_10'!B8-4),2<='Scenarios_10'!B8),'Scenarios_10'!F8,0)),0) | I54: =IF(2=0,'Scenarios_10'!E8,0) | J54: =IF(2=0,0,IF('Scenarios_10'!C8="uniform_pct",'Inputs_Data'!E7*(1-(MIN('Scenarios_10'!G8,'Assumptions'!B10))),IF('Scenarios_10'!C8="electricity_only_pct",('Inputs_Data'!C7*(1-(MIN('Scenarios_10'!G8,'Assumptions'!B10))))+'Inputs_Data'!D7,0+('Inputs_Data'!D7*(1-AVERAGE('Assumptions'!B6,'Assumptions'!B7,'Assumptions'!B8,'Assumptions'!B9)))))) | K54: =(IF(2=0,-'Inputs_Data'!H5,0))+(IF(AND(2>=1,2<='Scenarios_10'!B8),MAX(0,(MAX(0,'Scenarios_10'!D8-'Scenarios_10'!E8/'Scenarios_10'!B8))-IF(AND(2>('Scenarios_10'!B8-4),2<='Scenarios_10'!B8),'Scenarios_10'!F8,0)),0))+(IF(2=0,'Scenarios_10'!E8,0))-(IF(2=0,0,IF('Scenarios_10'!C8="uniform_pct",'Inputs_Data'!E7*(1-(MIN('Scenarios_10'!G8,'Assumptions'!B10))),IF('Scenarios_10'!C8="electricity_only_pct",('Inputs_Data'!C7*(1-(MIN('Scenarios_10'!G8,'Assumptions'!B10))))+'Inputs_Data'!D7,0+('Inputs_Data'!D7*(1-AVERAGE('Assumptions'!B6,'Assumptions'!B7,'Assumptions'!B8,'Assumptions'!B9))))))) | L54: =(L53)+(K54)
A55: 3 | B55: =IF(3=0,-'Inputs_Data'!H5,0) | C55: =IF(3=0,0,'Inputs_Data'!B8) | D55: =IF(3=0,0,'Inputs_Data'!E8) | E55: =(IF(3=0,-'Inputs_Data'!H5,0))+(IF(3=0,0,'Inputs_Data'!B8))-(IF(3=0,0,'Inputs_Data'!E8)) | F55: =(F54)+(E55) | G55: =IF(3=0,-'Inputs_Data'!H5,0) | H55: =IF(AND(3>=1,3<='Scenarios_10'!B8),MAX(0,(MAX(0,'Scenarios_10'!D8-'Scenarios_10'!E8/'Scenarios_10'!B8))-IF(AND(3>('Scenarios_10'!B8-4),3<='Scenarios_10'!B8),'Scenarios_10'!F8,0)),0) | I55: =IF(3=0,'Scenarios_10'!E8,0) | J55: =IF(3=0,0,IF('Scenarios_10'!C8="uniform_pct",'Inputs_Data'!E8*(1-(MIN('Scenarios_10'!G8,'Assumptions'!B10))),IF('Scenarios_10'!C8="electricity_only_pct",('Inputs_Data'!C8*(1-(MIN('Scenarios_10'!G8,'Assumptions'!B10))))+'Inputs_Data'!D8,0+('Inputs_Data'!D8*(1-AVERAGE('Assumptions'!B6,'Assumptions'!B7,'Assumptions'!B8,'Assumptions'!B9)))))) | K55: =(IF(3=0,-'Inputs_Data'!H5,0))+(IF(AND(3>=1,3<='Scenarios_10'!B8),MAX(0,(MAX(0,'Scenarios_10'!D8-'Scenarios_10'!E8/'Scenarios_10'!B8))-IF(AND(3>('Scenarios_10'!B8-4),3<='Scenarios_10'!B8),'Scenarios_10'!F8,0)),0))+(IF(3=0,'Scenarios_10'!E8,0))-(IF(3=0,0,IF('Scenarios_10'!C8="uniform_pct",'Inputs_Data'!E8*(1-(MIN('Scenarios_10'!G8,'Assumptions'!B10))),IF('Scenarios_10'!C8="electricity_only_pct",('Inputs_Data'!C8*(1-(MIN('Scenarios_10'!G8,'Assumptions'!B10))))+'Inputs_Data'!D8,0+('Inputs_Data'!D8*(1-AVERAGE('Assumptions'!B6,'Assumptions'!B7,'Assumptions'!B8,'Assumptions'!B9))))))) | L55: =(L54)+(K55)
A56: 4 | B56: =IF(4=0,-'Inputs_Data'!H5,0) | C56: =IF(4=0,0,'Inputs_Data'!B9) | D56: =IF(4=0,0,'Inputs_Data'!E9) | E56: =(IF(4=0,-'Inputs_Data'!H5,0))+(IF(4=0,0,'Inputs_Data'!B9))-(IF(4=0,0,'Inputs_Data'!E9)) | F56: =(F55)+(E56) | G56: =IF(4=0,-'Inputs_Data'!H5,0) | H56: =IF(AND(4>=1,4<='Scenarios_10'!B8),MAX(0,(MAX(0,'Scenarios_10'!D8-'Scenarios_10'!E8/'Scenarios_10'!B8))-IF(AND(4>('Scenarios_10'!B8-4),4<='Scenarios_10'!B8),'Scenarios_10'!F8,0)),0) | I56: =IF(4=0,'Scenarios_10'!E8,0) | J56: =IF(4=0,0,IF('Scenarios_10'!C8="uniform_pct",'Inputs_Data'!E9*(1-(MIN('Scenarios_10'!G8,'Assumptions'!B10))),IF('Scenarios_10'!C8="electricity_only_pct",('Inputs_Data'!C9*(1-(MIN('Scenarios_10'!G8,'Assumptions'!B10))))+'Inputs_Data'!D9,0+('Inputs_Data'!D9*(1-AVERAGE('Assumptions'!B6,'Assumptions'!B7,'Assumptions'!B8,'Assumptions'!B9)))))) | K56: =(IF(4=0,-'Inputs_Data'!H5,0))+(IF(AND(4>=1,4<='Scenarios_10'!B8),MAX(0,(MAX(0,'Scenarios_10'!D8-'Scenarios_10'!E8/'Scenarios_10'!B8))-IF(AND(4>('Scenarios_10'!B8-4),4<='Scenarios_10'!B8),'Scenarios_10'!F8,0)),0))+(IF(4=0,'Scenarios_10'!E8,0))-(IF(4=0,0,IF('Scenarios_10'!C8="uniform_pct",'Inputs_Data'!E9*(1-(MIN('Scenarios_10'!G8,'Assumptions'!B10))),IF('Scenarios_10'!C8="electricity_only_pct",('Inputs_Data'!C9*(1-(MIN('Scenarios_10'!G8,'Assumptions'!B10))))+'Inputs_Data'!D9,0+('Inputs_Data'!D9*(1-AVERAGE('Assumptions'!B6,'Assumptions'!B7,'Assumptions'!B8,'Assumptions'!B9))))))) | L56: =(L55)+(K56)
A57: 5 | B57: =IF(5=0,-'Inputs_Data'!H5,0) | C57: =IF(5=0,0,'Inputs_Data'!B10) | D57: =IF(5=0,0,'Inputs_Data'!E10) | E57: =(IF(5=0,-'Inputs_Data'!H5,0))+(IF(5=0,0,'Inputs_Data'!B10))-(IF(5=0,0,'Inputs_Data'!E10)) | F57: =(F56)+(E57) | G57: =IF(5=0,-'Inputs_Data'!H5,0) | H57: =IF(AND(5>=1,5<='Scenarios_10'!B8),MAX(0,(MAX(0,'Scenarios_10'!D8-'Scenarios_10'!E8/'Scenarios_10'!B8))-IF(AND(5>('Scenarios_10'!B8-4),5<='Scenarios_10'!B8),'Scenarios_10'!F8,0)),0) | I57: =IF(5=0,'Scenarios_10'!E8,0) | J57: =IF(5=0,0,IF('Scenarios_10'!C8="uniform_pct",'Inputs_Data'!E10*(1-(MIN('Scenarios_10'!G8,'Assumptions'!B10))),IF('Scenarios_10'!C8="electricity_only_pct",('Inputs_Data'!C10*(1-(MIN('Scenarios_10'!G8,'Assumptions'!B10))))+'Inputs_Data'!D10,0+('Inputs_Data'!D10*(1-AVERAGE('Assumptions'!B6,'Assumptions'!B7,'Assumptions'!B8,'Assumptions'!B9)))))) | K57: =(IF(5=0,-'Inputs_Data'!H5,0))+(IF(AND(5>=1,5<='Scenarios_10'!B8),MAX(0,(MAX(0,'Scenarios_10'!D8-'Scenarios_10'!E8/'Scenarios_10'!B8))-IF(AND(5>('Scenarios_10'!B8-4),5<='Scenarios_10'!B8),'Scenarios_10'!F8,0)),0))+(IF(5=0,'Scenarios_10'!E8,0))-(IF(5=0,0,IF('Scenarios_10'!C8="uniform_pct",'Inputs_Data'!E10*(1-(MIN('Scenarios_10'!G8,'Assumptions'!B10))),IF('Scenarios_10'!C8="electricity_only_pct",('Inputs_Data'!C10*(1-(MIN('Scenarios_10'!G8,'Assumptions'!B10))))+'Inputs_Data'!D10,0+('Inputs_Data'!D10*(1-AVERAGE('Assumptions'!B6,'Assumptions'!B7,'Assumptions'!B8,'Assumptions'!B9))))))) | L57: =(L56)+(K57)
A58: 6 | B58: =IF(6=0,-'Inputs_Data'!H5,0) | C58: =IF(6=0,0,'Inputs_Data'!B11) | D58: =IF(6=0,0,'Inputs_Data'!E11) | E58: =(IF(6=0,-'Inputs_Data'!H5,0))+(IF(6=0,0,'Inputs_Data'!B11))-(IF(6=0,0,'Inputs_Data'!E11)) | F58: =(F57)+(E58) | G58: =IF(6=0,-'Inputs_Data'!H5,0) | H58: =IF(AND(6>=1,6<='Scenarios_10'!B8),MAX(0,(MAX(0,'Scenarios_10'!D8-'Scenarios_10'!E8/'Scenarios_10'!B8))-IF(AND(6>('Scenarios_10'!B8-4),6<='Scenarios_10'!B8),'Scenarios_10'!F8,0)),0) | I58: =IF(6=0,'Scenarios_10'!E8,0) | J58: =IF(6=0,0,IF('Scenarios_10'!C8="uniform_pct",'Inputs_Data'!E11*(1-(MIN('Scenarios_10'!G8,'Assumptions'!B10))),IF('Scenarios_10'!C8="electricity_only_pct",('Inputs_Data'!C11*(1-(MIN('Scenarios_10'!G8,'Assumptions'!B10))))+'Inputs_Data'!D11,0+('Inputs_Data'!D11*(1-AVERAGE('Assumptions'!B6,'Assumptions'!B7,'Assumptions'!B8,'Assumptions'!B9)))))) | K58: =(IF(6=0,-'Inputs_Data'!H5,0))+(IF(AND(6>=1,6<='Scenarios_10'!B8),MAX(0,(MAX(0,'Scenarios_10'!D8-'Scenarios_10'!E8/'Scenarios_10'!B8))-IF(AND(6>('Scenarios_10'!B8-4),6<='Scenarios_10'!B8),'Scenarios_10'!F8,0)),0))+(IF(6=0,'Scenarios_10'!E8,0))-(IF(6=0,0,IF('Scenarios_10'!C8="uniform_pct",'Inputs_Data'!E11*(1-(MIN('Scenarios_10'!G8,'Assumptions'!B10))),IF('Scenarios_10'!C8="electricity_only_pct",('Inputs_Data'!C11*(1-(MIN('Scenarios_10'!G8,'Assumptions'!B10))))+'Inputs_Data'!D11,0+('Inputs_Data'!D11*(1-AVERAGE('Assumptions'!B6,'Assumptions'!B7,'Assumptions'!B8,'Assumptions'!B9))))))) | L58: =(L57)+(K58)
A59: 7 | B59: =IF(7=0,-'Inputs_Data'!H5,0) | C59: =IF(7=0,0,'Inputs_Data'!B12) | D59: =IF(7=0,0,'Inputs_Data'!E12) | E59: =(IF(7=0,-'Inputs_Data'!H5,0))+(IF(7=0,0,'Inputs_Data'!B12))-(IF(7=0,0,'Inputs_Data'!E12)) | F59: =(F58)+(E59) | G59: =IF(7=0,-'Inputs_Data'!H5,0) | H59: =IF(AND(7>=1,7<='Scenarios_10'!B8),MAX(0,(MAX(0,'Scenarios_10'!D8-'Scenarios_10'!E8/'Scenarios_10'!B8))-IF(AND(7>('Scenarios_10'!B8-4),7<='Scenarios_10'!B8),'Scenarios_10'!F8,0)),0) | I59: =IF(7=0,'Scenarios_10'!E8,0) | J59: =IF(7=0,0,IF('Scenarios_10'!C8="uniform_pct",'Inputs_Data'!E12*(1-(MIN('Scenarios_10'!G8,'Assumptions'!B10))),IF('Scenarios_10'!C8="electricity_only_pct",('Inputs_Data'!C12*(1-(MIN('Scenarios_10'!G8,'Assumptions'!B10))))+'Inputs_Data'!D12,0+('Inputs_Data'!D12*(1-AVERAGE('Assumptions'!B6,'Assumptions'!B7,'Assumptions'!B8,'Assumptions'!B9)))))) | K59: =(IF(7=0,-'Inputs_Data'!H5,0))+(IF(AND(7>=1,7<='Scenarios_10'!B8),MAX(0,(MAX(0,'Scenarios_10'!D8-'Scenarios_10'!E8/'Scenarios_10'!B8))-IF(AND(7>('Scenarios_10'!B8-4),7<='Scenarios_10'!B8),'Scenarios_10'!F8,0)),0))+(IF(7=0,'Scenarios_10'!E8,0))-(IF(7=0,0,IF('Scenarios_10'!C8="uniform_pct",'Inputs_Data'!E12*(1-(MIN('Scenarios_10'!G8,'Assumptions'!B10))),IF('Scenarios_10'!C8="electricity_only_pct",('Inputs_Data'!C12*(1-(MIN('Scenarios_10'!G8,'Assumptions'!B10))))+'Inputs_Data'!D12,0+('Inputs_Data'!D12*(1-AVERAGE('Assumptions'!B6,'Assumptions'!B7,'Assumptions'!B8,'Assumptions'!B9))))))) | L59: =(L58)+(K59)
A60: 8 | B60: =IF(8=0,-'Inputs_Data'!H5,0) | C60: =IF(8=0,0,'Inputs_Data'!B13) | D60: =IF(8=0,0,'Inputs_Data'!E13) | E60: =(IF(8=0,-'Inputs_Data'!H5,0))+(IF(8=0,0,'Inputs_Data'!B13))-(IF(8=0,0,'Inputs_Data'!E13)) | F60: =(F59)+(E60) | G60: =IF(8=0,-'Inputs_Data'!H5,0) | H60: =IF(AND(8>=1,8<='Scenarios_10'!B8),MAX(0,(MAX(0,'Scenarios_10'!D8-'Scenarios_10'!E8/'Scenarios_10'!B8))-IF(AND(8>('Scenarios_10'!B8-4),8<='Scenarios_10'!B8),'Scenarios_10'!F8,0)),0) | I60: =IF(8=0,'Scenarios_10'!E8,0) | J60: =IF(8=0,0,IF('Scenarios_10'!C8="uniform_pct",'Inputs_Data'!E13*(1-(MIN('Scenarios_10'!G8,'Assumptions'!B10))),IF('Scenarios_10'!C8="electricity_only_pct",('Inputs_Data'!C13*(1-(MIN('Scenarios_10'!G8,'Assumptions'!B10))))+'Inputs_Data'!D13,0+('Inputs_Data'!D13*(1-AVERAGE('Assumptions'!B6,'Assumptions'!B7,'Assumptions'!B8,'Assumptions'!B9)))))) | K60: =(IF(8=0,-'Inputs_Data'!H5,0))+(IF(AND(8>=1,8<='Scenarios_10'!B8),MAX(0,(MAX(0,'Scenarios_10'!D8-'Scenarios_10'!E8/'Scenarios_10'!B8))-IF(AND(8>('Scenarios_10'!B8-4),8<='Scenarios_10'!B8),'Scenarios_10'!F8,0)),0))+(IF(8=0,'Scenarios_10'!E8,0))-(IF(8=0,0,IF('Scenarios_10'!C8="uniform_pct",'Inputs_Data'!E13*(1-(MIN('Scenarios_10'!G8,'Assumptions'!B10))),IF('Scenarios_10'!C8="electricity_only_pct",('Inputs_Data'!C13*(1-(MIN('Scenarios_10'!G8,'Assumptions'!B10))))+'Inputs_Data'!D13,0+('Inputs_Data'!D13*(1-AVERAGE('Assumptions'!B6,'Assumptions'!B7,'Assumptions'!B8,'Assumptions'!B9))))))) | L60: =(L59)+(K60)
A61: 9 | B61: =IF(9=0,-'Inputs_Data'!H5,0) | C61: =IF(9=0,0,'Inputs_Data'!B14) | D61: =IF(9=0,0,'Inputs_Data'!E14) | E61: =(IF(9=0,-'Inputs_Data'!H5,0))+(IF(9=0,0,'Inputs_Data'!B14))-(IF(9=0,0,'Inputs_Data'!E14)) | F61: =(F60)+(E61) | G61: =IF(9=0,-'Inputs_Data'!H5,0) | H61: =IF(AND(9>=1,9<='Scenarios_10'!B8),MAX(0,(MAX(0,'Scenarios_10'!D8-'Scenarios_10'!E8/'Scenarios_10'!B8))-IF(AND(9>('Scenarios_10'!B8-4),9<='Scenarios_10'!B8),'Scenarios_10'!F8,0)),0) | I61: =IF(9=0,'Scenarios_10'!E8,0) | J61: =IF(9=0,0,IF('Scenarios_10'!C8="uniform_pct",'Inputs_Data'!E14*(1-(MIN('Scenarios_10'!G8,'Assumptions'!B10))),IF('Scenarios_10'!C8="electricity_only_pct",('Inputs_Data'!C14*(1-(MIN('Scenarios_10'!G8,'Assumptions'!B10))))+'Inputs_Data'!D14,0+('Inputs_Data'!D14*(1-AVERAGE('Assumptions'!B6,'Assumptions'!B7,'Assumptions'!B8,'Assumptions'!B9)))))) | K61: =(IF(9=0,-'Inputs_Data'!H5,0))+(IF(AND(9>=1,9<='Scenarios_10'!B8),MAX(0,(MAX(0,'Scenarios_10'!D8-'Scenarios_10'!E8/'Scenarios_10'!B8))-IF(AND(9>('Scenarios_10'!B8-4),9<='Scenarios_10'!B8),'Scenarios_10'!F8,0)),0))+(IF(9=0,'Scenarios_10'!E8,0))-(IF(9=0,0,IF('Scenarios_10'!C8="uniform_pct",'Inputs_Data'!E14*(1-(MIN('Scenarios_10'!G8,'Assumptions'!B10))),IF('Scenarios_10'!C8="electricity_only_pct",('Inputs_Data'!C14*(1-(MIN('Scenarios_10'!G8,'Assumptions'!B10))))+'Inputs_Data'!D14,0+('Inputs_Data'!D14*(1-AVERAGE('Assumptions'!B6,'Assumptions'!B7,'Assumptions'!B8,'Assumptions'!B9))))))) | L61: =(L60)+(K61)
A62: 10 | B62: =IF(10=0,-'Inputs_Data'!H5,0) | C62: =IF(10=0,0,'Inputs_Data'!B15) | D62: =IF(10=0,0,'Inputs_Data'!E15) | E62: =(IF(10=0,-'Inputs_Data'!H5,0))+(IF(10=0,0,'Inputs_Data'!B15))-(IF(10=0,0,'Inputs_Data'!E15)) | F62: =(F61)+(E62) | G62: =IF(10=0,-'Inputs_Data'!H5,0) | H62: =IF(AND(10>=1,10<='Scenarios_10'!B8),MAX(0,(MAX(0,'Scenarios_10'!D8-'Scenarios_10'!E8/'Scenarios_10'!B8))-IF(AND(10>('Scenarios_10'!B8-4),10<='Scenarios_10'!B8),'Scenarios_10'!F8,0)),0) | I62: =IF(10=0,'Scenarios_10'!E8,0) | J62: =IF(10=0,0,IF('Scenarios_10'!C8="uniform_pct",'Inputs_Data'!E15*(1-(MIN('Scenarios_10'!G8,'Assumptions'!B10))),IF('Scenarios_10'!C8="electricity_only_pct",('Inputs_Data'!C15*(1-(MIN('Scenarios_10'!G8,'Assumptions'!B10))))+'Inputs_Data'!D15,0+('Inputs_Data'!D15*(1-AVERAGE('Assumptions'!B6,'Assumptions'!B7,'Assumptions'!B8,'Assumptions'!B9)))))) | K62: =(IF(10=0,-'Inputs_Data'!H5,0))+(IF(AND(10>=1,10<='Scenarios_10'!B8),MAX(0,(MAX(0,'Scenarios_10'!D8-'Scenarios_10'!E8/'Scenarios_10'!B8))-IF(AND(10>('Scenarios_10'!B8-4),10<='Scenarios_10'!B8),'Scenarios_10'!F8,0)),0))+(IF(10=0,'Scenarios_10'!E8,0))-(IF(10=0,0,IF('Scenarios_10'!C8="uniform_pct",'Inputs_Data'!E15*(1-(MIN('Scenarios_10'!G8,'Assumptions'!B10))),IF('Scenarios_10'!C8="electricity_only_pct",('Inputs_Data'!C15*(1-(MIN('Scenarios_10'!G8,'Assumptions'!B10))))+'Inputs_Data'!D15,0+('Inputs_Data'!D15*(1-AVERAGE('Assumptions'!B6,'Assumptions'!B7,'Assumptions'!B8,'Assumptions'!B9))))))) | L62: =(L61)+(K62)
A65: Tier: ='Scenarios_10'!A9
A66: year | B66: trust_capex | C66: trust_fee | D66: trust_cash_opex | E66: trust_net_cf | F66: trust_cum_cf | G66: laas_capex | H66: laas_fee | I66: laas_upfront | J66: laas_cash_opex | K66: laas_net_cf | L66: laas_cum_cf
A67: 0 | B67: =IF(0=0,-'Inputs_Data'!H5,0) | C67: =IF(0=0,0,'Inputs_Data'!B5) | D67: =IF(0=0,0,'Inputs_Data'!E5) | E67: =(IF(0=0,-'Inputs_Data'!H5,0))+(IF(0=0,0,'Inputs_Data'!B5))-(IF(0=0,0,'Inputs_Data'!E5)) | F67: =(0)+(E67) | G67: =IF(0=0,-'Inputs_Data'!H5,0) | H67: =IF(AND(0>=1,0<='Scenarios_10'!B9),MAX(0,(MAX(0,'Scenarios_10'!D9-'Scenarios_10'!E9/'Scenarios_10'!B9))-IF(AND(0>('Scenarios_10'!B9-4),0<='Scenarios_10'!B9),'Scenarios_10'!F9,0)),0) | I67: =IF(0=0,'Scenarios_10'!E9,0) | J67: =IF(0=0,0,IF('Scenarios_10'!C9="uniform_pct",'Inputs_Data'!E5*(1-(MIN('Scenarios_10'!G9,'Assumptions'!B10))),IF('Scenarios_10'!C9="electricity_only_pct",('Inputs_Data'!C5*(1-(MIN('Scenarios_10'!G9,'Assumptions'!B10))))+'Inputs_Data'!D5,0+('Inputs_Data'!D5*(1-AVERAGE('Assumptions'!B6,'Assumptions'!B7,'Assumptions'!B8,'Assumptions'!B9)))))) | K67: =(IF(0=0,-'Inputs_Data'!H5,0))+(IF(AND(0>=1,0<='Scenarios_10'!B9),MAX(0,(MAX(0,'Scenarios_10'!D9-'Scenarios_10'!E9/'Scenarios_10'!B9))-IF(AND(0>('Scenarios_10'!B9-4),0<='Scenarios_10'!B9),'Scenarios_10'!F9,0)),0))+(IF(0=0,'Scenarios_10'!E9,0))-(IF(0=0,0,IF('Scenarios_10'!C9="uniform_pct",'Inputs_Data'!E5*(1-(MIN('Scenarios_10'!G9,'Assumptions'!B10))),IF('Scenarios_10'!C9="electricity_only_pct",('Inputs_Data'!C5*(1-(MIN('Scenarios_10'!G9,'Assumptions'!B10))))+'Inputs_Data'!D5,0+('Inputs_Data'!D5*(1-AVERAGE('Assumptions'!B6,'Assumptions'!B7,'Assumptions'!B8,'Assumptions'!B9))))))) | L67: =(0)+(K67)
A68: 1 | B68: =IF(1=0,-'Inputs_Data'!H5,0) | C68: =IF(1=0,0,'Inputs_Data'!B6) | D68: =IF(1=0,0,'Inputs_Data'!E6) | E68: =(IF(1=0,-'Inputs_Data'!H5,0))+(IF(1=0,0,'Inputs_Data'!B6))-(IF(1=0,0,'Inputs_Data'!E6)) | F68: =(F67)+(E68) | G68: =IF(1=0,-'Inputs_Data'!H5,0) | H68: =IF(AND(1>=1,1<='Scenarios_10'!B9),MAX(0,(MAX(0,'Scenarios_10'!D9-'Scenarios_10'!E9/'Scenarios_10'!B9))-IF(AND(1>('Scenarios_10'!B9-4),1<='Scenarios_10'!B9),'Scenarios_10'!F9,0)),0) | I68: =IF(1=0,'Scenarios_10'!E9,0) | J68: =IF(1=0,0,IF('Scenarios_10'!C9="uniform_pct",'Inputs_Data'!E6*(1-(MIN('Scenarios_10'!G9,'Assumptions'!B10))),IF('Scenarios_10'!C9="electricity_only_pct",('Inputs_Data'!C6*(1-(MIN('Scenarios_10'!G9,'Assumptions'!B10))))+'Inputs_Data'!D6,0+('Inputs_Data'!D6*(1-AVERAGE('Assumptions'!B6,'Assumptions'!B7,'Assumptions'!B8,'Assumptions'!B9)))))) | K68: =(IF(1=0,-'Inputs_Data'!H5,0))+(IF(AND(1>=1,1<='Scenarios_10'!B9),MAX(0,(MAX(0,'Scenarios_10'!D9-'Scenarios_10'!E9/'Scenarios_10'!B9))-IF(AND(1>('Scenarios_10'!B9-4),1<='Scenarios_10'!B9),'Scenarios_10'!F9,0)),0))+(IF(1=0,'Scenarios_10'!E9,0))-(IF(1=0,0,IF('Scenarios_10'!C9="uniform_pct",'Inputs_Data'!E6*(1-(MIN('Scenarios_10'!G9,'Assumptions'!B10))),IF('Scenarios_10'!C9="electricity_only_pct",('Inputs_Data'!C6*(1-(MIN('Scenarios_10'!G9,'Assumptions'!B10))))+'Inputs_Data'!D6,0+('Inputs_Data'!D6*(1-AVERAGE('Assumptions'!B6,'Assumptions'!B7,'Assumptions'!B8,'Assumptions'!B9))))))) | L68: =(L67)+(K68)
A69: 2 | B69: =IF(2=0,-'Inputs_Data'!H5,0) | C69: =IF(2=0,0,'Inputs_Data'!B7) | D69: =IF(2=0,0,'Inputs_Data'!E7) | E69: =(IF(2=0,-'Inputs_Data'!H5,0))+(IF(2=0,0,'Inputs_Data'!B7))-(IF(2=0,0,'Inputs_Data'!E7)) | F69: =(F68)+(E69) | G69: =IF(2=0,-'Inputs_Data'!H5,0) | H69: =IF(AND(2>=1,2<='Scenarios_10'!B9),MAX(0,(MAX(0,'Scenarios_10'!D9-'Scenarios_10'!E9/'Scenarios_10'!B9))-IF(AND(2>('Scenarios_10'!B9-4),2<='Scenarios_10'!B9),'Scenarios_10'!F9,0)),0) | I69: =IF(2=0,'Scenarios_10'!E9,0) | J69: =IF(2=0,0,IF('Scenarios_10'!C9="uniform_pct",'Inputs_Data'!E7*(1-(MIN('Scenarios_10'!G9,'Assumptions'!B10))),IF('Scenarios_10'!C9="electricity_only_pct",('Inputs_Data'!C7*(1-(MIN('Scenarios_10'!G9,'Assumptions'!B10))))+'Inputs_Data'!D7,0+('Inputs_Data'!D7*(1-AVERAGE('Assumptions'!B6,'Assumptions'!B7,'Assumptions'!B8,'Assumptions'!B9)))))) | K69: =(IF(2=0,-'Inputs_Data'!H5,0))+(IF(AND(2>=1,2<='Scenarios_10'!B9),MAX(0,(MAX(0,'Scenarios_10'!D9-'Scenarios_10'!E9/'Scenarios_10'!B9))-IF(AND(2>('Scenarios_10'!B9-4),2<='Scenarios_10'!B9),'Scenarios_10'!F9,0)),0))+(IF(2=0,'Scenarios_10'!E9,0))-(IF(2=0,0,IF('Scenarios_10'!C9="uniform_pct",'Inputs_Data'!E7*(1-(MIN('Scenarios_10'!G9,'Assumptions'!B10))),IF('Scenarios_10'!C9="electricity_only_pct",('Inputs_Data'!C7*(1-(MIN('Scenarios_10'!G9,'Assumptions'!B10))))+'Inputs_Data'!D7,0+('Inputs_Data'!D7*(1-AVERAGE('Assumptions'!B6,'Assumptions'!B7,'Assumptions'!B8,'Assumptions'!B9))))))) | L69: =(L68)+(K69)
A70: 3 | B70: =IF(3=0,-'Inputs_Data'!H5,0) | C70: =IF(3=0,0,'Inputs_Data'!B8) | D70: =IF(3=0,0,'Inputs_Data'!E8) | E70: =(IF(3=0,-'Inputs_Data'!H5,0))+(IF(3=0,0,'Inputs_Data'!B8))-(IF(3=0,0,'Inputs_Data'!E8)) | F70: =(F69)+(E70) | G70: =IF(3=0,-'Inputs_Data'!H5,0) | H70: =IF(AND(3>=1,3<='Scenarios_10'!B9),MAX(0,(MAX(0,'Scenarios_10'!D9-'Scenarios_10'!E9/'Scenarios_10'!B9))-IF(AND(3>('Scenarios_10'!B9-4),3<='Scenarios_10'!B9),'Scenarios_10'!F9,0)),0) | I70: =IF(3=0,'Scenarios_10'!E9,0) | J70: =IF(3=0,0,IF('Scenarios_10'!C9="uniform_pct",'Inputs_Data'!E8*(1-(MIN('Scenarios_10'!G9,'Assumptions'!B10))),IF('Scenarios_10'!C9="electricity_only_pct",('Inputs_Data'!C8*(1-(MIN('Scenarios_10'!G9,'Assumptions'!B10))))+'Inputs_Data'!D8,0+('Inputs_Data'!D8*(1-AVERAGE('Assumptions'!B6,'Assumptions'!B7,'Assumptions'!B8,'Assumptions'!B9)))))) | K70: =(IF(3=0,-'Inputs_Data'!H5,0))+(IF(AND(3>=1,3<='Scenarios_10'!B9),MAX(0,(MAX(0,'Scenarios_10'!D9-'Scenarios_10'!E9/'Scenarios_10'!B9))-IF(AND(3>('Scenarios_10'!B9-4),3<='Scenarios_10'!B9),'Scenarios_10'!F9,0)),0))+(IF(3=0,'Scenarios_10'!E9,0))-(IF(3=0,0,IF('Scenarios_10'!C9="uniform_pct",'Inputs_Data'!E8*(1-(MIN('Scenarios_10'!G9,'Assumptions'!B10))),IF('Scenarios_10'!C9="electricity_only_pct",('Inputs_Data'!C8*(1-(MIN('Scenarios_10'!G9,'Assumptions'!B10))))+'Inputs_Data'!D8,0+('Inputs_Data'!D8*(1-AVERAGE('Assumptions'!B6,'Assumptions'!B7,'Assumptions'!B8,'Assumptions'!B9))))))) | L70: =(L69)+(K70)
A71: 4 | B71: =IF(4=0,-'Inputs_Data'!H5,0) | C71: =IF(4=0,0,'Inputs_Data'!B9) | D71: =IF(4=0,0,'Inputs_Data'!E9) | E71: =(IF(4=0,-'Inputs_Data'!H5,0))+(IF(4=0,0,'Inputs_Data'!B9))-(IF(4=0,0,'Inputs_Data'!E9)) | F71: =(F70)+(E71) | G71: =IF(4=0,-'Inputs_Data'!H5,0) | H71: =IF(AND(4>=1,4<='Scenarios_10'!B9),MAX(0,(MAX(0,'Scenarios_10'!D9-'Scenarios_10'!E9/'Scenarios_10'!B9))-IF(AND(4>('Scenarios_10'!B9-4),4<='Scenarios_10'!B9),'Scenarios_10'!F9,0)),0) | I71: =IF(4=0,'Scenarios_10'!E9,0) | J71: =IF(4=0,0,IF('Scenarios_10'!C9="uniform_pct",'Inputs_Data'!E9*(1-(MIN('Scenarios_10'!G9,'Assumptions'!B10))),IF('Scenarios_10'!C9="electricity_only_pct",('Inputs_Data'!C9*(1-(MIN('Scenarios_10'!G9,'Assumptions'!B10))))+'Inputs_Data'!D9,0+('Inputs_Data'!D9*(1-AVERAGE('Assumptions'!B6,'Assumptions'!B7,'Assumptions'!B8,'Assumptions'!B9)))))) | K71: =(IF(4=0,-'Inputs_Data'!H5,0))+(IF(AND(4>=1,4<='Scenarios_10'!B9),MAX(0,(MAX(0,'Scenarios_10'!D9-'Scenarios_10'!E9/'Scenarios_10'!B9))-IF(AND(4>('Scenarios_10'!B9-4),4<='Scenarios_10'!B9),'Scenarios_10'!F9,0)),0))+(IF(4=0,'Scenarios_10'!E9,0))-(IF(4=0,0,IF('Scenarios_10'!C9="uniform_pct",'Inputs_Data'!E9*(1-(MIN('Scenarios_10'!G9,'Assumptions'!B10))),IF('Scenarios_10'!C9="electricity_only_pct",('Inputs_Data'!C9*(1-(MIN('Scenarios_10'!G9,'Assumptions'!B10))))+'Inputs_Data'!D9,0+('Inputs_Data'!D9*(1-AVERAGE('Assumptions'!B6,'Assumptions'!B7,'Assumptions'!B8,'Assumptions'!B9))))))) | L71: =(L70)+(K71)
A72: 5 | B72: =IF(5=0,-'Inputs_Data'!H5,0) | C72: =IF(5=0,0,'Inputs_Data'!B10) | D72: =IF(5=0,0,'Inputs_Data'!E10) | E72: =(IF(5=0,-'Inputs_Data'!H5,0))+(IF(5=0,0,'Inputs_Data'!B10))-(IF(5=0,0,'Inputs_Data'!E10)) | F72: =(F71)+(E72) | G72: =IF(5=0,-'Inputs_Data'!H5,0) | H72: =IF(AND(5>=1,5<='Scenarios_10'!B9),MAX(0,(MAX(0,'Scenarios_10'!D9-'Scenarios_10'!E9/'Scenarios_10'!B9))-IF(AND(5>('Scenarios_10'!B9-4),5<='Scenarios_10'!B9),'Scenarios_10'!F9,0)),0) | I72: =IF(5=0,'Scenarios_10'!E9,0) | J72: =IF(5=0,0,IF('Scenarios_10'!C9="uniform_pct",'Inputs_Data'!E10*(1-(MIN('Scenarios_10'!G9,'Assumptions'!B10))),IF('Scenarios_10'!C9="electricity_only_pct",('Inputs_Data'!C10*(1-(MIN('Scenarios_10'!G9,'Assumptions'!B10))))+'Inputs_Data'!D10,0+('Inputs_Data'!D10*(1-AVERAGE('Assumptions'!B6,'Assumptions'!B7,'Assumptions'!B8,'Assumptions'!B9)))))) | K72: =(IF(5=0,-'Inputs_Data'!H5,0))+(IF(AND(5>=1,5<='Scenarios_10'!B9),MAX(0,(MAX(0,'Scenarios_10'!D9-'Scenarios_10'!E9/'Scenarios_10'!B9))-IF(AND(5>('Scenarios_10'!B9-4),5<='Scenarios_10'!B9),'Scenarios_10'!F9,0)),0))+(IF(5=0,'Scenarios_10'!E9,0))-(IF(5=0,0,IF('Scenarios_10'!C9="uniform_pct",'Inputs_Data'!E10*(1-(MIN('Scenarios_10'!G9,'Assumptions'!B10))),IF('Scenarios_10'!C9="electricity_only_pct",('Inputs_Data'!C10*(1-(MIN('Scenarios_10'!G9,'Assumptions'!B10))))+'Inputs_Data'!D10,0+('Inputs_Data'!D10*(1-AVERAGE('Assumptions'!B6,'Assumptions'!B7,'Assumptions'!B8,'Assumptions'!B9))))))) | L72: =(L71)+(K72)
A73: 6 | B73: =IF(6=0,-'Inputs_Data'!H5,0) | C73: =IF(6=0,0,'Inputs_Data'!B11) | D73: =IF(6=0,0,'Inputs_Data'!E11) | E73: =(IF(6=0,-'Inputs_Data'!H5,0))+(IF(6=0,0,'Inputs_Data'!B11))-(IF(6=0,0,'Inputs_Data'!E11)) | F73: =(F72)+(E73) | G73: =IF(6=0,-'Inputs_Data'!H5,0) | H73: =IF(AND(6>=1,6<='Scenarios_10'!B9),MAX(0,(MAX(0,'Scenarios_10'!D9-'Scenarios_10'!E9/'Scenarios_10'!B9))-IF(AND(6>('Scenarios_10'!B9-4),6<='Scenarios_10'!B9),'Scenarios_10'!F9,0)),0) | I73: =IF(6=0,'Scenarios_10'!E9,0) | J73: =IF(6=0,0,IF('Scenarios_10'!C9="uniform_pct",'Inputs_Data'!E11*(1-(MIN('Scenarios_10'!G9,'Assumptions'!B10))),IF('Scenarios_10'!C9="electricity_only_pct",('Inputs_Data'!C11*(1-(MIN('Scenarios_10'!G9,'Assumptions'!B10))))+'Inputs_Data'!D11,0+('Inputs_Data'!D11*(1-AVERAGE('Assumptions'!B6,'Assumptions'!B7,'Assumptions'!B8,'Assumptions'!B9)))))) | K73: =(IF(6=0,-'Inputs_Data'!H5,0))+(IF(AND(6>=1,6<='Scenarios_10'!B9),MAX(0,(MAX(0,'Scenarios_10'!D9-'Scenarios_10'!E9/'Scenarios_10'!B9))-IF(AND(6>('Scenarios_10'!B9-4),6<='Scenarios_10'!B9),'Scenarios_10'!F9,0)),0))+(IF(6=0,'Scenarios_10'!E9,0))-(IF(6=0,0,IF('Scenarios_10'!C9="uniform_pct",'Inputs_Data'!E11*(1-(MIN('Scenarios_10'!G9,'Assumptions'!B10))),IF('Scenarios_10'!C9="electricity_only_pct",('Inputs_Data'!C11*(1-(MIN('Scenarios_10'!G9,'Assumptions'!B10))))+'Inputs_Data'!D11,0+('Inputs_Data'!D11*(1-AVERAGE('Assumptions'!B6,'Assumptions'!B7,'Assumptions'!B8,'Assumptions'!B9))))))) | L73: =(L72)+(K73)
A74: 7 | B74: =IF(7=0,-'Inputs_Data'!H5,0) | C74: =IF(7=0,0,'Inputs_Data'!B12) | D74: =IF(7=0,0,'Inputs_Data'!E12) | E74: =(IF(7=0,-'Inputs_Data'!H5,0))+(IF(7=0,0,'Inputs_Data'!B12))-(IF(7=0,0,'Inputs_Data'!E12)) | F74: =(F73)+(E74) | G74: =IF(7=0,-'Inputs_Data'!H5,0) | H74: =IF(AND(7>=1,7<='Scenarios_10'!B9),MAX(0,(MAX(0,'Scenarios_10'!D9-'Scenarios_10'!E9/'Scenarios_10'!B9))-IF(AND(7>('Scenarios_10'!B9-4),7<='Scenarios_10'!B9),'Scenarios_10'!F9,0)),0) | I74: =IF(7=0,'Scenarios_10'!E9,0) | J74: =IF(7=0,0,IF('Scenarios_10'!C9="uniform_pct",'Inputs_Data'!E12*(1-(MIN('Scenarios_10'!G9,'Assumptions'!B10))),IF('Scenarios_10'!C9="electricity_only_pct",('Inputs_Data'!C12*(1-(MIN('Scenarios_10'!G9,'Assumptions'!B10))))+'Inputs_Data'!D12,0+('Inputs_Data'!D12*(1-AVERAGE('Assumptions'!B6,'Assumptions'!B7,'Assumptions'!B8,'Assumptions'!B9)))))) | K74: =(IF(7=0,-'Inputs_Data'!H5,0))+(IF(AND(7>=1,7<='Scenarios_10'!B9),MAX(0,(MAX(0,'Scenarios_10'!D9-'Scenarios_10'!E9/'Scenarios_10'!B9))-IF(AND(7>('Scenarios_10'!B9-4),7<='Scenarios_10'!B9),'Scenarios_10'!F9,0)),0))+(IF(7=0,'Scenarios_10'!E9,0))-(IF(7=0,0,IF('Scenarios_10'!C9="uniform_pct",'Inputs_Data'!E12*(1-(MIN('Scenarios_10'!G9,'Assumptions'!B10))),IF('Scenarios_10'!C9="electricity_only_pct",('Inputs_Data'!C12*(1-(MIN('Scenarios_10'!G9,'Assumptions'!B10))))+'Inputs_Data'!D12,0+('Inputs_Data'!D12*(1-AVERAGE('Assumptions'!B6,'Assumptions'!B7,'Assumptions'!B8,'Assumptions'!B9))))))) | L74: =(L73)+(K74)
A75: 8 | B75: =IF(8=0,-'Inputs_Data'!H5,0) | C75: =IF(8=0,0,'Inputs_Data'!B13) | D75: =IF(8=0,0,'Inputs_Data'!E13) | E75: =(IF(8=0,-'Inputs_Data'!H5,0))+(IF(8=0,0,'Inputs_Data'!B13))-(IF(8=0,0,'Inputs_Data'!E13)) | F75: =(F74)+(E75) | G75: =IF(8=0,-'Inputs_Data'!H5,0) | H75: =IF(AND(8>=1,8<='Scenarios_10'!B9),MAX(0,(MAX(0,'Scenarios_10'!D9-'Scenarios_10'!E9/'Scenarios_10'!B9))-IF(AND(8>('Scenarios_10'!B9-4),8<='Scenarios_10'!B9),'Scenarios_10'!F9,0)),0) | I75: =IF(8=0,'Scenarios_10'!E9,0) | J75: =IF(8=0,0,IF('Scenarios_10'!C9="uniform_pct",'Inputs_Data'!E13*(1-(MIN('Scenarios_10'!G9,'Assumptions'!B10))),IF('Scenarios_10'!C9="electricity_only_pct",('Inputs_Data'!C13*(1-(MIN('Scenarios_10'!G9,'Assumptions'!B10))))+'Inputs_Data'!D13,0+('Inputs_Data'!D13*(1-AVERAGE('Assumptions'!B6,'Assumptions'!B7,'Assumptions'!B8,'Assumptions'!B9)))))) | K75: =(IF(8=0,-'Inputs_Data'!H5,0))+(IF(AND(8>=1,8<='Scenarios_10'!B9),MAX(0,(MAX(0,'Scenarios_10'!D9-'Scenarios_10'!E9/'Scenarios_10'!B9))-IF(AND(8>('Scenarios_10'!B9-4),8<='Scenarios_10'!B9),'Scenarios_10'!F9,0)),0))+(IF(8=0,'Scenarios_10'!E9,0))-(IF(8=0,0,IF('Scenarios_10'!C9="uniform_pct",'Inputs_Data'!E13*(1-(MIN('Scenarios_10'!G9,'Assumptions'!B10))),IF('Scenarios_10'!C9="electricity_only_pct",('Inputs_Data'!C13*(1-(MIN('Scenarios_10'!G9,'Assumptions'!B10))))+'Inputs_Data'!D13,0+('Inputs_Data'!D13*(1-AVERAGE('Assumptions'!B6,'Assumptions'!B7,'Assumptions'!B8,'Assumptions'!B9))))))) | L75: =(L74)+(K75)
A76: 9 | B76: =IF(9=0,-'Inputs_Data'!H5,0) | C76: =IF(9=0,0,'Inputs_Data'!B14) | D76: =IF(9=0,0,'Inputs_Data'!E14) | E76: =(IF(9=0,-'Inputs_Data'!H5,0))+(IF(9=0,0,'Inputs_Data'!B14))-(IF(9=0,0,'Inputs_Data'!E14)) | F76: =(F75)+(E76) | G76: =IF(9=0,-'Inputs_Data'!H5,0) | H76: =IF(AND(9>=1,9<='Scenarios_10'!B9),MAX(0,(MAX(0,'Scenarios_10'!D9-'Scenarios_10'!E9/'Scenarios_10'!B9))-IF(AND(9>('Scenarios_10'!B9-4),9<='Scenarios_10'!B9),'Scenarios_10'!F9,0)),0) | I76: =IF(9=0,'Scenarios_10'!E9,0) | J76: =IF(9=0,0,IF('Scenarios_10'!C9="uniform_pct",'Inputs_Data'!E14*(1-(MIN('Scenarios_10'!G9,'Assumptions'!B10))),IF('Scenarios_10'!C9="electricity_only_pct",('Inputs_Data'!C14*(1-(MIN('Scenarios_10'!G9,'Assumptions'!B10))))+'Inputs_Data'!D14,0+('Inputs_Data'!D14*(1-AVERAGE('Assumptions'!B6,'Assumptions'!B7,'Assumptions'!B8,'Assumptions'!B9)))))) | K76: =(IF(9=0,-'Inputs_Data'!H5,0))+(IF(AND(9>=1,9<='Scenarios_10'!B9),MAX(0,(MAX(0,'Scenarios_10'!D9-'Scenarios_10'!E9/'Scenarios_10'!B9))-IF(AND(9>('Scenarios_10'!B9-4),9<='Scenarios_10'!B9),'Scenarios_10'!F9,0)),0))+(IF(9=0,'Scenarios_10'!E9,0))-(IF(9=0,0,IF('Scenarios_10'!C9="uniform_pct",'Inputs_Data'!E14*(1-(MIN('Scenarios_10'!G9,'Assumptions'!B10))),IF('Scenarios_10'!C9="electricity_only_pct",('Inputs_Data'!C14*(1-(MIN('Scenarios_10'!G9,'Assumptions'!B10))))+'Inputs_Data'!D14,0+('Inputs_Data'!D14*(1-AVERAGE('Assumptions'!B6,'Assumptions'!B7,'Assumptions'!B8,'Assumptions'!B9))))))) | L76: =(L75)+(K76)
A77: 10 | B77: =IF(10=0,-'Inputs_Data'!H5,0) | C77: =IF(10=0,0,'Inputs_Data'!B15) | D77: =IF(10=0,0,'Inputs_Data'!E15) | E77: =(IF(10=0,-'Inputs_Data'!H5,0))+(IF(10=0,0,'Inputs_Data'!B15))-(IF(10=0,0,'Inputs_Data'!E15)) | F77: =(F76)+(E77) | G77: =IF(10=0,-'Inputs_Data'!H5,0) | H77: =IF(AND(10>=1,10<='Scenarios_10'!B9),MAX(0,(MAX(0,'Scenarios_10'!D9-'Scenarios_10'!E9/'Scenarios_10'!B9))-IF(AND(10>('Scenarios_10'!B9-4),10<='Scenarios_10'!B9),'Scenarios_10'!F9,0)),0) | I77: =IF(10=0,'Scenarios_10'!E9,0) | J77: =IF(10=0,0,IF('Scenarios_10'!C9="uniform_pct",'Inputs_Data'!E15*(1-(MIN('Scenarios_10'!G9,'Assumptions'!B10))),IF('Scenarios_10'!C9="electricity_only_pct",('Inputs_Data'!C15*(1-(MIN('Scenarios_10'!G9,'Assumptions'!B10))))+'Inputs_Data'!D15,0+('Inputs_Data'!D15*(1-AVERAGE('Assumptions'!B6,'Assumptions'!B7,'Assumptions'!B8,'Assumptions'!B9)))))) | K77: =(IF(10=0,-'Inputs_Data'!H5,0))+(IF(AND(10>=1,10<='Scenarios_10'!B9),MAX(0,(MAX(0,'Scenarios_10'!D9-'Scenarios_10'!E9/'Scenarios_10'!B9))-IF(AND(10>('Scenarios_10'!B9-4),10<='Scenarios_10'!B9),'Scenarios_10'!F9,0)),0))+(IF(10=0,'Scenarios_10'!E9,0))-(IF(10=0,0,IF('Scenarios_10'!C9="uniform_pct",'Inputs_Data'!E15*(1-(MIN('Scenarios_10'!G9,'Assumptions'!B10))),IF('Scenarios_10'!C9="electricity_only_pct",('Inputs_Data'!C15*(1-(MIN('Scenarios_10'!G9,'Assumptions'!B10))))+'Inputs_Data'!D15,0+('Inputs_Data'!D15*(1-AVERAGE('Assumptions'!B6,'Assumptions'!B7,'Assumptions'!B8,'Assumptions'!B9))))))) | L77: =(L76)+(K77)
A80: Tier: ='Scenarios_10'!A10
A81: year | B81: trust_capex | C81: trust_fee | D81: trust_cash_opex | E81: trust_net_cf | F81: trust_cum_cf | G81: laas_capex | H81: laas_fee | I81: laas_upfront | J81: laas_cash_opex | K81: laas_net_cf | L81: laas_cum_cf
A82: 0 | B82: =IF(0=0,-'Inputs_Data'!H5,0) | C82: =IF(0=0,0,'Inputs_Data'!B5) | D82: =IF(0=0,0,'Inputs_Data'!E5) | E82: =(IF(0=0,-'Inputs_Data'!H5,0))+(IF(0=0,0,'Inputs_Data'!B5))-(IF(0=0,0,'Inputs_Data'!E5)) | F82: =(0)+(E82) | G82: =IF(0=0,-'Inputs_Data'!H5,0) | H82: =IF(AND(0>=1,0<='Scenarios_10'!B10),MAX(0,(MAX(0,'Scenarios_10'!D10-'Scenarios_10'!E10/'Scenarios_10'!B10))-IF(AND(0>('Scenarios_10'!B10-4),0<='Scenarios_10'!B10),'Scenarios_10'!F10,0)),0) | I82: =IF(0=0,'Scenarios_10'!E10,0) | J82: =IF(0=0,0,IF('Scenarios_10'!C10="uniform_pct",'Inputs_Data'!E5*(1-(MIN('Scenarios_10'!G10,'Assumptions'!B10))),IF('Scenarios_10'!C10="electricity_only_pct",('Inputs_Data'!C5*(1-(MIN('Scenarios_10'!G10,'Assumptions'!B10))))+'Inputs_Data'!D5,0+('Inputs_Data'!D5*(1-AVERAGE('Assumptions'!B6,'Assumptions'!B7,'Assumptions'!B8,'Assumptions'!B9)))))) | K82: =(IF(0=0,-'Inputs_Data'!H5,0))+(IF(AND(0>=1,0<='Scenarios_10'!B10),MAX(0,(MAX(0,'Scenarios_10'!D10-'Scenarios_10'!E10/'Scenarios_10'!B10))-IF(AND(0>('Scenarios_10'!B10-4),0<='Scenarios_10'!B10),'Scenarios_10'!F10,0)),0))+(IF(0=0,'Scenarios_10'!E10,0))-(IF(0=0,0,IF('Scenarios_10'!C10="uniform_pct",'Inputs_Data'!E5*(1-(MIN('Scenarios_10'!G10,'Assumptions'!B10))),IF('Scenarios_10'!C10="electricity_only_pct",('Inputs_Data'!C5*(1-(MIN('Scenarios_10'!G10,'Assumptions'!B10))))+'Inputs_Data'!D5,0+('Inputs_Data'!D5*(1-AVERAGE('Assumptions'!B6,'Assumptions'!B7,'Assumptions'!B8,'Assumptions'!B9))))))) | L82: =(0)+(K82)
A83: 1 | B83: =IF(1=0,-'Inputs_Data'!H5,0) | C83: =IF(1=0,0,'Inputs_Data'!B6) | D83: =IF(1=0,0,'Inputs_Data'!E6) | E83: =(IF(1=0,-'Inputs_Data'!H5,0))+(IF(1=0,0,'Inputs_Data'!B6))-(IF(1=0,0,'Inputs_Data'!E6)) | F83: =(F82)+(E83) | G83: =IF(1=0,-'Inputs_Data'!H5,0) | H83: =IF(AND(1>=1,1<='Scenarios_10'!B10),MAX(0,(MAX(0,'Scenarios_10'!D10-'Scenarios_10'!E10/'Scenarios_10'!B10))-IF(AND(1>('Scenarios_10'!B10-4),1<='Scenarios_10'!B10),'Scenarios_10'!F10,0)),0) | I83: =IF(1=0,'Scenarios_10'!E10,0) | J83: =IF(1=0,0,IF('Scenarios_10'!C10="uniform_pct",'Inputs_Data'!E6*(1-(MIN('Scenarios_10'!G10,'Assumptions'!B10))),IF('Scenarios_10'!C10="electricity_only_pct",('Inputs_Data'!C6*(1-(MIN('Scenarios_10'!G10,'Assumptions'!B10))))+'Inputs_Data'!D6,0+('Inputs_Data'!D6*(1-AVERAGE('Assumptions'!B6,'Assumptions'!B7,'Assumptions'!B8,'Assumptions'!B9)))))) | K83: =(IF(1=0,-'Inputs_Data'!H5,0))+(IF(AND(1>=1,1<='Scenarios_10'!B10),MAX(0,(MAX(0,'Scenarios_10'!D10-'Scenarios_10'!E10/'Scenarios_10'!B10))-IF(AND(1>('Scenarios_10'!B10-4),1<='Scenarios_10'!B10),'Scenarios_10'!F10,0)),0))+(IF(1=0,'Scenarios_10'!E10,0))-(IF(1=0,0,IF('Scenarios_10'!C10="uniform_pct",'Inputs_Data'!E6*(1-(MIN('Scenarios_10'!G10,'Assumptions'!B10))),IF('Scenarios_10'!C10="electricity_only_pct",('Inputs_Data'!C6*(1-(MIN('Scenarios_10'!G10,'Assumptions'!B10))))+'Inputs_Data'!D6,0+('Inputs_Data'!D6*(1-AVERAGE('Assumptions'!B6,'Assumptions'!B7,'Assumptions'!B8,'Assumptions'!B9))))))) | L83: =(L82)+(K83)
A84: 2 | B84: =IF(2=0,-'Inputs_Data'!H5,0) | C84: =IF(2=0,0,'Inputs_Data'!B7) | D84: =IF(2=0,0,'Inputs_Data'!E7) | E84: =(IF(2=0,-'Inputs_Data'!H5,0))+(IF(2=0,0,'Inputs_Data'!B7))-(IF(2=0,0,'Inputs_Data'!E7)) | F84: =(F83)+(E84) | G84: =IF(2=0,-'Inputs_Data'!H5,0) | H84: =IF(AND(2>=1,2<='Scenarios_10'!B10),MAX(0,(MAX(0,'Scenarios_10'!D10-'Scenarios_10'!E10/'Scenarios_10'!B10))-IF(AND(2>('Scenarios_10'!B10-4),2<='Scenarios_10'!B10),'Scenarios_10'!F10,0)),0) | I84: =IF(2=0,'Scenarios_10'!E10,0) | J84: =IF(2=0,0,IF('Scenarios_10'!C10="uniform_pct",'Inputs_Data'!E7*(1-(MIN('Scenarios_10'!G10,'Assumptions'!B10))),IF('Scenarios_10'!C10="electricity_only_pct",('Inputs_Data'!C7*(1-(MIN('Scenarios_10'!G10,'Assumptions'!B10))))+'Inputs_Data'!D7,0+('Inputs_Data'!D7*(1-AVERAGE('Assumptions'!B6,'Assumptions'!B7,'Assumptions'!B8,'Assumptions'!B9)))))) | K84: =(IF(2=0,-'Inputs_Data'!H5,0))+(IF(AND(2>=1,2<='Scenarios_10'!B10),MAX(0,(MAX(0,'Scenarios_10'!D10-'Scenarios_10'!E10/'Scenarios_10'!B10))-IF(AND(2>('Scenarios_10'!B10-4),2<='Scenarios_10'!B10),'Scenarios_10'!F10,0)),0))+(IF(2=0,'Scenarios_10'!E10,0))-(IF(2=0,0,IF('Scenarios_10'!C10="uniform_pct",'Inputs_Data'!E7*(1-(MIN('Scenarios_10'!G10,'Assumptions'!B10))),IF('Scenarios_10'!C10="electricity_only_pct",('Inputs_Data'!C7*(1-(MIN('Scenarios_10'!G10,'Assumptions'!B10))))+'Inputs_Data'!D7,0+('Inputs_Data'!D7*(1-AVERAGE('Assumptions'!B6,'Assumptions'!B7,'Assumptions'!B8,'Assumptions'!B9))))))) | L84: =(L83)+(K84)
A85: 3 | B85: =IF(3=0,-'Inputs_Data'!H5,0) | C85: =IF(3=0,0,'Inputs_Data'!B8) | D85: =IF(3=0,0,'Inputs_Data'!E8) | E85: =(IF(3=0,-'Inputs_Data'!H5,0))+(IF(3=0,0,'Inputs_Data'!B8))-(IF(3=0,0,'Inputs_Data'!E8)) | F85: =(F84)+(E85) | G85: =IF(3=0,-'Inputs_Data'!H5,0) | H85: =IF(AND(3>=1,3<='Scenarios_10'!B10),MAX(0,(MAX(0,'Scenarios_10'!D10-'Scenarios_10'!E10/'Scenarios_10'!B10))-IF(AND(3>('Scenarios_10'!B10-4),3<='Scenarios_10'!B10),'Scenarios_10'!F10,0)),0) | I85: =IF(3=0,'Scenarios_10'!E10,0) | J85: =IF(3=0,0,IF('Scenarios_10'!C10="uniform_pct",'Inputs_Data'!E8*(1-(MIN('Scenarios_10'!G10,'Assumptions'!B10))),IF('Scenarios_10'!C10="electricity_only_pct",('Inputs_Data'!C8*(1-(MIN('Scenarios_10'!G10,'Assumptions'!B10))))+'Inputs_Data'!D8,0+('Inputs_Data'!D8*(1-AVERAGE('Assumptions'!B6,'Assumptions'!B7,'Assumptions'!B8,'Assumptions'!B9)))))) | K85: =(IF(3=0,-'Inputs_Data'!H5,0))+(IF(AND(3>=1,3<='Scenarios_10'!B10),MAX(0,(MAX(0,'Scenarios_10'!D10-'Scenarios_10'!E10/'Scenarios_10'!B10))-IF(AND(3>('Scenarios_10'!B10-4),3<='Scenarios_10'!B10),'Scenarios_10'!F10,0)),0))+(IF(3=0,'Scenarios_10'!E10,0))-(IF(3=0,0,IF('Scenarios_10'!C10="uniform_pct",'Inputs_Data'!E8*(1-(MIN('Scenarios_10'!G10,'Assumptions'!B10))),IF('Scenarios_10'!C10="electricity_only_pct",('Inputs_Data'!C8*(1-(MIN('Scenarios_10'!G10,'Assumptions'!B10))))+'Inputs_Data'!D8,0+('Inputs_Data'!D8*(1-AVERAGE('Assumptions'!B6,'Assumptions'!B7,'Assumptions'!B8,'Assumptions'!B9))))))) | L85: =(L84)+(K85)
A86: 4 | B86: =IF(4=0,-'Inputs_Data'!H5,0) | C86: =IF(4=0,0,'Inputs_Data'!B9) | D86: =IF(4=0,0,'Inputs_Data'!E9) | E86: =(IF(4=0,-'Inputs_Data'!H5,0))+(IF(4=0,0,'Inputs_Data'!B9))-(IF(4=0,0,'Inputs_Data'!E9)) | F86: =(F85)+(E86) | G86: =IF(4=0,-'Inputs_Data'!H5,0) | H86: =IF(AND(4>=1,4<='Scenarios_10'!B10),MAX(0,(MAX(0,'Scenarios_10'!D10-'Scenarios_10'!E10/'Scenarios_10'!B10))-IF(AND(4>('Scenarios_10'!B10-4),4<='Scenarios_10'!B10),'Scenarios_10'!F10,0)),0) | I86: =IF(4=0,'Scenarios_10'!E10,0) | J86: =IF(4=0,0,IF('Scenarios_10'!C10="uniform_pct",'Inputs_Data'!E9*(1-(MIN('Scenarios_10'!G10,'Assumptions'!B10))),IF('Scenarios_10'!C10="electricity_only_pct",('Inputs_Data'!C9*(1-(MIN('Scenarios_10'!G10,'Assumptions'!B10))))+'Inputs_Data'!D9,0+('Inputs_Data'!D9*(1-AVERAGE('Assumptions'!B6,'Assumptions'!B7,'Assumptions'!B8,'Assumptions'!B9)))))) | K86: =(IF(4=0,-'Inputs_Data'!H5,0))+(IF(AND(4>=1,4<='Scenarios_10'!B10),MAX(0,(MAX(0,'Scenarios_10'!D10-'Scenarios_10'!E10/'Scenarios_10'!B10))-IF(AND(4>('Scenarios_10'!B10-4),4<='Scenarios_10'!B10),'Scenarios_10'!F10,0)),0))+(IF(4=0,'Scenarios_10'!E10,0))-(IF(4=0,0,IF('Scenarios_10'!C10="uniform_pct",'Inputs_Data'!E9*(1-(MIN('Scenarios_10'!G10,'Assumptions'!B10))),IF('Scenarios_10'!C10="electricity_only_pct",('Inputs_Data'!C9*(1-(MIN('Scenarios_10'!G10,'Assumptions'!B10))))+'Inputs_Data'!D9,0+('Inputs_Data'!D9*(1-AVERAGE('Assumptions'!B6,'Assumptions'!B7,'Assumptions'!B8,'Assumptions'!B9))))))) | L86: =(L85)+(K86)
A87: 5 | B87: =IF(5=0,-'Inputs_Data'!H5,0) | C87: =IF(5=0,0,'Inputs_Data'!B10) | D87: =IF(5=0,0,'Inputs_Data'!E10) | E87: =(IF(5=0,-'Inputs_Data'!H5,0))+(IF(5=0,0,'Inputs_Data'!B10))-(IF(5=0,0,'Inputs_Data'!E10)) | F87: =(F86)+(E87) | G87: =IF(5=0,-'Inputs_Data'!H5,0) | H87: =IF(AND(5>=1,5<='Scenarios_10'!B10),MAX(0,(MAX(0,'Scenarios_10'!D10-'Scenarios_10'!E10/'Scenarios_10'!B10))-IF(AND(5>('Scenarios_10'!B10-4),5<='Scenarios_10'!B10),'Scenarios_10'!F10,0)),0) | I87: =IF(5=0,'Scenarios_10'!E10,0) | J87: =IF(5=0,0,IF('Scenarios_10'!C10="uniform_pct",'Inputs_Data'!E10*(1-(MIN('Scenarios_10'!G10,'Assumptions'!B10))),IF('Scenarios_10'!C10="electricity_only_pct",('Inputs_Data'!C10*(1-(MIN('Scenarios_10'!G10,'Assumptions'!B10))))+'Inputs_Data'!D10,0+('Inputs_Data'!D10*(1-AVERAGE('Assumptions'!B6,'Assumptions'!B7,'Assumptions'!B8,'Assumptions'!B9)))))) | K87: =(IF(5=0,-'Inputs_Data'!H5,0))+(IF(AND(5>=1,5<='Scenarios_10'!B10),MAX(0,(MAX(0,'Scenarios_10'!D10-'Scenarios_10'!E10/'Scenarios_10'!B10))-IF(AND(5>('Scenarios_10'!B10-4),5<='Scenarios_10'!B10),'Scenarios_10'!F10,0)),0))+(IF(5=0,'Scenarios_10'!E10,0))-(IF(5=0,0,IF('Scenarios_10'!C10="uniform_pct",'Inputs_Data'!E10*(1-(MIN('Scenarios_10'!G10,'Assumptions'!B10))),IF('Scenarios_10'!C10="electricity_only_pct",('Inputs_Data'!C10*(1-(MIN('Scenarios_10'!G10,'Assumptions'!B10))))+'Inputs_Data'!D10,0+('Inputs_Data'!D10*(1-AVERAGE('Assumptions'!B6,'Assumptions'!B7,'Assumptions'!B8,'Assumptions'!B9))))))) | L87: =(L86)+(K87)
A88: 6 | B88: =IF(6=0,-'Inputs_Data'!H5,0) | C88: =IF(6=0,0,'Inputs_Data'!B11) | D88: =IF(6=0,0,'Inputs_Data'!E11) | E88: =(IF(6=0,-'Inputs_Data'!H5,0))+(IF(6=0,0,'Inputs_Data'!B11))-(IF(6=0,0,'Inputs_Data'!E11)) | F88: =(F87)+(E88) | G88: =IF(6=0,-'Inputs_Data'!H5,0) | H88: =IF(AND(6>=1,6<='Scenarios_10'!B10),MAX(0,(MAX(0,'Scenarios_10'!D10-'Scenarios_10'!E10/'Scenarios_10'!B10))-IF(AND(6>('Scenarios_10'!B10-4),6<='Scenarios_10'!B10),'Scenarios_10'!F10,0)),0) | I88: =IF(6=0,'Scenarios_10'!E10,0) | J88: =IF(6=0,0,IF('Scenarios_10'!C10="uniform_pct",'Inputs_Data'!E11*(1-(MIN('Scenarios_10'!G10,'Assumptions'!B10))),IF('Scenarios_10'!C10="electricity_only_pct",('Inputs_Data'!C11*(1-(MIN('Scenarios_10'!G10,'Assumptions'!B10))))+'Inputs_Data'!D11,0+('Inputs_Data'!D11*(1-AVERAGE('Assumptions'!B6,'Assumptions'!B7,'Assumptions'!B8,'Assumptions'!B9)))))) | K88: =(IF(6=0,-'Inputs_Data'!H5,0))+(IF(AND(6>=1,6<='Scenarios_10'!B10),MAX(0,(MAX(0,'Scenarios_10'!D10-'Scenarios_10'!E10/'Scenarios_10'!B10))-IF(AND(6>('Scenarios_10'!B10-4),6<='Scenarios_10'!B10),'Scenarios_10'!F10,0)),0))+(IF(6=0,'Scenarios_10'!E10,0))-(IF(6=0,0,IF('Scenarios_10'!C10="uniform_pct",'Inputs_Data'!E11*(1-(MIN('Scenarios_10'!G10,'Assumptions'!B10))),IF('Scenarios_10'!C10="electricity_only_pct",('Inputs_Data'!C11*(1-(MIN('Scenarios_10'!G10,'Assumptions'!B10))))+'Inputs_Data'!D11,0+('Inputs_Data'!D11*(1-AVERAGE('Assumptions'!B6,'Assumptions'!B7,'Assumptions'!B8,'Assumptions'!B9))))))) | L88: =(L87)+(K88)
A89: 7 | B89: =IF(7=0,-'Inputs_Data'!H5,0) | C89: =IF(7=0,0,'Inputs_Data'!B12) | D89: =IF(7=0,0,'Inputs_Data'!E12) | E89: =(IF(7=0,-'Inputs_Data'!H5,0))+(IF(7=0,0,'Inputs_Data'!B12))-(IF(7=0,0,'Inputs_Data'!E12)) | F89: =(F88)+(E89) | G89: =IF(7=0,-'Inputs_Data'!H5,0) | H89: =IF(AND(7>=1,7<='Scenarios_10'!B10),MAX(0,(MAX(0,'Scenarios_10'!D10-'Scenarios_10'!E10/'Scenarios_10'!B10))-IF(AND(7>('Scenarios_10'!B10-4),7<='Scenarios_10'!B10),'Scenarios_10'!F10,0)),0) | I89: =IF(7=0,'Scenarios_10'!E10,0) | J89: =IF(7=0,0,IF('Scenarios_10'!C10="uniform_pct",'Inputs_Data'!E12*(1-(MIN('Scenarios_10'!G10,'Assumptions'!B10))),IF('Scenarios_10'!C10="electricity_only_pct",('Inputs_Data'!C12*(1-(MIN('Scenarios_10'!G10,'Assumptions'!B10))))+'Inputs_Data'!D12,0+('Inputs_Data'!D12*(1-AVERAGE('Assumptions'!B6,'Assumptions'!B7,'Assumptions'!B8,'Assumptions'!B9)))))) | K89: =(IF(7=0,-'Inputs_Data'!H5,0))+(IF(AND(7>=1,7<='Scenarios_10'!B10),MAX(0,(MAX(0,'Scenarios_10'!D10-'Scenarios_10'!E10/'Scenarios_10'!B10))-IF(AND(7>('Scenarios_10'!B10-4),7<='Scenarios_10'!B10),'Scenarios_10'!F10,0)),0))+(IF(7=0,'Scenarios_10'!E10,0))-(IF(7=0,0,IF('Scenarios_10'!C10="uniform_pct",'Inputs_Data'!E12*(1-(MIN('Scenarios_10'!G10,'Assumptions'!B10))),IF('Scenarios_10'!C10="electricity_only_pct",('Inputs_Data'!C12*(1-(MIN('Scenarios_10'!G10,'Assumptions'!B10))))+'Inputs_Data'!D12,0+('Inputs_Data'!D12*(1-AVERAGE('Assumptions'!B6,'Assumptions'!B7,'Assumptions'!B8,'Assumptions'!B9))))))) | L89: =(L88)+(K89)
A90: 8 | B90: =IF(8=0,-'Inputs_Data'!H5,0) | C90: =IF(8=0,0,'Inputs_Data'!B13) | D90: =IF(8=0,0,'Inputs_Data'!E13) | E90: =(IF(8=0,-'Inputs_Data'!H5,0))+(IF(8=0,0,'Inputs_Data'!B13))-(IF(8=0,0,'Inputs_Data'!E13)) | F90: =(F89)+(E90) | G90: =IF(8=0,-'Inputs_Data'!H5,0) | H90: =IF(AND(8>=1,8<='Scenarios_10'!B10),MAX(0,(MAX(0,'Scenarios_10'!D10-'Scenarios_10'!E10/'Scenarios_10'!B10))-IF(AND(8>('Scenarios_10'!B10-4),8<='Scenarios_10'!B10),'Scenarios_10'!F10,0)),0) | I90: =IF(8=0,'Scenarios_10'!E10,0) | J90: =IF(8=0,0,IF('Scenarios_10'!C10="uniform_pct",'Inputs_Data'!E13*(1-(MIN('Scenarios_10'!G10,'Assumptions'!B10))),IF('Scenarios_10'!C10="electricity_only_pct",('Inputs_Data'!C13*(1-(MIN('Scenarios_10'!G10,'Assumptions'!B10))))+'Inputs_Data'!D13,0+('Inputs_Data'!D13*(1-AVERAGE('Assumptions'!B6,'Assumptions'!B7,'Assumptions'!B8,'Assumptions'!B9)))))) | K90: =(IF(8=0,-'Inputs_Data'!H5,0))+(IF(AND(8>=1,8<='Scenarios_10'!B10),MAX(0,(MAX(0,'Scenarios_10'!D10-'Scenarios_10'!E10/'Scenarios_10'!B10))-IF(AND(8>('Scenarios_10'!B10-4),8<='Scenarios_10'!B10),'Scenarios_10'!F10,0)),0))+(IF(8=0,'Scenarios_10'!E10,0))-(IF(8=0,0,IF('Scenarios_10'!C10="uniform_pct",'Inputs_Data'!E13*(1-(MIN('Scenarios_10'!G10,'Assumptions'!B10))),IF('Scenarios_10'!C10="electricity_only_pct",('Inputs_Data'!C13*(1-(MIN('Scenarios_10'!G10,'Assumptions'!B10))))+'Inputs_Data'!D13,0+('Inputs_Data'!D13*(1-AVERAGE('Assumptions'!B6,'Assumptions'!B7,'Assumptions'!B8,'Assumptions'!B9))))))) | L90: =(L89)+(K90)
A91: 9 | B91: =IF(9=0,-'Inputs_Data'!H5,0) | C91: =IF(9=0,0,'Inputs_Data'!B14) | D91: =IF(9=0,0,'Inputs_Data'!E14) | E91: =(IF(9=0,-'Inputs_Data'!H5,0))+(IF(9=0,0,'Inputs_Data'!B14))-(IF(9=0,0,'Inputs_Data'!E14)) | F91: =(F90)+(E91) | G91: =IF(9=0,-'Inputs_Data'!H5,0) | H91: =IF(AND(9>=1,9<='Scenarios_10'!B10),MAX(0,(MAX(0,'Scenarios_10'!D10-'Scenarios_10'!E10/'Scenarios_10'!B10))-IF(AND(9>('Scenarios_10'!B10-4),9<='Scenarios_10'!B10),'Scenarios_10'!F10,0)),0) | I91: =IF(9=0,'Scenarios_10'!E10,0) | J91: =IF(9=0,0,IF('Scenarios_10'!C10="uniform_pct",'Inputs_Data'!E14*(1-(MIN('Scenarios_10'!G10,'Assumptions'!B10))),IF('Scenarios_10'!C10="electricity_only_pct",('Inputs_Data'!C14*(1-(MIN('Scenarios_10'!G10,'Assumptions'!B10))))+'Inputs_Data'!D14,0+('Inputs_Data'!D14*(1-AVERAGE('Assumptions'!B6,'Assumptions'!B7,'Assumptions'!B8,'Assumptions'!B9)))))) | K91: =(IF(9=0,-'Inputs_Data'!H5,0))+(IF(AND(9>=1,9<='Scenarios_10'!B10),MAX(0,(MAX(0,'Scenarios_10'!D10-'Scenarios_10'!E10/'Scenarios_10'!B10))-IF(AND(9>('Scenarios_10'!B10-4),9<='Scenarios_10'!B10),'Scenarios_10'!F10,0)),0))+(IF(9=0,'Scenarios_10'!E10,0))-(IF(9=0,0,IF('Scenarios_10'!C10="uniform_pct",'Inputs_Data'!E14*(1-(MIN('Scenarios_10'!G10,'Assumptions'!B10))),IF('Scenarios_10'!C10="electricity_only_pct",('Inputs_Data'!C14*(1-(MIN('Scenarios_10'!G10,'Assumptions'!B10))))+'Inputs_Data'!D14,0+('Inputs_Data'!D14*(1-AVERAGE('Assumptions'!B6,'Assumptions'!B7,'Assumptions'!B8,'Assumptions'!B9))))))) | L91: =(L90)+(K91)
A92: 10 | B92: =IF(10=0,-'Inputs_Data'!H5,0) | C92: =IF(10=0,0,'Inputs_Data'!B15) | D92: =IF(10=0,0,'Inputs_Data'!E15) | E92: =(IF(10=0,-'Inputs_Data'!H5,0))+(IF(10=0,0,'Inputs_Data'!B15))-(IF(10=0,0,'Inputs_Data'!E15)) | F92: =(F91)+(E92) | G92: =IF(10=0,-'Inputs_Data'!H5,0) | H92: =IF(AND(10>=1,10<='Scenarios_10'!B10),MAX(0,(MAX(0,'Scenarios_10'!D10-'Scenarios_10'!E10/'Scenarios_10'!B10))-IF(AND(10>('Scenarios_10'!B10-4),10<='Scenarios_10'!B10),'Scenarios_10'!F10,0)),0) | I92: =IF(10=0,'Scenarios_10'!E10,0) | J92: =IF(10=0,0,IF('Scenarios_10'!C10="uniform_pct",'Inputs_Data'!E15*(1-(MIN('Scenarios_10'!G10,'Assumptions'!B10))),IF('Scenarios_10'!C10="electricity_only_pct",('Inputs_Data'!C15*(1-(MIN('Scenarios_10'!G10,'Assumptions'!B10))))+'Inputs_Data'!D15,0+('Inputs_Data'!D15*(1-AVERAGE('Assumptions'!B6,'Assumptions'!B7,'Assumptions'!B8,'Assumptions'!B9)))))) | K92: =(IF(10=0,-'Inputs_Data'!H5,0))+(IF(AND(10>=1,10<='Scenarios_10'!B10),MAX(0,(MAX(0,'Scenarios_10'!D10-'Scenarios_10'!E10/'Scenarios_10'!B10))-IF(AND(10>('Scenarios_10'!B10-4),10<='Scenarios_10'!B10),'Scenarios_10'!F10,0)),0))+(IF(10=0,'Scenarios_10'!E10,0))-(IF(10=0,0,IF('Scenarios_10'!C10="uniform_pct",'Inputs_Data'!E15*(1-(MIN('Scenarios_10'!G10,'Assumptions'!B10))),IF('Scenarios_10'!C10="electricity_only_pct",('Inputs_Data'!C15*(1-(MIN('Scenarios_10'!G10,'Assumptions'!B10))))+'Inputs_Data'!D15,0+('Inputs_Data'!D15*(1-AVERAGE('Assumptions'!B6,'Assumptions'!B7,'Assumptions'!B8,'Assumptions'!B9))))))) | L92: =(L91)+(K92)
A95: Tier: ='Scenarios_10'!A11
A96: year | B96: trust_capex | C96: trust_fee | D96: trust_cash_opex | E96: trust_net_cf | F96: trust_cum_cf | G96: laas_capex | H96: laas_fee | I96: laas_upfront | J96: laas_cash_opex | K96: laas_net_cf | L96: laas_cum_cf
A97: 0 | B97: =IF(0=0,-'Inputs_Data'!H5,0) | C97: =IF(0=0,0,'Inputs_Data'!B5) | D97: =IF(0=0,0,'Inputs_Data'!E5) | E97: =(IF(0=0,-'Inputs_Data'!H5,0))+(IF(0=0,0,'Inputs_Data'!B5))-(IF(0=0,0,'Inputs_Data'!E5)) | F97: =(0)+(E97) | G97: =IF(0=0,-'Inputs_Data'!H5,0) | H97: =IF(AND(0>=1,0<='Scenarios_10'!B11),MAX(0,(MAX(0,'Scenarios_10'!D11-'Scenarios_10'!E11/'Scenarios_10'!B11))-IF(AND(0>('Scenarios_10'!B11-4),0<='Scenarios_10'!B11),'Scenarios_10'!F11,0)),0) | I97: =IF(0=0,'Scenarios_10'!E11,0) | J97: =IF(0=0,0,IF('Scenarios_10'!C11="uniform_pct",'Inputs_Data'!E5*(1-(MIN('Scenarios_10'!G11,'Assumptions'!B10))),IF('Scenarios_10'!C11="electricity_only_pct",('Inputs_Data'!C5*(1-(MIN('Scenarios_10'!G11,'Assumptions'!B10))))+'Inputs_Data'!D5,0+('Inputs_Data'!D5*(1-AVERAGE('Assumptions'!B6,'Assumptions'!B7,'Assumptions'!B8,'Assumptions'!B9)))))) | K97: =(IF(0=0,-'Inputs_Data'!H5,0))+(IF(AND(0>=1,0<='Scenarios_10'!B11),MAX(0,(MAX(0,'Scenarios_10'!D11-'Scenarios_10'!E11/'Scenarios_10'!B11))-IF(AND(0>('Scenarios_10'!B11-4),0<='Scenarios_10'!B11),'Scenarios_10'!F11,0)),0))+(IF(0=0,'Scenarios_10'!E11,0))-(IF(0=0,0,IF('Scenarios_10'!C11="uniform_pct",'Inputs_Data'!E5*(1-(MIN('Scenarios_10'!G11,'Assumptions'!B10))),IF('Scenarios_10'!C11="electricity_only_pct",('Inputs_Data'!C5*(1-(MIN('Scenarios_10'!G11,'Assumptions'!B10))))+'Inputs_Data'!D5,0+('Inputs_Data'!D5*(1-AVERAGE('Assumptions'!B6,'Assumptions'!B7,'Assumptions'!B8,'Assumptions'!B9))))))) | L97: =(0)+(K97)
A98: 1 | B98: =IF(1=0,-'Inputs_Data'!H5,0) | C98: =IF(1=0,0,'Inputs_Data'!B6) | D98: =IF(1=0,0,'Inputs_Data'!E6) | E98: =(IF(1=0,-'Inputs_Data'!H5,0))+(IF(1=0,0,'Inputs_Data'!B6))-(IF(1=0,0,'Inputs_Data'!E6)) | F98: =(F97)+(E98) | G98: =IF(1=0,-'Inputs_Data'!H5,0) | H98: =IF(AND(1>=1,1<='Scenarios_10'!B11),MAX(0,(MAX(0,'Scenarios_10'!D11-'Scenarios_10'!E11/'Scenarios_10'!B11))-IF(AND(1>('Scenarios_10'!B11-4),1<='Scenarios_10'!B11),'Scenarios_10'!F11,0)),0) | I98: =IF(1=0,'Scenarios_10'!E11,0) | J98: =IF(1=0,0,IF('Scenarios_10'!C11="uniform_pct",'Inputs_Data'!E6*(1-(MIN('Scenarios_10'!G11,'Assumptions'!B10))),IF('Scenarios_10'!C11="electricity_only_pct",('Inputs_Data'!C6*(1-(MIN('Scenarios_10'!G11,'Assumptions'!B10))))+'Inputs_Data'!D6,0+('Inputs_Data'!D6*(1-AVERAGE('Assumptions'!B6,'Assumptions'!B7,'Assumptions'!B8,'Assumptions'!B9)))))) | K98: =(IF(1=0,-'Inputs_Data'!H5,0))+(IF(AND(1>=1,1<='Scenarios_10'!B11),MAX(0,(MAX(0,'Scenarios_10'!D11-'Scenarios_10'!E11/'Scenarios_10'!B11))-IF(AND(1>('Scenarios_10'!B11-4),1<='Scenarios_10'!B11),'Scenarios_10'!F11,0)),0))+(IF(1=0,'Scenarios_10'!E11,0))-(IF(1=0,0,IF('Scenarios_10'!C11="uniform_pct",'Inputs_Data'!E6*(1-(MIN('Scenarios_10'!G11,'Assumptions'!B10))),IF('Scenarios_10'!C11="electricity_only_pct",('Inputs_Data'!C6*(1-(MIN('Scenarios_10'!G11,'Assumptions'!B10))))+'Inputs_Data'!D6,0+('Inputs_Data'!D6*(1-AVERAGE('Assumptions'!B6,'Assumptions'!B7,'Assumptions'!B8,'Assumptions'!B9))))))) | L98: =(L97)+(K98)
A99: 2 | B99: =IF(2=0,-'Inputs_Data'!H5,0) | C99: =IF(2=0,0,'Inputs_Data'!B7) | D99: =IF(2=0,0,'Inputs_Data'!E7) | E99: =(IF(2=0,-'Inputs_Data'!H5,0))+(IF(2=0,0,'Inputs_Data'!B7))-(IF(2=0,0,'Inputs_Data'!E7)) | F99: =(F98)+(E99) | G99: =IF(2=0,-'Inputs_Data'!H5,0) | H99: =IF(AND(2>=1,2<='Scenarios_10'!B11),MAX(0,(MAX(0,'Scenarios_10'!D11-'Scenarios_10'!E11/'Scenarios_10'!B11))-IF(AND(2>('Scenarios_10'!B11-4),2<='Scenarios_10'!B11),'Scenarios_10'!F11,0)),0) | I99: =IF(2=0,'Scenarios_10'!E11,0) | J99: =IF(2=0,0,IF('Scenarios_10'!C11="uniform_pct",'Inputs_Data'!E7*(1-(MIN('Scenarios_10'!G11,'Assumptions'!B10))),IF('Scenarios_10'!C11="electricity_only_pct",('Inputs_Data'!C7*(1-(MIN('Scenarios_10'!G11,'Assumptions'!B10))))+'Inputs_Data'!D7,0+('Inputs_Data'!D7*(1-AVERAGE('Assumptions'!B6,'Assumptions'!B7,'Assumptions'!B8,'Assumptions'!B9)))))) | K99: =(IF(2=0,-'Inputs_Data'!H5,0))+(IF(AND(2>=1,2<='Scenarios_10'!B11),MAX(0,(MAX(0,'Scenarios_10'!D11-'Scenarios_10'!E11/'Scenarios_10'!B11))-IF(AND(2>('Scenarios_10'!B11-4),2<='Scenarios_10'!B11),'Scenarios_10'!F11,0)),0))+(IF(2=0,'Scenarios_10'!E11,0))-(IF(2=0,0,IF('Scenarios_10'!C11="uniform_pct",'Inputs_Data'!E7*(1-(MIN('Scenarios_10'!G11,'Assumptions'!B10))),IF('Scenarios_10'!C11="electricity_only_pct",('Inputs_Data'!C7*(1-(MIN('Scenarios_10'!G11,'Assumptions'!B10))))+'Inputs_Data'!D7,0+('Inputs_Data'!D7*(1-AVERAGE('Assumptions'!B6,'Assumptions'!B7,'Assumptions'!B8,'Assumptions'!B9))))))) | L99: =(L98)+(K99)
A100: 3 | B100: =IF(3=0,-'Inputs_Data'!H5,0) | C100: =IF(3=0,0,'Inputs_Data'!B8) | D100: =IF(3=0,0,'Inputs_Data'!E8) | E100: =(IF(3=0,-'Inputs_Data'!H5,0))+(IF(3=0,0,'Inputs_Data'!B8))-(IF(3=0,0,'Inputs_Data'!E8)) | F100: =(F99)+(E100) | G100: =IF(3=0,-'Inputs_Data'!H5,0) | H100: =IF(AND(3>=1,3<='Scenarios_10'!B11),MAX(0,(MAX(0,'Scenarios_10'!D11-'Scenarios_10'!E11/'Scenarios_10'!B11))-IF(AND(3>('Scenarios_10'!B11-4),3<='Scenarios_10'!B11),'Scenarios_10'!F11,0)),0) | I100: =IF(3=0,'Scenarios_10'!E11,0) | J100: =IF(3=0,0,IF('Scenarios_10'!C11="uniform_pct",'Inputs_Data'!E8*(1-(MIN('Scenarios_10'!G11,'Assumptions'!B10))),IF('Scenarios_10'!C11="electricity_only_pct",('Inputs_Data'!C8*(1-(MIN('Scenarios_10'!G11,'Assumptions'!B10))))+'Inputs_Data'!D8,0+('Inputs_Data'!D8*(1-AVERAGE('Assumptions'!B6,'Assumptions'!B7,'Assumptions'!B8,'Assumptions'!B9)))))) | K100: =(IF(3=0,-'Inputs_Data'!H5,0))+(IF(AND(3>=1,3<='Scenarios_10'!B11),MAX(0,(MAX(0,'Scenarios_10'!D11-'Scenarios_10'!E11/'Scenarios_10'!B11))-IF(AND(3>('Scenarios_10'!B11-4),3<='Scenarios_10'!B11),'Scenarios_10'!F11,0)),0))+(IF(3=0,'Scenarios_10'!E11,0))-(IF(3=0,0,IF('Scenarios_10'!C11="uniform_pct",'Inputs_Data'!E8*(1-(MIN('Scenarios_10'!G11,'Assumptions'!B10))),IF('Scenarios_10'!C11="electricity_only_pct",('Inputs_Data'!C8*(1-(MIN('Scenarios_10'!G11,'Assumptions'!B10))))+'Inputs_Data'!D8,0+('Inputs_Data'!D8*(1-AVERAGE('Assumptions'!B6,'Assumptions'!B7,'Assumptions'!B8,'Assumptions'!B9))))))) | L100: =(L99)+(K100)
A101: 4 | B101: =IF(4=0,-'Inputs_Data'!H5,0) | C101: =IF(4=0,0,'Inputs_Data'!B9) | D101: =IF(4=0,0,'Inputs_Data'!E9) | E101: =(IF(4=0,-'Inputs_Data'!H5,0))+(IF(4=0,0,'Inputs_Data'!B9))-(IF(4=0,0,'Inputs_Data'!E9)) | F101: =(F100)+(E101) | G101: =IF(4=0,-'Inputs_Data'!H5,0) | H101: =IF(AND(4>=1,4<='Scenarios_10'!B11),MAX(0,(MAX(0,'Scenarios_10'!D11-'Scenarios_10'!E11/'Scenarios_10'!B11))-IF(AND(4>('Scenarios_10'!B11-4),4<='Scenarios_10'!B11),'Scenarios_10'!F11,0)),0) | I101: =IF(4=0,'Scenarios_10'!E11,0) | J101: =IF(4=0,0,IF('Scenarios_10'!C11="uniform_pct",'Inputs_Data'!E9*(1-(MIN('Scenarios_10'!G11,'Assumptions'!B10))),IF('Scenarios_10'!C11="electricity_only_pct",('Inputs_Data'!C9*(1-(MIN('Scenarios_10'!G11,'Assumptions'!B10))))+'Inputs_Data'!D9,0+('Inputs_Data'!D9*(1-AVERAGE('Assumptions'!B6,'Assumptions'!B7,'Assumptions'!B8,'Assumptions'!B9)))))) | K101: =(IF(4=0,-'Inputs_Data'!H5,0))+(IF(AND(4>=1,4<='Scenarios_10'!B11),MAX(0,(MAX(0,'Scenarios_10'!D11-'Scenarios_10'!E11/'Scenarios_10'!B11))-IF(AND(4>('Scenarios_10'!B11-4),4<='Scenarios_10'!B11),'Scenarios_10'!F11,0)),0))+(IF(4=0,'Scenarios_10'!E11,0))-(IF(4=0,0,IF('Scenarios_10'!C11="uniform_pct",'Inputs_Data'!E9*(1-(MIN('Scenarios_10'!G11,'Assumptions'!B10))),IF('Scenarios_10'!C11="electricity_only_pct",('Inputs_Data'!C9*(1-(MIN('Scenarios_10'!G11,'Assumptions'!B10))))+'Inputs_Data'!D9,0+('Inputs_Data'!D9*(1-AVERAGE('Assumptions'!B6,'Assumptions'!B7,'Assumptions'!B8,'Assumptions'!B9))))))) | L101: =(L100)+(K101)
A102: 5 | B102: =IF(5=0,-'Inputs_Data'!H5,0) | C102: =IF(5=0,0,'Inputs_Data'!B10) | D102: =IF(5=0,0,'Inputs_Data'!E10) | E102: =(IF(5=0,-'Inputs_Data'!H5,0))+(IF(5=0,0,'Inputs_Data'!B10))-(IF(5=0,0,'Inputs_Data'!E10)) | F102: =(F101)+(E102) | G102: =IF(5=0,-'Inputs_Data'!H5,0) | H102: =IF(AND(5>=1,5<='Scenarios_10'!B11),MAX(0,(MAX(0,'Scenarios_10'!D11-'Scenarios_10'!E11/'Scenarios_10'!B11))-IF(AND(5>('Scenarios_10'!B11-4),5<='Scenarios_10'!B11),'Scenarios_10'!F11,0)),0) | I102: =IF(5=0,'Scenarios_10'!E11,0) | J102: =IF(5=0,0,IF('Scenarios_10'!C11="uniform_pct",'Inputs_Data'!E10*(1-(MIN('Scenarios_10'!G11,'Assumptions'!B10))),IF('Scenarios_10'!C11="electricity_only_pct",('Inputs_Data'!C10*(1-(MIN('Scenarios_10'!G11,'Assumptions'!B10))))+'Inputs_Data'!D10,0+('Inputs_Data'!D10*(1-AVERAGE('Assumptions'!B6,'Assumptions'!B7,'Assumptions'!B8,'Assumptions'!B9)))))) | K102: =(IF(5=0,-'Inputs_Data'!H5,0))+(IF(AND(5>=1,5<='Scenarios_10'!B11),MAX(0,(MAX(0,'Scenarios_10'!D11-'Scenarios_10'!E11/'Scenarios_10'!B11))-IF(AND(5>('Scenarios_10'!B11-4),5<='Scenarios_10'!B11),'Scenarios_10'!F11,0)),0))+(IF(5=0,'Scenarios_10'!E11,0))-(IF(5=0,0,IF('Scenarios_10'!C11="uniform_pct",'Inputs_Data'!E10*(1-(MIN('Scenarios_10'!G11,'Assumptions'!B10))),IF('Scenarios_10'!C11="electricity_only_pct",('Inputs_Data'!C10*(1-(MIN('Scenarios_10'!G11,'Assumptions'!B10))))+'Inputs_Data'!D10,0+('Inputs_Data'!D10*(1-AVERAGE('Assumptions'!B6,'Assumptions'!B7,'Assumptions'!B8,'Assumptions'!B9))))))) | L102: =(L101)+(K102)
A103: 6 | B103: =IF(6=0,-'Inputs_Data'!H5,0) | C103: =IF(6=0,0,'Inputs_Data'!B11) | D103: =IF(6=0,0,'Inputs_Data'!E11) | E103: =(IF(6=0,-'Inputs_Data'!H5,0))+(IF(6=0,0,'Inputs_Data'!B11))-(IF(6=0,0,'Inputs_Data'!E11)) | F103: =(F102)+(E103) | G103: =IF(6=0,-'Inputs_Data'!H5,0) | H103: =IF(AND(6>=1,6<='Scenarios_10'!B11),MAX(0,(MAX(0,'Scenarios_10'!D11-'Scenarios_10'!E11/'Scenarios_10'!B11))-IF(AND(6>('Scenarios_10'!B11-4),6<='Scenarios_10'!B11),'Scenarios_10'!F11,0)),0) | I103: =IF(6=0,'Scenarios_10'!E11,0) | J103: =IF(6=0,0,IF('Scenarios_10'!C11="uniform_pct",'Inputs_Data'!E11*(1-(MIN('Scenarios_10'!G11,'Assumptions'!B10))),IF('Scenarios_10'!C11="electricity_only_pct",('Inputs_Data'!C11*(1-(MIN('Scenarios_10'!G11,'Assumptions'!B10))))+'Inputs_Data'!D11,0+('Inputs_Data'!D11*(1-AVERAGE('Assumptions'!B6,'Assumptions'!B7,'Assumptions'!B8,'Assumptions'!B9)))))) | K103: =(IF(6=0,-'Inputs_Data'!H5,0))+(IF(AND(6>=1,6<='Scenarios_10'!B11),MAX(0,(MAX(0,'Scenarios_10'!D11-'Scenarios_10'!E11/'Scenarios_10'!B11))-IF(AND(6>('Scenarios_10'!B11-4),6<='Scenarios_10'!B11),'Scenarios_10'!F11,0)),0))+(IF(6=0,'Scenarios_10'!E11,0))-(IF(6=0,0,IF('Scenarios_10'!C11="uniform_pct",'Inputs_Data'!E11*(1-(MIN('Scenarios_10'!G11,'Assumptions'!B10))),IF('Scenarios_10'!C11="electricity_only_pct",('Inputs_Data'!C11*(1-(MIN('Scenarios_10'!G11,'Assumptions'!B10))))+'Inputs_Data'!D11,0+('Inputs_Data'!D11*(1-AVERAGE('Assumptions'!B6,'Assumptions'!B7,'Assumptions'!B8,'Assumptions'!B9))))))) | L103: =(L102)+(K103)
A104: 7 | B104: =IF(7=0,-'Inputs_Data'!H5,0) | C104: =IF(7=0,0,'Inputs_Data'!B12) | D104: =IF(7=0,0,'Inputs_Data'!E12) | E104: =(IF(7=0,-'Inputs_Data'!H5,0))+(IF(7=0,0,'Inputs_Data'!B12))-(IF(7=0,0,'Inputs_Data'!E12)) | F104: =(F103)+(E104) | G104: =IF(7=0,-'Inputs_Data'!H5,0) | H104: =IF(AND(7>=1,7<='Scenarios_10'!B11),MAX(0,(MAX(0,'Scenarios_10'!D11-'Scenarios_10'!E11/'Scenarios_10'!B11))-IF(AND(7>('Scenarios_10'!B11-4),7<='Scenarios_10'!B11),'Scenarios_10'!F11,0)),0) | I104: =IF(7=0,'Scenarios_10'!E11,0) | J104: =IF(7=0,0,IF('Scenarios_10'!C11="uniform_pct",'Inputs_Data'!E12*(1-(MIN('Scenarios_10'!G11,'Assumptions'!B10))),IF('Scenarios_10'!C11="electricity_only_pct",('Inputs_Data'!C12*(1-(MIN('Scenarios_10'!G11,'Assumptions'!B10))))+'Inputs_Data'!D12,0+('Inputs_Data'!D12*(1-AVERAGE('Assumptions'!B6,'Assumptions'!B7,'Assumptions'!B8,'Assumptions'!B9)))))) | K104: =(IF(7=0,-'Inputs_Data'!H5,0))+(IF(AND(7>=1,7<='Scenarios_10'!B11),MAX(0,(MAX(0,'Scenarios_10'!D11-'Scenarios_10'!E11/'Scenarios_10'!B11))-IF(AND(7>('Scenarios_10'!B11-4),7<='Scenarios_10'!B11),'Scenarios_10'!F11,0)),0))+(IF(7=0,'Scenarios_10'!E11,0))-(IF(7=0,0,IF('Scenarios_10'!C11="uniform_pct",'Inputs_Data'!E12*(1-(MIN('Scenarios_10'!G11,'Assumptions'!B10))),IF('Scenarios_10'!C11="electricity_only_pct",('Inputs_Data'!C12*(1-(MIN('Scenarios_10'!G11,'Assumptions'!B10))))+'Inputs_Data'!D12,0+('Inputs_Data'!D12*(1-AVERAGE('Assumptions'!B6,'Assumptions'!B7,'Assumptions'!B8,'Assumptions'!B9))))))) | L104: =(L103)+(K104)
A105: 8 | B105: =IF(8=0,-'Inputs_Data'!H5,0) | C105: =IF(8=0,0,'Inputs_Data'!B13) | D105: =IF(8=0,0,'Inputs_Data'!E13) | E105: =(IF(8=0,-'Inputs_Data'!H5,0))+(IF(8=0,0,'Inputs_Data'!B13))-(IF(8=0,0,'Inputs_Data'!E13)) | F105: =(F104)+(E105) | G105: =IF(8=0,-'Inputs_Data'!H5,0) | H105: =IF(AND(8>=1,8<='Scenarios_10'!B11),MAX(0,(MAX(0,'Scenarios_10'!D11-'Scenarios_10'!E11/'Scenarios_10'!B11))-IF(AND(8>('Scenarios_10'!B11-4),8<='Scenarios_10'!B11),'Scenarios_10'!F11,0)),0) | I105: =IF(8=0,'Scenarios_10'!E11,0) | J105: =IF(8=0,0,IF('Scenarios_10'!C11="uniform_pct",'Inputs_Data'!E13*(1-(MIN('Scenarios_10'!G11,'Assumptions'!B10))),IF('Scenarios_10'!C11="electricity_only_pct",('Inputs_Data'!C13*(1-(MIN('Scenarios_10'!G11,'Assumptions'!B10))))+'Inputs_Data'!D13,0+('Inputs_Data'!D13*(1-AVERAGE('Assumptions'!B6,'Assumptions'!B7,'Assumptions'!B8,'Assumptions'!B9)))))) | K105: =(IF(8=0,-'Inputs_Data'!H5,0))+(IF(AND(8>=1,8<='Scenarios_10'!B11),MAX(0,(MAX(0,'Scenarios_10'!D11-'Scenarios_10'!E11/'Scenarios_10'!B11))-IF(AND(8>('Scenarios_10'!B11-4),8<='Scenarios_10'!B11),'Scenarios_10'!F11,0)),0))+(IF(8=0,'Scenarios_10'!E11,0))-(IF(8=0,0,IF('Scenarios_10'!C11="uniform_pct",'Inputs_Data'!E13*(1-(MIN('Scenarios_10'!G11,'Assumptions'!B10))),IF('Scenarios_10'!C11="electricity_only_pct",('Inputs_Data'!C13*(1-(MIN('Scenarios_10'!G11,'Assumptions'!B10))))+'Inputs_Data'!D13,0+('Inputs_Data'!D13*(1-AVERAGE('Assumptions'!B6,'Assumptions'!B7,'Assumptions'!B8,'Assumptions'!B9))))))) | L105: =(L104)+(K105)
A106: 9 | B106: =IF(9=0,-'Inputs_Data'!H5,0) | C106: =IF(9=0,0,'Inputs_Data'!B14) | D106: =IF(9=0,0,'Inputs_Data'!E14) | E106: =(IF(9=0,-'Inputs_Data'!H5,0))+(IF(9=0,0,'Inputs_Data'!B14))-(IF(9=0,0,'Inputs_Data'!E14)) | F106: =(F105)+(E106) | G106: =IF(9=0,-'Inputs_Data'!H5,0) | H106: =IF(AND(9>=1,9<='Scenarios_10'!B11),MAX(0,(MAX(0,'Scenarios_10'!D11-'Scenarios_10'!E11/'Scenarios_10'!B11))-IF(AND(9>('Scenarios_10'!B11-4),9<='Scenarios_10'!B11),'Scenarios_10'!F11,0)),0) | I106: =IF(9=0,'Scenarios_10'!E11,0) | J106: =IF(9=0,0,IF('Scenarios_10'!C11="uniform_pct",'Inputs_Data'!E14*(1-(MIN('Scenarios_10'!G11,'Assumptions'!B10))),IF('Scenarios_10'!C11="electricity_only_pct",('Inputs_Data'!C14*(1-(MIN('Scenarios_10'!G11,'Assumptions'!B10))))+'Inputs_Data'!D14,0+('Inputs_Data'!D14*(1-AVERAGE('Assumptions'!B6,'Assumptions'!B7,'Assumptions'!B8,'Assumptions'!B9)))))) | K106: =(IF(9=0,-'Inputs_Data'!H5,0))+(IF(AND(9>=1,9<='Scenarios_10'!B11),MAX(0,(MAX(0,'Scenarios_10'!D11-'Scenarios_10'!E11/'Scenarios_10'!B11))-IF(AND(9>('Scenarios_10'!B11-4),9<='Scenarios_10'!B11),'Scenarios_10'!F11,0)),0))+(IF(9=0,'Scenarios_10'!E11,0))-(IF(9=0,0,IF('Scenarios_10'!C11="uniform_pct",'Inputs_Data'!E14*(1-(MIN('Scenarios_10'!G11,'Assumptions'!B10))),IF('Scenarios_10'!C11="electricity_only_pct",('Inputs_Data'!C14*(1-(MIN('Scenarios_10'!G11,'Assumptions'!B10))))+'Inputs_Data'!D14,0+('Inputs_Data'!D14*(1-AVERAGE('Assumptions'!B6,'Assumptions'!B7,'Assumptions'!B8,'Assumptions'!B9))))))) | L106: =(L105)+(K106)
A107: 10 | B107: =IF(10=0,-'Inputs_Data'!H5,0) | C107: =IF(10=0,0,'Inputs_Data'!B15) | D107: =IF(10=0,0,'Inputs_Data'!E15) | E107: =(IF(10=0,-'Inputs_Data'!H5,0))+(IF(10=0,0,'Inputs_Data'!B15))-(IF(10=0,0,'Inputs_Data'!E15)) | F107: =(F106)+(E107) | G107: =IF(10=0,-'Inputs_Data'!H5,0) | H107: =IF(AND(10>=1,10<='Scenarios_10'!B11),MAX(0,(MAX(0,'Scenarios_10'!D11-'Scenarios_10'!E11/'Scenarios_10'!B11))-IF(AND(10>('Scenarios_10'!B11-4),10<='Scenarios_10'!B11),'Scenarios_10'!F11,0)),0) | I107: =IF(10=0,'Scenarios_10'!E11,0) | J107: =IF(10=0,0,IF('Scenarios_10'!C11="uniform_pct",'Inputs_Data'!E15*(1-(MIN('Scenarios_10'!G11,'Assumptions'!B10))),IF('Scenarios_10'!C11="electricity_only_pct",('Inputs_Data'!C15*(1-(MIN('Scenarios_10'!G11,'Assumptions'!B10))))+'Inputs_Data'!D15,0+('Inputs_Data'!D15*(1-AVERAGE('Assumptions'!B6,'Assumptions'!B7,'Assumptions'!B8,'Assumptions'!B9)))))) | K107: =(IF(10=0,-'Inputs_Data'!H5,0))+(IF(AND(10>=1,10<='Scenarios_10'!B11),MAX(0,(MAX(0,'Scenarios_10'!D11-'Scenarios_10'!E11/'Scenarios_10'!B11))-IF(AND(10>('Scenarios_10'!B11-4),10<='Scenarios_10'!B11),'Scenarios_10'!F11,0)),0))+(IF(10=0,'Scenarios_10'!E11,0))-(IF(10=0,0,IF('Scenarios_10'!C11="uniform_pct",'Inputs_Data'!E15*(1-(MIN('Scenarios_10'!G11,'Assumptions'!B10))),IF('Scenarios_10'!C11="electricity_only_pct",('Inputs_Data'!C15*(1-(MIN('Scenarios_10'!G11,'Assumptions'!B10))))+'Inputs_Data'!D15,0+('Inputs_Data'!D15*(1-AVERAGE('Assumptions'!B6,'Assumptions'!B7,'Assumptions'!B8,'Assumptions'!B9))))))) | L107: =(L106)+(K107)
A110: Tier: ='Scenarios_10'!A12
A111: year | B111: trust_capex | C111: trust_fee | D111: trust_cash_opex | E111: trust_net_cf | F111: trust_cum_cf | G111: laas_capex | H111: laas_fee | I111: laas_upfront | J111: laas_cash_opex | K111: laas_net_cf | L111: laas_cum_cf
A112: 0 | B112: =IF(0=0,-'Inputs_Data'!H5,0) | C112: =IF(0=0,0,'Inputs_Data'!B5) | D112: =IF(0=0,0,'Inputs_Data'!E5) | E112: =(IF(0=0,-'Inputs_Data'!H5,0))+(IF(0=0,0,'Inputs_Data'!B5))-(IF(0=0,0,'Inputs_Data'!E5)) | F112: =(0)+(E112) | G112: =IF(0=0,-'Inputs_Data'!H5,0) | H112: =IF(AND(0>=1,0<='Scenarios_10'!B12),MAX(0,(MAX(0,'Scenarios_10'!D12-'Scenarios_10'!E12/'Scenarios_10'!B12))-IF(AND(0>('Scenarios_10'!B12-4),0<='Scenarios_10'!B12),'Scenarios_10'!F12,0)),0) | I112: =IF(0=0,'Scenarios_10'!E12,0) | J112: =IF(0=0,0,IF('Scenarios_10'!C12="uniform_pct",'Inputs_Data'!E5*(1-(MIN('Scenarios_10'!G12,'Assumptions'!B10))),IF('Scenarios_10'!C12="electricity_only_pct",('Inputs_Data'!C5*(1-(MIN('Scenarios_10'!G12,'Assumptions'!B10))))+'Inputs_Data'!D5,0+('Inputs_Data'!D5*(1-AVERAGE('Assumptions'!B6,'Assumptions'!B7,'Assumptions'!B8,'Assumptions'!B9)))))) | K112: =(IF(0=0,-'Inputs_Data'!H5,0))+(IF(AND(0>=1,0<='Scenarios_10'!B12),MAX(0,(MAX(0,'Scenarios_10'!D12-'Scenarios_10'!E12/'Scenarios_10'!B12))-IF(AND(0>('Scenarios_10'!B12-4),0<='Scenarios_10'!B12),'Scenarios_10'!F12,0)),0))+(IF(0=0,'Scenarios_10'!E12,0))-(IF(0=0,0,IF('Scenarios_10'!C12="uniform_pct",'Inputs_Data'!E5*(1-(MIN('Scenarios_10'!G12,'Assumptions'!B10))),IF('Scenarios_10'!C12="electricity_only_pct",('Inputs_Data'!C5*(1-(MIN('Scenarios_10'!G12,'Assumptions'!B10))))+'Inputs_Data'!D5,0+('Inputs_Data'!D5*(1-AVERAGE('Assumptions'!B6,'Assumptions'!B7,'Assumptions'!B8,'Assumptions'!B9))))))) | L112: =(0)+(K112)
A113: 1 | B113: =IF(1=0,-'Inputs_Data'!H5,0) | C113: =IF(1=0,0,'Inputs_Data'!B6) | D113: =IF(1=0,0,'Inputs_Data'!E6) | E113: =(IF(1=0,-'Inputs_Data'!H5,0))+(IF(1=0,0,'Inputs_Data'!B6))-(IF(1=0,0,'Inputs_Data'!E6)) | F113: =(F112)+(E113) | G113: =IF(1=0,-'Inputs_Data'!H5,0) | H113: =IF(AND(1>=1,1<='Scenarios_10'!B12),MAX(0,(MAX(0,'Scenarios_10'!D12-'Scenarios_10'!E12/'Scenarios_10'!B12))-IF(AND(1>('Scenarios_10'!B12-4),1<='Scenarios_10'!B12),'Scenarios_10'!F12,0)),0) | I113: =IF(1=0,'Scenarios_10'!E12,0) | J113: =IF(1=0,0,IF('Scenarios_10'!C12="uniform_pct",'Inputs_Data'!E6*(1-(MIN('Scenarios_10'!G12,'Assumptions'!B10))),IF('Scenarios_10'!C12="electricity_only_pct",('Inputs_Data'!C6*(1-(MIN('Scenarios_10'!G12,'Assumptions'!B10))))+'Inputs_Data'!D6,0+('Inputs_Data'!D6*(1-AVERAGE('Assumptions'!B6,'Assumptions'!B7,'Assumptions'!B8,'Assumptions'!B9)))))) | K113: =(IF(1=0,-'Inputs_Data'!H5,0))+(IF(AND(1>=1,1<='Scenarios_10'!B12),MAX(0,(MAX(0,'Scenarios_10'!D12-'Scenarios_10'!E12/'Scenarios_10'!B12))-IF(AND(1>('Scenarios_10'!B12-4),1<='Scenarios_10'!B12),'Scenarios_10'!F12,0)),0))+(IF(1=0,'Scenarios_10'!E12,0))-(IF(1=0,0,IF('Scenarios_10'!C12="uniform_pct",'Inputs_Data'!E6*(1-(MIN('Scenarios_10'!G12,'Assumptions'!B10))),IF('Scenarios_10'!C12="electricity_only_pct",('Inputs_Data'!C6*(1-(MIN('Scenarios_10'!G12,'Assumptions'!B10))))+'Inputs_Data'!D6,0+('Inputs_Data'!D6*(1-AVERAGE('Assumptions'!B6,'Assumptions'!B7,'Assumptions'!B8,'Assumptions'!B9))))))) | L113: =(L112)+(K113)
A114: 2 | B114: =IF(2=0,-'Inputs_Data'!H5,0) | C114: =IF(2=0,0,'Inputs_Data'!B7) | D114: =IF(2=0,0,'Inputs_Data'!E7) | E114: =(IF(2=0,-'Inputs_Data'!H5,0))+(IF(2=0,0,'Inputs_Data'!B7))-(IF(2=0,0,'Inputs_Data'!E7)) | F114: =(F113)+(E114) | G114: =IF(2=0,-'Inputs_Data'!H5,0) | H114: =IF(AND(2>=1,2<='Scenarios_10'!B12),MAX(0,(MAX(0,'Scenarios_10'!D12-'Scenarios_10'!E12/'Scenarios_10'!B12))-IF(AND(2>('Scenarios_10'!B12-4),2<='Scenarios_10'!B12),'Scenarios_10'!F12,0)),0) | I114: =IF(2=0,'Scenarios_10'!E12,0) | J114: =IF(2=0,0,IF('Scenarios_10'!C12="uniform_pct",'Inputs_Data'!E7*(1-(MIN('Scenarios_10'!G12,'Assumptions'!B10))),IF('Scenarios_10'!C12="electricity_only_pct",('Inputs_Data'!C7*(1-(MIN('Scenarios_10'!G12,'Assumptions'!B10))))+'Inputs_Data'!D7,0+('Inputs_Data'!D7*(1-AVERAGE('Assumptions'!B6,'Assumptions'!B7,'Assumptions'!B8,'Assumptions'!B9)))))) | K114: =(IF(2=0,-'Inputs_Data'!H5,0))+(IF(AND(2>=1,2<='Scenarios_10'!B12),MAX(0,(MAX(0,'Scenarios_10'!D12-'Scenarios_10'!E12/'Scenarios_10'!B12))-IF(AND(2>('Scenarios_10'!B12-4),2<='Scenarios_10'!B12),'Scenarios_10'!F12,0)),0))+(IF(2=0,'Scenarios_10'!E12,0))-(IF(2=0,0,IF('Scenarios_10'!C12="uniform_pct",'Inputs_Data'!E7*(1-(MIN('Scenarios_10'!G12,'Assumptions'!B10))),IF('Scenarios_10'!C12="electricity_only_pct",('Inputs_Data'!C7*(1-(MIN('Scenarios_10'!G12,'Assumptions'!B10))))+'Inputs_Data'!D7,0+('Inputs_Data'!D7*(1-AVERAGE('Assumptions'!B6,'Assumptions'!B7,'Assumptions'!B8,'Assumptions'!B9))))))) | L114: =(L113)+(K114)
A115: 3 | B115: =IF(3=0,-'Inputs_Data'!H5,0) | C115: =IF(3=0,0,'Inputs_Data'!B8) | D115: =IF(3=0,0,'Inputs_Data'!E8) | E115: =(IF(3=0,-'Inputs_Data'!H5,0))+(IF(3=0,0,'Inputs_Data'!B8))-(IF(3=0,0,'Inputs_Data'!E8)) | F115: =(F114)+(E115) | G115: =IF(3=0,-'Inputs_Data'!H5,0) | H115: =IF(AND(3>=1,3<='Scenarios_10'!B12),MAX(0,(MAX(0,'Scenarios_10'!D12-'Scenarios_10'!E12/'Scenarios_10'!B12))-IF(AND(3>('Scenarios_10'!B12-4),3<='Scenarios_10'!B12),'Scenarios_10'!F12,0)),0) | I115: =IF(3=0,'Scenarios_10'!E12,0) | J115: =IF(3=0,0,IF('Scenarios_10'!C12="uniform_pct",'Inputs_Data'!E8*(1-(MIN('Scenarios_10'!G12,'Assumptions'!B10))),IF('Scenarios_10'!C12="electricity_only_pct",('Inputs_Data'!C8*(1-(MIN('Scenarios_10'!G12,'Assumptions'!B10))))+'Inputs_Data'!D8,0+('Inputs_Data'!D8*(1-AVERAGE('Assumptions'!B6,'Assumptions'!B7,'Assumptions'!B8,'Assumptions'!B9)))))) | K115: =(IF(3=0,-'Inputs_Data'!H5,0))+(IF(AND(3>=1,3<='Scenarios_10'!B12),MAX(0,(MAX(0,'Scenarios_10'!D12-'Scenarios_10'!E12/'Scenarios_10'!B12))-IF(AND(3>('Scenarios_10'!B12-4),3<='Scenarios_10'!B12),'Scenarios_10'!F12,0)),0))+(IF(3=0,'Scenarios_10'!E12,0))-(IF(3=0,0,IF('Scenarios_10'!C12="uniform_pct",'Inputs_Data'!E8*(1-(MIN('Scenarios_10'!G12,'Assumptions'!B10))),IF('Scenarios_10'!C12="electricity_only_pct",('Inputs_Data'!C8*(1-(MIN('Scenarios_10'!G12,'Assumptions'!B10))))+'Inputs_Data'!D8,0+('Inputs_Data'!D8*(1-AVERAGE('Assumptions'!B6,'Assumptions'!B7,'Assumptions'!B8,'Assumptions'!B9))))))) | L115: =(L114)+(K115)
A116: 4 | B116: =IF(4=0,-'Inputs_Data'!H5,0) | C116: =IF(4=0,0,'Inputs_Data'!B9) | D116: =IF(4=0,0,'Inputs_Data'!E9) | E116: =(IF(4=0,-'Inputs_Data'!H5,0))+(IF(4=0,0,'Inputs_Data'!B9))-(IF(4=0,0,'Inputs_Data'!E9)) | F116: =(F115)+(E116) | G116: =IF(4=0,-'Inputs_Data'!H5,0) | H116: =IF(AND(4>=1,4<='Scenarios_10'!B12),MAX(0,(MAX(0,'Scenarios_10'!D12-'Scenarios_10'!E12/'Scenarios_10'!B12))-IF(AND(4>('Scenarios_10'!B12-4),4<='Scenarios_10'!B12),'Scenarios_10'!F12,0)),0) | I116: =IF(4=0,'Scenarios_10'!E12,0) | J116: =IF(4=0,0,IF('Scenarios_10'!C12="uniform_pct",'Inputs_Data'!E9*(1-(MIN('Scenarios_10'!G12,'Assumptions'!B10))),IF('Scenarios_10'!C12="electricity_only_pct",('Inputs_Data'!C9*(1-(MIN('Scenarios_10'!G12,'Assumptions'!B10))))+'Inputs_Data'!D9,0+('Inputs_Data'!D9*(1-AVERAGE('Assumptions'!B6,'Assumptions'!B7,'Assumptions'!B8,'Assumptions'!B9)))))) | K116: =(IF(4=0,-'Inputs_Data'!H5,0))+(IF(AND(4>=1,4<='Scenarios_10'!B12),MAX(0,(MAX(0,'Scenarios_10'!D12-'Scenarios_10'!E12/'Scenarios_10'!B12))-IF(AND(4>('Scenarios_10'!B12-4),4<='Scenarios_10'!B12),'Scenarios_10'!F12,0)),0))+(IF(4=0,'Scenarios_10'!E12,0))-(IF(4=0,0,IF('Scenarios_10'!C12="uniform_pct",'Inputs_Data'!E9*(1-(MIN('Scenarios_10'!G12,'Assumptions'!B10))),IF('Scenarios_10'!C12="electricity_only_pct",('Inputs_Data'!C9*(1-(MIN('Scenarios_10'!G12,'Assumptions'!B10))))+'Inputs_Data'!D9,0+('Inputs_Data'!D9*(1-AVERAGE('Assumptions'!B6,'Assumptions'!B7,'Assumptions'!B8,'Assumptions'!B9))))))) | L116: =(L115)+(K116)
...

Sheet 01_Dashboard
A1: Generic model | Trust vs LaaS/AI
A2: Generated 2026-04-25
A4: 10 tiers (from Model_Calc)
A5: Tier | B5: ClientPay_Y1 | C5: Savings_Y1 | D5: LaaS_OPEX_Y1
A6: ='Model_Calc'!A6 | B6: ='Model_Calc'!B6 | C6: ='Model_Calc'!D6 | D6: ='Model_Calc'!E6
A7: ='Model_Calc'!A7 | B7: ='Model_Calc'!B7 | C7: ='Model_Calc'!D7 | D7: ='Model_Calc'!E7
A8: ='Model_Calc'!A8 | B8: ='Model_Calc'!B8 | C8: ='Model_Calc'!D8 | D8: ='Model_Calc'!E8
A9: ='Model_Calc'!A9 | B9: ='Model_Calc'!B9 | C9: ='Model_Calc'!D9 | D9: ='Model_Calc'!E9
A10: ='Model_Calc'!A10 | B10: ='Model_Calc'!B10 | C10: ='Model_Calc'!D10 | D10: ='Model_Calc'!E10
A11: ='Model_Calc'!A11 | B11: ='Model_Calc'!B11 | C11: ='Model_Calc'!D11 | D11: ='Model_Calc'!E11
A12: ='Model_Calc'!A12 | B12: ='Model_Calc'!B12 | C12: ='Model_Calc'!D12 | D12: ='Model_Calc'!E12
A13: ='Model_Calc'!A13 | B13: ='Model_Calc'!B13 | C13: ='Model_Calc'!D13 | D13: ='Model_Calc'!E13
A14: ='Model_Calc'!A14 | B14: ='Model_Calc'!B14 | C14: ='Model_Calc'!D14 | D14: ='Model_Calc'!E14
A15: ='Model_Calc'!A15 | B15: ='Model_Calc'!B15 | C15: ='Model_Calc'!D15 | D15: ='Model_Calc'!E15

Sheet 02_Inputs
A1: Inputs | Trust vs LaaS/AI
A2: Editable inputs (blue).

Sheet 03_Baseline
A1: Baseline | No retrofit
A2: All savings relative to this baseline.
A5: Baseline electricity (Y1) | B5: ='Inputs_Data'!C6
A6: Baseline cash OPEX (Y1) | B6: ='Inputs_Data'!E6

Sheet 04_Mode_Params
A1: Mode params
A2: (placeholder; see WPS export for full layout)

Sheet 05_Annual_Model
A1: Annual model
A2: (placeholder)

Sheet 06_Sensitivity
A1: Sensitivity
A2: (placeholder)

Sheet 07_Model_Checks
A1: Model checks
A2: (placeholder)

Sheet 08_Calc_Logic
A1: Calc logic
A2: (placeholder)

Sheet 09_Glossary
A1: Glossary
A2: (placeholder)

Sheet Story_and_Sources
A1: Story_and_Sources
A2: Each assumption is mapped to a model lever and backed by a public source link.
A4: Benchmarks and how they map into the model
A5: Driver | B5: Metric (benchmark) | C5: How used in model | D5: Assumption cell | E5: Source (URL)
A6: Predictive maintenance / remote diagnostics | B6: Avoided patrols / optimized repairs (qualitative + routing savings) | C6: Maps to reductions in staff / vehicles / materials OPEX (line-item factors) | D6: Assumptions!B8:B12 | E6: https://oxmaint.com/industries/government/street-lighting-lamp-out-ai-detection
A7: Adaptive controls / dimming | B7: Energy savings can be large depending on baseline and dimming strategy (literature) | C7: Maps to electricity OPEX reduction factor (electricity_only_pct mode) | D7: Assumptions!B6 | E7: https://mdpi-res.com/d_attachment/smartcities/smartcities-03-00071/article_deploy/smartcities-03-00071-v2.pdf?version=1607517901
A8: City case study | B8: Energy costs cut by 61% (case; not universal) | C8: Used as an upper-bound sense check; model uses conservative default | D8: Assumptions!B6 | E8: https://insights.acuitybrands.com/casestudies/city-of-west-richland-case-study
A9: Utility case study | B9: Avoided truck rolls (evidence of O&M reduction potential) | C9: Supports reductions in vehicles / staff OPEX lines (dispatch, truck rolls) | D9: Assumptions!B9:B11 | E9: https://lam.itron.com/documents/d/asset-library-120736/itron-tampa-electric-case-study-1
A10: Solarization (street lights) | B10: System-level feasibility context (LCC / solarization programs) | C10: Used only to justify the AI+solar tier narrative; electricity=0 is a contract/engineering assumption | D10: Assumptions!B6 (ai_plus_solar tier) | E10: https://www.saarcenergy.org/wp-content/uploads/2022/08/Draft-report-of-EE-Solarisation-of-Street-Lighting_Rev4_04.07.2022_No-Markup.pdf
