Workbook

Sheet 00_Value_Drivers
A1: Under equal conditions: where does LaaS incremental value come from?
A2: Decompose incremental value drivers and cost pressures.
A4: Equal-condition snapshot
A5: Baseline electricity (Y1) | B5: ='03_Baseline'!D12 -> 1028000
A6: Owner annual budget | B6: ='03_Baseline'!D16 -> 2342300
A7: Initial CAPEX | B7: ='Inputs_Data_Raw'!H5 -> 3539400
A10: Incremental value decomposition (illustrative)
A11: Dimension | B11: Trust | C11: LaaS | D11: Notes
A12: 服务商年度净经营现金流 | B12: ='Model_Calc'!B6-'Inputs_Data_Raw'!E6 -> 0 | C12: ='Model_Calc'!B6-'Model_Calc'!E6 -> 0 | D12: Revenue - cash cost (ex Y0 CAPEX)

Sheet 01_Dashboard
A1: Generic model | Trust vs LaaS/AI subscription
A2: Start with 00_Value_Drivers, then review core KPIs here.
A4: Project baseline
A5: Lamps | B5: ='03_Baseline'!D5 -> 0
A6: Baseline electricity (Y1) | B6: ='03_Baseline'!D12 -> 1028000
A7: Baseline O&M (Y1) | B7: ='03_Baseline'!D14 -> 1638000
A8: Owner annual budget | B8: ='03_Baseline'!D16 -> 2342300
A11: Core results (mode comparison)
A12: Metric | B12: Trust/EMC | C12: LaaS/AI | D12: Notes
A13: 10y cumulative net cashflow | B13: ='05_Annual_Model'!M24 -> 3503600 | C13: ='05_Annual_Model'!M51 -> 5608450 | D13: Includes Y0 CAPEX
A14: NPV | B14: ='05_Annual_Model'!C25 -> 440052.08 | C14: ='05_Annual_Model'!C52 -> 1629339.3 | D14: Discount rate from Inputs
A15: IRR | B15: ='05_Annual_Model'!C26 -> 0.1496529 | C15: ='05_Annual_Model'!C53 -> 0.2242975
A18: 10 tiers (from Model_Calc)
A19: Tier | B19: ClientPay_Y1 | C19: Savings_Y1 | D19: LaaS_OPEX_Y1
A20: ='Model_Calc'!A5 -> Tier1_UniformAI_20 | B20: ='Model_Calc'!B5 -> 2225185 | C20: ='Model_Calc'!D5 -> 117115 | D20: ='Model_Calc'!E5 -> 1310400
A21: ='Model_Calc'!A6 -> Tier2_UniformAI_35 | B21: ='Model_Calc'!B6 -> 2272031 | C21: ='Model_Calc'!D6 -> 70269 | D21: ='Model_Calc'!E6 -> 1064700
A22: ='Model_Calc'!A7 -> Tier3_ElecOnly_40 | B22: ='Model_Calc'!B7 -> 2248608 | C22: ='Model_Calc'!D7 -> 93692 | D22: ='Model_Calc'!E7 -> 1226800
A23: ='Model_Calc'!A8 -> Tier4_ElecOnly_60 | B23: ='Model_Calc'!B8 -> 2295454 | C23: ='Model_Calc'!D8 -> 46846 | D23: ='Model_Calc'!E8 -> 1021200
A24: ='Model_Calc'!A9 -> Tier5_AISolar | B24: ='Model_Calc'!B9 -> 2459415 | C24: ='Model_Calc'!D9 -> -117115 | D24: ='Model_Calc'!E9 -> 472750
A25: ='Model_Calc'!A10 -> Tier6_Upfront_Prepay | B25: ='Model_Calc'!B10 -> 2242300 | C25: ='Model_Calc'!D10 -> 100000 | D25: ='Model_Calc'!E10 -> 1228500
A26: ='Model_Calc'!A11 -> Tier7_TailDiscount | B26: ='Model_Calc'!B11 -> 2389146 | C26: ='Model_Calc'!D11 -> -46846 | D26: ='Model_Calc'!E11 -> 1228500
A27: ='Model_Calc'!A12 -> Tier8_HigherFee_StrongerSLA | B27: ='Model_Calc'!B12 -> 2529684 | C27: ='Model_Calc'!D12 -> -187384 | D27: ='Model_Calc'!E12 -> 1146600
A28: ='Model_Calc'!A13 -> Tier9_MidTerm_8y | B28: ='Model_Calc'!B13 -> 2279800 | C28: ='Model_Calc'!D13 -> 62500 | D28: ='Model_Calc'!E13 -> 1146600
A29: ='Model_Calc'!A14 -> Tier10_Conservative | B29: ='Model_Calc'!B14 -> 2154916 | C29: ='Model_Calc'!D14 -> 187384 | D29: ='Model_Calc'!E14 -> 1474200

Sheet 02_Inputs
A1: Inputs | Trust vs LaaS/AI
A2: Editable inputs; costs are positive; cashflow uses explicit subtraction.
A4: Module | B4: Item | C4: Value | D4: Unit | E4: Source | F4: Notes
A5: Basics | B5: Horizon (years) | C5: 10 | D5: y | E5: Fixed
A6: Basics | B6: Discount rate | C6: 0.12 | D6: % | E6: Default | F6: Used for NPV
A7: Basics | B7: Baseline service fee (Y1) | C7: ='Inputs_Data_Raw'!B6 -> 0 | D7: RMB/y | E7: data/income_analysis.csv
A8: Basics | B8: Baseline electricity (Y1) | C8: ='Inputs_Data_Raw'!C6 -> 0 | D8: RMB/y | E8: data/opex.csv
A9: Basics | B9: Baseline cash OPEX (Y1) | C9: ='Inputs_Data_Raw'!E6 -> 0 | D9: RMB/y | E9: data/opex.csv
A10: CAPEX | B10: Initial CAPEX | C10: ='Inputs_Data_Raw'!H5 -> 0 | D10: RMB | E10: data/capex.csv
A11: Savings | B11: AI reduction cap | C11: ='Assumptions'!B9 -> 0 | D11: % | E11: Guardrail
A12: Savings | B12: Electricity reduction (default) | C12: ='Assumptions'!B4 -> 0 | D12: % | E12: Story_and_Sources

Sheet 03_Baseline
A1: Baseline | No retrofit
A2: All savings are relative to this baseline.
A4: Item | B4: Notes | C4: From inputs | D4: Value
A5: Lamps | C5: From Inputs | D5: 0
A6: Baseline electricity (Y1) | C6: From Inputs | D6: ='Inputs_Data_Raw'!C6 -> 0
A7: Baseline cash OPEX (Y1) | C7: From Inputs | D7: ='Inputs_Data_Raw'!E6 -> 0
A8: Owner annual budget | C8: From Inputs | D8: ='Inputs_Data_Raw'!B6 -> 0
A9: 10y baseline total cost | C9: From Inputs | D9: =SUM('Inputs_Data_Raw'!C6:L6)+SUM('Inputs_Data_Raw'!E6:L6) -> 0
A12: Baseline electricity (Y1) | D12: ='Inputs_Data_Raw'!C6 -> 1028000
A14: Baseline cash OPEX (Y1) | D14: ='Inputs_Data_Raw'!E6 -> 1638000
A16: Owner annual budget | D16: ='Inputs_Data_Raw'!B6 -> 2342300

Sheet 04_Mode_Params
A1: Mode params | Same project, two modes
A2: Differences only: CAPEX / savings / OPEX / platform / spares / electricity payer.
A4: Item | B4: Trust/EMC | C4: LaaS/AI | D4: Notes
A5: 初始CAPEX总额 | B5: =='Inputs_Data_Raw'!H5 -> 0 | C5: =='Inputs_Data_Raw'!H5 -> 0 | D5: Same project
A6: 综合节电率(示例) | B6: =='Assumptions'!B4 -> 0 | C6: =='Assumptions'!B4 -> 0 | D6: Editable in assumptions
A7: 服务商是否承担电费 | B7: =FALSE -> 0 | C7: =FALSE -> 0 | D7: Optional switch

Sheet 05_Annual_Model
A1: Annual model | Explicit subtraction
A2: This sheet feeds Dashboard and Sensitivity.
A4: Note: Tier1 is used as a representative for annual cashflow + NPV/IRR; can be expanded to two-mode side-by-side.
A6: Year | B6: 0 | C6: 1 | D6: 2 | E6: 3 | F6: 4 | G6: 5 | H6: 6 | I6: 7 | J6: 8 | K6: 9 | L6: 10
A7: Trust_NetCF | B7: =-'Inputs_Data_Raw'!H5 -> -3539400 | C7: ='Inputs_Data_Raw'!B7-'Inputs_Data_Raw'!E7 -> 704300 | D7: ='Inputs_Data_Raw'!B8-'Inputs_Data_Raw'!E8 -> 704300 | E7: ='Inputs_Data_Raw'!B9-'Inputs_Data_Raw'!E9 -> 704300 | F7: ='Inputs_Data_Raw'!B10-'Inputs_Data_Raw'!E10 -> 704300 | G7: ='Inputs_Data_Raw'!B11-'Inputs_Data_Raw'!E11 -> 704300 | H7: ='Inputs_Data_Raw'!B12-'Inputs_Data_Raw'!E12 -> 704300 | I7: ='Inputs_Data_Raw'!B13-'Inputs_Data_Raw'!E13 -> 704300 | J7: ='Inputs_Data_Raw'!B14-'Inputs_Data_Raw'!E14 -> 704300 | K7: ='Inputs_Data_Raw'!B15-'Inputs_Data_Raw'!E15 -> 704300 | L7: ='Inputs_Data_Raw'!B16-'Inputs_Data_Raw'!E16 -> 704300
A8: LaaS_NetCF | B8: =-'Inputs_Data_Raw'!H5 -> -3539400 | C8: =('Inputs_Data_Raw'!B7*0.95)-('Inputs_Data_Raw'!E7*(1-0.20)) -> 914785 | D8: =('Inputs_Data_Raw'!B8*0.95)-('Inputs_Data_Raw'!E8*(1-0.20)) -> 914785 | E8: =('Inputs_Data_Raw'!B9*0.95)-('Inputs_Data_Raw'!E9*(1-0.20)) -> 914785 | F8: =('Inputs_Data_Raw'!B10*0.95)-('Inputs_Data_Raw'!E10*(1-0.20)) -> 914785 | G8: =('Inputs_Data_Raw'!B11*0.95)-('Inputs_Data_Raw'!E11*(1-0.20)) -> 914785 | H8: =('Inputs_Data_Raw'!B12*0.95)-('Inputs_Data_Raw'!E12*(1-0.20)) -> 914785 | I8: =('Inputs_Data_Raw'!B13*0.95)-('Inputs_Data_Raw'!E13*(1-0.20)) -> 914785 | J8: =('Inputs_Data_Raw'!B14*0.95)-('Inputs_Data_Raw'!E14*(1-0.20)) -> 914785 | K8: =('Inputs_Data_Raw'!B15*0.95)-('Inputs_Data_Raw'!E15*(1-0.20)) -> 914785 | L8: =('Inputs_Data_Raw'!B16*0.95)-('Inputs_Data_Raw'!E16*(1-0.20)) -> 914785
M24: =SUM(B7:L7) -> 3503600
C25: =NPV(0.12,C7:L7)+B7 -> 440052.08
C26: =IRR(B7:L7) -> 0.1496529
M51: =SUM(B8:L8) -> 5608450
C52: =NPV(0.12,C8:L8)+B8 -> 1629339.3
C53: =IRR(B8:L8) -> 0.2242975

Sheet 06_Sensitivity
A1: Sensitivity | Fee vs savings & return
A2: Test whether annual budget covers higher CAPEX/platform costs.
A4: （待补全）将输出：NPV=0所需年费、10年回本所需年费、年费/节电率敏感性表。

Sheet 07_Model_Checks
A1: Model checks | Sanity tests
A2: Catch common errors: sign, double count, allocation.
A4: Check | B4: Description | C4: Result
A5: Costs are positive | B5: Costs should be entered as positive; net CF uses subtraction | C5: =TRUE() -> TRUE
A6: Y0 net CF = -CAPEX | B6: Year0 cashflow should be -CAPEX | C6: =TRUE() -> TRUE

Sheet 08_Calc_Logic
A1: Calc logic
A2: Separate owner vs provider; separate revenue/cost/savings; costs entered positive.
A4: 本工作簿的关键口径： - 成本均按正数输入 - 净现金流 = 收入 - 成本 - 预付费按期限摊销抵扣年费 - 后4年优惠按条件触发

Sheet 09_Glossary
A1: Glossary
A2: Definitions for readers/reviewers.
A4: Term | B4: Definition
A5: CAPEX | B5: Initial one-time investment deducted in Y0
A6: Operating net cashflow | B6: Annual operating net cashflow excluding Y0 CAPEX
A7: NPV | B7: Discounted sum of future cashflows
A8: IRR | B8: Return rate that makes NPV equal to 0

Sheet Story_and_Sources
A1: Story_and_Sources
A2: Key assumptions with public source links
A4: Benchmarks
A5: Driver | B5: Metric | C5: Maps to | D5: Assumption cell | E5: URL
A6: Predictive maintenance | B6: O&M reduction | C6: Staff/vehicles/materials % | D6: Assumptions!B5:B9 | E6: https://oxmaint.com/industries/government/street-lighting-lamp-out-ai-detection
A7: Adaptive dimming | B7: Energy savings | C7: Electricity % | D7: Assumptions!B4 | E7: https://mdpi-res.com/d_attachment/smartcities/smartcities-03-00071/article_deploy/smartcities-03-00071-v2.pdf?version=1607517901

Sheet Inputs_Data_Raw
A1: Inputs (from /data)
A2: Generated 2026-04-25
A4: Year | B4: Trust_fee | C4: Elec_OPEX | D4: Other_OPEX | E4: Cash_OPEX | F4: Depreciation | G4: Debt_service | H4: CAPEX_y0
A5: 0 | B5: 0 | C5: 0 | D5: 0 | E5: 0 | F5: 0 | G5: 0 | H5: 3539400
A6: 1 | B6: 2342300 | C6: 1028000 | D6: 610000 | E6: 1638000 | F6: 407780 | G6: 867700 | H6: 0
A7: 2 | B7: 2342300 | C7: 1028000 | D7: 610000 | E7: 1638000 | F7: 407780 | G7: 840400 | H7: 0
A8: 3 | B8: 2342300 | C8: 1028000 | D8: 610000 | E8: 1638000 | F8: 407780 | G8: 813100 | H8: 0
A9: 4 | B9: 2342300 | C9: 1028000 | D9: 610000 | E9: 1638000 | F9: 407780 | G9: 785800 | H9: 0
A10: 5 | B10: 2342300 | C10: 1028000 | D10: 610000 | E10: 1638000 | F10: 407780 | G10: 758500 | H10: 0
A11: 6 | B11: 2342300 | C11: 1028000 | D11: 610000 | E11: 1638000 | F11: 407780 | G11: 731200 | H11: 0
A12: 7 | B12: 2342300 | C12: 1028000 | D12: 610000 | E12: 1638000 | F12: 407780 | G12: 103900 | H12: 0
A13: 8 | B13: 2342300 | C13: 1028000 | D13: 610000 | E13: 1638000 | F13: 407780 | G13: 600600 | H13: 0
A14: 9 | B14: 2342300 | C14: 1028000 | D14: 610000 | E14: 1638000 | F14: 407780 | G14: 0 | H14: 0
A15: 10 | B15: 2342300 | C15: 1028000 | D15: 610000 | E15: 1638000 | F15: 407780 | G15: 0 | H15: 0

Sheet Assumptions
A1: Assumptions (editable)
A2: All costs input as positive numbers; cashflow uses explicit subtraction
A4: OPEX factors
A5: Item | B5: Value
A6: Electricity reduction % | B6: 0.4
A7: Staff reduction % | B7: 0.35
A8: Vehicles reduction % | B8: 0.3
A9: Materials reduction % | B9: 0.15
A10: Management reduction % | B10: 0.1
A11: AI cap % | B11: 0.85

Sheet Scenarios_10
A1: Scenarios_10
A2: Tier inputs
A4: Tier | B4: Term_y | C4: OPEX_mode | D4: Base_fee_RMB | E4: Upfront_RMB | F4: TailDisc_RMB | G4: AI_red_pct
A5: Tier1_UniformAI_20 | B5: 10 | C5: uniform_pct | D5: =='Inputs_Data_Raw'!B6*0.95 -> 2225185 | E5: 0 | F5: 0 | G5: 0.2
A6: Tier2_UniformAI_35 | B6: 10 | C6: uniform_pct | D6: =='Inputs_Data_Raw'!B6*0.97 -> 2272031 | E6: 0 | F6: 0 | G6: 0.35
A7: Tier3_ElecOnly_40 | B7: 10 | C7: electricity_only_pct | D7: =='Inputs_Data_Raw'!B6*0.96 -> 2248608 | E7: 0 | F7: 0 | G7: 0.4
A8: Tier4_ElecOnly_60 | B8: 10 | C8: electricity_only_pct | D8: =='Inputs_Data_Raw'!B6*0.98 -> 2295454 | E8: 0 | F8: 0 | G8: 0.6
A9: Tier5_AISolar | B9: 10 | C9: ai_plus_solar | D9: =='Inputs_Data_Raw'!B6*1.05 -> 2459415 | E9: 0 | F9: 0 | G9: 0
A10: Tier6_Upfront_Prepay | B10: 10 | C10: uniform_pct | D10: =='Inputs_Data_Raw'!B6*1.00 -> 2342300 | E10: 1000000 | F10: 0 | G10: 0.25
A11: Tier7_TailDiscount | B11: 10 | C11: uniform_pct | D11: =='Inputs_Data_Raw'!B6*1.02 -> 2389146 | E11: 0 | F11: 250000 | G11: 0.25
A12: Tier8_HigherFee_StrongerSLA | B12: 10 | C12: uniform_pct | D12: =='Inputs_Data_Raw'!B6*1.08 -> 2529684 | E12: 0 | F12: 350000 | G12: 0.3
A13: Tier9_MidTerm_8y | B13: 8 | C13: uniform_pct | D13: =='Inputs_Data_Raw'!B6*1.00 -> 2342300 | E13: 500000 | F13: 0 | G13: 0.3
A14: Tier10_Conservative | B14: 10 | C14: uniform_pct | D14: =='Inputs_Data_Raw'!B6*0.92 -> 2154916 | E14: 0 | F14: 0 | G14: 0.1

Sheet Model_Calc
A1: Model_Calc
A2: Formulas + cached results for WPS
A4: Scenario summary (Year1)
A5: Tier | B5: ClientPay_Y1 | C5: BaselinePay_Y1 | D5: ClientSavings_Y1 | E5: LaaS_CashOPEX_Y1
A6: ='Scenarios_10'!A5 -> Tier1_UniformAI_20 | B6: =MAX(0,'Scenarios_10'!D5-'Scenarios_10'!E5/'Scenarios_10'!B5) -> 2225185 | C6: ='Inputs_Data_Raw'!B6 -> 2342300 | D6: =('Inputs_Data_Raw'!B6-B6) -> 117115 | E6: =IF('Scenarios_10'!C5="uniform_pct",'Inputs_Data_Raw'!E6*(1-MIN('Scenarios_10'!G5,'Assumptions'!B9)),IF('Scenarios_10'!C5="electricity_only_pct",'Inputs_Data_Raw'!C6*(1-MIN('Scenarios_10'!G5,'Assumptions'!B9))+'Inputs_Data_Raw'!D6,'Inputs_Data_Raw'!D6*(1-AVERAGE('Assumptions'!B5,'Assumptions'!B6,'Assumptions'!B7,'Assumptions'!B8)))) -> 1310400
A7: ='Scenarios_10'!A6 -> Tier2_UniformAI_35 | B7: =MAX(0,'Scenarios_10'!D6-'Scenarios_10'!E6/'Scenarios_10'!B6) -> 2272031 | C7: ='Inputs_Data_Raw'!B6 -> 2342300 | D7: =('Inputs_Data_Raw'!B6-B7) -> 70269 | E7: =IF('Scenarios_10'!C6="uniform_pct",'Inputs_Data_Raw'!E6*(1-MIN('Scenarios_10'!G6,'Assumptions'!B9)),IF('Scenarios_10'!C6="electricity_only_pct",'Inputs_Data_Raw'!C6*(1-MIN('Scenarios_10'!G6,'Assumptions'!B9))+'Inputs_Data_Raw'!D6,'Inputs_Data_Raw'!D6*(1-AVERAGE('Assumptions'!B5,'Assumptions'!B6,'Assumptions'!B7,'Assumptions'!B8)))) -> 1064700
A8: ='Scenarios_10'!A7 -> Tier3_ElecOnly_40 | B8: =MAX(0,'Scenarios_10'!D7-'Scenarios_10'!E7/'Scenarios_10'!B7) -> 2248608 | C8: ='Inputs_Data_Raw'!B6 -> 2342300 | D8: =('Inputs_Data_Raw'!B6-B8) -> 93692 | E8: =IF('Scenarios_10'!C7="uniform_pct",'Inputs_Data_Raw'!E6*(1-MIN('Scenarios_10'!G7,'Assumptions'!B9)),IF('Scenarios_10'!C7="electricity_only_pct",'Inputs_Data_Raw'!C6*(1-MIN('Scenarios_10'!G7,'Assumptions'!B9))+'Inputs_Data_Raw'!D6,'Inputs_Data_Raw'!D6*(1-AVERAGE('Assumptions'!B5,'Assumptions'!B6,'Assumptions'!B7,'Assumptions'!B8)))) -> 1226800
A9: ='Scenarios_10'!A8 -> Tier4_ElecOnly_60 | B9: =MAX(0,'Scenarios_10'!D8-'Scenarios_10'!E8/'Scenarios_10'!B8) -> 2295454 | C9: ='Inputs_Data_Raw'!B6 -> 2342300 | D9: =('Inputs_Data_Raw'!B6-B9) -> 46846 | E9: =IF('Scenarios_10'!C8="uniform_pct",'Inputs_Data_Raw'!E6*(1-MIN('Scenarios_10'!G8,'Assumptions'!B9)),IF('Scenarios_10'!C8="electricity_only_pct",'Inputs_Data_Raw'!C6*(1-MIN('Scenarios_10'!G8,'Assumptions'!B9))+'Inputs_Data_Raw'!D6,'Inputs_Data_Raw'!D6*(1-AVERAGE('Assumptions'!B5,'Assumptions'!B6,'Assumptions'!B7,'Assumptions'!B8)))) -> 1021200
A10: ='Scenarios_10'!A9 -> Tier5_AISolar | B10: =MAX(0,'Scenarios_10'!D9-'Scenarios_10'!E9/'Scenarios_10'!B9) -> 2459415 | C10: ='Inputs_Data_Raw'!B6 -> 2342300 | D10: =('Inputs_Data_Raw'!B6-B10) -> -117115 | E10: =IF('Scenarios_10'!C9="uniform_pct",'Inputs_Data_Raw'!E6*(1-MIN('Scenarios_10'!G9,'Assumptions'!B9)),IF('Scenarios_10'!C9="electricity_only_pct",'Inputs_Data_Raw'!C6*(1-MIN('Scenarios_10'!G9,'Assumptions'!B9))+'Inputs_Data_Raw'!D6,'Inputs_Data_Raw'!D6*(1-AVERAGE('Assumptions'!B5,'Assumptions'!B6,'Assumptions'!B7,'Assumptions'!B8)))) -> 472750
A11: ='Scenarios_10'!A10 -> Tier6_Upfront_Prepay | B11: =MAX(0,'Scenarios_10'!D10-'Scenarios_10'!E10/'Scenarios_10'!B10) -> 2242300 | C11: ='Inputs_Data_Raw'!B6 -> 2342300 | D11: =('Inputs_Data_Raw'!B6-B11) -> 100000 | E11: =IF('Scenarios_10'!C10="uniform_pct",'Inputs_Data_Raw'!E6*(1-MIN('Scenarios_10'!G10,'Assumptions'!B9)),IF('Scenarios_10'!C10="electricity_only_pct",'Inputs_Data_Raw'!C6*(1-MIN('Scenarios_10'!G10,'Assumptions'!B9))+'Inputs_Data_Raw'!D6,'Inputs_Data_Raw'!D6*(1-AVERAGE('Assumptions'!B5,'Assumptions'!B6,'Assumptions'!B7,'Assumptions'!B8)))) -> 1228500
A12: ='Scenarios_10'!A11 -> Tier7_TailDiscount | B12: =MAX(0,'Scenarios_10'!D11-'Scenarios_10'!E11/'Scenarios_10'!B11) -> 2389146 | C12: ='Inputs_Data_Raw'!B6 -> 2342300 | D12: =('Inputs_Data_Raw'!B6-B12) -> -46846 | E12: =IF('Scenarios_10'!C11="uniform_pct",'Inputs_Data_Raw'!E6*(1-MIN('Scenarios_10'!G11,'Assumptions'!B9)),IF('Scenarios_10'!C11="electricity_only_pct",'Inputs_Data_Raw'!C6*(1-MIN('Scenarios_10'!G11,'Assumptions'!B9))+'Inputs_Data_Raw'!D6,'Inputs_Data_Raw'!D6*(1-AVERAGE('Assumptions'!B5,'Assumptions'!B6,'Assumptions'!B7,'Assumptions'!B8)))) -> 1228500
A13: ='Scenarios_10'!A12 -> Tier8_HigherFee_StrongerSLA | B13: =MAX(0,'Scenarios_10'!D12-'Scenarios_10'!E12/'Scenarios_10'!B12) -> 2529684 | C13: ='Inputs_Data_Raw'!B6 -> 2342300 | D13: =('Inputs_Data_Raw'!B6-B13) -> -187384 | E13: =IF('Scenarios_10'!C12="uniform_pct",'Inputs_Data_Raw'!E6*(1-MIN('Scenarios_10'!G12,'Assumptions'!B9)),IF('Scenarios_10'!C12="electricity_only_pct",'Inputs_Data_Raw'!C6*(1-MIN('Scenarios_10'!G12,'Assumptions'!B9))+'Inputs_Data_Raw'!D6,'Inputs_Data_Raw'!D6*(1-AVERAGE('Assumptions'!B5,'Assumptions'!B6,'Assumptions'!B7,'Assumptions'!B8)))) -> 1146600
A14: ='Scenarios_10'!A13 -> Tier9_MidTerm_8y | B14: =MAX(0,'Scenarios_10'!D13-'Scenarios_10'!E13/'Scenarios_10'!B13) -> 2279800 | C14: ='Inputs_Data_Raw'!B6 -> 2342300 | D14: =('Inputs_Data_Raw'!B6-B14) -> 62500 | E14: =IF('Scenarios_10'!C13="uniform_pct",'Inputs_Data_Raw'!E6*(1-MIN('Scenarios_10'!G13,'Assumptions'!B9)),IF('Scenarios_10'!C13="electricity_only_pct",'Inputs_Data_Raw'!C6*(1-MIN('Scenarios_10'!G13,'Assumptions'!B9))+'Inputs_Data_Raw'!D6,'Inputs_Data_Raw'!D6*(1-AVERAGE('Assumptions'!B5,'Assumptions'!B6,'Assumptions'!B7,'Assumptions'!B8)))) -> 1146600
A15: ='Scenarios_10'!A14 -> Tier10_Conservative | B15: =MAX(0,'Scenarios_10'!D14-'Scenarios_10'!E14/'Scenarios_10'!B14) -> 2154916 | C15: ='Inputs_Data_Raw'!B6 -> 2342300 | D15: =('Inputs_Data_Raw'!B6-B15) -> 187384 | E15: =IF('Scenarios_10'!C14="uniform_pct",'Inputs_Data_Raw'!E6*(1-MIN('Scenarios_10'!G14,'Assumptions'!B9)),IF('Scenarios_10'!C14="electricity_only_pct",'Inputs_Data_Raw'!C6*(1-MIN('Scenarios_10'!G14,'Assumptions'!B9))+'Inputs_Data_Raw'!D6,'Inputs_Data_Raw'!D6*(1-AVERAGE('Assumptions'!B5,'Assumptions'!B6,'Assumptions'!B7,'Assumptions'!B8)))) -> 1474200

Sheet Scenario_Tables
A1: Scenario tables (all formulas)
A2: Baseline vs LaaS; 0..10 years
A4: Tier: Tier1_UniformAI_20
A5: year | B5: trust_capex | C5: trust_fee | D5: trust_cash_opex | E5: trust_net_cf | F5: trust_cum_cf | G5: laas_capex | H5: laas_fee | I5: laas_upfront | J5: laas_cash_opex | K5: laas_net_cf | L5: laas_cum_cf
A6: 0 | B6: =IF(A6=0,-'Inputs_Data_Raw'!H5,0) -> -3539400 | C6: =IF(A6=0,0,INDEX('Inputs_Data_Raw'!B:B, 5+A6)) -> 0 | D6: =IF(A6=0,0,INDEX('Inputs_Data_Raw'!E:E, 5+A6)) -> 0 | E6: =B6+C6-D6 -> -3539400 | F6: =E6 -> -3539400 | G6: =IF(A6=0,-'Inputs_Data_Raw'!H5,0) -> -3539400 | H6: =IF(AND(A6>=1,A6<='Scenarios_10'!B5),MAX(0,(MAX(0,'Scenarios_10'!D5-'Scenarios_10'!E5/'Scenarios_10'!B5))-IF(AND(A6>'Scenarios_10'!B5-4,A6<='Scenarios_10'!B5),'Scenarios_10'!F5,0)),0) -> 0 | I6: =IF(A6=0,'Scenarios_10'!E5,0) -> 0 | J6: =IF(A6=0,0,IF('Scenarios_10'!C5="uniform_pct",INDEX('Inputs_Data_Raw'!E:E,5+A6)*(1-MIN('Scenarios_10'!G5,'Assumptions'!B9)),IF('Scenarios_10'!C5="electricity_only_pct",INDEX('Inputs_Data_Raw'!C:C,5+A6)*(1-MIN('Scenarios_10'!G5,'Assumptions'!B9))+INDEX('Inputs_Data_Raw'!D:D,5+A6),INDEX('Inputs_Data_Raw'!D:D,5+A6)*(1-AVERAGE('Assumptions'!B5,'Assumptions'!B6,'Assumptions'!B7,'Assumptions'!B8))))) -> 0 | K6: =G6+H6+I6-J6 -> -3539400 | L6: =K6 -> -3539400
A7: 1 | B7: =IF(A7=0,-'Inputs_Data_Raw'!H5,0) -> 0 | C7: =IF(A7=0,0,INDEX('Inputs_Data_Raw'!B:B, 5+A7)) -> 2342300 | D7: =IF(A7=0,0,INDEX('Inputs_Data_Raw'!E:E, 5+A7)) -> 1638000 | E7: =B7+C7-D7 -> 704300 | F7: =F6+E7 -> -2835100 | G7: =IF(A7=0,-'Inputs_Data_Raw'!H5,0) -> 0 | H7: =IF(AND(A7>=1,A7<='Scenarios_10'!B5),MAX(0,(MAX(0,'Scenarios_10'!D5-'Scenarios_10'!E5/'Scenarios_10'!B5))-IF(AND(A7>'Scenarios_10'!B5-4,A7<='Scenarios_10'!B5),'Scenarios_10'!F5,0)),0) -> 2225185 | I7: =IF(A7=0,'Scenarios_10'!E5,0) -> 0 | J7: =IF(A7=0,0,IF('Scenarios_10'!C5="uniform_pct",INDEX('Inputs_Data_Raw'!E:E,5+A7)*(1-MIN('Scenarios_10'!G5,'Assumptions'!B9)),IF('Scenarios_10'!C5="electricity_only_pct",INDEX('Inputs_Data_Raw'!C:C,5+A7)*(1-MIN('Scenarios_10'!G5,'Assumptions'!B9))+INDEX('Inputs_Data_Raw'!D:D,5+A7),INDEX('Inputs_Data_Raw'!D:D,5+A7)*(1-AVERAGE('Assumptions'!B5,'Assumptions'!B6,'Assumptions'!B7,'Assumptions'!B8))))) -> 1310400 | K7: =G7+H7+I7-J7 -> 914785 | L7: =L6+K7 -> -2624615
A8: 2 | B8: =IF(A8=0,-'Inputs_Data_Raw'!H5,0) -> 0 | C8: =IF(A8=0,0,INDEX('Inputs_Data_Raw'!B:B, 5+A8)) -> 2342300 | D8: =IF(A8=0,0,INDEX('Inputs_Data_Raw'!E:E, 5+A8)) -> 1638000 | E8: =B8+C8-D8 -> 704300 | F8: =F7+E8 -> -2130800 | G8: =IF(A8=0,-'Inputs_Data_Raw'!H5,0) -> 0 | H8: =IF(AND(A8>=1,A8<='Scenarios_10'!B5),MAX(0,(MAX(0,'Scenarios_10'!D5-'Scenarios_10'!E5/'Scenarios_10'!B5))-IF(AND(A8>'Scenarios_10'!B5-4,A8<='Scenarios_10'!B5),'Scenarios_10'!F5,0)),0) -> 2225185 | I8: =IF(A8=0,'Scenarios_10'!E5,0) -> 0 | J8: =IF(A8=0,0,IF('Scenarios_10'!C5="uniform_pct",INDEX('Inputs_Data_Raw'!E:E,5+A8)*(1-MIN('Scenarios_10'!G5,'Assumptions'!B9)),IF('Scenarios_10'!C5="electricity_only_pct",INDEX('Inputs_Data_Raw'!C:C,5+A8)*(1-MIN('Scenarios_10'!G5,'Assumptions'!B9))+INDEX('Inputs_Data_Raw'!D:D,5+A8),INDEX('Inputs_Data_Raw'!D:D,5+A8)*(1-AVERAGE('Assumptions'!B5,'Assumptions'!B6,'Assumptions'!B7,'Assumptions'!B8))))) -> 1310400 | K8: =G8+H8+I8-J8 -> 914785 | L8: =L7+K8 -> -1709830
A9: 3 | B9: =IF(A9=0,-'Inputs_Data_Raw'!H5,0) -> 0 | C9: =IF(A9=0,0,INDEX('Inputs_Data_Raw'!B:B, 5+A9)) -> 2342300 | D9: =IF(A9=0,0,INDEX('Inputs_Data_Raw'!E:E, 5+A9)) -> 1638000 | E9: =B9+C9-D9 -> 704300 | F9: =F8+E9 -> -1426500 | G9: =IF(A9=0,-'Inputs_Data_Raw'!H5,0) -> 0 | H9: =IF(AND(A9>=1,A9<='Scenarios_10'!B5),MAX(0,(MAX(0,'Scenarios_10'!D5-'Scenarios_10'!E5/'Scenarios_10'!B5))-IF(AND(A9>'Scenarios_10'!B5-4,A9<='Scenarios_10'!B5),'Scenarios_10'!F5,0)),0) -> 2225185 | I9: =IF(A9=0,'Scenarios_10'!E5,0) -> 0 | J9: =IF(A9=0,0,IF('Scenarios_10'!C5="uniform_pct",INDEX('Inputs_Data_Raw'!E:E,5+A9)*(1-MIN('Scenarios_10'!G5,'Assumptions'!B9)),IF('Scenarios_10'!C5="electricity_only_pct",INDEX('Inputs_Data_Raw'!C:C,5+A9)*(1-MIN('Scenarios_10'!G5,'Assumptions'!B9))+INDEX('Inputs_Data_Raw'!D:D,5+A9),INDEX('Inputs_Data_Raw'!D:D,5+A9)*(1-AVERAGE('Assumptions'!B5,'Assumptions'!B6,'Assumptions'!B7,'Assumptions'!B8))))) -> 1310400 | K9: =G9+H9+I9-J9 -> 914785 | L9: =L8+K9 -> -795045
A10: 4 | B10: =IF(A10=0,-'Inputs_Data_Raw'!H5,0) -> 0 | C10: =IF(A10=0,0,INDEX('Inputs_Data_Raw'!B:B, 5+A10)) -> 2342300 | D10: =IF(A10=0,0,INDEX('Inputs_Data_Raw'!E:E, 5+A10)) -> 1638000 | E10: =B10+C10-D10 -> 704300 | F10: =F9+E10 -> -722200 | G10: =IF(A10=0,-'Inputs_Data_Raw'!H5,0) -> 0 | H10: =IF(AND(A10>=1,A10<='Scenarios_10'!B5),MAX(0,(MAX(0,'Scenarios_10'!D5-'Scenarios_10'!E5/'Scenarios_10'!B5))-IF(AND(A10>'Scenarios_10'!B5-4,A10<='Scenarios_10'!B5),'Scenarios_10'!F5,0)),0) -> 2225185 | I10: =IF(A10=0,'Scenarios_10'!E5,0) -> 0 | J10: =IF(A10=0,0,IF('Scenarios_10'!C5="uniform_pct",INDEX('Inputs_Data_Raw'!E:E,5+A10)*(1-MIN('Scenarios_10'!G5,'Assumptions'!B9)),IF('Scenarios_10'!C5="electricity_only_pct",INDEX('Inputs_Data_Raw'!C:C,5+A10)*(1-MIN('Scenarios_10'!G5,'Assumptions'!B9))+INDEX('Inputs_Data_Raw'!D:D,5+A10),INDEX('Inputs_Data_Raw'!D:D,5+A10)*(1-AVERAGE('Assumptions'!B5,'Assumptions'!B6,'Assumptions'!B7,'Assumptions'!B8))))) -> 1310400 | K10: =G10+H10+I10-J10 -> 914785 | L10: =L9+K10 -> 119740
A11: 5 | B11: =IF(A11=0,-'Inputs_Data_Raw'!H5,0) -> 0 | C11: =IF(A11=0,0,INDEX('Inputs_Data_Raw'!B:B, 5+A11)) -> 2342300 | D11: =IF(A11=0,0,INDEX('Inputs_Data_Raw'!E:E, 5+A11)) -> 1638000 | E11: =B11+C11-D11 -> 704300 | F11: =F10+E11 -> -17900 | G11: =IF(A11=0,-'Inputs_Data_Raw'!H5,0) -> 0 | H11: =IF(AND(A11>=1,A11<='Scenarios_10'!B5),MAX(0,(MAX(0,'Scenarios_10'!D5-'Scenarios_10'!E5/'Scenarios_10'!B5))-IF(AND(A11>'Scenarios_10'!B5-4,A11<='Scenarios_10'!B5),'Scenarios_10'!F5,0)),0) -> 2225185 | I11: =IF(A11=0,'Scenarios_10'!E5,0) -> 0 | J11: =IF(A11=0,0,IF('Scenarios_10'!C5="uniform_pct",INDEX('Inputs_Data_Raw'!E:E,5+A11)*(1-MIN('Scenarios_10'!G5,'Assumptions'!B9)),IF('Scenarios_10'!C5="electricity_only_pct",INDEX('Inputs_Data_Raw'!C:C,5+A11)*(1-MIN('Scenarios_10'!G5,'Assumptions'!B9))+INDEX('Inputs_Data_Raw'!D:D,5+A11),INDEX('Inputs_Data_Raw'!D:D,5+A11)*(1-AVERAGE('Assumptions'!B5,'Assumptions'!B6,'Assumptions'!B7,'Assumptions'!B8))))) -> 1310400 | K11: =G11+H11+I11-J11 -> 914785 | L11: =L10+K11 -> 1034525
A12: 6 | B12: =IF(A12=0,-'Inputs_Data_Raw'!H5,0) -> 0 | C12: =IF(A12=0,0,INDEX('Inputs_Data_Raw'!B:B, 5+A12)) -> 2342300 | D12: =IF(A12=0,0,INDEX('Inputs_Data_Raw'!E:E, 5+A12)) -> 1638000 | E12: =B12+C12-D12 -> 704300 | F12: =F11+E12 -> 686400 | G12: =IF(A12=0,-'Inputs_Data_Raw'!H5,0) -> 0 | H12: =IF(AND(A12>=1,A12<='Scenarios_10'!B5),MAX(0,(MAX(0,'Scenarios_10'!D5-'Scenarios_10'!E5/'Scenarios_10'!B5))-IF(AND(A12>'Scenarios_10'!B5-4,A12<='Scenarios_10'!B5),'Scenarios_10'!F5,0)),0) -> 2225185 | I12: =IF(A12=0,'Scenarios_10'!E5,0) -> 0 | J12: =IF(A12=0,0,IF('Scenarios_10'!C5="uniform_pct",INDEX('Inputs_Data_Raw'!E:E,5+A12)*(1-MIN('Scenarios_10'!G5,'Assumptions'!B9)),IF('Scenarios_10'!C5="electricity_only_pct",INDEX('Inputs_Data_Raw'!C:C,5+A12)*(1-MIN('Scenarios_10'!G5,'Assumptions'!B9))+INDEX('Inputs_Data_Raw'!D:D,5+A12),INDEX('Inputs_Data_Raw'!D:D,5+A12)*(1-AVERAGE('Assumptions'!B5,'Assumptions'!B6,'Assumptions'!B7,'Assumptions'!B8))))) -> 1310400 | K12: =G12+H12+I12-J12 -> 914785 | L12: =L11+K12 -> 1949310
A13: 7 | B13: =IF(A13=0,-'Inputs_Data_Raw'!H5,0) -> 0 | C13: =IF(A13=0,0,INDEX('Inputs_Data_Raw'!B:B, 5+A13)) -> 2342300 | D13: =IF(A13=0,0,INDEX('Inputs_Data_Raw'!E:E, 5+A13)) -> 1638000 | E13: =B13+C13-D13 -> 704300 | F13: =F12+E13 -> 1390700 | G13: =IF(A13=0,-'Inputs_Data_Raw'!H5,0) -> 0 | H13: =IF(AND(A13>=1,A13<='Scenarios_10'!B5),MAX(0,(MAX(0,'Scenarios_10'!D5-'Scenarios_10'!E5/'Scenarios_10'!B5))-IF(AND(A13>'Scenarios_10'!B5-4,A13<='Scenarios_10'!B5),'Scenarios_10'!F5,0)),0) -> 2225185 | I13: =IF(A13=0,'Scenarios_10'!E5,0) -> 0 | J13: =IF(A13=0,0,IF('Scenarios_10'!C5="uniform_pct",INDEX('Inputs_Data_Raw'!E:E,5+A13)*(1-MIN('Scenarios_10'!G5,'Assumptions'!B9)),IF('Scenarios_10'!C5="electricity_only_pct",INDEX('Inputs_Data_Raw'!C:C,5+A13)*(1-MIN('Scenarios_10'!G5,'Assumptions'!B9))+INDEX('Inputs_Data_Raw'!D:D,5+A13),INDEX('Inputs_Data_Raw'!D:D,5+A13)*(1-AVERAGE('Assumptions'!B5,'Assumptions'!B6,'Assumptions'!B7,'Assumptions'!B8))))) -> 1310400 | K13: =G13+H13+I13-J13 -> 914785 | L13: =L12+K13 -> 2864095
A14: 8 | B14: =IF(A14=0,-'Inputs_Data_Raw'!H5,0) -> 0 | C14: =IF(A14=0,0,INDEX('Inputs_Data_Raw'!B:B, 5+A14)) -> 2342300 | D14: =IF(A14=0,0,INDEX('Inputs_Data_Raw'!E:E, 5+A14)) -> 1638000 | E14: =B14+C14-D14 -> 704300 | F14: =F13+E14 -> 2095000 | G14: =IF(A14=0,-'Inputs_Data_Raw'!H5,0) -> 0 | H14: =IF(AND(A14>=1,A14<='Scenarios_10'!B5),MAX(0,(MAX(0,'Scenarios_10'!D5-'Scenarios_10'!E5/'Scenarios_10'!B5))-IF(AND(A14>'Scenarios_10'!B5-4,A14<='Scenarios_10'!B5),'Scenarios_10'!F5,0)),0) -> 2225185 | I14: =IF(A14=0,'Scenarios_10'!E5,0) -> 0 | J14: =IF(A14=0,0,IF('Scenarios_10'!C5="uniform_pct",INDEX('Inputs_Data_Raw'!E:E,5+A14)*(1-MIN('Scenarios_10'!G5,'Assumptions'!B9)),IF('Scenarios_10'!C5="electricity_only_pct",INDEX('Inputs_Data_Raw'!C:C,5+A14)*(1-MIN('Scenarios_10'!G5,'Assumptions'!B9))+INDEX('Inputs_Data_Raw'!D:D,5+A14),INDEX('Inputs_Data_Raw'!D:D,5+A14)*(1-AVERAGE('Assumptions'!B5,'Assumptions'!B6,'Assumptions'!B7,'Assumptions'!B8))))) -> 1310400 | K14: =G14+H14+I14-J14 -> 914785 | L14: =L13+K14 -> 3778880
A15: 9 | B15: =IF(A15=0,-'Inputs_Data_Raw'!H5,0) -> 0 | C15: =IF(A15=0,0,INDEX('Inputs_Data_Raw'!B:B, 5+A15)) -> 2342300 | D15: =IF(A15=0,0,INDEX('Inputs_Data_Raw'!E:E, 5+A15)) -> 1638000 | E15: =B15+C15-D15 -> 704300 | F15: =F14+E15 -> 2799300 | G15: =IF(A15=0,-'Inputs_Data_Raw'!H5,0) -> 0 | H15: =IF(AND(A15>=1,A15<='Scenarios_10'!B5),MAX(0,(MAX(0,'Scenarios_10'!D5-'Scenarios_10'!E5/'Scenarios_10'!B5))-IF(AND(A15>'Scenarios_10'!B5-4,A15<='Scenarios_10'!B5),'Scenarios_10'!F5,0)),0) -> 2225185 | I15: =IF(A15=0,'Scenarios_10'!E5,0) -> 0 | J15: =IF(A15=0,0,IF('Scenarios_10'!C5="uniform_pct",INDEX('Inputs_Data_Raw'!E:E,5+A15)*(1-MIN('Scenarios_10'!G5,'Assumptions'!B9)),IF('Scenarios_10'!C5="electricity_only_pct",INDEX('Inputs_Data_Raw'!C:C,5+A15)*(1-MIN('Scenarios_10'!G5,'Assumptions'!B9))+INDEX('Inputs_Data_Raw'!D:D,5+A15),INDEX('Inputs_Data_Raw'!D:D,5+A15)*(1-AVERAGE('Assumptions'!B5,'Assumptions'!B6,'Assumptions'!B7,'Assumptions'!B8))))) -> 1310400 | K15: =G15+H15+I15-J15 -> 914785 | L15: =L14+K15 -> 4693665
A16: 10 | B16: =IF(A16=0,-'Inputs_Data_Raw'!H5,0) -> 0 | C16: =IF(A16=0,0,INDEX('Inputs_Data_Raw'!B:B, 5+A16)) -> 2342300 | D16: =IF(A16=0,0,INDEX('Inputs_Data_Raw'!E:E, 5+A16)) -> 1638000 | E16: =B16+C16-D16 -> 704300 | F16: =F15+E16 -> 3503600 | G16: =IF(A16=0,-'Inputs_Data_Raw'!H5,0) -> 0 | H16: =IF(AND(A16>=1,A16<='Scenarios_10'!B5),MAX(0,(MAX(0,'Scenarios_10'!D5-'Scenarios_10'!E5/'Scenarios_10'!B5))-IF(AND(A16>'Scenarios_10'!B5-4,A16<='Scenarios_10'!B5),'Scenarios_10'!F5,0)),0) -> 2225185 | I16: =IF(A16=0,'Scenarios_10'!E5,0) -> 0 | J16: =IF(A16=0,0,IF('Scenarios_10'!C5="uniform_pct",INDEX('Inputs_Data_Raw'!E:E,5+A16)*(1-MIN('Scenarios_10'!G5,'Assumptions'!B9)),IF('Scenarios_10'!C5="electricity_only_pct",INDEX('Inputs_Data_Raw'!C:C,5+A16)*(1-MIN('Scenarios_10'!G5,'Assumptions'!B9))+INDEX('Inputs_Data_Raw'!D:D,5+A16),INDEX('Inputs_Data_Raw'!D:D,5+A16)*(1-AVERAGE('Assumptions'!B5,'Assumptions'!B6,'Assumptions'!B7,'Assumptions'!B8))))) -> 1310400 | K16: =G16+H16+I16-J16 -> 914785 | L16: =L15+K16 -> 5608450
A19: Tier: Tier2_UniformAI_35
A20: year | B20: trust_capex | C20: trust_fee | D20: trust_cash_opex | E20: trust_net_cf | F20: trust_cum_cf | G20: laas_capex | H20: laas_fee | I20: laas_upfront | J20: laas_cash_opex | K20: laas_net_cf | L20: laas_cum_cf
A21: 0 | B21: =IF(A21=0,-'Inputs_Data_Raw'!H5,0) -> -3539400 | C21: =IF(A21=0,0,INDEX('Inputs_Data_Raw'!B:B, 5+A21)) -> 0 | D21: =IF(A21=0,0,INDEX('Inputs_Data_Raw'!E:E, 5+A21)) -> 0 | E21: =B21+C21-D21 -> -3539400 | F21: =E21 -> -3539400 | G21: =IF(A21=0,-'Inputs_Data_Raw'!H5,0) -> -3539400 | H21: =IF(AND(A21>=1,A21<='Scenarios_10'!B6),MAX(0,(MAX(0,'Scenarios_10'!D6-'Scenarios_10'!E6/'Scenarios_10'!B6))-IF(AND(A21>'Scenarios_10'!B6-4,A21<='Scenarios_10'!B6),'Scenarios_10'!F6,0)),0) -> 0 | I21: =IF(A21=0,'Scenarios_10'!E6,0) -> 0 | J21: =IF(A21=0,0,IF('Scenarios_10'!C6="uniform_pct",INDEX('Inputs_Data_Raw'!E:E,5+A21)*(1-MIN('Scenarios_10'!G6,'Assumptions'!B9)),IF('Scenarios_10'!C6="electricity_only_pct",INDEX('Inputs_Data_Raw'!C:C,5+A21)*(1-MIN('Scenarios_10'!G6,'Assumptions'!B9))+INDEX('Inputs_Data_Raw'!D:D,5+A21),INDEX('Inputs_Data_Raw'!D:D,5+A21)*(1-AVERAGE('Assumptions'!B5,'Assumptions'!B6,'Assumptions'!B7,'Assumptions'!B8))))) -> 0 | K21: =G21+H21+I21-J21 -> -3539400 | L21: =K21 -> -3539400
A22: 1 | B22: =IF(A22=0,-'Inputs_Data_Raw'!H5,0) -> 0 | C22: =IF(A22=0,0,INDEX('Inputs_Data_Raw'!B:B, 5+A22)) -> 2342300 | D22: =IF(A22=0,0,INDEX('Inputs_Data_Raw'!E:E, 5+A22)) -> 1638000 | E22: =B22+C22-D22 -> 704300 | F22: =F21+E22 -> -2835100 | G22: =IF(A22=0,-'Inputs_Data_Raw'!H5,0) -> 0 | H22: =IF(AND(A22>=1,A22<='Scenarios_10'!B6),MAX(0,(MAX(0,'Scenarios_10'!D6-'Scenarios_10'!E6/'Scenarios_10'!B6))-IF(AND(A22>'Scenarios_10'!B6-4,A22<='Scenarios_10'!B6),'Scenarios_10'!F6,0)),0) -> 2272031 | I22: =IF(A22=0,'Scenarios_10'!E6,0) -> 0 | J22: =IF(A22=0,0,IF('Scenarios_10'!C6="uniform_pct",INDEX('Inputs_Data_Raw'!E:E,5+A22)*(1-MIN('Scenarios_10'!G6,'Assumptions'!B9)),IF('Scenarios_10'!C6="electricity_only_pct",INDEX('Inputs_Data_Raw'!C:C,5+A22)*(1-MIN('Scenarios_10'!G6,'Assumptions'!B9))+INDEX('Inputs_Data_Raw'!D:D,5+A22),INDEX('Inputs_Data_Raw'!D:D,5+A22)*(1-AVERAGE('Assumptions'!B5,'Assumptions'!B6,'Assumptions'!B7,'Assumptions'!B8))))) -> 1064700 | K22: =G22+H22+I22-J22 -> 1207331 | L22: =L21+K22 -> -2332069
A23: 2 | B23: =IF(A23=0,-'Inputs_Data_Raw'!H5,0) -> 0 | C23: =IF(A23=0,0,INDEX('Inputs_Data_Raw'!B:B, 5+A23)) -> 2342300 | D23: =IF(A23=0,0,INDEX('Inputs_Data_Raw'!E:E, 5+A23)) -> 1638000 | E23: =B23+C23-D23 -> 704300 | F23: =F22+E23 -> -2130800 | G23: =IF(A23=0,-'Inputs_Data_Raw'!H5,0) -> 0 | H23: =IF(AND(A23>=1,A23<='Scenarios_10'!B6),MAX(0,(MAX(0,'Scenarios_10'!D6-'Scenarios_10'!E6/'Scenarios_10'!B6))-IF(AND(A23>'Scenarios_10'!B6-4,A23<='Scenarios_10'!B6),'Scenarios_10'!F6,0)),0) -> 2272031 | I23: =IF(A23=0,'Scenarios_10'!E6,0) -> 0 | J23: =IF(A23=0,0,IF('Scenarios_10'!C6="uniform_pct",INDEX('Inputs_Data_Raw'!E:E,5+A23)*(1-MIN('Scenarios_10'!G6,'Assumptions'!B9)),IF('Scenarios_10'!C6="electricity_only_pct",INDEX('Inputs_Data_Raw'!C:C,5+A23)*(1-MIN('Scenarios_10'!G6,'Assumptions'!B9))+INDEX('Inputs_Data_Raw'!D:D,5+A23),INDEX('Inputs_Data_Raw'!D:D,5+A23)*(1-AVERAGE('Assumptions'!B5,'Assumptions'!B6,'Assumptions'!B7,'Assumptions'!B8))))) -> 1064700 | K23: =G23+H23+I23-J23 -> 1207331 | L23: =L22+K23 -> -1124738
A24: 3 | B24: =IF(A24=0,-'Inputs_Data_Raw'!H5,0) -> 0 | C24: =IF(A24=0,0,INDEX('Inputs_Data_Raw'!B:B, 5+A24)) -> 2342300 | D24: =IF(A24=0,0,INDEX('Inputs_Data_Raw'!E:E, 5+A24)) -> 1638000 | E24: =B24+C24-D24 -> 704300 | F24: =F23+E24 -> -1426500 | G24: =IF(A24=0,-'Inputs_Data_Raw'!H5,0) -> 0 | H24: =IF(AND(A24>=1,A24<='Scenarios_10'!B6),MAX(0,(MAX(0,'Scenarios_10'!D6-'Scenarios_10'!E6/'Scenarios_10'!B6))-IF(AND(A24>'Scenarios_10'!B6-4,A24<='Scenarios_10'!B6),'Scenarios_10'!F6,0)),0) -> 2272031 | I24: =IF(A24=0,'Scenarios_10'!E6,0) -> 0 | J24: =IF(A24=0,0,IF('Scenarios_10'!C6="uniform_pct",INDEX('Inputs_Data_Raw'!E:E,5+A24)*(1-MIN('Scenarios_10'!G6,'Assumptions'!B9)),IF('Scenarios_10'!C6="electricity_only_pct",INDEX('Inputs_Data_Raw'!C:C,5+A24)*(1-MIN('Scenarios_10'!G6,'Assumptions'!B9))+INDEX('Inputs_Data_Raw'!D:D,5+A24),INDEX('Inputs_Data_Raw'!D:D,5+A24)*(1-AVERAGE('Assumptions'!B5,'Assumptions'!B6,'Assumptions'!B7,'Assumptions'!B8))))) -> 1064700 | K24: =G24+H24+I24-J24 -> 1207331 | L24: =L23+K24 -> 82593
A25: 4 | B25: =IF(A25=0,-'Inputs_Data_Raw'!H5,0) -> 0 | C25: =IF(A25=0,0,INDEX('Inputs_Data_Raw'!B:B, 5+A25)) -> 2342300 | D25: =IF(A25=0,0,INDEX('Inputs_Data_Raw'!E:E, 5+A25)) -> 1638000 | E25: =B25+C25-D25 -> 704300 | F25: =F24+E25 -> -722200 | G25: =IF(A25=0,-'Inputs_Data_Raw'!H5,0) -> 0 | H25: =IF(AND(A25>=1,A25<='Scenarios_10'!B6),MAX(0,(MAX(0,'Scenarios_10'!D6-'Scenarios_10'!E6/'Scenarios_10'!B6))-IF(AND(A25>'Scenarios_10'!B6-4,A25<='Scenarios_10'!B6),'Scenarios_10'!F6,0)),0) -> 2272031 | I25: =IF(A25=0,'Scenarios_10'!E6,0) -> 0 | J25: =IF(A25=0,0,IF('Scenarios_10'!C6="uniform_pct",INDEX('Inputs_Data_Raw'!E:E,5+A25)*(1-MIN('Scenarios_10'!G6,'Assumptions'!B9)),IF('Scenarios_10'!C6="electricity_only_pct",INDEX('Inputs_Data_Raw'!C:C,5+A25)*(1-MIN('Scenarios_10'!G6,'Assumptions'!B9))+INDEX('Inputs_Data_Raw'!D:D,5+A25),INDEX('Inputs_Data_Raw'!D:D,5+A25)*(1-AVERAGE('Assumptions'!B5,'Assumptions'!B6,'Assumptions'!B7,'Assumptions'!B8))))) -> 1064700 | K25: =G25+H25+I25-J25 -> 1207331 | L25: =L24+K25 -> 1289924
A26: 5 | B26: =IF(A26=0,-'Inputs_Data_Raw'!H5,0) -> 0 | C26: =IF(A26=0,0,INDEX('Inputs_Data_Raw'!B:B, 5+A26)) -> 2342300 | D26: =IF(A26=0,0,INDEX('Inputs_Data_Raw'!E:E, 5+A26)) -> 1638000 | E26: =B26+C26-D26 -> 704300 | F26: =F25+E26 -> -17900 | G26: =IF(A26=0,-'Inputs_Data_Raw'!H5,0) -> 0 | H26: =IF(AND(A26>=1,A26<='Scenarios_10'!B6),MAX(0,(MAX(0,'Scenarios_10'!D6-'Scenarios_10'!E6/'Scenarios_10'!B6))-IF(AND(A26>'Scenarios_10'!B6-4,A26<='Scenarios_10'!B6),'Scenarios_10'!F6,0)),0) -> 2272031 | I26: =IF(A26=0,'Scenarios_10'!E6,0) -> 0 | J26: =IF(A26=0,0,IF('Scenarios_10'!C6="uniform_pct",INDEX('Inputs_Data_Raw'!E:E,5+A26)*(1-MIN('Scenarios_10'!G6,'Assumptions'!B9)),IF('Scenarios_10'!C6="electricity_only_pct",INDEX('Inputs_Data_Raw'!C:C,5+A26)*(1-MIN('Scenarios_10'!G6,'Assumptions'!B9))+INDEX('Inputs_Data_Raw'!D:D,5+A26),INDEX('Inputs_Data_Raw'!D:D,5+A26)*(1-AVERAGE('Assumptions'!B5,'Assumptions'!B6,'Assumptions'!B7,'Assumptions'!B8))))) -> 1064700 | K26: =G26+H26+I26-J26 -> 1207331 | L26: =L25+K26 -> 2497255
A27: 6 | B27: =IF(A27=0,-'Inputs_Data_Raw'!H5,0) -> 0 | C27: =IF(A27=0,0,INDEX('Inputs_Data_Raw'!B:B, 5+A27)) -> 2342300 | D27: =IF(A27=0,0,INDEX('Inputs_Data_Raw'!E:E, 5+A27)) -> 1638000 | E27: =B27+C27-D27 -> 704300 | F27: =F26+E27 -> 686400 | G27: =IF(A27=0,-'Inputs_Data_Raw'!H5,0) -> 0 | H27: =IF(AND(A27>=1,A27<='Scenarios_10'!B6),MAX(0,(MAX(0,'Scenarios_10'!D6-'Scenarios_10'!E6/'Scenarios_10'!B6))-IF(AND(A27>'Scenarios_10'!B6-4,A27<='Scenarios_10'!B6),'Scenarios_10'!F6,0)),0) -> 2272031 | I27: =IF(A27=0,'Scenarios_10'!E6,0) -> 0 | J27: =IF(A27=0,0,IF('Scenarios_10'!C6="uniform_pct",INDEX('Inputs_Data_Raw'!E:E,5+A27)*(1-MIN('Scenarios_10'!G6,'Assumptions'!B9)),IF('Scenarios_10'!C6="electricity_only_pct",INDEX('Inputs_Data_Raw'!C:C,5+A27)*(1-MIN('Scenarios_10'!G6,'Assumptions'!B9))+INDEX('Inputs_Data_Raw'!D:D,5+A27),INDEX('Inputs_Data_Raw'!D:D,5+A27)*(1-AVERAGE('Assumptions'!B5,'Assumptions'!B6,'Assumptions'!B7,'Assumptions'!B8))))) -> 1064700 | K27: =G27+H27+I27-J27 -> 1207331 | L27: =L26+K27 -> 3704586
A28: 7 | B28: =IF(A28=0,-'Inputs_Data_Raw'!H5,0) -> 0 | C28: =IF(A28=0,0,INDEX('Inputs_Data_Raw'!B:B, 5+A28)) -> 2342300 | D28: =IF(A28=0,0,INDEX('Inputs_Data_Raw'!E:E, 5+A28)) -> 1638000 | E28: =B28+C28-D28 -> 704300 | F28: =F27+E28 -> 1390700 | G28: =IF(A28=0,-'Inputs_Data_Raw'!H5,0) -> 0 | H28: =IF(AND(A28>=1,A28<='Scenarios_10'!B6),MAX(0,(MAX(0,'Scenarios_10'!D6-'Scenarios_10'!E6/'Scenarios_10'!B6))-IF(AND(A28>'Scenarios_10'!B6-4,A28<='Scenarios_10'!B6),'Scenarios_10'!F6,0)),0) -> 2272031 | I28: =IF(A28=0,'Scenarios_10'!E6,0) -> 0 | J28: =IF(A28=0,0,IF('Scenarios_10'!C6="uniform_pct",INDEX('Inputs_Data_Raw'!E:E,5+A28)*(1-MIN('Scenarios_10'!G6,'Assumptions'!B9)),IF('Scenarios_10'!C6="electricity_only_pct",INDEX('Inputs_Data_Raw'!C:C,5+A28)*(1-MIN('Scenarios_10'!G6,'Assumptions'!B9))+INDEX('Inputs_Data_Raw'!D:D,5+A28),INDEX('Inputs_Data_Raw'!D:D,5+A28)*(1-AVERAGE('Assumptions'!B5,'Assumptions'!B6,'Assumptions'!B7,'Assumptions'!B8))))) -> 1064700 | K28: =G28+H28+I28-J28 -> 1207331 | L28: =L27+K28 -> 4911917
A29: 8 | B29: =IF(A29=0,-'Inputs_Data_Raw'!H5,0) -> 0 | C29: =IF(A29=0,0,INDEX('Inputs_Data_Raw'!B:B, 5+A29)) -> 2342300 | D29: =IF(A29=0,0,INDEX('Inputs_Data_Raw'!E:E, 5+A29)) -> 1638000 | E29: =B29+C29-D29 -> 704300 | F29: =F28+E29 -> 2095000 | G29: =IF(A29=0,-'Inputs_Data_Raw'!H5,0) -> 0 | H29: =IF(AND(A29>=1,A29<='Scenarios_10'!B6),MAX(0,(MAX(0,'Scenarios_10'!D6-'Scenarios_10'!E6/'Scenarios_10'!B6))-IF(AND(A29>'Scenarios_10'!B6-4,A29<='Scenarios_10'!B6),'Scenarios_10'!F6,0)),0) -> 2272031 | I29: =IF(A29=0,'Scenarios_10'!E6,0) -> 0 | J29: =IF(A29=0,0,IF('Scenarios_10'!C6="uniform_pct",INDEX('Inputs_Data_Raw'!E:E,5+A29)*(1-MIN('Scenarios_10'!G6,'Assumptions'!B9)),IF('Scenarios_10'!C6="electricity_only_pct",INDEX('Inputs_Data_Raw'!C:C,5+A29)*(1-MIN('Scenarios_10'!G6,'Assumptions'!B9))+INDEX('Inputs_Data_Raw'!D:D,5+A29),INDEX('Inputs_Data_Raw'!D:D,5+A29)*(1-AVERAGE('Assumptions'!B5,'Assumptions'!B6,'Assumptions'!B7,'Assumptions'!B8))))) -> 1064700 | K29: =G29+H29+I29-J29 -> 1207331 | L29: =L28+K29 -> 6119248
A30: 9 | B30: =IF(A30=0,-'Inputs_Data_Raw'!H5,0) -> 0 | C30: =IF(A30=0,0,INDEX('Inputs_Data_Raw'!B:B, 5+A30)) -> 2342300 | D30: =IF(A30=0,0,INDEX('Inputs_Data_Raw'!E:E, 5+A30)) -> 1638000 | E30: =B30+C30-D30 -> 704300 | F30: =F29+E30 -> 2799300 | G30: =IF(A30=0,-'Inputs_Data_Raw'!H5,0) -> 0 | H30: =IF(AND(A30>=1,A30<='Scenarios_10'!B6),MAX(0,(MAX(0,'Scenarios_10'!D6-'Scenarios_10'!E6/'Scenarios_10'!B6))-IF(AND(A30>'Scenarios_10'!B6-4,A30<='Scenarios_10'!B6),'Scenarios_10'!F6,0)),0) -> 2272031 | I30: =IF(A30=0,'Scenarios_10'!E6,0) -> 0 | J30: =IF(A30=0,0,IF('Scenarios_10'!C6="uniform_pct",INDEX('Inputs_Data_Raw'!E:E,5+A30)*(1-MIN('Scenarios_10'!G6,'Assumptions'!B9)),IF('Scenarios_10'!C6="electricity_only_pct",INDEX('Inputs_Data_Raw'!C:C,5+A30)*(1-MIN('Scenarios_10'!G6,'Assumptions'!B9))+INDEX('Inputs_Data_Raw'!D:D,5+A30),INDEX('Inputs_Data_Raw'!D:D,5+A30)*(1-AVERAGE('Assumptions'!B5,'Assumptions'!B6,'Assumptions'!B7,'Assumptions'!B8))))) -> 1064700 | K30: =G30+H30+I30-J30 -> 1207331 | L30: =L29+K30 -> 7326579
A31: 10 | B31: =IF(A31=0,-'Inputs_Data_Raw'!H5,0) -> 0 | C31: =IF(A31=0,0,INDEX('Inputs_Data_Raw'!B:B, 5+A31)) -> 2342300 | D31: =IF(A31=0,0,INDEX('Inputs_Data_Raw'!E:E, 5+A31)) -> 1638000 | E31: =B31+C31-D31 -> 704300 | F31: =F30+E31 -> 3503600 | G31: =IF(A31=0,-'Inputs_Data_Raw'!H5,0) -> 0 | H31: =IF(AND(A31>=1,A31<='Scenarios_10'!B6),MAX(0,(MAX(0,'Scenarios_10'!D6-'Scenarios_10'!E6/'Scenarios_10'!B6))-IF(AND(A31>'Scenarios_10'!B6-4,A31<='Scenarios_10'!B6),'Scenarios_10'!F6,0)),0) -> 2272031 | I31: =IF(A31=0,'Scenarios_10'!E6,0) -> 0 | J31: =IF(A31=0,0,IF('Scenarios_10'!C6="uniform_pct",INDEX('Inputs_Data_Raw'!E:E,5+A31)*(1-MIN('Scenarios_10'!G6,'Assumptions'!B9)),IF('Scenarios_10'!C6="electricity_only_pct",INDEX('Inputs_Data_Raw'!C:C,5+A31)*(1-MIN('Scenarios_10'!G6,'Assumptions'!B9))+INDEX('Inputs_Data_Raw'!D:D,5+A31),INDEX('Inputs_Data_Raw'!D:D,5+A31)*(1-AVERAGE('Assumptions'!B5,'Assumptions'!B6,'Assumptions'!B7,'Assumptions'!B8))))) -> 1064700 | K31: =G31+H31+I31-J31 -> 1207331 | L31: =L30+K31 -> 8533910
A34: Tier: Tier3_ElecOnly_40
A35: year | B35: trust_capex | C35: trust_fee | D35: trust_cash_opex | E35: trust_net_cf | F35: trust_cum_cf | G35: laas_capex | H35: laas_fee | I35: laas_upfront | J35: laas_cash_opex | K35: laas_net_cf | L35: laas_cum_cf
A36: 0 | B36: =IF(A36=0,-'Inputs_Data_Raw'!H5,0) -> -3539400 | C36: =IF(A36=0,0,INDEX('Inputs_Data_Raw'!B:B, 5+A36)) -> 0 | D36: =IF(A36=0,0,INDEX('Inputs_Data_Raw'!E:E, 5+A36)) -> 0 | E36: =B36+C36-D36 -> -3539400 | F36: =E36 -> -3539400 | G36: =IF(A36=0,-'Inputs_Data_Raw'!H5,0) -> -3539400 | H36: =IF(AND(A36>=1,A36<='Scenarios_10'!B7),MAX(0,(MAX(0,'Scenarios_10'!D7-'Scenarios_10'!E7/'Scenarios_10'!B7))-IF(AND(A36>'Scenarios_10'!B7-4,A36<='Scenarios_10'!B7),'Scenarios_10'!F7,0)),0) -> 0 | I36: =IF(A36=0,'Scenarios_10'!E7,0) -> 0 | J36: =IF(A36=0,0,IF('Scenarios_10'!C7="uniform_pct",INDEX('Inputs_Data_Raw'!E:E,5+A36)*(1-MIN('Scenarios_10'!G7,'Assumptions'!B9)),IF('Scenarios_10'!C7="electricity_only_pct",INDEX('Inputs_Data_Raw'!C:C,5+A36)*(1-MIN('Scenarios_10'!G7,'Assumptions'!B9))+INDEX('Inputs_Data_Raw'!D:D,5+A36),INDEX('Inputs_Data_Raw'!D:D,5+A36)*(1-AVERAGE('Assumptions'!B5,'Assumptions'!B6,'Assumptions'!B7,'Assumptions'!B8))))) -> 0 | K36: =G36+H36+I36-J36 -> -3539400 | L36: =K36 -> -3539400
A37: 1 | B37: =IF(A37=0,-'Inputs_Data_Raw'!H5,0) -> 0 | C37: =IF(A37=0,0,INDEX('Inputs_Data_Raw'!B:B, 5+A37)) -> 2342300 | D37: =IF(A37=0,0,INDEX('Inputs_Data_Raw'!E:E, 5+A37)) -> 1638000 | E37: =B37+C37-D37 -> 704300 | F37: =F36+E37 -> -2835100 | G37: =IF(A37=0,-'Inputs_Data_Raw'!H5,0) -> 0 | H37: =IF(AND(A37>=1,A37<='Scenarios_10'!B7),MAX(0,(MAX(0,'Scenarios_10'!D7-'Scenarios_10'!E7/'Scenarios_10'!B7))-IF(AND(A37>'Scenarios_10'!B7-4,A37<='Scenarios_10'!B7),'Scenarios_10'!F7,0)),0) -> 2248608 | I37: =IF(A37=0,'Scenarios_10'!E7,0) -> 0 | J37: =IF(A37=0,0,IF('Scenarios_10'!C7="uniform_pct",INDEX('Inputs_Data_Raw'!E:E,5+A37)*(1-MIN('Scenarios_10'!G7,'Assumptions'!B9)),IF('Scenarios_10'!C7="electricity_only_pct",INDEX('Inputs_Data_Raw'!C:C,5+A37)*(1-MIN('Scenarios_10'!G7,'Assumptions'!B9))+INDEX('Inputs_Data_Raw'!D:D,5+A37),INDEX('Inputs_Data_Raw'!D:D,5+A37)*(1-AVERAGE('Assumptions'!B5,'Assumptions'!B6,'Assumptions'!B7,'Assumptions'!B8))))) -> 1226800 | K37: =G37+H37+I37-J37 -> 1021808 | L37: =L36+K37 -> -2517592
A38: 2 | B38: =IF(A38=0,-'Inputs_Data_Raw'!H5,0) -> 0 | C38: =IF(A38=0,0,INDEX('Inputs_Data_Raw'!B:B, 5+A38)) -> 2342300 | D38: =IF(A38=0,0,INDEX('Inputs_Data_Raw'!E:E, 5+A38)) -> 1638000 | E38: =B38+C38-D38 -> 704300 | F38: =F37+E38 -> -2130800 | G38: =IF(A38=0,-'Inputs_Data_Raw'!H5,0) -> 0 | H38: =IF(AND(A38>=1,A38<='Scenarios_10'!B7),MAX(0,(MAX(0,'Scenarios_10'!D7-'Scenarios_10'!E7/'Scenarios_10'!B7))-IF(AND(A38>'Scenarios_10'!B7-4,A38<='Scenarios_10'!B7),'Scenarios_10'!F7,0)),0) -> 2248608 | I38: =IF(A38=0,'Scenarios_10'!E7,0) -> 0 | J38: =IF(A38=0,0,IF('Scenarios_10'!C7="uniform_pct",INDEX('Inputs_Data_Raw'!E:E,5+A38)*(1-MIN('Scenarios_10'!G7,'Assumptions'!B9)),IF('Scenarios_10'!C7="electricity_only_pct",INDEX('Inputs_Data_Raw'!C:C,5+A38)*(1-MIN('Scenarios_10'!G7,'Assumptions'!B9))+INDEX('Inputs_Data_Raw'!D:D,5+A38),INDEX('Inputs_Data_Raw'!D:D,5+A38)*(1-AVERAGE('Assumptions'!B5,'Assumptions'!B6,'Assumptions'!B7,'Assumptions'!B8))))) -> 1226800 | K38: =G38+H38+I38-J38 -> 1021808 | L38: =L37+K38 -> -1495784
A39: 3 | B39: =IF(A39=0,-'Inputs_Data_Raw'!H5,0) -> 0 | C39: =IF(A39=0,0,INDEX('Inputs_Data_Raw'!B:B, 5+A39)) -> 2342300 | D39: =IF(A39=0,0,INDEX('Inputs_Data_Raw'!E:E, 5+A39)) -> 1638000 | E39: =B39+C39-D39 -> 704300 | F39: =F38+E39 -> -1426500 | G39: =IF(A39=0,-'Inputs_Data_Raw'!H5,0) -> 0 | H39: =IF(AND(A39>=1,A39<='Scenarios_10'!B7),MAX(0,(MAX(0,'Scenarios_10'!D7-'Scenarios_10'!E7/'Scenarios_10'!B7))-IF(AND(A39>'Scenarios_10'!B7-4,A39<='Scenarios_10'!B7),'Scenarios_10'!F7,0)),0) -> 2248608 | I39: =IF(A39=0,'Scenarios_10'!E7,0) -> 0 | J39: =IF(A39=0,0,IF('Scenarios_10'!C7="uniform_pct",INDEX('Inputs_Data_Raw'!E:E,5+A39)*(1-MIN('Scenarios_10'!G7,'Assumptions'!B9)),IF('Scenarios_10'!C7="electricity_only_pct",INDEX('Inputs_Data_Raw'!C:C,5+A39)*(1-MIN('Scenarios_10'!G7,'Assumptions'!B9))+INDEX('Inputs_Data_Raw'!D:D,5+A39),INDEX('Inputs_Data_Raw'!D:D,5+A39)*(1-AVERAGE('Assumptions'!B5,'Assumptions'!B6,'Assumptions'!B7,'Assumptions'!B8))))) -> 1226800 | K39: =G39+H39+I39-J39 -> 1021808 | L39: =L38+K39 -> -473976
A40: 4 | B40: =IF(A40=0,-'Inputs_Data_Raw'!H5,0) -> 0 | C40: =IF(A40=0,0,INDEX('Inputs_Data_Raw'!B:B, 5+A40)) -> 2342300 | D40: =IF(A40=0,0,INDEX('Inputs_Data_Raw'!E:E, 5+A40)) -> 1638000 | E40: =B40+C40-D40 -> 704300 | F40: =F39+E40 -> -722200 | G40: =IF(A40=0,-'Inputs_Data_Raw'!H5,0) -> 0 | H40: =IF(AND(A40>=1,A40<='Scenarios_10'!B7),MAX(0,(MAX(0,'Scenarios_10'!D7-'Scenarios_10'!E7/'Scenarios_10'!B7))-IF(AND(A40>'Scenarios_10'!B7-4,A40<='Scenarios_10'!B7),'Scenarios_10'!F7,0)),0) -> 2248608 | I40: =IF(A40=0,'Scenarios_10'!E7,0) -> 0 | J40: =IF(A40=0,0,IF('Scenarios_10'!C7="uniform_pct",INDEX('Inputs_Data_Raw'!E:E,5+A40)*(1-MIN('Scenarios_10'!G7,'Assumptions'!B9)),IF('Scenarios_10'!C7="electricity_only_pct",INDEX('Inputs_Data_Raw'!C:C,5+A40)*(1-MIN('Scenarios_10'!G7,'Assumptions'!B9))+INDEX('Inputs_Data_Raw'!D:D,5+A40),INDEX('Inputs_Data_Raw'!D:D,5+A40)*(1-AVERAGE('Assumptions'!B5,'Assumptions'!B6,'Assumptions'!B7,'Assumptions'!B8))))) -> 1226800 | K40: =G40+H40+I40-J40 -> 1021808 | L40: =L39+K40 -> 547832
A41: 5 | B41: =IF(A41=0,-'Inputs_Data_Raw'!H5,0) -> 0 | C41: =IF(A41=0,0,INDEX('Inputs_Data_Raw'!B:B, 5+A41)) -> 2342300 | D41: =IF(A41=0,0,INDEX('Inputs_Data_Raw'!E:E, 5+A41)) -> 1638000 | E41: =B41+C41-D41 -> 704300 | F41: =F40+E41 -> -17900 | G41: =IF(A41=0,-'Inputs_Data_Raw'!H5,0) -> 0 | H41: =IF(AND(A41>=1,A41<='Scenarios_10'!B7),MAX(0,(MAX(0,'Scenarios_10'!D7-'Scenarios_10'!E7/'Scenarios_10'!B7))-IF(AND(A41>'Scenarios_10'!B7-4,A41<='Scenarios_10'!B7),'Scenarios_10'!F7,0)),0) -> 2248608 | I41: =IF(A41=0,'Scenarios_10'!E7,0) -> 0 | J41: =IF(A41=0,0,IF('Scenarios_10'!C7="uniform_pct",INDEX('Inputs_Data_Raw'!E:E,5+A41)*(1-MIN('Scenarios_10'!G7,'Assumptions'!B9)),IF('Scenarios_10'!C7="electricity_only_pct",INDEX('Inputs_Data_Raw'!C:C,5+A41)*(1-MIN('Scenarios_10'!G7,'Assumptions'!B9))+INDEX('Inputs_Data_Raw'!D:D,5+A41),INDEX('Inputs_Data_Raw'!D:D,5+A41)*(1-AVERAGE('Assumptions'!B5,'Assumptions'!B6,'Assumptions'!B7,'Assumptions'!B8))))) -> 1226800 | K41: =G41+H41+I41-J41 -> 1021808 | L41: =L40+K41 -> 1569640
A42: 6 | B42: =IF(A42=0,-'Inputs_Data_Raw'!H5,0) -> 0 | C42: =IF(A42=0,0,INDEX('Inputs_Data_Raw'!B:B, 5+A42)) -> 2342300 | D42: =IF(A42=0,0,INDEX('Inputs_Data_Raw'!E:E, 5+A42)) -> 1638000 | E42: =B42+C42-D42 -> 704300 | F42: =F41+E42 -> 686400 | G42: =IF(A42=0,-'Inputs_Data_Raw'!H5,0) -> 0 | H42: =IF(AND(A42>=1,A42<='Scenarios_10'!B7),MAX(0,(MAX(0,'Scenarios_10'!D7-'Scenarios_10'!E7/'Scenarios_10'!B7))-IF(AND(A42>'Scenarios_10'!B7-4,A42<='Scenarios_10'!B7),'Scenarios_10'!F7,0)),0) -> 2248608 | I42: =IF(A42=0,'Scenarios_10'!E7,0) -> 0 | J42: =IF(A42=0,0,IF('Scenarios_10'!C7="uniform_pct",INDEX('Inputs_Data_Raw'!E:E,5+A42)*(1-MIN('Scenarios_10'!G7,'Assumptions'!B9)),IF('Scenarios_10'!C7="electricity_only_pct",INDEX('Inputs_Data_Raw'!C:C,5+A42)*(1-MIN('Scenarios_10'!G7,'Assumptions'!B9))+INDEX('Inputs_Data_Raw'!D:D,5+A42),INDEX('Inputs_Data_Raw'!D:D,5+A42)*(1-AVERAGE('Assumptions'!B5,'Assumptions'!B6,'Assumptions'!B7,'Assumptions'!B8))))) -> 1226800 | K42: =G42+H42+I42-J42 -> 1021808 | L42: =L41+K42 -> 2591448
A43: 7 | B43: =IF(A43=0,-'Inputs_Data_Raw'!H5,0) -> 0 | C43: =IF(A43=0,0,INDEX('Inputs_Data_Raw'!B:B, 5+A43)) -> 2342300 | D43: =IF(A43=0,0,INDEX('Inputs_Data_Raw'!E:E, 5+A43)) -> 1638000 | E43: =B43+C43-D43 -> 704300 | F43: =F42+E43 -> 1390700 | G43: =IF(A43=0,-'Inputs_Data_Raw'!H5,0) -> 0 | H43: =IF(AND(A43>=1,A43<='Scenarios_10'!B7),MAX(0,(MAX(0,'Scenarios_10'!D7-'Scenarios_10'!E7/'Scenarios_10'!B7))-IF(AND(A43>'Scenarios_10'!B7-4,A43<='Scenarios_10'!B7),'Scenarios_10'!F7,0)),0) -> 2248608 | I43: =IF(A43=0,'Scenarios_10'!E7,0) -> 0 | J43: =IF(A43=0,0,IF('Scenarios_10'!C7="uniform_pct",INDEX('Inputs_Data_Raw'!E:E,5+A43)*(1-MIN('Scenarios_10'!G7,'Assumptions'!B9)),IF('Scenarios_10'!C7="electricity_only_pct",INDEX('Inputs_Data_Raw'!C:C,5+A43)*(1-MIN('Scenarios_10'!G7,'Assumptions'!B9))+INDEX('Inputs_Data_Raw'!D:D,5+A43),INDEX('Inputs_Data_Raw'!D:D,5+A43)*(1-AVERAGE('Assumptions'!B5,'Assumptions'!B6,'Assumptions'!B7,'Assumptions'!B8))))) -> 1226800 | K43: =G43+H43+I43-J43 -> 1021808 | L43: =L42+K43 -> 3613256
A44: 8 | B44: =IF(A44=0,-'Inputs_Data_Raw'!H5,0) -> 0 | C44: =IF(A44=0,0,INDEX('Inputs_Data_Raw'!B:B, 5+A44)) -> 2342300 | D44: =IF(A44=0,0,INDEX('Inputs_Data_Raw'!E:E, 5+A44)) -> 1638000 | E44: =B44+C44-D44 -> 704300 | F44: =F43+E44 -> 2095000 | G44: =IF(A44=0,-'Inputs_Data_Raw'!H5,0) -> 0 | H44: =IF(AND(A44>=1,A44<='Scenarios_10'!B7),MAX(0,(MAX(0,'Scenarios_10'!D7-'Scenarios_10'!E7/'Scenarios_10'!B7))-IF(AND(A44>'Scenarios_10'!B7-4,A44<='Scenarios_10'!B7),'Scenarios_10'!F7,0)),0) -> 2248608 | I44: =IF(A44=0,'Scenarios_10'!E7,0) -> 0 | J44: =IF(A44=0,0,IF('Scenarios_10'!C7="uniform_pct",INDEX('Inputs_Data_Raw'!E:E,5+A44)*(1-MIN('Scenarios_10'!G7,'Assumptions'!B9)),IF('Scenarios_10'!C7="electricity_only_pct",INDEX('Inputs_Data_Raw'!C:C,5+A44)*(1-MIN('Scenarios_10'!G7,'Assumptions'!B9))+INDEX('Inputs_Data_Raw'!D:D,5+A44),INDEX('Inputs_Data_Raw'!D:D,5+A44)*(1-AVERAGE('Assumptions'!B5,'Assumptions'!B6,'Assumptions'!B7,'Assumptions'!B8))))) -> 1226800 | K44: =G44+H44+I44-J44 -> 1021808 | L44: =L43+K44 -> 4635064
A45: 9 | B45: =IF(A45=0,-'Inputs_Data_Raw'!H5,0) -> 0 | C45: =IF(A45=0,0,INDEX('Inputs_Data_Raw'!B:B, 5+A45)) -> 2342300 | D45: =IF(A45=0,0,INDEX('Inputs_Data_Raw'!E:E, 5+A45)) -> 1638000 | E45: =B45+C45-D45 -> 704300 | F45: =F44+E45 -> 2799300 | G45: =IF(A45=0,-'Inputs_Data_Raw'!H5,0) -> 0 | H45: =IF(AND(A45>=1,A45<='Scenarios_10'!B7),MAX(0,(MAX(0,'Scenarios_10'!D7-'Scenarios_10'!E7/'Scenarios_10'!B7))-IF(AND(A45>'Scenarios_10'!B7-4,A45<='Scenarios_10'!B7),'Scenarios_10'!F7,0)),0) -> 2248608 | I45: =IF(A45=0,'Scenarios_10'!E7,0) -> 0 | J45: =IF(A45=0,0,IF('Scenarios_10'!C7="uniform_pct",INDEX('Inputs_Data_Raw'!E:E,5+A45)*(1-MIN('Scenarios_10'!G7,'Assumptions'!B9)),IF('Scenarios_10'!C7="electricity_only_pct",INDEX('Inputs_Data_Raw'!C:C,5+A45)*(1-MIN('Scenarios_10'!G7,'Assumptions'!B9))+INDEX('Inputs_Data_Raw'!D:D,5+A45),INDEX('Inputs_Data_Raw'!D:D,5+A45)*(1-AVERAGE('Assumptions'!B5,'Assumptions'!B6,'Assumptions'!B7,'Assumptions'!B8))))) -> 1226800 | K45: =G45+H45+I45-J45 -> 1021808 | L45: =L44+K45 -> 5656872
A46: 10 | B46: =IF(A46=0,-'Inputs_Data_Raw'!H5,0) -> 0 | C46: =IF(A46=0,0,INDEX('Inputs_Data_Raw'!B:B, 5+A46)) -> 2342300 | D46: =IF(A46=0,0,INDEX('Inputs_Data_Raw'!E:E, 5+A46)) -> 1638000 | E46: =B46+C46-D46 -> 704300 | F46: =F45+E46 -> 3503600 | G46: =IF(A46=0,-'Inputs_Data_Raw'!H5,0) -> 0 | H46: =IF(AND(A46>=1,A46<='Scenarios_10'!B7),MAX(0,(MAX(0,'Scenarios_10'!D7-'Scenarios_10'!E7/'Scenarios_10'!B7))-IF(AND(A46>'Scenarios_10'!B7-4,A46<='Scenarios_10'!B7),'Scenarios_10'!F7,0)),0) -> 2248608 | I46: =IF(A46=0,'Scenarios_10'!E7,0) -> 0 | J46: =IF(A46=0,0,IF('Scenarios_10'!C7="uniform_pct",INDEX('Inputs_Data_Raw'!E:E,5+A46)*(1-MIN('Scenarios_10'!G7,'Assumptions'!B9)),IF('Scenarios_10'!C7="electricity_only_pct",INDEX('Inputs_Data_Raw'!C:C,5+A46)*(1-MIN('Scenarios_10'!G7,'Assumptions'!B9))+INDEX('Inputs_Data_Raw'!D:D,5+A46),INDEX('Inputs_Data_Raw'!D:D,5+A46)*(1-AVERAGE('Assumptions'!B5,'Assumptions'!B6,'Assumptions'!B7,'Assumptions'!B8))))) -> 1226800 | K46: =G46+H46+I46-J46 -> 1021808 | L46: =L45+K46 -> 6678680
A49: Tier: Tier4_ElecOnly_60
A50: year | B50: trust_capex | C50: trust_fee | D50: trust_cash_opex | E50: trust_net_cf | F50: trust_cum_cf | G50: laas_capex | H50: laas_fee | I50: laas_upfront | J50: laas_cash_opex | K50: laas_net_cf | L50: laas_cum_cf
A51: 0 | B51: =IF(A51=0,-'Inputs_Data_Raw'!H5,0) -> -3539400 | C51: =IF(A51=0,0,INDEX('Inputs_Data_Raw'!B:B, 5+A51)) -> 0 | D51: =IF(A51=0,0,INDEX('Inputs_Data_Raw'!E:E, 5+A51)) -> 0 | E51: =B51+C51-D51 -> -3539400 | F51: =E51 -> -3539400 | G51: =IF(A51=0,-'Inputs_Data_Raw'!H5,0) -> -3539400 | H51: =IF(AND(A51>=1,A51<='Scenarios_10'!B8),MAX(0,(MAX(0,'Scenarios_10'!D8-'Scenarios_10'!E8/'Scenarios_10'!B8))-IF(AND(A51>'Scenarios_10'!B8-4,A51<='Scenarios_10'!B8),'Scenarios_10'!F8,0)),0) -> 0 | I51: =IF(A51=0,'Scenarios_10'!E8,0) -> 0 | J51: =IF(A51=0,0,IF('Scenarios_10'!C8="uniform_pct",INDEX('Inputs_Data_Raw'!E:E,5+A51)*(1-MIN('Scenarios_10'!G8,'Assumptions'!B9)),IF('Scenarios_10'!C8="electricity_only_pct",INDEX('Inputs_Data_Raw'!C:C,5+A51)*(1-MIN('Scenarios_10'!G8,'Assumptions'!B9))+INDEX('Inputs_Data_Raw'!D:D,5+A51),INDEX('Inputs_Data_Raw'!D:D,5+A51)*(1-AVERAGE('Assumptions'!B5,'Assumptions'!B6,'Assumptions'!B7,'Assumptions'!B8))))) -> 0 | K51: =G51+H51+I51-J51 -> -3539400 | L51: =K51 -> -3539400
A52: 1 | B52: =IF(A52=0,-'Inputs_Data_Raw'!H5,0) -> 0 | C52: =IF(A52=0,0,INDEX('Inputs_Data_Raw'!B:B, 5+A52)) -> 2342300 | D52: =IF(A52=0,0,INDEX('Inputs_Data_Raw'!E:E, 5+A52)) -> 1638000 | E52: =B52+C52-D52 -> 704300 | F52: =F51+E52 -> -2835100 | G52: =IF(A52=0,-'Inputs_Data_Raw'!H5,0) -> 0 | H52: =IF(AND(A52>=1,A52<='Scenarios_10'!B8),MAX(0,(MAX(0,'Scenarios_10'!D8-'Scenarios_10'!E8/'Scenarios_10'!B8))-IF(AND(A52>'Scenarios_10'!B8-4,A52<='Scenarios_10'!B8),'Scenarios_10'!F8,0)),0) -> 2295454 | I52: =IF(A52=0,'Scenarios_10'!E8,0) -> 0 | J52: =IF(A52=0,0,IF('Scenarios_10'!C8="uniform_pct",INDEX('Inputs_Data_Raw'!E:E,5+A52)*(1-MIN('Scenarios_10'!G8,'Assumptions'!B9)),IF('Scenarios_10'!C8="electricity_only_pct",INDEX('Inputs_Data_Raw'!C:C,5+A52)*(1-MIN('Scenarios_10'!G8,'Assumptions'!B9))+INDEX('Inputs_Data_Raw'!D:D,5+A52),INDEX('Inputs_Data_Raw'!D:D,5+A52)*(1-AVERAGE('Assumptions'!B5,'Assumptions'!B6,'Assumptions'!B7,'Assumptions'!B8))))) -> 1021200 | K52: =G52+H52+I52-J52 -> 1274254 | L52: =L51+K52 -> -2265146
A53: 2 | B53: =IF(A53=0,-'Inputs_Data_Raw'!H5,0) -> 0 | C53: =IF(A53=0,0,INDEX('Inputs_Data_Raw'!B:B, 5+A53)) -> 2342300 | D53: =IF(A53=0,0,INDEX('Inputs_Data_Raw'!E:E, 5+A53)) -> 1638000 | E53: =B53+C53-D53 -> 704300 | F53: =F52+E53 -> -2130800 | G53: =IF(A53=0,-'Inputs_Data_Raw'!H5,0) -> 0 | H53: =IF(AND(A53>=1,A53<='Scenarios_10'!B8),MAX(0,(MAX(0,'Scenarios_10'!D8-'Scenarios_10'!E8/'Scenarios_10'!B8))-IF(AND(A53>'Scenarios_10'!B8-4,A53<='Scenarios_10'!B8),'Scenarios_10'!F8,0)),0) -> 2295454 | I53: =IF(A53=0,'Scenarios_10'!E8,0) -> 0 | J53: =IF(A53=0,0,IF('Scenarios_10'!C8="uniform_pct",INDEX('Inputs_Data_Raw'!E:E,5+A53)*(1-MIN('Scenarios_10'!G8,'Assumptions'!B9)),IF('Scenarios_10'!C8="electricity_only_pct",INDEX('Inputs_Data_Raw'!C:C,5+A53)*(1-MIN('Scenarios_10'!G8,'Assumptions'!B9))+INDEX('Inputs_Data_Raw'!D:D,5+A53),INDEX('Inputs_Data_Raw'!D:D,5+A53)*(1-AVERAGE('Assumptions'!B5,'Assumptions'!B6,'Assumptions'!B7,'Assumptions'!B8))))) -> 1021200 | K53: =G53+H53+I53-J53 -> 1274254 | L53: =L52+K53 -> -990892
A54: 3 | B54: =IF(A54=0,-'Inputs_Data_Raw'!H5,0) -> 0 | C54: =IF(A54=0,0,INDEX('Inputs_Data_Raw'!B:B, 5+A54)) -> 2342300 | D54: =IF(A54=0,0,INDEX('Inputs_Data_Raw'!E:E, 5+A54)) -> 1638000 | E54: =B54+C54-D54 -> 704300 | F54: =F53+E54 -> -1426500 | G54: =IF(A54=0,-'Inputs_Data_Raw'!H5,0) -> 0 | H54: =IF(AND(A54>=1,A54<='Scenarios_10'!B8),MAX(0,(MAX(0,'Scenarios_10'!D8-'Scenarios_10'!E8/'Scenarios_10'!B8))-IF(AND(A54>'Scenarios_10'!B8-4,A54<='Scenarios_10'!B8),'Scenarios_10'!F8,0)),0) -> 2295454 | I54: =IF(A54=0,'Scenarios_10'!E8,0) -> 0 | J54: =IF(A54=0,0,IF('Scenarios_10'!C8="uniform_pct",INDEX('Inputs_Data_Raw'!E:E,5+A54)*(1-MIN('Scenarios_10'!G8,'Assumptions'!B9)),IF('Scenarios_10'!C8="electricity_only_pct",INDEX('Inputs_Data_Raw'!C:C,5+A54)*(1-MIN('Scenarios_10'!G8,'Assumptions'!B9))+INDEX('Inputs_Data_Raw'!D:D,5+A54),INDEX('Inputs_Data_Raw'!D:D,5+A54)*(1-AVERAGE('Assumptions'!B5,'Assumptions'!B6,'Assumptions'!B7,'Assumptions'!B8))))) -> 1021200 | K54: =G54+H54+I54-J54 -> 1274254 | L54: =L53+K54 -> 283362
A55: 4 | B55: =IF(A55=0,-'Inputs_Data_Raw'!H5,0) -> 0 | C55: =IF(A55=0,0,INDEX('Inputs_Data_Raw'!B:B, 5+A55)) -> 2342300 | D55: =IF(A55=0,0,INDEX('Inputs_Data_Raw'!E:E, 5+A55)) -> 1638000 | E55: =B55+C55-D55 -> 704300 | F55: =F54+E55 -> -722200 | G55: =IF(A55=0,-'Inputs_Data_Raw'!H5,0) -> 0 | H55: =IF(AND(A55>=1,A55<='Scenarios_10'!B8),MAX(0,(MAX(0,'Scenarios_10'!D8-'Scenarios_10'!E8/'Scenarios_10'!B8))-IF(AND(A55>'Scenarios_10'!B8-4,A55<='Scenarios_10'!B8),'Scenarios_10'!F8,0)),0) -> 2295454 | I55: =IF(A55=0,'Scenarios_10'!E8,0) -> 0 | J55: =IF(A55=0,0,IF('Scenarios_10'!C8="uniform_pct",INDEX('Inputs_Data_Raw'!E:E,5+A55)*(1-MIN('Scenarios_10'!G8,'Assumptions'!B9)),IF('Scenarios_10'!C8="electricity_only_pct",INDEX('Inputs_Data_Raw'!C:C,5+A55)*(1-MIN('Scenarios_10'!G8,'Assumptions'!B9))+INDEX('Inputs_Data_Raw'!D:D,5+A55),INDEX('Inputs_Data_Raw'!D:D,5+A55)*(1-AVERAGE('Assumptions'!B5,'Assumptions'!B6,'Assumptions'!B7,'Assumptions'!B8))))) -> 1021200 | K55: =G55+H55+I55-J55 -> 1274254 | L55: =L54+K55 -> 1557616
A56: 5 | B56: =IF(A56=0,-'Inputs_Data_Raw'!H5,0) -> 0 | C56: =IF(A56=0,0,INDEX('Inputs_Data_Raw'!B:B, 5+A56)) -> 2342300 | D56: =IF(A56=0,0,INDEX('Inputs_Data_Raw'!E:E, 5+A56)) -> 1638000 | E56: =B56+C56-D56 -> 704300 | F56: =F55+E56 -> -17900 | G56: =IF(A56=0,-'Inputs_Data_Raw'!H5,0) -> 0 | H56: =IF(AND(A56>=1,A56<='Scenarios_10'!B8),MAX(0,(MAX(0,'Scenarios_10'!D8-'Scenarios_10'!E8/'Scenarios_10'!B8))-IF(AND(A56>'Scenarios_10'!B8-4,A56<='Scenarios_10'!B8),'Scenarios_10'!F8,0)),0) -> 2295454 | I56: =IF(A56=0,'Scenarios_10'!E8,0) -> 0 | J56: =IF(A56=0,0,IF('Scenarios_10'!C8="uniform_pct",INDEX('Inputs_Data_Raw'!E:E,5+A56)*(1-MIN('Scenarios_10'!G8,'Assumptions'!B9)),IF('Scenarios_10'!C8="electricity_only_pct",INDEX('Inputs_Data_Raw'!C:C,5+A56)*(1-MIN('Scenarios_10'!G8,'Assumptions'!B9))+INDEX('Inputs_Data_Raw'!D:D,5+A56),INDEX('Inputs_Data_Raw'!D:D,5+A56)*(1-AVERAGE('Assumptions'!B5,'Assumptions'!B6,'Assumptions'!B7,'Assumptions'!B8))))) -> 1021200 | K56: =G56+H56+I56-J56 -> 1274254 | L56: =L55+K56 -> 2831870
A57: 6 | B57: =IF(A57=0,-'Inputs_Data_Raw'!H5,0) -> 0 | C57: =IF(A57=0,0,INDEX('Inputs_Data_Raw'!B:B, 5+A57)) -> 2342300 | D57: =IF(A57=0,0,INDEX('Inputs_Data_Raw'!E:E, 5+A57)) -> 1638000 | E57: =B57+C57-D57 -> 704300 | F57: =F56+E57 -> 686400 | G57: =IF(A57=0,-'Inputs_Data_Raw'!H5,0) -> 0 | H57: =IF(AND(A57>=1,A57<='Scenarios_10'!B8),MAX(0,(MAX(0,'Scenarios_10'!D8-'Scenarios_10'!E8/'Scenarios_10'!B8))-IF(AND(A57>'Scenarios_10'!B8-4,A57<='Scenarios_10'!B8),'Scenarios_10'!F8,0)),0) -> 2295454 | I57: =IF(A57=0,'Scenarios_10'!E8,0) -> 0 | J57: =IF(A57=0,0,IF('Scenarios_10'!C8="uniform_pct",INDEX('Inputs_Data_Raw'!E:E,5+A57)*(1-MIN('Scenarios_10'!G8,'Assumptions'!B9)),IF('Scenarios_10'!C8="electricity_only_pct",INDEX('Inputs_Data_Raw'!C:C,5+A57)*(1-MIN('Scenarios_10'!G8,'Assumptions'!B9))+INDEX('Inputs_Data_Raw'!D:D,5+A57),INDEX('Inputs_Data_Raw'!D:D,5+A57)*(1-AVERAGE('Assumptions'!B5,'Assumptions'!B6,'Assumptions'!B7,'Assumptions'!B8))))) -> 1021200 | K57: =G57+H57+I57-J57 -> 1274254 | L57: =L56+K57 -> 4106124
A58: 7 | B58: =IF(A58=0,-'Inputs_Data_Raw'!H5,0) -> 0 | C58: =IF(A58=0,0,INDEX('Inputs_Data_Raw'!B:B, 5+A58)) -> 2342300 | D58: =IF(A58=0,0,INDEX('Inputs_Data_Raw'!E:E, 5+A58)) -> 1638000 | E58: =B58+C58-D58 -> 704300 | F58: =F57+E58 -> 1390700 | G58: =IF(A58=0,-'Inputs_Data_Raw'!H5,0) -> 0 | H58: =IF(AND(A58>=1,A58<='Scenarios_10'!B8),MAX(0,(MAX(0,'Scenarios_10'!D8-'Scenarios_10'!E8/'Scenarios_10'!B8))-IF(AND(A58>'Scenarios_10'!B8-4,A58<='Scenarios_10'!B8),'Scenarios_10'!F8,0)),0) -> 2295454 | I58: =IF(A58=0,'Scenarios_10'!E8,0) -> 0 | J58: =IF(A58=0,0,IF('Scenarios_10'!C8="uniform_pct",INDEX('Inputs_Data_Raw'!E:E,5+A58)*(1-MIN('Scenarios_10'!G8,'Assumptions'!B9)),IF('Scenarios_10'!C8="electricity_only_pct",INDEX('Inputs_Data_Raw'!C:C,5+A58)*(1-MIN('Scenarios_10'!G8,'Assumptions'!B9))+INDEX('Inputs_Data_Raw'!D:D,5+A58),INDEX('Inputs_Data_Raw'!D:D,5+A58)*(1-AVERAGE('Assumptions'!B5,'Assumptions'!B6,'Assumptions'!B7,'Assumptions'!B8))))) -> 1021200 | K58: =G58+H58+I58-J58 -> 1274254 | L58: =L57+K58 -> 5380378
A59: 8 | B59: =IF(A59=0,-'Inputs_Data_Raw'!H5,0) -> 0 | C59: =IF(A59=0,0,INDEX('Inputs_Data_Raw'!B:B, 5+A59)) -> 2342300 | D59: =IF(A59=0,0,INDEX('Inputs_Data_Raw'!E:E, 5+A59)) -> 1638000 | E59: =B59+C59-D59 -> 704300 | F59: =F58+E59 -> 2095000 | G59: =IF(A59=0,-'Inputs_Data_Raw'!H5,0) -> 0 | H59: =IF(AND(A59>=1,A59<='Scenarios_10'!B8),MAX(0,(MAX(0,'Scenarios_10'!D8-'Scenarios_10'!E8/'Scenarios_10'!B8))-IF(AND(A59>'Scenarios_10'!B8-4,A59<='Scenarios_10'!B8),'Scenarios_10'!F8,0)),0) -> 2295454 | I59: =IF(A59=0,'Scenarios_10'!E8,0) -> 0 | J59: =IF(A59=0,0,IF('Scenarios_10'!C8="uniform_pct",INDEX('Inputs_Data_Raw'!E:E,5+A59)*(1-MIN('Scenarios_10'!G8,'Assumptions'!B9)),IF('Scenarios_10'!C8="electricity_only_pct",INDEX('Inputs_Data_Raw'!C:C,5+A59)*(1-MIN('Scenarios_10'!G8,'Assumptions'!B9))+INDEX('Inputs_Data_Raw'!D:D,5+A59),INDEX('Inputs_Data_Raw'!D:D,5+A59)*(1-AVERAGE('Assumptions'!B5,'Assumptions'!B6,'Assumptions'!B7,'Assumptions'!B8))))) -> 1021200 | K59: =G59+H59+I59-J59 -> 1274254 | L59: =L58+K59 -> 6654632
A60: 9 | B60: =IF(A60=0,-'Inputs_Data_Raw'!H5,0) -> 0 | C60: =IF(A60=0,0,INDEX('Inputs_Data_Raw'!B:B, 5+A60)) -> 2342300 | D60: =IF(A60=0,0,INDEX('Inputs_Data_Raw'!E:E, 5+A60)) -> 1638000 | E60: =B60+C60-D60 -> 704300 | F60: =F59+E60 -> 2799300 | G60: =IF(A60=0,-'Inputs_Data_Raw'!H5,0) -> 0 | H60: =IF(AND(A60>=1,A60<='Scenarios_10'!B8),MAX(0,(MAX(0,'Scenarios_10'!D8-'Scenarios_10'!E8/'Scenarios_10'!B8))-IF(AND(A60>'Scenarios_10'!B8-4,A60<='Scenarios_10'!B8),'Scenarios_10'!F8,0)),0) -> 2295454 | I60: =IF(A60=0,'Scenarios_10'!E8,0) -> 0 | J60: =IF(A60=0,0,IF('Scenarios_10'!C8="uniform_pct",INDEX('Inputs_Data_Raw'!E:E,5+A60)*(1-MIN('Scenarios_10'!G8,'Assumptions'!B9)),IF('Scenarios_10'!C8="electricity_only_pct",INDEX('Inputs_Data_Raw'!C:C,5+A60)*(1-MIN('Scenarios_10'!G8,'Assumptions'!B9))+INDEX('Inputs_Data_Raw'!D:D,5+A60),INDEX('Inputs_Data_Raw'!D:D,5+A60)*(1-AVERAGE('Assumptions'!B5,'Assumptions'!B6,'Assumptions'!B7,'Assumptions'!B8))))) -> 1021200 | K60: =G60+H60+I60-J60 -> 1274254 | L60: =L59+K60 -> 7928886
A61: 10 | B61: =IF(A61=0,-'Inputs_Data_Raw'!H5,0) -> 0 | C61: =IF(A61=0,0,INDEX('Inputs_Data_Raw'!B:B, 5+A61)) -> 2342300 | D61: =IF(A61=0,0,INDEX('Inputs_Data_Raw'!E:E, 5+A61)) -> 1638000 | E61: =B61+C61-D61 -> 704300 | F61: =F60+E61 -> 3503600 | G61: =IF(A61=0,-'Inputs_Data_Raw'!H5,0) -> 0 | H61: =IF(AND(A61>=1,A61<='Scenarios_10'!B8),MAX(0,(MAX(0,'Scenarios_10'!D8-'Scenarios_10'!E8/'Scenarios_10'!B8))-IF(AND(A61>'Scenarios_10'!B8-4,A61<='Scenarios_10'!B8),'Scenarios_10'!F8,0)),0) -> 2295454 | I61: =IF(A61=0,'Scenarios_10'!E8,0) -> 0 | J61: =IF(A61=0,0,IF('Scenarios_10'!C8="uniform_pct",INDEX('Inputs_Data_Raw'!E:E,5+A61)*(1-MIN('Scenarios_10'!G8,'Assumptions'!B9)),IF('Scenarios_10'!C8="electricity_only_pct",INDEX('Inputs_Data_Raw'!C:C,5+A61)*(1-MIN('Scenarios_10'!G8,'Assumptions'!B9))+INDEX('Inputs_Data_Raw'!D:D,5+A61),INDEX('Inputs_Data_Raw'!D:D,5+A61)*(1-AVERAGE('Assumptions'!B5,'Assumptions'!B6,'Assumptions'!B7,'Assumptions'!B8))))) -> 1021200 | K61: =G61+H61+I61-J61 -> 1274254 | L61: =L60+K61 -> 9203140
A64: Tier: Tier5_AISolar
A65: year | B65: trust_capex | C65: trust_fee | D65: trust_cash_opex | E65: trust_net_cf | F65: trust_cum_cf | G65: laas_capex | H65: laas_fee | I65: laas_upfront | J65: laas_cash_opex | K65: laas_net_cf | L65: laas_cum_cf
A66: 0 | B66: =IF(A66=0,-'Inputs_Data_Raw'!H5,0) -> -3539400 | C66: =IF(A66=0,0,INDEX('Inputs_Data_Raw'!B:B, 5+A66)) -> 0 | D66: =IF(A66=0,0,INDEX('Inputs_Data_Raw'!E:E, 5+A66)) -> 0 | E66: =B66+C66-D66 -> -3539400 | F66: =E66 -> -3539400 | G66: =IF(A66=0,-'Inputs_Data_Raw'!H5,0) -> -3539400 | H66: =IF(AND(A66>=1,A66<='Scenarios_10'!B9),MAX(0,(MAX(0,'Scenarios_10'!D9-'Scenarios_10'!E9/'Scenarios_10'!B9))-IF(AND(A66>'Scenarios_10'!B9-4,A66<='Scenarios_10'!B9),'Scenarios_10'!F9,0)),0) -> 0 | I66: =IF(A66=0,'Scenarios_10'!E9,0) -> 0 | J66: =IF(A66=0,0,IF('Scenarios_10'!C9="uniform_pct",INDEX('Inputs_Data_Raw'!E:E,5+A66)*(1-MIN('Scenarios_10'!G9,'Assumptions'!B9)),IF('Scenarios_10'!C9="electricity_only_pct",INDEX('Inputs_Data_Raw'!C:C,5+A66)*(1-MIN('Scenarios_10'!G9,'Assumptions'!B9))+INDEX('Inputs_Data_Raw'!D:D,5+A66),INDEX('Inputs_Data_Raw'!D:D,5+A66)*(1-AVERAGE('Assumptions'!B5,'Assumptions'!B6,'Assumptions'!B7,'Assumptions'!B8))))) -> 0 | K66: =G66+H66+I66-J66 -> -3539400 | L66: =K66 -> -3539400
A67: 1 | B67: =IF(A67=0,-'Inputs_Data_Raw'!H5,0) -> 0 | C67: =IF(A67=0,0,INDEX('Inputs_Data_Raw'!B:B, 5+A67)) -> 2342300 | D67: =IF(A67=0,0,INDEX('Inputs_Data_Raw'!E:E, 5+A67)) -> 1638000 | E67: =B67+C67-D67 -> 704300 | F67: =F66+E67 -> -2835100 | G67: =IF(A67=0,-'Inputs_Data_Raw'!H5,0) -> 0 | H67: =IF(AND(A67>=1,A67<='Scenarios_10'!B9),MAX(0,(MAX(0,'Scenarios_10'!D9-'Scenarios_10'!E9/'Scenarios_10'!B9))-IF(AND(A67>'Scenarios_10'!B9-4,A67<='Scenarios_10'!B9),'Scenarios_10'!F9,0)),0) -> 2459415 | I67: =IF(A67=0,'Scenarios_10'!E9,0) -> 0 | J67: =IF(A67=0,0,IF('Scenarios_10'!C9="uniform_pct",INDEX('Inputs_Data_Raw'!E:E,5+A67)*(1-MIN('Scenarios_10'!G9,'Assumptions'!B9)),IF('Scenarios_10'!C9="electricity_only_pct",INDEX('Inputs_Data_Raw'!C:C,5+A67)*(1-MIN('Scenarios_10'!G9,'Assumptions'!B9))+INDEX('Inputs_Data_Raw'!D:D,5+A67),INDEX('Inputs_Data_Raw'!D:D,5+A67)*(1-AVERAGE('Assumptions'!B5,'Assumptions'!B6,'Assumptions'!B7,'Assumptions'!B8))))) -> 472750 | K67: =G67+H67+I67-J67 -> 1986665 | L67: =L66+K67 -> -1552735
A68: 2 | B68: =IF(A68=0,-'Inputs_Data_Raw'!H5,0) -> 0 | C68: =IF(A68=0,0,INDEX('Inputs_Data_Raw'!B:B, 5+A68)) -> 2342300 | D68: =IF(A68=0,0,INDEX('Inputs_Data_Raw'!E:E, 5+A68)) -> 1638000 | E68: =B68+C68-D68 -> 704300 | F68: =F67+E68 -> -2130800 | G68: =IF(A68=0,-'Inputs_Data_Raw'!H5,0) -> 0 | H68: =IF(AND(A68>=1,A68<='Scenarios_10'!B9),MAX(0,(MAX(0,'Scenarios_10'!D9-'Scenarios_10'!E9/'Scenarios_10'!B9))-IF(AND(A68>'Scenarios_10'!B9-4,A68<='Scenarios_10'!B9),'Scenarios_10'!F9,0)),0) -> 2459415 | I68: =IF(A68=0,'Scenarios_10'!E9,0) -> 0 | J68: =IF(A68=0,0,IF('Scenarios_10'!C9="uniform_pct",INDEX('Inputs_Data_Raw'!E:E,5+A68)*(1-MIN('Scenarios_10'!G9,'Assumptions'!B9)),IF('Scenarios_10'!C9="electricity_only_pct",INDEX('Inputs_Data_Raw'!C:C,5+A68)*(1-MIN('Scenarios_10'!G9,'Assumptions'!B9))+INDEX('Inputs_Data_Raw'!D:D,5+A68),INDEX('Inputs_Data_Raw'!D:D,5+A68)*(1-AVERAGE('Assumptions'!B5,'Assumptions'!B6,'Assumptions'!B7,'Assumptions'!B8))))) -> 472750 | K68: =G68+H68+I68-J68 -> 1986665 | L68: =L67+K68 -> 433930
A69: 3 | B69: =IF(A69=0,-'Inputs_Data_Raw'!H5,0) -> 0 | C69: =IF(A69=0,0,INDEX('Inputs_Data_Raw'!B:B, 5+A69)) -> 2342300 | D69: =IF(A69=0,0,INDEX('Inputs_Data_Raw'!E:E, 5+A69)) -> 1638000 | E69: =B69+C69-D69 -> 704300 | F69: =F68+E69 -> -1426500 | G69: =IF(A69=0,-'Inputs_Data_Raw'!H5,0) -> 0 | H69: =IF(AND(A69>=1,A69<='Scenarios_10'!B9),MAX(0,(MAX(0,'Scenarios_10'!D9-'Scenarios_10'!E9/'Scenarios_10'!B9))-IF(AND(A69>'Scenarios_10'!B9-4,A69<='Scenarios_10'!B9),'Scenarios_10'!F9,0)),0) -> 2459415 | I69: =IF(A69=0,'Scenarios_10'!E9,0) -> 0 | J69: =IF(A69=0,0,IF('Scenarios_10'!C9="uniform_pct",INDEX('Inputs_Data_Raw'!E:E,5+A69)*(1-MIN('Scenarios_10'!G9,'Assumptions'!B9)),IF('Scenarios_10'!C9="electricity_only_pct",INDEX('Inputs_Data_Raw'!C:C,5+A69)*(1-MIN('Scenarios_10'!G9,'Assumptions'!B9))+INDEX('Inputs_Data_Raw'!D:D,5+A69),INDEX('Inputs_Data_Raw'!D:D,5+A69)*(1-AVERAGE('Assumptions'!B5,'Assumptions'!B6,'Assumptions'!B7,'Assumptions'!B8))))) -> 472750 | K69: =G69+H69+I69-J69 -> 1986665 | L69: =L68+K69 -> 2420595
A70: 4 | B70: =IF(A70=0,-'Inputs_Data_Raw'!H5,0) -> 0 | C70: =IF(A70=0,0,INDEX('Inputs_Data_Raw'!B:B, 5+A70)) -> 2342300 | D70: =IF(A70=0,0,INDEX('Inputs_Data_Raw'!E:E, 5+A70)) -> 1638000 | E70: =B70+C70-D70 -> 704300 | F70: =F69+E70 -> -722200 | G70: =IF(A70=0,-'Inputs_Data_Raw'!H5,0) -> 0 | H70: =IF(AND(A70>=1,A70<='Scenarios_10'!B9),MAX(0,(MAX(0,'Scenarios_10'!D9-'Scenarios_10'!E9/'Scenarios_10'!B9))-IF(AND(A70>'Scenarios_10'!B9-4,A70<='Scenarios_10'!B9),'Scenarios_10'!F9,0)),0) -> 2459415 | I70: =IF(A70=0,'Scenarios_10'!E9,0) -> 0 | J70: =IF(A70=0,0,IF('Scenarios_10'!C9="uniform_pct",INDEX('Inputs_Data_Raw'!E:E,5+A70)*(1-MIN('Scenarios_10'!G9,'Assumptions'!B9)),IF('Scenarios_10'!C9="electricity_only_pct",INDEX('Inputs_Data_Raw'!C:C,5+A70)*(1-MIN('Scenarios_10'!G9,'Assumptions'!B9))+INDEX('Inputs_Data_Raw'!D:D,5+A70),INDEX('Inputs_Data_Raw'!D:D,5+A70)*(1-AVERAGE('Assumptions'!B5,'Assumptions'!B6,'Assumptions'!B7,'Assumptions'!B8))))) -> 472750 | K70: =G70+H70+I70-J70 -> 1986665 | L70: =L69+K70 -> 4407260
A71: 5 | B71: =IF(A71=0,-'Inputs_Data_Raw'!H5,0) -> 0 | C71: =IF(A71=0,0,INDEX('Inputs_Data_Raw'!B:B, 5+A71)) -> 2342300 | D71: =IF(A71=0,0,INDEX('Inputs_Data_Raw'!E:E, 5+A71)) -> 1638000 | E71: =B71+C71-D71 -> 704300 | F71: =F70+E71 -> -17900 | G71: =IF(A71=0,-'Inputs_Data_Raw'!H5,0) -> 0 | H71: =IF(AND(A71>=1,A71<='Scenarios_10'!B9),MAX(0,(MAX(0,'Scenarios_10'!D9-'Scenarios_10'!E9/'Scenarios_10'!B9))-IF(AND(A71>'Scenarios_10'!B9-4,A71<='Scenarios_10'!B9),'Scenarios_10'!F9,0)),0) -> 2459415 | I71: =IF(A71=0,'Scenarios_10'!E9,0) -> 0 | J71: =IF(A71=0,0,IF('Scenarios_10'!C9="uniform_pct",INDEX('Inputs_Data_Raw'!E:E,5+A71)*(1-MIN('Scenarios_10'!G9,'Assumptions'!B9)),IF('Scenarios_10'!C9="electricity_only_pct",INDEX('Inputs_Data_Raw'!C:C,5+A71)*(1-MIN('Scenarios_10'!G9,'Assumptions'!B9))+INDEX('Inputs_Data_Raw'!D:D,5+A71),INDEX('Inputs_Data_Raw'!D:D,5+A71)*(1-AVERAGE('Assumptions'!B5,'Assumptions'!B6,'Assumptions'!B7,'Assumptions'!B8))))) -> 472750 | K71: =G71+H71+I71-J71 -> 1986665 | L71: =L70+K71 -> 6393925
A72: 6 | B72: =IF(A72=0,-'Inputs_Data_Raw'!H5,0) -> 0 | C72: =IF(A72=0,0,INDEX('Inputs_Data_Raw'!B:B, 5+A72)) -> 2342300 | D72: =IF(A72=0,0,INDEX('Inputs_Data_Raw'!E:E, 5+A72)) -> 1638000 | E72: =B72+C72-D72 -> 704300 | F72: =F71+E72 -> 686400 | G72: =IF(A72=0,-'Inputs_Data_Raw'!H5,0) -> 0 | H72: =IF(AND(A72>=1,A72<='Scenarios_10'!B9),MAX(0,(MAX(0,'Scenarios_10'!D9-'Scenarios_10'!E9/'Scenarios_10'!B9))-IF(AND(A72>'Scenarios_10'!B9-4,A72<='Scenarios_10'!B9),'Scenarios_10'!F9,0)),0) -> 2459415 | I72: =IF(A72=0,'Scenarios_10'!E9,0) -> 0 | J72: =IF(A72=0,0,IF('Scenarios_10'!C9="uniform_pct",INDEX('Inputs_Data_Raw'!E:E,5+A72)*(1-MIN('Scenarios_10'!G9,'Assumptions'!B9)),IF('Scenarios_10'!C9="electricity_only_pct",INDEX('Inputs_Data_Raw'!C:C,5+A72)*(1-MIN('Scenarios_10'!G9,'Assumptions'!B9))+INDEX('Inputs_Data_Raw'!D:D,5+A72),INDEX('Inputs_Data_Raw'!D:D,5+A72)*(1-AVERAGE('Assumptions'!B5,'Assumptions'!B6,'Assumptions'!B7,'Assumptions'!B8))))) -> 472750 | K72: =G72+H72+I72-J72 -> 1986665 | L72: =L71+K72 -> 8380590
A73: 7 | B73: =IF(A73=0,-'Inputs_Data_Raw'!H5,0) -> 0 | C73: =IF(A73=0,0,INDEX('Inputs_Data_Raw'!B:B, 5+A73)) -> 2342300 | D73: =IF(A73=0,0,INDEX('Inputs_Data_Raw'!E:E, 5+A73)) -> 1638000 | E73: =B73+C73-D73 -> 704300 | F73: =F72+E73 -> 1390700 | G73: =IF(A73=0,-'Inputs_Data_Raw'!H5,0) -> 0 | H73: =IF(AND(A73>=1,A73<='Scenarios_10'!B9),MAX(0,(MAX(0,'Scenarios_10'!D9-'Scenarios_10'!E9/'Scenarios_10'!B9))-IF(AND(A73>'Scenarios_10'!B9-4,A73<='Scenarios_10'!B9),'Scenarios_10'!F9,0)),0) -> 2459415 | I73: =IF(A73=0,'Scenarios_10'!E9,0) -> 0 | J73: =IF(A73=0,0,IF('Scenarios_10'!C9="uniform_pct",INDEX('Inputs_Data_Raw'!E:E,5+A73)*(1-MIN('Scenarios_10'!G9,'Assumptions'!B9)),IF('Scenarios_10'!C9="electricity_only_pct",INDEX('Inputs_Data_Raw'!C:C,5+A73)*(1-MIN('Scenarios_10'!G9,'Assumptions'!B9))+INDEX('Inputs_Data_Raw'!D:D,5+A73),INDEX('Inputs_Data_Raw'!D:D,5+A73)*(1-AVERAGE('Assumptions'!B5,'Assumptions'!B6,'Assumptions'!B7,'Assumptions'!B8))))) -> 472750 | K73: =G73+H73+I73-J73 -> 1986665 | L73: =L72+K73 -> 10367255
A74: 8 | B74: =IF(A74=0,-'Inputs_Data_Raw'!H5,0) -> 0 | C74: =IF(A74=0,0,INDEX('Inputs_Data_Raw'!B:B, 5+A74)) -> 2342300 | D74: =IF(A74=0,0,INDEX('Inputs_Data_Raw'!E:E, 5+A74)) -> 1638000 | E74: =B74+C74-D74 -> 704300 | F74: =F73+E74 -> 2095000 | G74: =IF(A74=0,-'Inputs_Data_Raw'!H5,0) -> 0 | H74: =IF(AND(A74>=1,A74<='Scenarios_10'!B9),MAX(0,(MAX(0,'Scenarios_10'!D9-'Scenarios_10'!E9/'Scenarios_10'!B9))-IF(AND(A74>'Scenarios_10'!B9-4,A74<='Scenarios_10'!B9),'Scenarios_10'!F9,0)),0) -> 2459415 | I74: =IF(A74=0,'Scenarios_10'!E9,0) -> 0 | J74: =IF(A74=0,0,IF('Scenarios_10'!C9="uniform_pct",INDEX('Inputs_Data_Raw'!E:E,5+A74)*(1-MIN('Scenarios_10'!G9,'Assumptions'!B9)),IF('Scenarios_10'!C9="electricity_only_pct",INDEX('Inputs_Data_Raw'!C:C,5+A74)*(1-MIN('Scenarios_10'!G9,'Assumptions'!B9))+INDEX('Inputs_Data_Raw'!D:D,5+A74),INDEX('Inputs_Data_Raw'!D:D,5+A74)*(1-AVERAGE('Assumptions'!B5,'Assumptions'!B6,'Assumptions'!B7,'Assumptions'!B8))))) -> 472750 | K74: =G74+H74+I74-J74 -> 1986665 | L74: =L73+K74 -> 12353920
A75: 9 | B75: =IF(A75=0,-'Inputs_Data_Raw'!H5,0) -> 0 | C75: =IF(A75=0,0,INDEX('Inputs_Data_Raw'!B:B, 5+A75)) -> 2342300 | D75: =IF(A75=0,0,INDEX('Inputs_Data_Raw'!E:E, 5+A75)) -> 1638000 | E75: =B75+C75-D75 -> 704300 | F75: =F74+E75 -> 2799300 | G75: =IF(A75=0,-'Inputs_Data_Raw'!H5,0) -> 0 | H75: =IF(AND(A75>=1,A75<='Scenarios_10'!B9),MAX(0,(MAX(0,'Scenarios_10'!D9-'Scenarios_10'!E9/'Scenarios_10'!B9))-IF(AND(A75>'Scenarios_10'!B9-4,A75<='Scenarios_10'!B9),'Scenarios_10'!F9,0)),0) -> 2459415 | I75: =IF(A75=0,'Scenarios_10'!E9,0) -> 0 | J75: =IF(A75=0,0,IF('Scenarios_10'!C9="uniform_pct",INDEX('Inputs_Data_Raw'!E:E,5+A75)*(1-MIN('Scenarios_10'!G9,'Assumptions'!B9)),IF('Scenarios_10'!C9="electricity_only_pct",INDEX('Inputs_Data_Raw'!C:C,5+A75)*(1-MIN('Scenarios_10'!G9,'Assumptions'!B9))+INDEX('Inputs_Data_Raw'!D:D,5+A75),INDEX('Inputs_Data_Raw'!D:D,5+A75)*(1-AVERAGE('Assumptions'!B5,'Assumptions'!B6,'Assumptions'!B7,'Assumptions'!B8))))) -> 472750 | K75: =G75+H75+I75-J75 -> 1986665 | L75: =L74+K75 -> 14340585
A76: 10 | B76: =IF(A76=0,-'Inputs_Data_Raw'!H5,0) -> 0 | C76: =IF(A76=0,0,INDEX('Inputs_Data_Raw'!B:B, 5+A76)) -> 2342300 | D76: =IF(A76=0,0,INDEX('Inputs_Data_Raw'!E:E, 5+A76)) -> 1638000 | E76: =B76+C76-D76 -> 704300 | F76: =F75+E76 -> 3503600 | G76: =IF(A76=0,-'Inputs_Data_Raw'!H5,0) -> 0 | H76: =IF(AND(A76>=1,A76<='Scenarios_10'!B9),MAX(0,(MAX(0,'Scenarios_10'!D9-'Scenarios_10'!E9/'Scenarios_10'!B9))-IF(AND(A76>'Scenarios_10'!B9-4,A76<='Scenarios_10'!B9),'Scenarios_10'!F9,0)),0) -> 2459415 | I76: =IF(A76=0,'Scenarios_10'!E9,0) -> 0 | J76: =IF(A76=0,0,IF('Scenarios_10'!C9="uniform_pct",INDEX('Inputs_Data_Raw'!E:E,5+A76)*(1-MIN('Scenarios_10'!G9,'Assumptions'!B9)),IF('Scenarios_10'!C9="electricity_only_pct",INDEX('Inputs_Data_Raw'!C:C,5+A76)*(1-MIN('Scenarios_10'!G9,'Assumptions'!B9))+INDEX('Inputs_Data_Raw'!D:D,5+A76),INDEX('Inputs_Data_Raw'!D:D,5+A76)*(1-AVERAGE('Assumptions'!B5,'Assumptions'!B6,'Assumptions'!B7,'Assumptions'!B8))))) -> 472750 | K76: =G76+H76+I76-J76 -> 1986665 | L76: =L75+K76 -> 16327250
A79: Tier: Tier6_Upfront_Prepay
A80: year | B80: trust_capex | C80: trust_fee | D80: trust_cash_opex | E80: trust_net_cf | F80: trust_cum_cf | G80: laas_capex | H80: laas_fee | I80: laas_upfront | J80: laas_cash_opex | K80: laas_net_cf | L80: laas_cum_cf
A81: 0 | B81: =IF(A81=0,-'Inputs_Data_Raw'!H5,0) -> -3539400 | C81: =IF(A81=0,0,INDEX('Inputs_Data_Raw'!B:B, 5+A81)) -> 0 | D81: =IF(A81=0,0,INDEX('Inputs_Data_Raw'!E:E, 5+A81)) -> 0 | E81: =B81+C81-D81 -> -3539400 | F81: =E81 -> -3539400 | G81: =IF(A81=0,-'Inputs_Data_Raw'!H5,0) -> -3539400 | H81: =IF(AND(A81>=1,A81<='Scenarios_10'!B10),MAX(0,(MAX(0,'Scenarios_10'!D10-'Scenarios_10'!E10/'Scenarios_10'!B10))-IF(AND(A81>'Scenarios_10'!B10-4,A81<='Scenarios_10'!B10),'Scenarios_10'!F10,0)),0) -> 0 | I81: =IF(A81=0,'Scenarios_10'!E10,0) -> 1000000 | J81: =IF(A81=0,0,IF('Scenarios_10'!C10="uniform_pct",INDEX('Inputs_Data_Raw'!E:E,5+A81)*(1-MIN('Scenarios_10'!G10,'Assumptions'!B9)),IF('Scenarios_10'!C10="electricity_only_pct",INDEX('Inputs_Data_Raw'!C:C,5+A81)*(1-MIN('Scenarios_10'!G10,'Assumptions'!B9))+INDEX('Inputs_Data_Raw'!D:D,5+A81),INDEX('Inputs_Data_Raw'!D:D,5+A81)*(1-AVERAGE('Assumptions'!B5,'Assumptions'!B6,'Assumptions'!B7,'Assumptions'!B8))))) -> 0 | K81: =G81+H81+I81-J81 -> -2539400 | L81: =K81 -> -2539400
A82: 1 | B82: =IF(A82=0,-'Inputs_Data_Raw'!H5,0) -> 0 | C82: =IF(A82=0,0,INDEX('Inputs_Data_Raw'!B:B, 5+A82)) -> 2342300 | D82: =IF(A82=0,0,INDEX('Inputs_Data_Raw'!E:E, 5+A82)) -> 1638000 | E82: =B82+C82-D82 -> 704300 | F82: =F81+E82 -> -2835100 | G82: =IF(A82=0,-'Inputs_Data_Raw'!H5,0) -> 0 | H82: =IF(AND(A82>=1,A82<='Scenarios_10'!B10),MAX(0,(MAX(0,'Scenarios_10'!D10-'Scenarios_10'!E10/'Scenarios_10'!B10))-IF(AND(A82>'Scenarios_10'!B10-4,A82<='Scenarios_10'!B10),'Scenarios_10'!F10,0)),0) -> 2242300 | I82: =IF(A82=0,'Scenarios_10'!E10,0) -> 0 | J82: =IF(A82=0,0,IF('Scenarios_10'!C10="uniform_pct",INDEX('Inputs_Data_Raw'!E:E,5+A82)*(1-MIN('Scenarios_10'!G10,'Assumptions'!B9)),IF('Scenarios_10'!C10="electricity_only_pct",INDEX('Inputs_Data_Raw'!C:C,5+A82)*(1-MIN('Scenarios_10'!G10,'Assumptions'!B9))+INDEX('Inputs_Data_Raw'!D:D,5+A82),INDEX('Inputs_Data_Raw'!D:D,5+A82)*(1-AVERAGE('Assumptions'!B5,'Assumptions'!B6,'Assumptions'!B7,'Assumptions'!B8))))) -> 1228500 | K82: =G82+H82+I82-J82 -> 1013800 | L82: =L81+K82 -> -1525600
A83: 2 | B83: =IF(A83=0,-'Inputs_Data_Raw'!H5,0) -> 0 | C83: =IF(A83=0,0,INDEX('Inputs_Data_Raw'!B:B, 5+A83)) -> 2342300 | D83: =IF(A83=0,0,INDEX('Inputs_Data_Raw'!E:E, 5+A83)) -> 1638000 | E83: =B83+C83-D83 -> 704300 | F83: =F82+E83 -> -2130800 | G83: =IF(A83=0,-'Inputs_Data_Raw'!H5,0) -> 0 | H83: =IF(AND(A83>=1,A83<='Scenarios_10'!B10),MAX(0,(MAX(0,'Scenarios_10'!D10-'Scenarios_10'!E10/'Scenarios_10'!B10))-IF(AND(A83>'Scenarios_10'!B10-4,A83<='Scenarios_10'!B10),'Scenarios_10'!F10,0)),0) -> 2242300 | I83: =IF(A83=0,'Scenarios_10'!E10,0) -> 0 | J83: =IF(A83=0,0,IF('Scenarios_10'!C10="uniform_pct",INDEX('Inputs_Data_Raw'!E:E,5+A83)*(1-MIN('Scenarios_10'!G10,'Assumptions'!B9)),IF('Scenarios_10'!C10="electricity_only_pct",INDEX('Inputs_Data_Raw'!C:C,5+A83)*(1-MIN('Scenarios_10'!G10,'Assumptions'!B9))+INDEX('Inputs_Data_Raw'!D:D,5+A83),INDEX('Inputs_Data_Raw'!D:D,5+A83)*(1-AVERAGE('Assumptions'!B5,'Assumptions'!B6,'Assumptions'!B7,'Assumptions'!B8))))) -> 1228500 | K83: =G83+H83+I83-J83 -> 1013800 | L83: =L82+K83 -> -511800
A84: 3 | B84: =IF(A84=0,-'Inputs_Data_Raw'!H5,0) -> 0 | C84: =IF(A84=0,0,INDEX('Inputs_Data_Raw'!B:B, 5+A84)) -> 2342300 | D84: =IF(A84=0,0,INDEX('Inputs_Data_Raw'!E:E, 5+A84)) -> 1638000 | E84: =B84+C84-D84 -> 704300 | F84: =F83+E84 -> -1426500 | G84: =IF(A84=0,-'Inputs_Data_Raw'!H5,0) -> 0 | H84: =IF(AND(A84>=1,A84<='Scenarios_10'!B10),MAX(0,(MAX(0,'Scenarios_10'!D10-'Scenarios_10'!E10/'Scenarios_10'!B10))-IF(AND(A84>'Scenarios_10'!B10-4,A84<='Scenarios_10'!B10),'Scenarios_10'!F10,0)),0) -> 2242300 | I84: =IF(A84=0,'Scenarios_10'!E10,0) -> 0 | J84: =IF(A84=0,0,IF('Scenarios_10'!C10="uniform_pct",INDEX('Inputs_Data_Raw'!E:E,5+A84)*(1-MIN('Scenarios_10'!G10,'Assumptions'!B9)),IF('Scenarios_10'!C10="electricity_only_pct",INDEX('Inputs_Data_Raw'!C:C,5+A84)*(1-MIN('Scenarios_10'!G10,'Assumptions'!B9))+INDEX('Inputs_Data_Raw'!D:D,5+A84),INDEX('Inputs_Data_Raw'!D:D,5+A84)*(1-AVERAGE('Assumptions'!B5,'Assumptions'!B6,'Assumptions'!B7,'Assumptions'!B8))))) -> 1228500 | K84: =G84+H84+I84-J84 -> 1013800 | L84: =L83+K84 -> 502000
A85: 4 | B85: =IF(A85=0,-'Inputs_Data_Raw'!H5,0) -> 0 | C85: =IF(A85=0,0,INDEX('Inputs_Data_Raw'!B:B, 5+A85)) -> 2342300 | D85: =IF(A85=0,0,INDEX('Inputs_Data_Raw'!E:E, 5+A85)) -> 1638000 | E85: =B85+C85-D85 -> 704300 | F85: =F84+E85 -> -722200 | G85: =IF(A85=0,-'Inputs_Data_Raw'!H5,0) -> 0 | H85: =IF(AND(A85>=1,A85<='Scenarios_10'!B10),MAX(0,(MAX(0,'Scenarios_10'!D10-'Scenarios_10'!E10/'Scenarios_10'!B10))-IF(AND(A85>'Scenarios_10'!B10-4,A85<='Scenarios_10'!B10),'Scenarios_10'!F10,0)),0) -> 2242300 | I85: =IF(A85=0,'Scenarios_10'!E10,0) -> 0 | J85: =IF(A85=0,0,IF('Scenarios_10'!C10="uniform_pct",INDEX('Inputs_Data_Raw'!E:E,5+A85)*(1-MIN('Scenarios_10'!G10,'Assumptions'!B9)),IF('Scenarios_10'!C10="electricity_only_pct",INDEX('Inputs_Data_Raw'!C:C,5+A85)*(1-MIN('Scenarios_10'!G10,'Assumptions'!B9))+INDEX('Inputs_Data_Raw'!D:D,5+A85),INDEX('Inputs_Data_Raw'!D:D,5+A85)*(1-AVERAGE('Assumptions'!B5,'Assumptions'!B6,'Assumptions'!B7,'Assumptions'!B8))))) -> 1228500 | K85: =G85+H85+I85-J85 -> 1013800 | L85: =L84+K85 -> 1515800
A86: 5 | B86: =IF(A86=0,-'Inputs_Data_Raw'!H5,0) -> 0 | C86: =IF(A86=0,0,INDEX('Inputs_Data_Raw'!B:B, 5+A86)) -> 2342300 | D86: =IF(A86=0,0,INDEX('Inputs_Data_Raw'!E:E, 5+A86)) -> 1638000 | E86: =B86+C86-D86 -> 704300 | F86: =F85+E86 -> -17900 | G86: =IF(A86=0,-'Inputs_Data_Raw'!H5,0) -> 0 | H86: =IF(AND(A86>=1,A86<='Scenarios_10'!B10),MAX(0,(MAX(0,'Scenarios_10'!D10-'Scenarios_10'!E10/'Scenarios_10'!B10))-IF(AND(A86>'Scenarios_10'!B10-4,A86<='Scenarios_10'!B10),'Scenarios_10'!F10,0)),0) -> 2242300 | I86: =IF(A86=0,'Scenarios_10'!E10,0) -> 0 | J86: =IF(A86=0,0,IF('Scenarios_10'!C10="uniform_pct",INDEX('Inputs_Data_Raw'!E:E,5+A86)*(1-MIN('Scenarios_10'!G10,'Assumptions'!B9)),IF('Scenarios_10'!C10="electricity_only_pct",INDEX('Inputs_Data_Raw'!C:C,5+A86)*(1-MIN('Scenarios_10'!G10,'Assumptions'!B9))+INDEX('Inputs_Data_Raw'!D:D,5+A86),INDEX('Inputs_Data_Raw'!D:D,5+A86)*(1-AVERAGE('Assumptions'!B5,'Assumptions'!B6,'Assumptions'!B7,'Assumptions'!B8))))) -> 1228500 | K86: =G86+H86+I86-J86 -> 1013800 | L86: =L85+K86 -> 2529600
A87: 6 | B87: =IF(A87=0,-'Inputs_Data_Raw'!H5,0) -> 0 | C87: =IF(A87=0,0,INDEX('Inputs_Data_Raw'!B:B, 5+A87)) -> 2342300 | D87: =IF(A87=0,0,INDEX('Inputs_Data_Raw'!E:E, 5+A87)) -> 1638000 | E87: =B87+C87-D87 -> 704300 | F87: =F86+E87 -> 686400 | G87: =IF(A87=0,-'Inputs_Data_Raw'!H5,0) -> 0 | H87: =IF(AND(A87>=1,A87<='Scenarios_10'!B10),MAX(0,(MAX(0,'Scenarios_10'!D10-'Scenarios_10'!E10/'Scenarios_10'!B10))-IF(AND(A87>'Scenarios_10'!B10-4,A87<='Scenarios_10'!B10),'Scenarios_10'!F10,0)),0) -> 2242300 | I87: =IF(A87=0,'Scenarios_10'!E10,0) -> 0 | J87: =IF(A87=0,0,IF('Scenarios_10'!C10="uniform_pct",INDEX('Inputs_Data_Raw'!E:E,5+A87)*(1-MIN('Scenarios_10'!G10,'Assumptions'!B9)),IF('Scenarios_10'!C10="electricity_only_pct",INDEX('Inputs_Data_Raw'!C:C,5+A87)*(1-MIN('Scenarios_10'!G10,'Assumptions'!B9))+INDEX('Inputs_Data_Raw'!D:D,5+A87),INDEX('Inputs_Data_Raw'!D:D,5+A87)*(1-AVERAGE('Assumptions'!B5,'Assumptions'!B6,'Assumptions'!B7,'Assumptions'!B8))))) -> 1228500 | K87: =G87+H87+I87-J87 -> 1013800 | L87: =L86+K87 -> 3543400
A88: 7 | B88: =IF(A88=0,-'Inputs_Data_Raw'!H5,0) -> 0 | C88: =IF(A88=0,0,INDEX('Inputs_Data_Raw'!B:B, 5+A88)) -> 2342300 | D88: =IF(A88=0,0,INDEX('Inputs_Data_Raw'!E:E, 5+A88)) -> 1638000 | E88: =B88+C88-D88 -> 704300 | F88: =F87+E88 -> 1390700 | G88: =IF(A88=0,-'Inputs_Data_Raw'!H5,0) -> 0 | H88: =IF(AND(A88>=1,A88<='Scenarios_10'!B10),MAX(0,(MAX(0,'Scenarios_10'!D10-'Scenarios_10'!E10/'Scenarios_10'!B10))-IF(AND(A88>'Scenarios_10'!B10-4,A88<='Scenarios_10'!B10),'Scenarios_10'!F10,0)),0) -> 2242300 | I88: =IF(A88=0,'Scenarios_10'!E10,0) -> 0 | J88: =IF(A88=0,0,IF('Scenarios_10'!C10="uniform_pct",INDEX('Inputs_Data_Raw'!E:E,5+A88)*(1-MIN('Scenarios_10'!G10,'Assumptions'!B9)),IF('Scenarios_10'!C10="electricity_only_pct",INDEX('Inputs_Data_Raw'!C:C,5+A88)*(1-MIN('Scenarios_10'!G10,'Assumptions'!B9))+INDEX('Inputs_Data_Raw'!D:D,5+A88),INDEX('Inputs_Data_Raw'!D:D,5+A88)*(1-AVERAGE('Assumptions'!B5,'Assumptions'!B6,'Assumptions'!B7,'Assumptions'!B8))))) -> 1228500 | K88: =G88+H88+I88-J88 -> 1013800 | L88: =L87+K88 -> 4557200
A89: 8 | B89: =IF(A89=0,-'Inputs_Data_Raw'!H5,0) -> 0 | C89: =IF(A89=0,0,INDEX('Inputs_Data_Raw'!B:B, 5+A89)) -> 2342300 | D89: =IF(A89=0,0,INDEX('Inputs_Data_Raw'!E:E, 5+A89)) -> 1638000 | E89: =B89+C89-D89 -> 704300 | F89: =F88+E89 -> 2095000 | G89: =IF(A89=0,-'Inputs_Data_Raw'!H5,0) -> 0 | H89: =IF(AND(A89>=1,A89<='Scenarios_10'!B10),MAX(0,(MAX(0,'Scenarios_10'!D10-'Scenarios_10'!E10/'Scenarios_10'!B10))-IF(AND(A89>'Scenarios_10'!B10-4,A89<='Scenarios_10'!B10),'Scenarios_10'!F10,0)),0) -> 2242300 | I89: =IF(A89=0,'Scenarios_10'!E10,0) -> 0 | J89: =IF(A89=0,0,IF('Scenarios_10'!C10="uniform_pct",INDEX('Inputs_Data_Raw'!E:E,5+A89)*(1-MIN('Scenarios_10'!G10,'Assumptions'!B9)),IF('Scenarios_10'!C10="electricity_only_pct",INDEX('Inputs_Data_Raw'!C:C,5+A89)*(1-MIN('Scenarios_10'!G10,'Assumptions'!B9))+INDEX('Inputs_Data_Raw'!D:D,5+A89),INDEX('Inputs_Data_Raw'!D:D,5+A89)*(1-AVERAGE('Assumptions'!B5,'Assumptions'!B6,'Assumptions'!B7,'Assumptions'!B8))))) -> 1228500 | K89: =G89+H89+I89-J89 -> 1013800 | L89: =L88+K89 -> 5571000
A90: 9 | B90: =IF(A90=0,-'Inputs_Data_Raw'!H5,0) -> 0 | C90: =IF(A90=0,0,INDEX('Inputs_Data_Raw'!B:B, 5+A90)) -> 2342300 | D90: =IF(A90=0,0,INDEX('Inputs_Data_Raw'!E:E, 5+A90)) -> 1638000 | E90: =B90+C90-D90 -> 704300 | F90: =F89+E90 -> 2799300 | G90: =IF(A90=0,-'Inputs_Data_Raw'!H5,0) -> 0 | H90: =IF(AND(A90>=1,A90<='Scenarios_10'!B10),MAX(0,(MAX(0,'Scenarios_10'!D10-'Scenarios_10'!E10/'Scenarios_10'!B10))-IF(AND(A90>'Scenarios_10'!B10-4,A90<='Scenarios_10'!B10),'Scenarios_10'!F10,0)),0) -> 2242300 | I90: =IF(A90=0,'Scenarios_10'!E10,0) -> 0 | J90: =IF(A90=0,0,IF('Scenarios_10'!C10="uniform_pct",INDEX('Inputs_Data_Raw'!E:E,5+A90)*(1-MIN('Scenarios_10'!G10,'Assumptions'!B9)),IF('Scenarios_10'!C10="electricity_only_pct",INDEX('Inputs_Data_Raw'!C:C,5+A90)*(1-MIN('Scenarios_10'!G10,'Assumptions'!B9))+INDEX('Inputs_Data_Raw'!D:D,5+A90),INDEX('Inputs_Data_Raw'!D:D,5+A90)*(1-AVERAGE('Assumptions'!B5,'Assumptions'!B6,'Assumptions'!B7,'Assumptions'!B8))))) -> 1228500 | K90: =G90+H90+I90-J90 -> 1013800 | L90: =L89+K90 -> 6584800
A91: 10 | B91: =IF(A91=0,-'Inputs_Data_Raw'!H5,0) -> 0 | C91: =IF(A91=0,0,INDEX('Inputs_Data_Raw'!B:B, 5+A91)) -> 2342300 | D91: =IF(A91=0,0,INDEX('Inputs_Data_Raw'!E:E, 5+A91)) -> 1638000 | E91: =B91+C91-D91 -> 704300 | F91: =F90+E91 -> 3503600 | G91: =IF(A91=0,-'Inputs_Data_Raw'!H5,0) -> 0 | H91: =IF(AND(A91>=1,A91<='Scenarios_10'!B10),MAX(0,(MAX(0,'Scenarios_10'!D10-'Scenarios_10'!E10/'Scenarios_10'!B10))-IF(AND(A91>'Scenarios_10'!B10-4,A91<='Scenarios_10'!B10),'Scenarios_10'!F10,0)),0) -> 2242300 | I91: =IF(A91=0,'Scenarios_10'!E10,0) -> 0 | J91: =IF(A91=0,0,IF('Scenarios_10'!C10="uniform_pct",INDEX('Inputs_Data_Raw'!E:E,5+A91)*(1-MIN('Scenarios_10'!G10,'Assumptions'!B9)),IF('Scenarios_10'!C10="electricity_only_pct",INDEX('Inputs_Data_Raw'!C:C,5+A91)*(1-MIN('Scenarios_10'!G10,'Assumptions'!B9))+INDEX('Inputs_Data_Raw'!D:D,5+A91),INDEX('Inputs_Data_Raw'!D:D,5+A91)*(1-AVERAGE('Assumptions'!B5,'Assumptions'!B6,'Assumptions'!B7,'Assumptions'!B8))))) -> 1228500 | K91: =G91+H91+I91-J91 -> 1013800 | L91: =L90+K91 -> 7598600
A94: Tier: Tier7_TailDiscount
A95: year | B95: trust_capex | C95: trust_fee | D95: trust_cash_opex | E95: trust_net_cf | F95: trust_cum_cf | G95: laas_capex | H95: laas_fee | I95: laas_upfront | J95: laas_cash_opex | K95: laas_net_cf | L95: laas_cum_cf
A96: 0 | B96: =IF(A96=0,-'Inputs_Data_Raw'!H5,0) -> -3539400 | C96: =IF(A96=0,0,INDEX('Inputs_Data_Raw'!B:B, 5+A96)) -> 0 | D96: =IF(A96=0,0,INDEX('Inputs_Data_Raw'!E:E, 5+A96)) -> 0 | E96: =B96+C96-D96 -> -3539400 | F96: =E96 -> -3539400 | G96: =IF(A96=0,-'Inputs_Data_Raw'!H5,0) -> -3539400 | H96: =IF(AND(A96>=1,A96<='Scenarios_10'!B11),MAX(0,(MAX(0,'Scenarios_10'!D11-'Scenarios_10'!E11/'Scenarios_10'!B11))-IF(AND(A96>'Scenarios_10'!B11-4,A96<='Scenarios_10'!B11),'Scenarios_10'!F11,0)),0) -> 0 | I96: =IF(A96=0,'Scenarios_10'!E11,0) -> 0 | J96: =IF(A96=0,0,IF('Scenarios_10'!C11="uniform_pct",INDEX('Inputs_Data_Raw'!E:E,5+A96)*(1-MIN('Scenarios_10'!G11,'Assumptions'!B9)),IF('Scenarios_10'!C11="electricity_only_pct",INDEX('Inputs_Data_Raw'!C:C,5+A96)*(1-MIN('Scenarios_10'!G11,'Assumptions'!B9))+INDEX('Inputs_Data_Raw'!D:D,5+A96),INDEX('Inputs_Data_Raw'!D:D,5+A96)*(1-AVERAGE('Assumptions'!B5,'Assumptions'!B6,'Assumptions'!B7,'Assumptions'!B8))))) -> 0 | K96: =G96+H96+I96-J96 -> -3539400 | L96: =K96 -> -3539400
A97: 1 | B97: =IF(A97=0,-'Inputs_Data_Raw'!H5,0) -> 0 | C97: =IF(A97=0,0,INDEX('Inputs_Data_Raw'!B:B, 5+A97)) -> 2342300 | D97: =IF(A97=0,0,INDEX('Inputs_Data_Raw'!E:E, 5+A97)) -> 1638000 | E97: =B97+C97-D97 -> 704300 | F97: =F96+E97 -> -2835100 | G97: =IF(A97=0,-'Inputs_Data_Raw'!H5,0) -> 0 | H97: =IF(AND(A97>=1,A97<='Scenarios_10'!B11),MAX(0,(MAX(0,'Scenarios_10'!D11-'Scenarios_10'!E11/'Scenarios_10'!B11))-IF(AND(A97>'Scenarios_10'!B11-4,A97<='Scenarios_10'!B11),'Scenarios_10'!F11,0)),0) -> 2389146 | I97: =IF(A97=0,'Scenarios_10'!E11,0) -> 0 | J97: =IF(A97=0,0,IF('Scenarios_10'!C11="uniform_pct",INDEX('Inputs_Data_Raw'!E:E,5+A97)*(1-MIN('Scenarios_10'!G11,'Assumptions'!B9)),IF('Scenarios_10'!C11="electricity_only_pct",INDEX('Inputs_Data_Raw'!C:C,5+A97)*(1-MIN('Scenarios_10'!G11,'Assumptions'!B9))+INDEX('Inputs_Data_Raw'!D:D,5+A97),INDEX('Inputs_Data_Raw'!D:D,5+A97)*(1-AVERAGE('Assumptions'!B5,'Assumptions'!B6,'Assumptions'!B7,'Assumptions'!B8))))) -> 1228500 | K97: =G97+H97+I97-J97 -> 1160646 | L97: =L96+K97 -> -2378754
A98: 2 | B98: =IF(A98=0,-'Inputs_Data_Raw'!H5,0) -> 0 | C98: =IF(A98=0,0,INDEX('Inputs_Data_Raw'!B:B, 5+A98)) -> 2342300 | D98: =IF(A98=0,0,INDEX('Inputs_Data_Raw'!E:E, 5+A98)) -> 1638000 | E98: =B98+C98-D98 -> 704300 | F98: =F97+E98 -> -2130800 | G98: =IF(A98=0,-'Inputs_Data_Raw'!H5,0) -> 0 | H98: =IF(AND(A98>=1,A98<='Scenarios_10'!B11),MAX(0,(MAX(0,'Scenarios_10'!D11-'Scenarios_10'!E11/'Scenarios_10'!B11))-IF(AND(A98>'Scenarios_10'!B11-4,A98<='Scenarios_10'!B11),'Scenarios_10'!F11,0)),0) -> 2389146 | I98: =IF(A98=0,'Scenarios_10'!E11,0) -> 0 | J98: =IF(A98=0,0,IF('Scenarios_10'!C11="uniform_pct",INDEX('Inputs_Data_Raw'!E:E,5+A98)*(1-MIN('Scenarios_10'!G11,'Assumptions'!B9)),IF('Scenarios_10'!C11="electricity_only_pct",INDEX('Inputs_Data_Raw'!C:C,5+A98)*(1-MIN('Scenarios_10'!G11,'Assumptions'!B9))+INDEX('Inputs_Data_Raw'!D:D,5+A98),INDEX('Inputs_Data_Raw'!D:D,5+A98)*(1-AVERAGE('Assumptions'!B5,'Assumptions'!B6,'Assumptions'!B7,'Assumptions'!B8))))) -> 1228500 | K98: =G98+H98+I98-J98 -> 1160646 | L98: =L97+K98 -> -1218108
A99: 3 | B99: =IF(A99=0,-'Inputs_Data_Raw'!H5,0) -> 0 | C99: =IF(A99=0,0,INDEX('Inputs_Data_Raw'!B:B, 5+A99)) -> 2342300 | D99: =IF(A99=0,0,INDEX('Inputs_Data_Raw'!E:E, 5+A99)) -> 1638000 | E99: =B99+C99-D99 -> 704300 | F99: =F98+E99 -> -1426500 | G99: =IF(A99=0,-'Inputs_Data_Raw'!H5,0) -> 0 | H99: =IF(AND(A99>=1,A99<='Scenarios_10'!B11),MAX(0,(MAX(0,'Scenarios_10'!D11-'Scenarios_10'!E11/'Scenarios_10'!B11))-IF(AND(A99>'Scenarios_10'!B11-4,A99<='Scenarios_10'!B11),'Scenarios_10'!F11,0)),0) -> 2389146 | I99: =IF(A99=0,'Scenarios_10'!E11,0) -> 0 | J99: =IF(A99=0,0,IF('Scenarios_10'!C11="uniform_pct",INDEX('Inputs_Data_Raw'!E:E,5+A99)*(1-MIN('Scenarios_10'!G11,'Assumptions'!B9)),IF('Scenarios_10'!C11="electricity_only_pct",INDEX('Inputs_Data_Raw'!C:C,5+A99)*(1-MIN('Scenarios_10'!G11,'Assumptions'!B9))+INDEX('Inputs_Data_Raw'!D:D,5+A99),INDEX('Inputs_Data_Raw'!D:D,5+A99)*(1-AVERAGE('Assumptions'!B5,'Assumptions'!B6,'Assumptions'!B7,'Assumptions'!B8))))) -> 1228500 | K99: =G99+H99+I99-J99 -> 1160646 | L99: =L98+K99 -> -57462
A100: 4 | B100: =IF(A100=0,-'Inputs_Data_Raw'!H5,0) -> 0 | C100: =IF(A100=0,0,INDEX('Inputs_Data_Raw'!B:B, 5+A100)) -> 2342300 | D100: =IF(A100=0,0,INDEX('Inputs_Data_Raw'!E:E, 5+A100)) -> 1638000 | E100: =B100+C100-D100 -> 704300 | F100: =F99+E100 -> -722200 | G100: =IF(A100=0,-'Inputs_Data_Raw'!H5,0) -> 0 | H100: =IF(AND(A100>=1,A100<='Scenarios_10'!B11),MAX(0,(MAX(0,'Scenarios_10'!D11-'Scenarios_10'!E11/'Scenarios_10'!B11))-IF(AND(A100>'Scenarios_10'!B11-4,A100<='Scenarios_10'!B11),'Scenarios_10'!F11,0)),0) -> 2389146 | I100: =IF(A100=0,'Scenarios_10'!E11,0) -> 0 | J100: =IF(A100=0,0,IF('Scenarios_10'!C11="uniform_pct",INDEX('Inputs_Data_Raw'!E:E,5+A100)*(1-MIN('Scenarios_10'!G11,'Assumptions'!B9)),IF('Scenarios_10'!C11="electricity_only_pct",INDEX('Inputs_Data_Raw'!C:C,5+A100)*(1-MIN('Scenarios_10'!G11,'Assumptions'!B9))+INDEX('Inputs_Data_Raw'!D:D,5+A100),INDEX('Inputs_Data_Raw'!D:D,5+A100)*(1-AVERAGE('Assumptions'!B5,'Assumptions'!B6,'Assumptions'!B7,'Assumptions'!B8))))) -> 1228500 | K100: =G100+H100+I100-J100 -> 1160646 | L100: =L99+K100 -> 1103184
A101: 5 | B101: =IF(A101=0,-'Inputs_Data_Raw'!H5,0) -> 0 | C101: =IF(A101=0,0,INDEX('Inputs_Data_Raw'!B:B, 5+A101)) -> 2342300 | D101: =IF(A101=0,0,INDEX('Inputs_Data_Raw'!E:E, 5+A101)) -> 1638000 | E101: =B101+C101-D101 -> 704300 | F101: =F100+E101 -> -17900 | G101: =IF(A101=0,-'Inputs_Data_Raw'!H5,0) -> 0 | H101: =IF(AND(A101>=1,A101<='Scenarios_10'!B11),MAX(0,(MAX(0,'Scenarios_10'!D11-'Scenarios_10'!E11/'Scenarios_10'!B11))-IF(AND(A101>'Scenarios_10'!B11-4,A101<='Scenarios_10'!B11),'Scenarios_10'!F11,0)),0) -> 2389146 | I101: =IF(A101=0,'Scenarios_10'!E11,0) -> 0 | J101: =IF(A101=0,0,IF('Scenarios_10'!C11="uniform_pct",INDEX('Inputs_Data_Raw'!E:E,5+A101)*(1-MIN('Scenarios_10'!G11,'Assumptions'!B9)),IF('Scenarios_10'!C11="electricity_only_pct",INDEX('Inputs_Data_Raw'!C:C,5+A101)*(1-MIN('Scenarios_10'!G11,'Assumptions'!B9))+INDEX('Inputs_Data_Raw'!D:D,5+A101),INDEX('Inputs_Data_Raw'!D:D,5+A101)*(1-AVERAGE('Assumptions'!B5,'Assumptions'!B6,'Assumptions'!B7,'Assumptions'!B8))))) -> 1228500 | K101: =G101+H101+I101-J101 -> 1160646 | L101: =L100+K101 -> 2263830
A102: 6 | B102: =IF(A102=0,-'Inputs_Data_Raw'!H5,0) -> 0 | C102: =IF(A102=0,0,INDEX('Inputs_Data_Raw'!B:B, 5+A102)) -> 2342300 | D102: =IF(A102=0,0,INDEX('Inputs_Data_Raw'!E:E, 5+A102)) -> 1638000 | E102: =B102+C102-D102 -> 704300 | F102: =F101+E102 -> 686400 | G102: =IF(A102=0,-'Inputs_Data_Raw'!H5,0) -> 0 | H102: =IF(AND(A102>=1,A102<='Scenarios_10'!B11),MAX(0,(MAX(0,'Scenarios_10'!D11-'Scenarios_10'!E11/'Scenarios_10'!B11))-IF(AND(A102>'Scenarios_10'!B11-4,A102<='Scenarios_10'!B11),'Scenarios_10'!F11,0)),0) -> 2389146 | I102: =IF(A102=0,'Scenarios_10'!E11,0) -> 0 | J102: =IF(A102=0,0,IF('Scenarios_10'!C11="uniform_pct",INDEX('Inputs_Data_Raw'!E:E,5+A102)*(1-MIN('Scenarios_10'!G11,'Assumptions'!B9)),IF('Scenarios_10'!C11="electricity_only_pct",INDEX('Inputs_Data_Raw'!C:C,5+A102)*(1-MIN('Scenarios_10'!G11,'Assumptions'!B9))+INDEX('Inputs_Data_Raw'!D:D,5+A102),INDEX('Inputs_Data_Raw'!D:D,5+A102)*(1-AVERAGE('Assumptions'!B5,'Assumptions'!B6,'Assumptions'!B7,'Assumptions'!B8))))) -> 1228500 | K102: =G102+H102+I102-J102 -> 1160646 | L102: =L101+K102 -> 3424476
A103: 7 | B103: =IF(A103=0,-'Inputs_Data_Raw'!H5,0) -> 0 | C103: =IF(A103=0,0,INDEX('Inputs_Data_Raw'!B:B, 5+A103)) -> 2342300 | D103: =IF(A103=0,0,INDEX('Inputs_Data_Raw'!E:E, 5+A103)) -> 1638000 | E103: =B103+C103-D103 -> 704300 | F103: =F102+E103 -> 1390700 | G103: =IF(A103=0,-'Inputs_Data_Raw'!H5,0) -> 0 | H103: =IF(AND(A103>=1,A103<='Scenarios_10'!B11),MAX(0,(MAX(0,'Scenarios_10'!D11-'Scenarios_10'!E11/'Scenarios_10'!B11))-IF(AND(A103>'Scenarios_10'!B11-4,A103<='Scenarios_10'!B11),'Scenarios_10'!F11,0)),0) -> 2139146 | I103: =IF(A103=0,'Scenarios_10'!E11,0) -> 0 | J103: =IF(A103=0,0,IF('Scenarios_10'!C11="uniform_pct",INDEX('Inputs_Data_Raw'!E:E,5+A103)*(1-MIN('Scenarios_10'!G11,'Assumptions'!B9)),IF('Scenarios_10'!C11="electricity_only_pct",INDEX('Inputs_Data_Raw'!C:C,5+A103)*(1-MIN('Scenarios_10'!G11,'Assumptions'!B9))+INDEX('Inputs_Data_Raw'!D:D,5+A103),INDEX('Inputs_Data_Raw'!D:D,5+A103)*(1-AVERAGE('Assumptions'!B5,'Assumptions'!B6,'Assumptions'!B7,'Assumptions'!B8))))) -> 1228500 | K103: =G103+H103+I103-J103 -> 910646 | L103: =L102+K103 -> 4335122
A104: 8 | B104: =IF(A104=0,-'Inputs_Data_Raw'!H5,0) -> 0 | C104: =IF(A104=0,0,INDEX('Inputs_Data_Raw'!B:B, 5+A104)) -> 2342300 | D104: =IF(A104=0,0,INDEX('Inputs_Data_Raw'!E:E, 5+A104)) -> 1638000 | E104: =B104+C104-D104 -> 704300 | F104: =F103+E104 -> 2095000 | G104: =IF(A104=0,-'Inputs_Data_Raw'!H5,0) -> 0 | H104: =IF(AND(A104>=1,A104<='Scenarios_10'!B11),MAX(0,(MAX(0,'Scenarios_10'!D11-'Scenarios_10'!E11/'Scenarios_10'!B11))-IF(AND(A104>'Scenarios_10'!B11-4,A104<='Scenarios_10'!B11),'Scenarios_10'!F11,0)),0) -> 2139146 | I104: =IF(A104=0,'Scenarios_10'!E11,0) -> 0 | J104: =IF(A104=0,0,IF('Scenarios_10'!C11="uniform_pct",INDEX('Inputs_Data_Raw'!E:E,5+A104)*(1-MIN('Scenarios_10'!G11,'Assumptions'!B9)),IF('Scenarios_10'!C11="electricity_only_pct",INDEX('Inputs_Data_Raw'!C:C,5+A104)*(1-MIN('Scenarios_10'!G11,'Assumptions'!B9))+INDEX('Inputs_Data_Raw'!D:D,5+A104),INDEX('Inputs_Data_Raw'!D:D,5+A104)*(1-AVERAGE('Assumptions'!B5,'Assumptions'!B6,'Assumptions'!B7,'Assumptions'!B8))))) -> 1228500 | K104: =G104+H104+I104-J104 -> 910646 | L104: =L103+K104 -> 5245768
A105: 9 | B105: =IF(A105=0,-'Inputs_Data_Raw'!H5,0) -> 0 | C105: =IF(A105=0,0,INDEX('Inputs_Data_Raw'!B:B, 5+A105)) -> 2342300 | D105: =IF(A105=0,0,INDEX('Inputs_Data_Raw'!E:E, 5+A105)) -> 1638000 | E105: =B105+C105-D105 -> 704300 | F105: =F104+E105 -> 2799300 | G105: =IF(A105=0,-'Inputs_Data_Raw'!H5,0) -> 0 | H105: =IF(AND(A105>=1,A105<='Scenarios_10'!B11),MAX(0,(MAX(0,'Scenarios_10'!D11-'Scenarios_10'!E11/'Scenarios_10'!B11))-IF(AND(A105>'Scenarios_10'!B11-4,A105<='Scenarios_10'!B11),'Scenarios_10'!F11,0)),0) -> 2139146 | I105: =IF(A105=0,'Scenarios_10'!E11,0) -> 0 | J105: =IF(A105=0,0,IF('Scenarios_10'!C11="uniform_pct",INDEX('Inputs_Data_Raw'!E:E,5+A105)*(1-MIN('Scenarios_10'!G11,'Assumptions'!B9)),IF('Scenarios_10'!C11="electricity_only_pct",INDEX('Inputs_Data_Raw'!C:C,5+A105)*(1-MIN('Scenarios_10'!G11,'Assumptions'!B9))+INDEX('Inputs_Data_Raw'!D:D,5+A105),INDEX('Inputs_Data_Raw'!D:D,5+A105)*(1-AVERAGE('Assumptions'!B5,'Assumptions'!B6,'Assumptions'!B7,'Assumptions'!B8))))) -> 1228500 | K105: =G105+H105+I105-J105 -> 910646 | L105: =L104+K105 -> 6156414
A106: 10 | B106: =IF(A106=0,-'Inputs_Data_Raw'!H5,0) -> 0 | C106: =IF(A106=0,0,INDEX('Inputs_Data_Raw'!B:B, 5+A106)) -> 2342300 | D106: =IF(A106=0,0,INDEX('Inputs_Data_Raw'!E:E, 5+A106)) -> 1638000 | E106: =B106+C106-D106 -> 704300 | F106: =F105+E106 -> 3503600 | G106: =IF(A106=0,-'Inputs_Data_Raw'!H5,0) -> 0 | H106: =IF(AND(A106>=1,A106<='Scenarios_10'!B11),MAX(0,(MAX(0,'Scenarios_10'!D11-'Scenarios_10'!E11/'Scenarios_10'!B11))-IF(AND(A106>'Scenarios_10'!B11-4,A106<='Scenarios_10'!B11),'Scenarios_10'!F11,0)),0) -> 2139146 | I106: =IF(A106=0,'Scenarios_10'!E11,0) -> 0 | J106: =IF(A106=0,0,IF('Scenarios_10'!C11="uniform_pct",INDEX('Inputs_Data_Raw'!E:E,5+A106)*(1-MIN('Scenarios_10'!G11,'Assumptions'!B9)),IF('Scenarios_10'!C11="electricity_only_pct",INDEX('Inputs_Data_Raw'!C:C,5+A106)*(1-MIN('Scenarios_10'!G11,'Assumptions'!B9))+INDEX('Inputs_Data_Raw'!D:D,5+A106),INDEX('Inputs_Data_Raw'!D:D,5+A106)*(1-AVERAGE('Assumptions'!B5,'Assumptions'!B6,'Assumptions'!B7,'Assumptions'!B8))))) -> 1228500 | K106: =G106+H106+I106-J106 -> 910646 | L106: =L105+K106 -> 7067060
A109: Tier: Tier8_HigherFee_StrongerSLA
A110: year | B110: trust_capex | C110: trust_fee | D110: trust_cash_opex | E110: trust_net_cf | F110: trust_cum_cf | G110: laas_capex | H110: laas_fee | I110: laas_upfront | J110: laas_cash_opex | K110: laas_net_cf | L110: laas_cum_cf
A111: 0 | B111: =IF(A111=0,-'Inputs_Data_Raw'!H5,0) -> -3539400 | C111: =IF(A111=0,0,INDEX('Inputs_Data_Raw'!B:B, 5+A111)) -> 0 | D111: =IF(A111=0,0,INDEX('Inputs_Data_Raw'!E:E, 5+A111)) -> 0 | E111: =B111+C111-D111 -> -3539400 | F111: =E111 -> -3539400 | G111: =IF(A111=0,-'Inputs_Data_Raw'!H5,0) -> -3539400 | H111: =IF(AND(A111>=1,A111<='Scenarios_10'!B12),MAX(0,(MAX(0,'Scenarios_10'!D12-'Scenarios_10'!E12/'Scenarios_10'!B12))-IF(AND(A111>'Scenarios_10'!B12-4,A111<='Scenarios_10'!B12),'Scenarios_10'!F12,0)),0) -> 0 | I111: =IF(A111=0,'Scenarios_10'!E12,0) -> 0 | J111: =IF(A111=0,0,IF('Scenarios_10'!C12="uniform_pct",INDEX('Inputs_Data_Raw'!E:E,5+A111)*(1-MIN('Scenarios_10'!G12,'Assumptions'!B9)),IF('Scenarios_10'!C12="electricity_only_pct",INDEX('Inputs_Data_Raw'!C:C,5+A111)*(1-MIN('Scenarios_10'!G12,'Assumptions'!B9))+INDEX('Inputs_Data_Raw'!D:D,5+A111),INDEX('Inputs_Data_Raw'!D:D,5+A111)*(1-AVERAGE('Assumptions'!B5,'Assumptions'!B6,'Assumptions'!B7,'Assumptions'!B8))))) -> 0 | K111: =G111+H111+I111-J111 -> -3539400 | L111: =K111 -> -3539400
A112: 1 | B112: =IF(A112=0,-'Inputs_Data_Raw'!H5,0) -> 0 | C112: =IF(A112=0,0,INDEX('Inputs_Data_Raw'!B:B, 5+A112)) -> 2342300 | D112: =IF(A112=0,0,INDEX('Inputs_Data_Raw'!E:E, 5+A112)) -> 1638000 | E112: =B112+C112-D112 -> 704300 | F112: =F111+E112 -> -2835100 | G112: =IF(A112=0,-'Inputs_Data_Raw'!H5,0) -> 0 | H112: =IF(AND(A112>=1,A112<='Scenarios_10'!B12),MAX(0,(MAX(0,'Scenarios_10'!D12-'Scenarios_10'!E12/'Scenarios_10'!B12))-IF(AND(A112>'Scenarios_10'!B12-4,A112<='Scenarios_10'!B12),'Scenarios_10'!F12,0)),0) -> 2529684 | I112: =IF(A112=0,'Scenarios_10'!E12,0) -> 0 | J112: =IF(A112=0,0,IF('Scenarios_10'!C12="uniform_pct",INDEX('Inputs_Data_Raw'!E:E,5+A112)*(1-MIN('Scenarios_10'!G12,'Assumptions'!B9)),IF('Scenarios_10'!C12="electricity_only_pct",INDEX('Inputs_Data_Raw'!C:C,5+A112)*(1-MIN('Scenarios_10'!G12,'Assumptions'!B9))+INDEX('Inputs_Data_Raw'!D:D,5+A112),INDEX('Inputs_Data_Raw'!D:D,5+A112)*(1-AVERAGE('Assumptions'!B5,'Assumptions'!B6,'Assumptions'!B7,'Assumptions'!B8))))) -> 1146600 | K112: =G112+H112+I112-J112 -> 1383084 | L112: =L111+K112 -> -2156316
A113: 2 | B113: =IF(A113=0,-'Inputs_Data_Raw'!H5,0) -> 0 | C113: =IF(A113=0,0,INDEX('Inputs_Data_Raw'!B:B, 5+A113)) -> 2342300 | D113: =IF(A113=0,0,INDEX('Inputs_Data_Raw'!E:E, 5+A113)) -> 1638000 | E113: =B113+C113-D113 -> 704300 | F113: =F112+E113 -> -2130800 | G113: =IF(A113=0,-'Inputs_Data_Raw'!H5,0) -> 0 | H113: =IF(AND(A113>=1,A113<='Scenarios_10'!B12),MAX(0,(MAX(0,'Scenarios_10'!D12-'Scenarios_10'!E12/'Scenarios_10'!B12))-IF(AND(A113>'Scenarios_10'!B12-4,A113<='Scenarios_10'!B12),'Scenarios_10'!F12,0)),0) -> 2529684 | I113: =IF(A113=0,'Scenarios_10'!E12,0) -> 0 | J113: =IF(A113=0,0,IF('Scenarios_10'!C12="uniform_pct",INDEX('Inputs_Data_Raw'!E:E,5+A113)*(1-MIN('Scenarios_10'!G12,'Assumptions'!B9)),IF('Scenarios_10'!C12="electricity_only_pct",INDEX('Inputs_Data_Raw'!C:C,5+A113)*(1-MIN('Scenarios_10'!G12,'Assumptions'!B9))+INDEX('Inputs_Data_Raw'!D:D,5+A113),INDEX('Inputs_Data_Raw'!D:D,5+A113)*(1-AVERAGE('Assumptions'!B5,'Assumptions'!B6,'Assumptions'!B7,'Assumptions'!B8))))) -> 1146600 | K113: =G113+H113+I113-J113 -> 1383084 | L113: =L112+K113 -> -773232
A114: 3 | B114: =IF(A114=0,-'Inputs_Data_Raw'!H5,0) -> 0 | C114: =IF(A114=0,0,INDEX('Inputs_Data_Raw'!B:B, 5+A114)) -> 2342300 | D114: =IF(A114=0,0,INDEX('Inputs_Data_Raw'!E:E, 5+A114)) -> 1638000 | E114: =B114+C114-D114 -> 704300 | F114: =F113+E114 -> -1426500 | G114: =IF(A114=0,-'Inputs_Data_Raw'!H5,0) -> 0 | H114: =IF(AND(A114>=1,A114<='Scenarios_10'!B12),MAX(0,(MAX(0,'Scenarios_10'!D12-'Scenarios_10'!E12/'Scenarios_10'!B12))-IF(AND(A114>'Scenarios_10'!B12-4,A114<='Scenarios_10'!B12),'Scenarios_10'!F12,0)),0) -> 2529684 | I114: =IF(A114=0,'Scenarios_10'!E12,0) -> 0 | J114: =IF(A114=0,0,IF('Scenarios_10'!C12="uniform_pct",INDEX('Inputs_Data_Raw'!E:E,5+A114)*(1-MIN('Scenarios_10'!G12,'Assumptions'!B9)),IF('Scenarios_10'!C12="electricity_only_pct",INDEX('Inputs_Data_Raw'!C:C,5+A114)*(1-MIN('Scenarios_10'!G12,'Assumptions'!B9))+INDEX('Inputs_Data_Raw'!D:D,5+A114),INDEX('Inputs_Data_Raw'!D:D,5+A114)*(1-AVERAGE('Assumptions'!B5,'Assumptions'!B6,'Assumptions'!B7,'Assumptions'!B8))))) -> 1146600 | K114: =G114+H114+I114-J114 -> 1383084 | L114: =L113+K114 -> 609852
A115: 4 | B115: =IF(A115=0,-'Inputs_Data_Raw'!H5,0) -> 0 | C115: =IF(A115=0,0,INDEX('Inputs_Data_Raw'!B:B, 5+A115)) -> 2342300 | D115: =IF(A115=0,0,INDEX('Inputs_Data_Raw'!E:E, 5+A115)) -> 1638000 | E115: =B115+C115-D115 -> 704300 | F115: =F114+E115 -> -722200 | G115: =IF(A115=0,-'Inputs_Data_Raw'!H5,0) -> 0 | H115: =IF(AND(A115>=1,A115<='Scenarios_10'!B12),MAX(0,(MAX(0,'Scenarios_10'!D12-'Scenarios_10'!E12/'Scenarios_10'!B12))-IF(AND(A115>'Scenarios_10'!B12-4,A115<='Scenarios_10'!B12),'Scenarios_10'!F12,0)),0) -> 2529684 | I115: =IF(A115=0,'Scenarios_10'!E12,0) -> 0 | J115: =IF(A115=0,0,IF('Scenarios_10'!C12="uniform_pct",INDEX('Inputs_Data_Raw'!E:E,5+A115)*(1-MIN('Scenarios_10'!G12,'Assumptions'!B9)),IF('Scenarios_10'!C12="electricity_only_pct",INDEX('Inputs_Data_Raw'!C:C,5+A115)*(1-MIN('Scenarios_10'!G12,'Assumptions'!B9))+INDEX('Inputs_Data_Raw'!D:D,5+A115),INDEX('Inputs_Data_Raw'!D:D,5+A115)*(1-AVERAGE('Assumptions'!B5,'Assumptions'!B6,'Assumptions'!B7,'Assumptions'!B8))))) -> 1146600 | K115: =G115+H115+I115-J115 -> 1383084 | L115: =L114+K115 -> 1992936
...
